package com.google.android.gms.common.api.internal;

import b.b.a.X;

public abstract class zzbb
  implements Runnable
{
  public zzbb(zzar paramZzar) {}
  
  /* Error */
  @X
  public void run()
  {
    // Byte code:
    //   0: aload_0
    //   1: getfield 12	com/google/android/gms/common/api/internal/zzbb:zzflx	Lcom/google/android/gms/common/api/internal/zzar;
    //   4: getfield 27	com/google/android/gms/common/api/internal/zzar:zzfke	Ljava/util/concurrent/locks/Lock;
    //   7: invokeinterface 32 1 0
    //   12: invokestatic 38	java/lang/Thread:interrupted	()Z
    //   15: istore_1
    //   16: iload_1
    //   17: ifeq +16 -> 33
    //   20: aload_0
    //   21: getfield 12	com/google/android/gms/common/api/internal/zzbb:zzflx	Lcom/google/android/gms/common/api/internal/zzar;
    //   24: getfield 27	com/google/android/gms/common/api/internal/zzar:zzfke	Ljava/util/concurrent/locks/Lock;
    //   27: invokeinterface 41 1 0
    //   32: return
    //   33: aload_0
    //   34: invokevirtual 44	com/google/android/gms/common/api/internal/zzbb:zzagz	()V
    //   37: aload_0
    //   38: getfield 12	com/google/android/gms/common/api/internal/zzbb:zzflx	Lcom/google/android/gms/common/api/internal/zzar;
    //   41: getfield 27	com/google/android/gms/common/api/internal/zzar:zzfke	Ljava/util/concurrent/locks/Lock;
    //   44: invokeinterface 41 1 0
    //   49: return
    //   50: astore_2
    //   51: goto +28 -> 79
    //   54: astore_2
    //   55: aload_0
    //   56: getfield 12	com/google/android/gms/common/api/internal/zzbb:zzflx	Lcom/google/android/gms/common/api/internal/zzar;
    //   59: getfield 48	com/google/android/gms/common/api/internal/zzar:zzflh	Lcom/google/android/gms/common/api/internal/zzbl;
    //   62: aload_2
    //   63: invokevirtual 54	com/google/android/gms/common/api/internal/zzbl:zza	(Ljava/lang/RuntimeException;)V
    //   66: aload_0
    //   67: getfield 12	com/google/android/gms/common/api/internal/zzbb:zzflx	Lcom/google/android/gms/common/api/internal/zzar;
    //   70: getfield 27	com/google/android/gms/common/api/internal/zzar:zzfke	Ljava/util/concurrent/locks/Lock;
    //   73: invokeinterface 41 1 0
    //   78: return
    //   79: aload_0
    //   80: getfield 12	com/google/android/gms/common/api/internal/zzbb:zzflx	Lcom/google/android/gms/common/api/internal/zzar;
    //   83: getfield 27	com/google/android/gms/common/api/internal/zzar:zzfke	Ljava/util/concurrent/locks/Lock;
    //   86: invokeinterface 41 1 0
    //   91: aload_2
    //   92: athrow
    // Local variable table:
    //   start	length	slot	name	signature
    //   0	93	0	this	zzbb
    //   15	2	1	bool	boolean
    //   50	1	2	localObject	Object
    //   54	38	2	localRuntimeException	RuntimeException
    // Exception table:
    //   from	to	target	type
    //   12	16	50	finally
    //   33	37	50	finally
    //   55	66	50	finally
    //   12	16	54	java/lang/RuntimeException
    //   33	37	54	java/lang/RuntimeException
  }
  
  @X
  public abstract void zzagz();
}
