package com.google.android.gms.common.api.internal;

import com.google.android.gms.common.api.Result;

public final class zzdh
  implements Runnable
{
  public zzdh(zzdg paramZzdg, Result paramResult) {}
  
  /* Error */
  @b.b.a.X
  public final void run()
  {
    // Byte code:
    //   0: getstatic 30	com/google/android/gms/common/api/internal/zzs:zzfje	Ljava/lang/ThreadLocal;
    //   3: iconst_1
    //   4: invokestatic 36	java/lang/Boolean:valueOf	(Z)Ljava/lang/Boolean;
    //   7: invokevirtual 42	java/lang/ThreadLocal:set	(Ljava/lang/Object;)V
    //   10: aload_0
    //   11: getfield 14	com/google/android/gms/common/api/internal/zzdh:zzfpp	Lcom/google/android/gms/common/api/internal/zzdg;
    //   14: getfield 48	com/google/android/gms/common/api/internal/zzdg:zzfph	Lcom/google/android/gms/common/api/ResultTransform;
    //   17: aload_0
    //   18: getfield 16	com/google/android/gms/common/api/internal/zzdh:zzfpo	Lcom/google/android/gms/common/api/Result;
    //   21: invokevirtual 54	com/google/android/gms/common/api/ResultTransform:onSuccess	(Lcom/google/android/gms/common/api/Result;)Lcom/google/android/gms/common/api/PendingResult;
    //   24: astore_1
    //   25: aload_0
    //   26: getfield 14	com/google/android/gms/common/api/internal/zzdh:zzfpp	Lcom/google/android/gms/common/api/internal/zzdg;
    //   29: getfield 58	com/google/android/gms/common/api/internal/zzdg:zzfpm	Lcom/google/android/gms/common/api/internal/zzdi;
    //   32: aload_0
    //   33: getfield 14	com/google/android/gms/common/api/internal/zzdh:zzfpp	Lcom/google/android/gms/common/api/internal/zzdg;
    //   36: getfield 58	com/google/android/gms/common/api/internal/zzdg:zzfpm	Lcom/google/android/gms/common/api/internal/zzdi;
    //   39: iconst_0
    //   40: aload_1
    //   41: invokevirtual 64	android/os/Handler:obtainMessage	(ILjava/lang/Object;)Landroid/os/Message;
    //   44: invokevirtual 68	android/os/Handler:sendMessage	(Landroid/os/Message;)Z
    //   47: pop
    //   48: getstatic 30	com/google/android/gms/common/api/internal/zzs:zzfje	Ljava/lang/ThreadLocal;
    //   51: iconst_0
    //   52: invokestatic 36	java/lang/Boolean:valueOf	(Z)Ljava/lang/Boolean;
    //   55: invokevirtual 42	java/lang/ThreadLocal:set	(Ljava/lang/Object;)V
    //   58: aload_0
    //   59: getfield 14	com/google/android/gms/common/api/internal/zzdh:zzfpp	Lcom/google/android/gms/common/api/internal/zzdg;
    //   62: astore_1
    //   63: aload_0
    //   64: getfield 16	com/google/android/gms/common/api/internal/zzdh:zzfpo	Lcom/google/android/gms/common/api/Result;
    //   67: invokestatic 72	com/google/android/gms/common/api/internal/zzdg:zzd	(Lcom/google/android/gms/common/api/Result;)V
    //   70: aload_0
    //   71: getfield 14	com/google/android/gms/common/api/internal/zzdh:zzfpp	Lcom/google/android/gms/common/api/internal/zzdg;
    //   74: getfield 76	com/google/android/gms/common/api/internal/zzdg:zzfjh	Ljava/lang/ref/WeakReference;
    //   77: invokevirtual 82	java/lang/ref/WeakReference:get	()Ljava/lang/Object;
    //   80: checkcast 84	com/google/android/gms/common/api/GoogleApiClient
    //   83: astore_1
    //   84: aload_1
    //   85: ifnull +11 -> 96
    //   88: aload_1
    //   89: aload_0
    //   90: getfield 14	com/google/android/gms/common/api/internal/zzdh:zzfpp	Lcom/google/android/gms/common/api/internal/zzdg;
    //   93: invokevirtual 88	com/google/android/gms/common/api/GoogleApiClient:zzb	(Lcom/google/android/gms/common/api/internal/zzdg;)V
    //   96: return
    //   97: astore_1
    //   98: goto +76 -> 174
    //   101: astore_1
    //   102: aload_0
    //   103: getfield 14	com/google/android/gms/common/api/internal/zzdh:zzfpp	Lcom/google/android/gms/common/api/internal/zzdg;
    //   106: getfield 58	com/google/android/gms/common/api/internal/zzdg:zzfpm	Lcom/google/android/gms/common/api/internal/zzdi;
    //   109: aload_0
    //   110: getfield 14	com/google/android/gms/common/api/internal/zzdh:zzfpp	Lcom/google/android/gms/common/api/internal/zzdg;
    //   113: getfield 58	com/google/android/gms/common/api/internal/zzdg:zzfpm	Lcom/google/android/gms/common/api/internal/zzdi;
    //   116: iconst_1
    //   117: aload_1
    //   118: invokevirtual 64	android/os/Handler:obtainMessage	(ILjava/lang/Object;)Landroid/os/Message;
    //   121: invokevirtual 68	android/os/Handler:sendMessage	(Landroid/os/Message;)Z
    //   124: pop
    //   125: getstatic 30	com/google/android/gms/common/api/internal/zzs:zzfje	Ljava/lang/ThreadLocal;
    //   128: iconst_0
    //   129: invokestatic 36	java/lang/Boolean:valueOf	(Z)Ljava/lang/Boolean;
    //   132: invokevirtual 42	java/lang/ThreadLocal:set	(Ljava/lang/Object;)V
    //   135: aload_0
    //   136: getfield 14	com/google/android/gms/common/api/internal/zzdh:zzfpp	Lcom/google/android/gms/common/api/internal/zzdg;
    //   139: astore_1
    //   140: aload_0
    //   141: getfield 16	com/google/android/gms/common/api/internal/zzdh:zzfpo	Lcom/google/android/gms/common/api/Result;
    //   144: invokestatic 72	com/google/android/gms/common/api/internal/zzdg:zzd	(Lcom/google/android/gms/common/api/Result;)V
    //   147: aload_0
    //   148: getfield 14	com/google/android/gms/common/api/internal/zzdh:zzfpp	Lcom/google/android/gms/common/api/internal/zzdg;
    //   151: getfield 76	com/google/android/gms/common/api/internal/zzdg:zzfjh	Ljava/lang/ref/WeakReference;
    //   154: invokevirtual 82	java/lang/ref/WeakReference:get	()Ljava/lang/Object;
    //   157: checkcast 84	com/google/android/gms/common/api/GoogleApiClient
    //   160: astore_1
    //   161: aload_1
    //   162: ifnull +11 -> 173
    //   165: aload_1
    //   166: aload_0
    //   167: getfield 14	com/google/android/gms/common/api/internal/zzdh:zzfpp	Lcom/google/android/gms/common/api/internal/zzdg;
    //   170: invokevirtual 88	com/google/android/gms/common/api/GoogleApiClient:zzb	(Lcom/google/android/gms/common/api/internal/zzdg;)V
    //   173: return
    //   174: getstatic 30	com/google/android/gms/common/api/internal/zzs:zzfje	Ljava/lang/ThreadLocal;
    //   177: iconst_0
    //   178: invokestatic 36	java/lang/Boolean:valueOf	(Z)Ljava/lang/Boolean;
    //   181: invokevirtual 42	java/lang/ThreadLocal:set	(Ljava/lang/Object;)V
    //   184: aload_0
    //   185: getfield 14	com/google/android/gms/common/api/internal/zzdh:zzfpp	Lcom/google/android/gms/common/api/internal/zzdg;
    //   188: astore_2
    //   189: aload_0
    //   190: getfield 16	com/google/android/gms/common/api/internal/zzdh:zzfpo	Lcom/google/android/gms/common/api/Result;
    //   193: invokestatic 72	com/google/android/gms/common/api/internal/zzdg:zzd	(Lcom/google/android/gms/common/api/Result;)V
    //   196: aload_0
    //   197: getfield 14	com/google/android/gms/common/api/internal/zzdh:zzfpp	Lcom/google/android/gms/common/api/internal/zzdg;
    //   200: getfield 76	com/google/android/gms/common/api/internal/zzdg:zzfjh	Ljava/lang/ref/WeakReference;
    //   203: invokevirtual 82	java/lang/ref/WeakReference:get	()Ljava/lang/Object;
    //   206: checkcast 84	com/google/android/gms/common/api/GoogleApiClient
    //   209: astore_2
    //   210: aload_2
    //   211: ifnull +11 -> 222
    //   214: aload_2
    //   215: aload_0
    //   216: getfield 14	com/google/android/gms/common/api/internal/zzdh:zzfpp	Lcom/google/android/gms/common/api/internal/zzdg;
    //   219: invokevirtual 88	com/google/android/gms/common/api/GoogleApiClient:zzb	(Lcom/google/android/gms/common/api/internal/zzdg;)V
    //   222: aload_1
    //   223: athrow
    // Local variable table:
    //   start	length	slot	name	signature
    //   0	224	0	this	zzdh
    //   24	65	1	localObject1	Object
    //   97	1	1	localObject2	Object
    //   101	17	1	localRuntimeException	RuntimeException
    //   139	84	1	localObject3	Object
    //   188	27	2	localObject4	Object
    // Exception table:
    //   from	to	target	type
    //   0	48	97	finally
    //   102	125	97	finally
    //   0	48	101	java/lang/RuntimeException
  }
}
