package com.google.android.gms.internal;

import android.content.ContentValues;
import android.content.Context;
import android.database.Cursor;
import android.database.sqlite.SQLiteDatabase;
import android.database.sqlite.SQLiteException;
import android.text.TextUtils;
import b.b.a.X;
import b.b.x.n.b;
import com.google.android.gms.common.internal.zzbp;
import com.google.android.gms.common.util.zzd;
import f.a.a.a.a;
import java.io.File;
import java.io.IOException;
import java.util.ArrayList;
import java.util.Collections;
import java.util.HashSet;
import java.util.Iterator;
import java.util.List;
import java.util.Map;
import java.util.Map.Entry;
import java.util.Set;

public final class zzcay
  extends zzcdu
{
  public static final Map<String, String> zzimr;
  public static final Map<String, String> zzims;
  public static final Map<String, String> zzimt;
  public static final Map<String, String> zzimu;
  public static final Map<String, String> zzimv;
  public final zzcbb zzimw;
  public final zzcfq zzimx = new zzcfq(zzvx());
  
  static
  {
    b localB = new b(1);
    zzimr = localB;
    localB.put("origin", "ALTER TABLE user_attributes ADD COLUMN origin TEXT;");
    localB = new b(18);
    zzims = localB;
    localB.put("app_version", "ALTER TABLE apps ADD COLUMN app_version TEXT;");
    zzims.put("app_store", "ALTER TABLE apps ADD COLUMN app_store TEXT;");
    zzims.put("gmp_version", "ALTER TABLE apps ADD COLUMN gmp_version INTEGER;");
    zzims.put("dev_cert_hash", "ALTER TABLE apps ADD COLUMN dev_cert_hash INTEGER;");
    zzims.put("measurement_enabled", "ALTER TABLE apps ADD COLUMN measurement_enabled INTEGER;");
    zzims.put("last_bundle_start_timestamp", "ALTER TABLE apps ADD COLUMN last_bundle_start_timestamp INTEGER;");
    zzims.put("day", "ALTER TABLE apps ADD COLUMN day INTEGER;");
    zzims.put("daily_public_events_count", "ALTER TABLE apps ADD COLUMN daily_public_events_count INTEGER;");
    zzims.put("daily_events_count", "ALTER TABLE apps ADD COLUMN daily_events_count INTEGER;");
    zzims.put("daily_conversions_count", "ALTER TABLE apps ADD COLUMN daily_conversions_count INTEGER;");
    zzims.put("remote_config", "ALTER TABLE apps ADD COLUMN remote_config BLOB;");
    zzims.put("config_fetched_time", "ALTER TABLE apps ADD COLUMN config_fetched_time INTEGER;");
    zzims.put("failed_config_fetch_time", "ALTER TABLE apps ADD COLUMN failed_config_fetch_time INTEGER;");
    zzims.put("app_version_int", "ALTER TABLE apps ADD COLUMN app_version_int INTEGER;");
    zzims.put("firebase_instance_id", "ALTER TABLE apps ADD COLUMN firebase_instance_id TEXT;");
    zzims.put("daily_error_events_count", "ALTER TABLE apps ADD COLUMN daily_error_events_count INTEGER;");
    zzims.put("daily_realtime_events_count", "ALTER TABLE apps ADD COLUMN daily_realtime_events_count INTEGER;");
    zzims.put("health_monitor_sample", "ALTER TABLE apps ADD COLUMN health_monitor_sample TEXT;");
    zzims.put("android_id", "ALTER TABLE apps ADD COLUMN android_id INTEGER;");
    localB = new b(1);
    zzimt = localB;
    localB.put("realtime", "ALTER TABLE raw_events ADD COLUMN realtime INTEGER;");
    localB = new b(1);
    zzimu = localB;
    localB.put("has_realtime", "ALTER TABLE queue ADD COLUMN has_realtime INTEGER;");
    localB = new b(1);
    zzimv = localB;
    localB.put("previous_install_count", "ALTER TABLE app2 ADD COLUMN previous_install_count INTEGER;");
  }
  
  public zzcay(zzccw paramZzccw)
  {
    super(paramZzccw);
    paramZzccw = zzcax.zzawi();
    zzimw = new zzcbb(this, getContext(), paramZzccw);
  }
  
  /* Error */
  @X
  private final long zza(String paramString, String[] paramArrayOfString, long paramLong)
  {
    // Byte code:
    //   0: aload_0
    //   1: invokevirtual 174	com/google/android/gms/internal/zzcay:getWritableDatabase	()Landroid/database/sqlite/SQLiteDatabase;
    //   4: astore 7
    //   6: aconst_null
    //   7: astore 6
    //   9: aconst_null
    //   10: astore 5
    //   12: aload 7
    //   14: aload_1
    //   15: aload_2
    //   16: invokevirtual 180	android/database/sqlite/SQLiteDatabase:rawQuery	(Ljava/lang/String;[Ljava/lang/String;)Landroid/database/Cursor;
    //   19: astore_2
    //   20: aload_2
    //   21: astore 5
    //   23: aload_2
    //   24: astore 6
    //   26: aload_2
    //   27: invokeinterface 186 1 0
    //   32: ifeq +25 -> 57
    //   35: aload_2
    //   36: astore 5
    //   38: aload_2
    //   39: astore 6
    //   41: aload_2
    //   42: iconst_0
    //   43: invokeinterface 190 2 0
    //   48: lstore_3
    //   49: aload_2
    //   50: invokeinterface 193 1 0
    //   55: lload_3
    //   56: lreturn
    //   57: aload_2
    //   58: invokeinterface 193 1 0
    //   63: lload_3
    //   64: lreturn
    //   65: astore_1
    //   66: goto +28 -> 94
    //   69: astore_2
    //   70: aload 6
    //   72: astore 5
    //   74: aload_0
    //   75: invokevirtual 197	com/google/android/gms/internal/zzcdt:zzaul	()Lcom/google/android/gms/internal/zzcbw;
    //   78: invokevirtual 203	com/google/android/gms/internal/zzcbw:zzayd	()Lcom/google/android/gms/internal/zzcby;
    //   81: ldc -51
    //   83: aload_1
    //   84: aload_2
    //   85: invokevirtual 211	com/google/android/gms/internal/zzcby:zze	(Ljava/lang/String;Ljava/lang/Object;Ljava/lang/Object;)V
    //   88: aload 6
    //   90: astore 5
    //   92: aload_2
    //   93: athrow
    //   94: aload 5
    //   96: ifnull +10 -> 106
    //   99: aload 5
    //   101: invokeinterface 193 1 0
    //   106: aload_1
    //   107: athrow
    // Local variable table:
    //   start	length	slot	name	signature
    //   0	108	0	this	zzcay
    //   0	108	1	paramString	String
    //   0	108	2	paramArrayOfString	String[]
    //   0	108	3	paramLong	long
    //   10	90	5	arrayOfString1	String[]
    //   7	82	6	arrayOfString2	String[]
    //   4	9	7	localSQLiteDatabase	SQLiteDatabase
    // Exception table:
    //   from	to	target	type
    //   12	20	65	finally
    //   26	35	65	finally
    //   41	49	65	finally
    //   74	88	65	finally
    //   92	94	65	finally
    //   12	20	69	android/database/sqlite/SQLiteException
    //   26	35	69	android/database/sqlite/SQLiteException
    //   41	49	69	android/database/sqlite/SQLiteException
  }
  
  @X
  private final Object zza(Cursor paramCursor, int paramInt)
  {
    int i = paramCursor.getType(paramInt);
    if (i != 0)
    {
      if (i != 1)
      {
        if (i != 2)
        {
          if (i != 3)
          {
            if (i != 4)
            {
              zzaul().zzayd().zzj("Loaded invalid unknown value type, ignoring it", Integer.valueOf(i));
              return null;
            }
            zzaul().zzayd().log("Loaded invalid blob type value, ignoring it");
            return null;
          }
          return paramCursor.getString(paramInt);
        }
        return Double.valueOf(paramCursor.getDouble(paramInt));
      }
      return Long.valueOf(paramCursor.getLong(paramInt));
    }
    zzaul().zzayd().log("Loaded invalid null value from database");
    return null;
  }
  
  @X
  public static void zza(ContentValues paramContentValues, String paramString, Object paramObject)
  {
    zzbp.zzgg(paramString);
    zzbp.zzu(paramObject);
    if ((paramObject instanceof String))
    {
      paramContentValues.put(paramString, (String)paramObject);
      return;
    }
    if ((paramObject instanceof Long))
    {
      paramContentValues.put(paramString, (Long)paramObject);
      return;
    }
    if ((paramObject instanceof Double))
    {
      paramContentValues.put(paramString, (Double)paramObject);
      return;
    }
    throw new IllegalArgumentException("Invalid value type");
  }
  
  public static void zza(zzcbw paramZzcbw, SQLiteDatabase paramSQLiteDatabase)
  {
    if (paramZzcbw != null)
    {
      paramSQLiteDatabase = new File(paramSQLiteDatabase.getPath());
      if (!paramSQLiteDatabase.setReadable(false, false)) {
        paramZzcbw.zzayf().log("Failed to turn off database read permission");
      }
      if (!paramSQLiteDatabase.setWritable(false, false)) {
        paramZzcbw.zzayf().log("Failed to turn off database write permission");
      }
      if (!paramSQLiteDatabase.setReadable(true, true)) {
        paramZzcbw.zzayf().log("Failed to turn on database read permission for owner");
      }
      if (!paramSQLiteDatabase.setWritable(true, true)) {
        paramZzcbw.zzayf().log("Failed to turn on database write permission for owner");
      }
      return;
    }
    throw new IllegalArgumentException("Monitor must not be null");
  }
  
  @X
  public static void zza(zzcbw paramZzcbw, SQLiteDatabase paramSQLiteDatabase, String paramString1, String paramString2, String paramString3, Map<String, String> paramMap)
    throws SQLiteException
  {
    if (paramZzcbw != null)
    {
      if (!zza(paramZzcbw, paramSQLiteDatabase, paramString1)) {
        paramSQLiteDatabase.execSQL(paramString2);
      }
      try
      {
        zza(paramZzcbw, paramSQLiteDatabase, paramString1, paramString3, paramMap);
        return;
      }
      catch (SQLiteException paramSQLiteDatabase)
      {
        paramZzcbw.zzayd().zzj("Failed to verify columns on table that was just created", paramString1);
        throw paramSQLiteDatabase;
      }
    }
    throw new IllegalArgumentException("Monitor must not be null");
  }
  
  @X
  public static void zza(zzcbw paramZzcbw, SQLiteDatabase paramSQLiteDatabase, String paramString1, String paramString2, Map<String, String> paramMap)
    throws SQLiteException
  {
    if (paramZzcbw != null)
    {
      Set localSet = zzb(paramSQLiteDatabase, paramString1);
      String[] arrayOfString = paramString2.split(",");
      int j = arrayOfString.length;
      int i = 0;
      while (i < j)
      {
        paramString2 = arrayOfString[i];
        if (localSet.remove(paramString2))
        {
          i += 1;
        }
        else
        {
          paramZzcbw = new StringBuilder(a.a(paramString2, a.a(paramString1, 35)));
          paramZzcbw.append("Table ");
          paramZzcbw.append(paramString1);
          paramZzcbw.append(" is missing required column: ");
          paramZzcbw.append(paramString2);
          throw new SQLiteException(paramZzcbw.toString());
        }
      }
      if (paramMap != null)
      {
        paramString2 = paramMap.entrySet().iterator();
        while (paramString2.hasNext())
        {
          paramMap = (Map.Entry)paramString2.next();
          if (!localSet.remove(paramMap.getKey())) {
            paramSQLiteDatabase.execSQL((String)paramMap.getValue());
          }
        }
      }
      if (!localSet.isEmpty()) {
        paramZzcbw.zzayf().zze("Table has extra columns. table, columns", paramString1, TextUtils.join(", ", localSet));
      }
      return;
    }
    paramZzcbw = new IllegalArgumentException("Monitor must not be null");
    for (;;)
    {
      throw paramZzcbw;
    }
  }
  
  /* Error */
  @X
  public static boolean zza(zzcbw paramZzcbw, SQLiteDatabase paramSQLiteDatabase, String paramString)
  {
    // Byte code:
    //   0: aload_0
    //   1: ifnull +111 -> 112
    //   4: aconst_null
    //   5: astore 5
    //   7: aconst_null
    //   8: astore 4
    //   10: aload_1
    //   11: ldc_w 406
    //   14: iconst_1
    //   15: anewarray 269	java/lang/String
    //   18: dup
    //   19: iconst_0
    //   20: ldc_w 408
    //   23: aastore
    //   24: ldc_w 410
    //   27: iconst_1
    //   28: anewarray 269	java/lang/String
    //   31: dup
    //   32: iconst_0
    //   33: aload_2
    //   34: aastore
    //   35: aconst_null
    //   36: aconst_null
    //   37: aconst_null
    //   38: invokevirtual 414	android/database/sqlite/SQLiteDatabase:query	(Ljava/lang/String;[Ljava/lang/String;Ljava/lang/String;[Ljava/lang/String;Ljava/lang/String;Ljava/lang/String;Ljava/lang/String;)Landroid/database/Cursor;
    //   41: astore_1
    //   42: aload_1
    //   43: astore 4
    //   45: aload_1
    //   46: astore 5
    //   48: aload_1
    //   49: invokeinterface 186 1 0
    //   54: istore_3
    //   55: aload_1
    //   56: invokeinterface 193 1 0
    //   61: iload_3
    //   62: ireturn
    //   63: astore_0
    //   64: goto +34 -> 98
    //   67: astore_1
    //   68: aload 5
    //   70: astore 4
    //   72: aload_0
    //   73: invokevirtual 300	com/google/android/gms/internal/zzcbw:zzayf	()Lcom/google/android/gms/internal/zzcby;
    //   76: ldc_w 416
    //   79: aload_2
    //   80: aload_1
    //   81: invokevirtual 211	com/google/android/gms/internal/zzcby:zze	(Ljava/lang/String;Ljava/lang/Object;Ljava/lang/Object;)V
    //   84: aload 5
    //   86: ifnull +10 -> 96
    //   89: aload 5
    //   91: invokeinterface 193 1 0
    //   96: iconst_0
    //   97: ireturn
    //   98: aload 4
    //   100: ifnull +10 -> 110
    //   103: aload 4
    //   105: invokeinterface 193 1 0
    //   110: aload_0
    //   111: athrow
    //   112: new 282	java/lang/IllegalArgumentException
    //   115: dup
    //   116: ldc_w 313
    //   119: invokespecial 286	java/lang/IllegalArgumentException:<init>	(Ljava/lang/String;)V
    //   122: athrow
    // Local variable table:
    //   start	length	slot	name	signature
    //   0	123	0	paramZzcbw	zzcbw
    //   0	123	1	paramSQLiteDatabase	SQLiteDatabase
    //   0	123	2	paramString	String
    //   54	8	3	bool	boolean
    //   8	96	4	localSQLiteDatabase1	SQLiteDatabase
    //   5	85	5	localSQLiteDatabase2	SQLiteDatabase
    // Exception table:
    //   from	to	target	type
    //   10	42	63	finally
    //   48	55	63	finally
    //   72	84	63	finally
    //   10	42	67	android/database/sqlite/SQLiteException
    //   48	55	67	android/database/sqlite/SQLiteException
  }
  
  @X
  private final boolean zza(String paramString, int paramInt, zzcfy paramZzcfy)
  {
    zzwk();
    zzuj();
    zzbp.zzgg(paramString);
    zzbp.zzu(paramZzcfy);
    if (TextUtils.isEmpty(zzixo))
    {
      zzaul().zzayf().zzd("Event filter had no event name. Audience definition ignored. appId, audienceId, filterId", zzcbw.zzjf(paramString), Integer.valueOf(paramInt), String.valueOf(zzixn));
      return false;
    }
    try
    {
      byte[] arrayOfByte = new byte[paramZzcfy.zzhi()];
      Object localObject = zzeyf.zzn(arrayOfByte, 0, arrayOfByte.length);
      paramZzcfy.zza((zzeyf)localObject);
      ((zzeyf)localObject).zzctn();
      localObject = new ContentValues();
      ((ContentValues)localObject).put("app_id", paramString);
      ((ContentValues)localObject).put("audience_id", Integer.valueOf(paramInt));
      ((ContentValues)localObject).put("filter_id", zzixn);
      ((ContentValues)localObject).put("event_name", zzixo);
      ((ContentValues)localObject).put("data", arrayOfByte);
      try
      {
        if (getWritableDatabase().insertWithOnConflict("event_filters", null, (ContentValues)localObject, 5) == -1L) {
          zzaul().zzayd().zzj("Failed to insert event filter (got -1). appId", zzcbw.zzjf(paramString));
        }
        return true;
      }
      catch (SQLiteException paramZzcfy)
      {
        zzaul().zzayd().zze("Error storing event filter. appId", zzcbw.zzjf(paramString), paramZzcfy);
        return false;
      }
      return false;
    }
    catch (IOException paramZzcfy)
    {
      zzaul().zzayd().zze("Configuration loss. Failed to serialize event filter. appId", zzcbw.zzjf(paramString), paramZzcfy);
    }
  }
  
  @X
  private final boolean zza(String paramString, int paramInt, zzcgb paramZzcgb)
  {
    zzwk();
    zzuj();
    zzbp.zzgg(paramString);
    zzbp.zzu(paramZzcgb);
    if (TextUtils.isEmpty(zziyd))
    {
      zzaul().zzayf().zzd("Property filter had no property name. Audience definition ignored. appId, audienceId, filterId", zzcbw.zzjf(paramString), Integer.valueOf(paramInt), String.valueOf(zzixn));
      return false;
    }
    try
    {
      byte[] arrayOfByte = new byte[paramZzcgb.zzhi()];
      Object localObject = zzeyf.zzn(arrayOfByte, 0, arrayOfByte.length);
      paramZzcgb.zza((zzeyf)localObject);
      ((zzeyf)localObject).zzctn();
      localObject = new ContentValues();
      ((ContentValues)localObject).put("app_id", paramString);
      ((ContentValues)localObject).put("audience_id", Integer.valueOf(paramInt));
      ((ContentValues)localObject).put("filter_id", zzixn);
      ((ContentValues)localObject).put("property_name", zziyd);
      ((ContentValues)localObject).put("data", arrayOfByte);
      try
      {
        if (getWritableDatabase().insertWithOnConflict("property_filters", null, (ContentValues)localObject, 5) == -1L)
        {
          zzaul().zzayd().zzj("Failed to insert property filter (got -1). appId", zzcbw.zzjf(paramString));
          return false;
        }
        return true;
      }
      catch (SQLiteException paramZzcgb)
      {
        zzaul().zzayd().zze("Error storing property filter. appId", zzcbw.zzjf(paramString), paramZzcgb);
        return false;
      }
      return false;
    }
    catch (IOException paramZzcgb)
    {
      zzaul().zzayd().zze("Configuration loss. Failed to serialize property filter. appId", zzcbw.zzjf(paramString), paramZzcgb);
    }
  }
  
  private final boolean zzaxq()
  {
    return getContext().getDatabasePath(zzcax.zzawi()).exists();
  }
  
  /* Error */
  @X
  private final long zzb(String paramString, String[] paramArrayOfString)
  {
    // Byte code:
    //   0: aload_0
    //   1: invokevirtual 174	com/google/android/gms/internal/zzcay:getWritableDatabase	()Landroid/database/sqlite/SQLiteDatabase;
    //   4: astore 7
    //   6: aconst_null
    //   7: astore 6
    //   9: aconst_null
    //   10: astore 5
    //   12: aload 7
    //   14: aload_1
    //   15: aload_2
    //   16: invokevirtual 180	android/database/sqlite/SQLiteDatabase:rawQuery	(Ljava/lang/String;[Ljava/lang/String;)Landroid/database/Cursor;
    //   19: astore_2
    //   20: aload_2
    //   21: astore 5
    //   23: aload_2
    //   24: astore 6
    //   26: aload_2
    //   27: invokeinterface 186 1 0
    //   32: ifeq +25 -> 57
    //   35: aload_2
    //   36: astore 5
    //   38: aload_2
    //   39: astore 6
    //   41: aload_2
    //   42: iconst_0
    //   43: invokeinterface 190 2 0
    //   48: lstore_3
    //   49: aload_2
    //   50: invokeinterface 193 1 0
    //   55: lload_3
    //   56: lreturn
    //   57: aload_2
    //   58: astore 5
    //   60: aload_2
    //   61: astore 6
    //   63: new 170	android/database/sqlite/SQLiteException
    //   66: dup
    //   67: ldc_w 540
    //   70: invokespecial 365	android/database/sqlite/SQLiteException:<init>	(Ljava/lang/String;)V
    //   73: athrow
    //   74: astore_1
    //   75: goto +28 -> 103
    //   78: astore_2
    //   79: aload 6
    //   81: astore 5
    //   83: aload_0
    //   84: invokevirtual 197	com/google/android/gms/internal/zzcdt:zzaul	()Lcom/google/android/gms/internal/zzcbw;
    //   87: invokevirtual 203	com/google/android/gms/internal/zzcbw:zzayd	()Lcom/google/android/gms/internal/zzcby;
    //   90: ldc -51
    //   92: aload_1
    //   93: aload_2
    //   94: invokevirtual 211	com/google/android/gms/internal/zzcby:zze	(Ljava/lang/String;Ljava/lang/Object;Ljava/lang/Object;)V
    //   97: aload 6
    //   99: astore 5
    //   101: aload_2
    //   102: athrow
    //   103: aload 5
    //   105: ifnull +10 -> 115
    //   108: aload 5
    //   110: invokeinterface 193 1 0
    //   115: aload_1
    //   116: athrow
    // Local variable table:
    //   start	length	slot	name	signature
    //   0	117	0	this	zzcay
    //   0	117	1	paramString	String
    //   0	117	2	paramArrayOfString	String[]
    //   48	8	3	l	long
    //   10	99	5	arrayOfString1	String[]
    //   7	91	6	arrayOfString2	String[]
    //   4	9	7	localSQLiteDatabase	SQLiteDatabase
    // Exception table:
    //   from	to	target	type
    //   12	20	74	finally
    //   26	35	74	finally
    //   41	49	74	finally
    //   63	74	74	finally
    //   83	97	74	finally
    //   101	103	74	finally
    //   12	20	78	android/database/sqlite/SQLiteException
    //   26	35	78	android/database/sqlite/SQLiteException
    //   41	49	78	android/database/sqlite/SQLiteException
    //   63	74	78	android/database/sqlite/SQLiteException
  }
  
  @X
  public static Set<String> zzb(SQLiteDatabase paramSQLiteDatabase, String paramString)
  {
    HashSet localHashSet = new HashSet();
    paramSQLiteDatabase = paramSQLiteDatabase.rawQuery(a.a(a.a(paramString, 22), "SELECT * FROM ", paramString, " LIMIT 0"), null);
    try
    {
      Collections.addAll(localHashSet, paramSQLiteDatabase.getColumnNames());
      return localHashSet;
    }
    finally
    {
      paramSQLiteDatabase.close();
    }
  }
  
  private final boolean zzc(String paramString, List<Integer> paramList)
  {
    zzbp.zzgg(paramString);
    zzwk();
    zzuj();
    SQLiteDatabase localSQLiteDatabase = getWritableDatabase();
    try
    {
      long l = zzb("select count(1) from audience_filter_values where app_id=?", new String[] { paramString });
      int j = Math.max(0, Math.min(2000, zzaun().zzb(paramString, zzcbm.zzipg)));
      if (l <= j) {
        return false;
      }
      ArrayList localArrayList = new ArrayList();
      int i = 0;
      while (i < paramList.size())
      {
        Integer localInteger = (Integer)paramList.get(i);
        if (localInteger != null)
        {
          localArrayList.add(Integer.toString(localInteger.intValue()));
          i += 1;
        }
        else
        {
          return false;
        }
      }
      paramList = TextUtils.join(",", localArrayList);
      paramList = a.a(a.a(paramList, 2), "(", paramList, ")");
      return localSQLiteDatabase.delete("audience_filter_values", a.a(a.a(paramList, 140), "audience_id in (select audience_id from audience_filter_values where app_id=? and audience_id not in ", paramList, " order by rowid desc limit -1 offset ?)"), new String[] { paramString, Integer.toString(j) }) > 0;
    }
    catch (SQLiteException paramList)
    {
      zzaul().zzayd().zze("Database error querying filters. appId", zzcbw.zzjf(paramString), paramList);
    }
    return false;
  }
  
  @X
  public final void beginTransaction()
  {
    zzwk();
    getWritableDatabase().beginTransaction();
  }
  
  @X
  public final void endTransaction()
  {
    zzwk();
    getWritableDatabase().endTransaction();
  }
  
  @X
  public final SQLiteDatabase getWritableDatabase()
  {
    zzuj();
    try
    {
      SQLiteDatabase localSQLiteDatabase = zzimw.getWritableDatabase();
      return localSQLiteDatabase;
    }
    catch (SQLiteException localSQLiteException)
    {
      zzaul().zzayf().zzj("Error opening database", localSQLiteException);
      throw localSQLiteException;
    }
  }
  
  @X
  public final void setTransactionSuccessful()
  {
    zzwk();
    getWritableDatabase().setTransactionSuccessful();
  }
  
  /* Error */
  public final long zza(zzcgk paramZzcgk)
    throws IOException
  {
    // Byte code:
    //   0: aload_0
    //   1: invokevirtual 425	com/google/android/gms/internal/zzcdt:zzuj	()V
    //   4: aload_0
    //   5: invokevirtual 422	com/google/android/gms/internal/zzcdu:zzwk	()V
    //   8: aload_1
    //   9: invokestatic 267	com/google/android/gms/common/internal/zzbp:zzu	(Ljava/lang/Object;)Ljava/lang/Object;
    //   12: pop
    //   13: aload_1
    //   14: getfield 644	com/google/android/gms/internal/zzcgk:zzci	Ljava/lang/String;
    //   17: invokestatic 263	com/google/android/gms/common/internal/zzbp:zzgg	(Ljava/lang/String;)Ljava/lang/String;
    //   20: pop
    //   21: aload_1
    //   22: invokevirtual 457	com/google/android/gms/internal/zzeyn:zzhi	()I
    //   25: newarray byte
    //   27: astore 4
    //   29: aload 4
    //   31: iconst_0
    //   32: aload 4
    //   34: arraylength
    //   35: invokestatic 463	com/google/android/gms/internal/zzeyf:zzn	([BII)Lcom/google/android/gms/internal/zzeyf;
    //   38: astore 5
    //   40: aload_1
    //   41: aload 5
    //   43: invokevirtual 645	com/google/android/gms/internal/zzcgk:zza	(Lcom/google/android/gms/internal/zzeyf;)V
    //   46: aload 5
    //   48: invokevirtual 469	com/google/android/gms/internal/zzeyf:zzctn	()V
    //   51: aload_0
    //   52: invokevirtual 649	com/google/android/gms/internal/zzcdt:zzauh	()Lcom/google/android/gms/internal/zzcfw;
    //   55: astore 5
    //   57: aload 4
    //   59: invokestatic 267	com/google/android/gms/common/internal/zzbp:zzu	(Ljava/lang/Object;)Ljava/lang/Object;
    //   62: pop
    //   63: aload 5
    //   65: invokevirtual 652	com/google/android/gms/internal/zzcfw:zzuj	()V
    //   68: ldc_w 654
    //   71: invokestatic 658	com/google/android/gms/internal/zzcfw:zzec	(Ljava/lang/String;)Ljava/security/MessageDigest;
    //   74: astore 6
    //   76: aload 6
    //   78: ifnonnull +22 -> 100
    //   81: aload 5
    //   83: invokevirtual 659	com/google/android/gms/internal/zzcfw:zzaul	()Lcom/google/android/gms/internal/zzcbw;
    //   86: invokevirtual 203	com/google/android/gms/internal/zzcbw:zzayd	()Lcom/google/android/gms/internal/zzcby;
    //   89: ldc_w 661
    //   92: invokevirtual 236	com/google/android/gms/internal/zzcby:log	(Ljava/lang/String;)V
    //   95: lconst_0
    //   96: lstore_2
    //   97: goto +14 -> 111
    //   100: aload 6
    //   102: aload 4
    //   104: invokevirtual 667	java/security/MessageDigest:digest	([B)[B
    //   107: invokestatic 671	com/google/android/gms/internal/zzcfw:zzr	([B)J
    //   110: lstore_2
    //   111: new 271	android/content/ContentValues
    //   114: dup
    //   115: invokespecial 471	android/content/ContentValues:<init>	()V
    //   118: astore 5
    //   120: aload 5
    //   122: ldc_w 473
    //   125: aload_1
    //   126: getfield 644	com/google/android/gms/internal/zzcgk:zzci	Ljava/lang/String;
    //   129: invokevirtual 274	android/content/ContentValues:put	(Ljava/lang/String;Ljava/lang/String;)V
    //   132: aload 5
    //   134: ldc_w 673
    //   137: lload_2
    //   138: invokestatic 254	java/lang/Long:valueOf	(J)Ljava/lang/Long;
    //   141: invokevirtual 277	android/content/ContentValues:put	(Ljava/lang/String;Ljava/lang/Long;)V
    //   144: aload 5
    //   146: ldc_w 675
    //   149: aload 4
    //   151: invokevirtual 487	android/content/ContentValues:put	(Ljava/lang/String;[B)V
    //   154: aload_0
    //   155: invokevirtual 174	com/google/android/gms/internal/zzcay:getWritableDatabase	()Landroid/database/sqlite/SQLiteDatabase;
    //   158: ldc_w 677
    //   161: aconst_null
    //   162: aload 5
    //   164: iconst_4
    //   165: invokevirtual 493	android/database/sqlite/SQLiteDatabase:insertWithOnConflict	(Ljava/lang/String;Ljava/lang/String;Landroid/content/ContentValues;I)J
    //   168: pop2
    //   169: lload_2
    //   170: lreturn
    //   171: astore 4
    //   173: aload_0
    //   174: invokevirtual 197	com/google/android/gms/internal/zzcdt:zzaul	()Lcom/google/android/gms/internal/zzcbw;
    //   177: invokevirtual 203	com/google/android/gms/internal/zzcbw:zzayd	()Lcom/google/android/gms/internal/zzcby;
    //   180: ldc_w 679
    //   183: aload_1
    //   184: getfield 644	com/google/android/gms/internal/zzcgk:zzci	Ljava/lang/String;
    //   187: invokestatic 440	com/google/android/gms/internal/zzcbw:zzjf	(Ljava/lang/String;)Ljava/lang/Object;
    //   190: aload 4
    //   192: invokevirtual 211	com/google/android/gms/internal/zzcby:zze	(Ljava/lang/String;Ljava/lang/Object;Ljava/lang/Object;)V
    //   195: aload 4
    //   197: athrow
    //   198: astore 4
    //   200: aload_0
    //   201: invokevirtual 197	com/google/android/gms/internal/zzcdt:zzaul	()Lcom/google/android/gms/internal/zzcbw;
    //   204: invokevirtual 203	com/google/android/gms/internal/zzcbw:zzayd	()Lcom/google/android/gms/internal/zzcby;
    //   207: ldc_w 681
    //   210: aload_1
    //   211: getfield 644	com/google/android/gms/internal/zzcgk:zzci	Ljava/lang/String;
    //   214: invokestatic 440	com/google/android/gms/internal/zzcbw:zzjf	(Ljava/lang/String;)Ljava/lang/Object;
    //   217: aload 4
    //   219: invokevirtual 211	com/google/android/gms/internal/zzcby:zze	(Ljava/lang/String;Ljava/lang/Object;Ljava/lang/Object;)V
    //   222: aload 4
    //   224: athrow
    // Local variable table:
    //   start	length	slot	name	signature
    //   0	225	0	this	zzcay
    //   0	225	1	paramZzcgk	zzcgk
    //   96	74	2	l	long
    //   27	123	4	arrayOfByte	byte[]
    //   171	25	4	localSQLiteException	SQLiteException
    //   198	25	4	localIOException	IOException
    //   38	125	5	localObject	Object
    //   74	27	6	localMessageDigest	java.security.MessageDigest
    // Exception table:
    //   from	to	target	type
    //   154	169	171	android/database/sqlite/SQLiteException
    //   21	51	198	java/io/IOException
  }
  
  /* Error */
  @X
  public final zzcaz zza(long paramLong, String paramString, boolean paramBoolean1, boolean paramBoolean2, boolean paramBoolean3, boolean paramBoolean4, boolean paramBoolean5)
  {
    // Byte code:
    //   0: aload_3
    //   1: invokestatic 263	com/google/android/gms/common/internal/zzbp:zzgg	(Ljava/lang/String;)Ljava/lang/String;
    //   4: pop
    //   5: aload_0
    //   6: invokevirtual 425	com/google/android/gms/internal/zzcdt:zzuj	()V
    //   9: aload_0
    //   10: invokevirtual 422	com/google/android/gms/internal/zzcdu:zzwk	()V
    //   13: new 684	com/google/android/gms/internal/zzcaz
    //   16: dup
    //   17: invokespecial 685	com/google/android/gms/internal/zzcaz:<init>	()V
    //   20: astore 13
    //   22: aconst_null
    //   23: astore 12
    //   25: aconst_null
    //   26: astore 11
    //   28: aload 11
    //   30: astore 9
    //   32: aload 12
    //   34: astore 10
    //   36: aload_0
    //   37: invokevirtual 174	com/google/android/gms/internal/zzcay:getWritableDatabase	()Landroid/database/sqlite/SQLiteDatabase;
    //   40: astore 14
    //   42: aload 11
    //   44: astore 9
    //   46: aload 12
    //   48: astore 10
    //   50: aload 14
    //   52: ldc_w 687
    //   55: bipush 6
    //   57: anewarray 269	java/lang/String
    //   60: dup
    //   61: iconst_0
    //   62: ldc 63
    //   64: aastore
    //   65: dup
    //   66: iconst_1
    //   67: ldc 71
    //   69: aastore
    //   70: dup
    //   71: iconst_2
    //   72: ldc 67
    //   74: aastore
    //   75: dup
    //   76: iconst_3
    //   77: ldc 75
    //   79: aastore
    //   80: dup
    //   81: iconst_4
    //   82: ldc 99
    //   84: aastore
    //   85: dup
    //   86: iconst_5
    //   87: ldc 103
    //   89: aastore
    //   90: ldc_w 689
    //   93: iconst_1
    //   94: anewarray 269	java/lang/String
    //   97: dup
    //   98: iconst_0
    //   99: aload_3
    //   100: aastore
    //   101: aconst_null
    //   102: aconst_null
    //   103: aconst_null
    //   104: invokevirtual 414	android/database/sqlite/SQLiteDatabase:query	(Ljava/lang/String;[Ljava/lang/String;Ljava/lang/String;[Ljava/lang/String;Ljava/lang/String;Ljava/lang/String;Ljava/lang/String;)Landroid/database/Cursor;
    //   107: astore 11
    //   109: aload 11
    //   111: astore 9
    //   113: aload 11
    //   115: astore 10
    //   117: aload 11
    //   119: invokeinterface 186 1 0
    //   124: ifne +38 -> 162
    //   127: aload 11
    //   129: astore 9
    //   131: aload 11
    //   133: astore 10
    //   135: aload_0
    //   136: invokevirtual 197	com/google/android/gms/internal/zzcdt:zzaul	()Lcom/google/android/gms/internal/zzcbw;
    //   139: invokevirtual 300	com/google/android/gms/internal/zzcbw:zzayf	()Lcom/google/android/gms/internal/zzcby;
    //   142: ldc_w 691
    //   145: aload_3
    //   146: invokestatic 440	com/google/android/gms/internal/zzcbw:zzjf	(Ljava/lang/String;)Ljava/lang/Object;
    //   149: invokevirtual 230	com/google/android/gms/internal/zzcby:zzj	(Ljava/lang/String;Ljava/lang/Object;)V
    //   152: aload 11
    //   154: invokeinterface 193 1 0
    //   159: aload 13
    //   161: areturn
    //   162: aload 11
    //   164: astore 9
    //   166: aload 11
    //   168: astore 10
    //   170: aload 11
    //   172: iconst_0
    //   173: invokeinterface 190 2 0
    //   178: lload_1
    //   179: lcmp
    //   180: ifne +108 -> 288
    //   183: aload 11
    //   185: astore 9
    //   187: aload 11
    //   189: astore 10
    //   191: aload 13
    //   193: aload 11
    //   195: iconst_1
    //   196: invokeinterface 190 2 0
    //   201: putfield 695	com/google/android/gms/internal/zzcaz:zzimz	J
    //   204: aload 11
    //   206: astore 9
    //   208: aload 11
    //   210: astore 10
    //   212: aload 13
    //   214: aload 11
    //   216: iconst_2
    //   217: invokeinterface 190 2 0
    //   222: putfield 698	com/google/android/gms/internal/zzcaz:zzimy	J
    //   225: aload 11
    //   227: astore 9
    //   229: aload 11
    //   231: astore 10
    //   233: aload 13
    //   235: aload 11
    //   237: iconst_3
    //   238: invokeinterface 190 2 0
    //   243: putfield 701	com/google/android/gms/internal/zzcaz:zzina	J
    //   246: aload 11
    //   248: astore 9
    //   250: aload 11
    //   252: astore 10
    //   254: aload 13
    //   256: aload 11
    //   258: iconst_4
    //   259: invokeinterface 190 2 0
    //   264: putfield 704	com/google/android/gms/internal/zzcaz:zzinb	J
    //   267: aload 11
    //   269: astore 9
    //   271: aload 11
    //   273: astore 10
    //   275: aload 13
    //   277: aload 11
    //   279: iconst_5
    //   280: invokeinterface 190 2 0
    //   285: putfield 707	com/google/android/gms/internal/zzcaz:zzinc	J
    //   288: iload 4
    //   290: ifeq +23 -> 313
    //   293: aload 11
    //   295: astore 9
    //   297: aload 11
    //   299: astore 10
    //   301: aload 13
    //   303: aload 13
    //   305: getfield 695	com/google/android/gms/internal/zzcaz:zzimz	J
    //   308: lconst_1
    //   309: ladd
    //   310: putfield 695	com/google/android/gms/internal/zzcaz:zzimz	J
    //   313: iload 5
    //   315: ifeq +23 -> 338
    //   318: aload 11
    //   320: astore 9
    //   322: aload 11
    //   324: astore 10
    //   326: aload 13
    //   328: aload 13
    //   330: getfield 698	com/google/android/gms/internal/zzcaz:zzimy	J
    //   333: lconst_1
    //   334: ladd
    //   335: putfield 698	com/google/android/gms/internal/zzcaz:zzimy	J
    //   338: iload 6
    //   340: ifeq +23 -> 363
    //   343: aload 11
    //   345: astore 9
    //   347: aload 11
    //   349: astore 10
    //   351: aload 13
    //   353: aload 13
    //   355: getfield 701	com/google/android/gms/internal/zzcaz:zzina	J
    //   358: lconst_1
    //   359: ladd
    //   360: putfield 701	com/google/android/gms/internal/zzcaz:zzina	J
    //   363: iload 7
    //   365: ifeq +23 -> 388
    //   368: aload 11
    //   370: astore 9
    //   372: aload 11
    //   374: astore 10
    //   376: aload 13
    //   378: aload 13
    //   380: getfield 704	com/google/android/gms/internal/zzcaz:zzinb	J
    //   383: lconst_1
    //   384: ladd
    //   385: putfield 704	com/google/android/gms/internal/zzcaz:zzinb	J
    //   388: iload 8
    //   390: ifeq +23 -> 413
    //   393: aload 11
    //   395: astore 9
    //   397: aload 11
    //   399: astore 10
    //   401: aload 13
    //   403: aload 13
    //   405: getfield 707	com/google/android/gms/internal/zzcaz:zzinc	J
    //   408: lconst_1
    //   409: ladd
    //   410: putfield 707	com/google/android/gms/internal/zzcaz:zzinc	J
    //   413: aload 11
    //   415: astore 9
    //   417: aload 11
    //   419: astore 10
    //   421: new 271	android/content/ContentValues
    //   424: dup
    //   425: invokespecial 471	android/content/ContentValues:<init>	()V
    //   428: astore 12
    //   430: aload 11
    //   432: astore 9
    //   434: aload 11
    //   436: astore 10
    //   438: aload 12
    //   440: ldc 63
    //   442: lload_1
    //   443: invokestatic 254	java/lang/Long:valueOf	(J)Ljava/lang/Long;
    //   446: invokevirtual 277	android/content/ContentValues:put	(Ljava/lang/String;Ljava/lang/Long;)V
    //   449: aload 11
    //   451: astore 9
    //   453: aload 11
    //   455: astore 10
    //   457: aload 12
    //   459: ldc 67
    //   461: aload 13
    //   463: getfield 698	com/google/android/gms/internal/zzcaz:zzimy	J
    //   466: invokestatic 254	java/lang/Long:valueOf	(J)Ljava/lang/Long;
    //   469: invokevirtual 277	android/content/ContentValues:put	(Ljava/lang/String;Ljava/lang/Long;)V
    //   472: aload 11
    //   474: astore 9
    //   476: aload 11
    //   478: astore 10
    //   480: aload 12
    //   482: ldc 71
    //   484: aload 13
    //   486: getfield 695	com/google/android/gms/internal/zzcaz:zzimz	J
    //   489: invokestatic 254	java/lang/Long:valueOf	(J)Ljava/lang/Long;
    //   492: invokevirtual 277	android/content/ContentValues:put	(Ljava/lang/String;Ljava/lang/Long;)V
    //   495: aload 11
    //   497: astore 9
    //   499: aload 11
    //   501: astore 10
    //   503: aload 12
    //   505: ldc 75
    //   507: aload 13
    //   509: getfield 701	com/google/android/gms/internal/zzcaz:zzina	J
    //   512: invokestatic 254	java/lang/Long:valueOf	(J)Ljava/lang/Long;
    //   515: invokevirtual 277	android/content/ContentValues:put	(Ljava/lang/String;Ljava/lang/Long;)V
    //   518: aload 11
    //   520: astore 9
    //   522: aload 11
    //   524: astore 10
    //   526: aload 12
    //   528: ldc 99
    //   530: aload 13
    //   532: getfield 704	com/google/android/gms/internal/zzcaz:zzinb	J
    //   535: invokestatic 254	java/lang/Long:valueOf	(J)Ljava/lang/Long;
    //   538: invokevirtual 277	android/content/ContentValues:put	(Ljava/lang/String;Ljava/lang/Long;)V
    //   541: aload 11
    //   543: astore 9
    //   545: aload 11
    //   547: astore 10
    //   549: aload 12
    //   551: ldc 103
    //   553: aload 13
    //   555: getfield 707	com/google/android/gms/internal/zzcaz:zzinc	J
    //   558: invokestatic 254	java/lang/Long:valueOf	(J)Ljava/lang/Long;
    //   561: invokevirtual 277	android/content/ContentValues:put	(Ljava/lang/String;Ljava/lang/Long;)V
    //   564: aload 11
    //   566: astore 9
    //   568: aload 11
    //   570: astore 10
    //   572: aload 14
    //   574: ldc_w 687
    //   577: aload 12
    //   579: ldc_w 689
    //   582: iconst_1
    //   583: anewarray 269	java/lang/String
    //   586: dup
    //   587: iconst_0
    //   588: aload_3
    //   589: aastore
    //   590: invokevirtual 711	android/database/sqlite/SQLiteDatabase:update	(Ljava/lang/String;Landroid/content/ContentValues;Ljava/lang/String;[Ljava/lang/String;)I
    //   593: pop
    //   594: aload 11
    //   596: invokeinterface 193 1 0
    //   601: aload 13
    //   603: areturn
    //   604: astore_3
    //   605: goto +43 -> 648
    //   608: astore 11
    //   610: aload 10
    //   612: astore 9
    //   614: aload_0
    //   615: invokevirtual 197	com/google/android/gms/internal/zzcdt:zzaul	()Lcom/google/android/gms/internal/zzcbw;
    //   618: invokevirtual 203	com/google/android/gms/internal/zzcbw:zzayd	()Lcom/google/android/gms/internal/zzcby;
    //   621: ldc_w 713
    //   624: aload_3
    //   625: invokestatic 440	com/google/android/gms/internal/zzcbw:zzjf	(Ljava/lang/String;)Ljava/lang/Object;
    //   628: aload 11
    //   630: invokevirtual 211	com/google/android/gms/internal/zzcby:zze	(Ljava/lang/String;Ljava/lang/Object;Ljava/lang/Object;)V
    //   633: aload 10
    //   635: ifnull +10 -> 645
    //   638: aload 10
    //   640: invokeinterface 193 1 0
    //   645: aload 13
    //   647: areturn
    //   648: aload 9
    //   650: ifnull +10 -> 660
    //   653: aload 9
    //   655: invokeinterface 193 1 0
    //   660: aload_3
    //   661: athrow
    // Local variable table:
    //   start	length	slot	name	signature
    //   0	662	0	this	zzcay
    //   0	662	1	paramLong	long
    //   0	662	3	paramString	String
    //   0	662	4	paramBoolean1	boolean
    //   0	662	5	paramBoolean2	boolean
    //   0	662	6	paramBoolean3	boolean
    //   0	662	7	paramBoolean4	boolean
    //   0	662	8	paramBoolean5	boolean
    //   30	624	9	localObject1	Object
    //   34	605	10	localObject2	Object
    //   26	569	11	localCursor	Cursor
    //   608	21	11	localSQLiteException	SQLiteException
    //   23	555	12	localContentValues	ContentValues
    //   20	626	13	localZzcaz	zzcaz
    //   40	533	14	localSQLiteDatabase	SQLiteDatabase
    // Exception table:
    //   from	to	target	type
    //   36	42	604	finally
    //   50	109	604	finally
    //   117	127	604	finally
    //   135	152	604	finally
    //   170	183	604	finally
    //   191	204	604	finally
    //   212	225	604	finally
    //   233	246	604	finally
    //   254	267	604	finally
    //   275	288	604	finally
    //   301	313	604	finally
    //   326	338	604	finally
    //   351	363	604	finally
    //   376	388	604	finally
    //   401	413	604	finally
    //   421	430	604	finally
    //   438	449	604	finally
    //   457	472	604	finally
    //   480	495	604	finally
    //   503	518	604	finally
    //   526	541	604	finally
    //   549	564	604	finally
    //   572	594	604	finally
    //   614	633	604	finally
    //   36	42	608	android/database/sqlite/SQLiteException
    //   50	109	608	android/database/sqlite/SQLiteException
    //   117	127	608	android/database/sqlite/SQLiteException
    //   135	152	608	android/database/sqlite/SQLiteException
    //   170	183	608	android/database/sqlite/SQLiteException
    //   191	204	608	android/database/sqlite/SQLiteException
    //   212	225	608	android/database/sqlite/SQLiteException
    //   233	246	608	android/database/sqlite/SQLiteException
    //   254	267	608	android/database/sqlite/SQLiteException
    //   275	288	608	android/database/sqlite/SQLiteException
    //   301	313	608	android/database/sqlite/SQLiteException
    //   326	338	608	android/database/sqlite/SQLiteException
    //   351	363	608	android/database/sqlite/SQLiteException
    //   376	388	608	android/database/sqlite/SQLiteException
    //   401	413	608	android/database/sqlite/SQLiteException
    //   421	430	608	android/database/sqlite/SQLiteException
    //   438	449	608	android/database/sqlite/SQLiteException
    //   457	472	608	android/database/sqlite/SQLiteException
    //   480	495	608	android/database/sqlite/SQLiteException
    //   503	518	608	android/database/sqlite/SQLiteException
    //   526	541	608	android/database/sqlite/SQLiteException
    //   549	564	608	android/database/sqlite/SQLiteException
    //   572	594	608	android/database/sqlite/SQLiteException
  }
  
  @X
  public final void zza(zzcar paramZzcar)
  {
    zzbp.zzu(paramZzcar);
    zzuj();
    zzwk();
    ContentValues localContentValues = new ContentValues();
    localContentValues.put("app_id", paramZzcar.getAppId());
    localContentValues.put("app_instance_id", paramZzcar.getAppInstanceId());
    localContentValues.put("gmp_app_id", paramZzcar.getGmpAppId());
    localContentValues.put("resettable_device_id_hash", paramZzcar.zzaup());
    localContentValues.put("last_bundle_index", Long.valueOf(paramZzcar.zzauy()));
    localContentValues.put("last_bundle_start_timestamp", Long.valueOf(paramZzcar.zzaur()));
    localContentValues.put("last_bundle_end_timestamp", Long.valueOf(paramZzcar.zzaus()));
    localContentValues.put("app_version", paramZzcar.zzuo());
    localContentValues.put("app_store", paramZzcar.zzauu());
    localContentValues.put("gmp_version", Long.valueOf(paramZzcar.zzauv()));
    localContentValues.put("dev_cert_hash", Long.valueOf(paramZzcar.zzauw()));
    localContentValues.put("measurement_enabled", Boolean.valueOf(paramZzcar.zzaux()));
    localContentValues.put("day", Long.valueOf(paramZzcar.zzavc()));
    localContentValues.put("daily_public_events_count", Long.valueOf(paramZzcar.zzavd()));
    localContentValues.put("daily_events_count", Long.valueOf(paramZzcar.zzave()));
    localContentValues.put("daily_conversions_count", Long.valueOf(paramZzcar.zzavf()));
    localContentValues.put("config_fetched_time", Long.valueOf(paramZzcar.zzauz()));
    localContentValues.put("failed_config_fetch_time", Long.valueOf(paramZzcar.zzava()));
    localContentValues.put("app_version_int", Long.valueOf(paramZzcar.zzaut()));
    localContentValues.put("firebase_instance_id", paramZzcar.zzauq());
    localContentValues.put("daily_error_events_count", Long.valueOf(paramZzcar.zzavh()));
    localContentValues.put("daily_realtime_events_count", Long.valueOf(paramZzcar.zzavg()));
    localContentValues.put("health_monitor_sample", paramZzcar.zzavi());
    localContentValues.put("android_id", Long.valueOf(paramZzcar.zzavk()));
    try
    {
      SQLiteDatabase localSQLiteDatabase = getWritableDatabase();
      if ((localSQLiteDatabase.update("apps", localContentValues, "app_id = ?", new String[] { paramZzcar.getAppId() }) == 0L) && (localSQLiteDatabase.insertWithOnConflict("apps", null, localContentValues, 5) == -1L)) {
        zzaul().zzayd().zzj("Failed to insert/update app (got -1). appId", zzcbw.zzjf(paramZzcar.getAppId()));
      }
      return;
    }
    catch (SQLiteException localSQLiteException)
    {
      zzaul().zzayd().zze("Error storing app. appId", zzcbw.zzjf(paramZzcar.getAppId()), localSQLiteException);
    }
  }
  
  @X
  public final void zza(zzcbg paramZzcbg)
  {
    zzbp.zzu(paramZzcbg);
    zzuj();
    zzwk();
    ContentValues localContentValues = new ContentValues();
    localContentValues.put("app_id", mAppId);
    localContentValues.put("name", mName);
    localContentValues.put("lifetime_count", Long.valueOf(zzinl));
    localContentValues.put("current_bundle_count", Long.valueOf(zzinm));
    localContentValues.put("last_fire_timestamp", Long.valueOf(zzinn));
    try
    {
      if (getWritableDatabase().insertWithOnConflict("events", null, localContentValues, 5) == -1L) {
        zzaul().zzayd().zzj("Failed to insert/update event aggregates (got -1). appId", zzcbw.zzjf(mAppId));
      }
      return;
    }
    catch (SQLiteException localSQLiteException)
    {
      zzaul().zzayd().zze("Error storing event aggregates. appId", zzcbw.zzjf(mAppId), localSQLiteException);
    }
  }
  
  @X
  public final void zza(String paramString, zzcfx[] paramArrayOfZzcfx)
  {
    zzwk();
    zzuj();
    zzbp.zzgg(paramString);
    zzbp.zzu(paramArrayOfZzcfx);
    localSQLiteDatabase = getWritableDatabase();
    localSQLiteDatabase.beginTransaction();
    try
    {
      zzwk();
      zzuj();
      zzbp.zzgg(paramString);
      localObject1 = getWritableDatabase();
      n = 0;
      ((SQLiteDatabase)localObject1).delete("property_filters", "app_id=?", new String[] { paramString });
      ((SQLiteDatabase)localObject1).delete("event_filters", "app_id=?", new String[] { paramString });
      i1 = paramArrayOfZzcfx.length;
      j = 0;
    }
    finally
    {
      for (;;)
      {
        Object localObject1;
        int n;
        int i1;
        int j;
        Object localObject2;
        int i2;
        int k;
        String str;
        Object localObject3;
        int m;
        int i3;
        localSQLiteDatabase.endTransaction();
        for (;;)
        {
          throw paramString;
        }
        break label607;
        i += 1;
        continue;
        i += 1;
        continue;
        i += 1;
        continue;
        int i = 1;
        continue;
        k += 1;
        continue;
        j += 1;
      }
    }
    if (j < i1)
    {
      localObject2 = paramArrayOfZzcfx[j];
      zzwk();
      zzuj();
      zzbp.zzgg(paramString);
      zzbp.zzu(localObject2);
      zzbp.zzu(zzixl);
      zzbp.zzu(zzixk);
      localObject1 = zzixj;
      if (localObject1 == null)
      {
        zzaul().zzayf().zzj("Audience with no ID. appId", zzcbw.zzjf(paramString));
      }
      else
      {
        i2 = ((Integer)localObject1).intValue();
        localObject1 = zzixl;
        k = localObject1.length;
        i = 0;
        if (i < k)
        {
          if (zzixn != null) {
            break label572;
          }
          localObject1 = zzaul().zzayf();
          str = "Event filter with no ID. Audience definition ignored. appId, audienceId";
          localObject3 = zzcbw.zzjf(paramString);
        }
        for (localObject2 = zzixj;; localObject2 = zzixj)
        {
          ((zzcby)localObject1).zze(str, localObject3, localObject2);
          break label569;
          localObject1 = zzixk;
          k = localObject1.length;
          i = 0;
          if (i >= k) {
            break;
          }
          if (zzixn != null) {
            break label579;
          }
          localObject1 = zzaul().zzayf();
          str = "Property filter with no ID. Audience definition ignored. appId, audienceId";
          localObject3 = zzcbw.zzjf(paramString);
        }
        localObject1 = zzixl;
        k = localObject1.length;
        i = 0;
        if (i >= k) {
          break label593;
        }
        if (zza(paramString, i2, localObject1[i])) {
          break label586;
        }
        i = 0;
        m = i;
        if (i != 0)
        {
          localObject1 = zzixk;
          i3 = localObject1.length;
          k = 0;
          m = i;
          if (k < i3)
          {
            if (zza(paramString, i2, localObject1[k])) {
              break label598;
            }
            m = 0;
          }
        }
        if (m == 0)
        {
          zzwk();
          zzuj();
          zzbp.zzgg(paramString);
          localObject1 = getWritableDatabase();
          ((SQLiteDatabase)localObject1).delete("property_filters", "app_id=? and audience_id=?", new String[] { paramString, String.valueOf(i2) });
          ((SQLiteDatabase)localObject1).delete("event_filters", "app_id=? and audience_id=?", new String[] { paramString, String.valueOf(i2) });
          break label607;
        }
      }
    }
    else
    {
      localObject1 = new ArrayList();
      j = paramArrayOfZzcfx.length;
      i = n;
      while (i < j)
      {
        ((List)localObject1).add(zzixj);
        i += 1;
      }
      zzc(paramString, (List)localObject1);
      localSQLiteDatabase.setTransactionSuccessful();
      localSQLiteDatabase.endTransaction();
      return;
    }
  }
  
  @X
  public final boolean zza(zzcav paramZzcav)
  {
    zzbp.zzu(paramZzcav);
    zzuj();
    zzwk();
    if (zzah(packageName, zzimh.name) == null)
    {
      long l = zzb("SELECT COUNT(1) FROM conditional_properties WHERE app_id=?", new String[] { packageName });
      zzcax.zzawb();
      if (l >= 1000L) {
        return false;
      }
    }
    ContentValues localContentValues = new ContentValues();
    localContentValues.put("app_id", packageName);
    localContentValues.put("origin", zzimg);
    localContentValues.put("name", zzimh.name);
    zza(localContentValues, "value", zzimh.getValue());
    localContentValues.put("active", Boolean.valueOf(zzimj));
    localContentValues.put("trigger_event_name", zzimk);
    localContentValues.put("trigger_timeout", Long.valueOf(zzimm));
    zzauh();
    localContentValues.put("timed_out_event", zzcfw.zza(zziml));
    localContentValues.put("creation_timestamp", Long.valueOf(zzimi));
    zzauh();
    localContentValues.put("triggered_event", zzcfw.zza(zzimn));
    localContentValues.put("triggered_timestamp", Long.valueOf(zzimh.zziwz));
    localContentValues.put("time_to_live", Long.valueOf(zzimo));
    zzauh();
    localContentValues.put("expired_event", zzcfw.zza(zzimp));
    try
    {
      if (getWritableDatabase().insertWithOnConflict("conditional_properties", null, localContentValues, 5) == -1L)
      {
        zzaul().zzayd().zzj("Failed to insert/update conditional user property (got -1)", zzcbw.zzjf(packageName));
        return true;
      }
    }
    catch (SQLiteException localSQLiteException)
    {
      zzaul().zzayd().zze("Error storing conditional user property", zzcbw.zzjf(packageName), localSQLiteException);
    }
    return true;
  }
  
  public final boolean zza(zzcbf paramZzcbf, long paramLong, boolean paramBoolean)
  {
    throw new Runtime("d2j fail translate: java.lang.RuntimeException: can not merge I and Z\n\tat com.googlecode.dex2jar.ir.TypeClass.merge(TypeClass.java:100)\n\tat com.googlecode.dex2jar.ir.ts.TypeTransformer$TypeRef.updateTypeClass(TypeTransformer.java:174)\n\tat com.googlecode.dex2jar.ir.ts.TypeTransformer$TypeAnalyze.copyTypes(TypeTransformer.java:311)\n\tat com.googlecode.dex2jar.ir.ts.TypeTransformer$TypeAnalyze.fixTypes(TypeTransformer.java:226)\n\tat com.googlecode.dex2jar.ir.ts.TypeTransformer$TypeAnalyze.analyze(TypeTransformer.java:207)\n\tat com.googlecode.dex2jar.ir.ts.TypeTransformer.transform(TypeTransformer.java:44)\n\tat com.googlecode.d2j.dex.Dex2jar$2.optimize(Dex2jar.java:162)\n\tat com.googlecode.d2j.dex.Dex2Asm.convertCode(Dex2Asm.java:414)\n\tat com.googlecode.d2j.dex.ExDex2Asm.convertCode(ExDex2Asm.java:42)\n\tat com.googlecode.d2j.dex.Dex2jar$2.convertCode(Dex2jar.java:128)\n\tat com.googlecode.d2j.dex.Dex2Asm.convertMethod(Dex2Asm.java:509)\n\tat com.googlecode.d2j.dex.Dex2Asm.convertClass(Dex2Asm.java:406)\n\tat com.googlecode.d2j.dex.Dex2Asm.convertDex(Dex2Asm.java:422)\n\tat com.googlecode.d2j.dex.Dex2jar.doTranslate(Dex2jar.java:172)\n\tat com.googlecode.d2j.dex.Dex2jar.to(Dex2jar.java:272)\n\tat com.googlecode.dex2jar.tools.Dex2jarCmd.doCommandLine(Dex2jarCmd.java:108)\n\tat com.googlecode.dex2jar.tools.BaseCmd.doMain(BaseCmd.java:288)\n\tat com.googlecode.dex2jar.tools.Dex2jarCmd.main(Dex2jarCmd.java:32)\n");
  }
  
  @X
  public final boolean zza(zzcfv paramZzcfv)
  {
    zzbp.zzu(paramZzcfv);
    zzuj();
    zzwk();
    if (zzah(mAppId, mName) == null)
    {
      long l;
      if (zzcfw.zzju(mName))
      {
        l = zzb("select count(1) from user_attributes where app_id=? and name not like '!_%' escape '!'", new String[] { mAppId });
        zzcax.zzavy();
        if (l >= 25L) {
          return false;
        }
      }
      else
      {
        l = zzb("select count(1) from user_attributes where app_id=? and origin=? AND name like '!_%' escape '!'", new String[] { mAppId, mOrigin });
        zzcax.zzawa();
        if (l >= 25L) {
          return false;
        }
      }
    }
    ContentValues localContentValues = new ContentValues();
    localContentValues.put("app_id", mAppId);
    localContentValues.put("origin", mOrigin);
    localContentValues.put("name", mName);
    localContentValues.put("set_timestamp", Long.valueOf(zzixd));
    zza(localContentValues, "value", mValue);
    try
    {
      if (getWritableDatabase().insertWithOnConflict("user_attributes", null, localContentValues, 5) == -1L)
      {
        zzaul().zzayd().zzj("Failed to insert/update user property (got -1). appId", zzcbw.zzjf(mAppId));
        return true;
      }
    }
    catch (SQLiteException localSQLiteException)
    {
      zzaul().zzayd().zze("Error storing user property. appId", zzcbw.zzjf(mAppId), localSQLiteException);
    }
    return true;
  }
  
  @X
  public final boolean zza(zzcgk paramZzcgk, boolean paramBoolean)
  {
    throw new Runtime("d2j fail translate: java.lang.RuntimeException: can not merge I and Z\n\tat com.googlecode.dex2jar.ir.TypeClass.merge(TypeClass.java:100)\n\tat com.googlecode.dex2jar.ir.ts.TypeTransformer$TypeRef.updateTypeClass(TypeTransformer.java:174)\n\tat com.googlecode.dex2jar.ir.ts.TypeTransformer$TypeAnalyze.copyTypes(TypeTransformer.java:311)\n\tat com.googlecode.dex2jar.ir.ts.TypeTransformer$TypeAnalyze.fixTypes(TypeTransformer.java:226)\n\tat com.googlecode.dex2jar.ir.ts.TypeTransformer$TypeAnalyze.analyze(TypeTransformer.java:207)\n\tat com.googlecode.dex2jar.ir.ts.TypeTransformer.transform(TypeTransformer.java:44)\n\tat com.googlecode.d2j.dex.Dex2jar$2.optimize(Dex2jar.java:162)\n\tat com.googlecode.d2j.dex.Dex2Asm.convertCode(Dex2Asm.java:414)\n\tat com.googlecode.d2j.dex.ExDex2Asm.convertCode(ExDex2Asm.java:42)\n\tat com.googlecode.d2j.dex.Dex2jar$2.convertCode(Dex2jar.java:128)\n\tat com.googlecode.d2j.dex.Dex2Asm.convertMethod(Dex2Asm.java:509)\n\tat com.googlecode.d2j.dex.Dex2Asm.convertClass(Dex2Asm.java:406)\n\tat com.googlecode.d2j.dex.Dex2Asm.convertDex(Dex2Asm.java:422)\n\tat com.googlecode.d2j.dex.Dex2jar.doTranslate(Dex2jar.java:172)\n\tat com.googlecode.d2j.dex.Dex2jar.to(Dex2jar.java:272)\n\tat com.googlecode.dex2jar.tools.Dex2jarCmd.doCommandLine(Dex2jarCmd.java:108)\n\tat com.googlecode.dex2jar.tools.BaseCmd.doMain(BaseCmd.java:288)\n\tat com.googlecode.dex2jar.tools.Dex2jarCmd.main(Dex2jarCmd.java:32)\n");
  }
  
  public final void zzae(List<Long> paramList)
  {
    zzbp.zzu(paramList);
    zzuj();
    zzwk();
    StringBuilder localStringBuilder = new StringBuilder("rowid in (");
    int i = 0;
    while (i < paramList.size())
    {
      if (i != 0) {
        localStringBuilder.append(",");
      }
      localStringBuilder.append(((Long)paramList.get(i)).longValue());
      i += 1;
    }
    localStringBuilder.append(")");
    i = getWritableDatabase().delete("raw_events", localStringBuilder.toString(), null);
    if (i != paramList.size()) {
      zzaul().zzayd().zze("Deleted fewer rows from raw events table than expected", Integer.valueOf(i), Integer.valueOf(paramList.size()));
    }
  }
  
  /* Error */
  @X
  public final zzcbg zzaf(String paramString1, String paramString2)
  {
    // Byte code:
    //   0: aload_1
    //   1: invokestatic 263	com/google/android/gms/common/internal/zzbp:zzgg	(Ljava/lang/String;)Ljava/lang/String;
    //   4: pop
    //   5: aload_2
    //   6: invokestatic 263	com/google/android/gms/common/internal/zzbp:zzgg	(Ljava/lang/String;)Ljava/lang/String;
    //   9: pop
    //   10: aload_0
    //   11: invokevirtual 425	com/google/android/gms/internal/zzcdt:zzuj	()V
    //   14: aload_0
    //   15: invokevirtual 422	com/google/android/gms/internal/zzcdu:zzwk	()V
    //   18: aload_0
    //   19: invokevirtual 174	com/google/android/gms/internal/zzcay:getWritableDatabase	()Landroid/database/sqlite/SQLiteDatabase;
    //   22: ldc_w 839
    //   25: iconst_3
    //   26: anewarray 269	java/lang/String
    //   29: dup
    //   30: iconst_0
    //   31: ldc_w 824
    //   34: aastore
    //   35: dup
    //   36: iconst_1
    //   37: ldc_w 829
    //   40: aastore
    //   41: dup
    //   42: iconst_2
    //   43: ldc_w 834
    //   46: aastore
    //   47: ldc_w 1030
    //   50: iconst_2
    //   51: anewarray 269	java/lang/String
    //   54: dup
    //   55: iconst_0
    //   56: aload_1
    //   57: aastore
    //   58: dup
    //   59: iconst_1
    //   60: aload_2
    //   61: aastore
    //   62: aconst_null
    //   63: aconst_null
    //   64: aconst_null
    //   65: invokevirtual 414	android/database/sqlite/SQLiteDatabase:query	(Ljava/lang/String;[Ljava/lang/String;Ljava/lang/String;[Ljava/lang/String;Ljava/lang/String;Ljava/lang/String;Ljava/lang/String;)Landroid/database/Cursor;
    //   68: astore 5
    //   70: aload 5
    //   72: astore 4
    //   74: aload 5
    //   76: invokeinterface 186 1 0
    //   81: istore_3
    //   82: iload_3
    //   83: ifne +12 -> 95
    //   86: aload 5
    //   88: invokeinterface 193 1 0
    //   93: aconst_null
    //   94: areturn
    //   95: aload 5
    //   97: astore 4
    //   99: new 816	com/google/android/gms/internal/zzcbg
    //   102: dup
    //   103: aload_1
    //   104: aload_2
    //   105: aload 5
    //   107: iconst_0
    //   108: invokeinterface 190 2 0
    //   113: aload 5
    //   115: iconst_1
    //   116: invokeinterface 190 2 0
    //   121: aload 5
    //   123: iconst_2
    //   124: invokeinterface 190 2 0
    //   129: invokespecial 1033	com/google/android/gms/internal/zzcbg:<init>	(Ljava/lang/String;Ljava/lang/String;JJJ)V
    //   132: astore 6
    //   134: aload 5
    //   136: astore 4
    //   138: aload 5
    //   140: invokeinterface 1036 1 0
    //   145: ifeq +24 -> 169
    //   148: aload 5
    //   150: astore 4
    //   152: aload_0
    //   153: invokevirtual 197	com/google/android/gms/internal/zzcdt:zzaul	()Lcom/google/android/gms/internal/zzcbw;
    //   156: invokevirtual 203	com/google/android/gms/internal/zzcbw:zzayd	()Lcom/google/android/gms/internal/zzcby;
    //   159: ldc_w 1038
    //   162: aload_1
    //   163: invokestatic 440	com/google/android/gms/internal/zzcbw:zzjf	(Ljava/lang/String;)Ljava/lang/Object;
    //   166: invokevirtual 230	com/google/android/gms/internal/zzcby:zzj	(Ljava/lang/String;Ljava/lang/Object;)V
    //   169: aload 5
    //   171: invokeinterface 193 1 0
    //   176: aload 6
    //   178: areturn
    //   179: astore 6
    //   181: goto +15 -> 196
    //   184: astore_1
    //   185: aconst_null
    //   186: astore 4
    //   188: goto +54 -> 242
    //   191: astore 6
    //   193: aconst_null
    //   194: astore 5
    //   196: aload 5
    //   198: astore 4
    //   200: aload_0
    //   201: invokevirtual 197	com/google/android/gms/internal/zzcdt:zzaul	()Lcom/google/android/gms/internal/zzcbw;
    //   204: invokevirtual 203	com/google/android/gms/internal/zzcbw:zzayd	()Lcom/google/android/gms/internal/zzcby;
    //   207: ldc_w 1040
    //   210: aload_1
    //   211: invokestatic 440	com/google/android/gms/internal/zzcbw:zzjf	(Ljava/lang/String;)Ljava/lang/Object;
    //   214: aload_0
    //   215: invokevirtual 1044	com/google/android/gms/internal/zzcdt:zzaug	()Lcom/google/android/gms/internal/zzcbu;
    //   218: aload_2
    //   219: invokevirtual 1049	com/google/android/gms/internal/zzcbu:zzjc	(Ljava/lang/String;)Ljava/lang/String;
    //   222: aload 6
    //   224: invokevirtual 451	com/google/android/gms/internal/zzcby:zzd	(Ljava/lang/String;Ljava/lang/Object;Ljava/lang/Object;Ljava/lang/Object;)V
    //   227: aload 5
    //   229: ifnull +10 -> 239
    //   232: aload 5
    //   234: invokeinterface 193 1 0
    //   239: aconst_null
    //   240: areturn
    //   241: astore_1
    //   242: aload 4
    //   244: ifnull +10 -> 254
    //   247: aload 4
    //   249: invokeinterface 193 1 0
    //   254: aload_1
    //   255: athrow
    // Local variable table:
    //   start	length	slot	name	signature
    //   0	256	0	this	zzcay
    //   0	256	1	paramString1	String
    //   0	256	2	paramString2	String
    //   81	2	3	bool	boolean
    //   72	176	4	localCursor1	Cursor
    //   68	165	5	localCursor2	Cursor
    //   132	45	6	localZzcbg	zzcbg
    //   179	1	6	localSQLiteException1	SQLiteException
    //   191	32	6	localSQLiteException2	SQLiteException
    // Exception table:
    //   from	to	target	type
    //   74	82	179	android/database/sqlite/SQLiteException
    //   99	134	179	android/database/sqlite/SQLiteException
    //   138	148	179	android/database/sqlite/SQLiteException
    //   152	169	179	android/database/sqlite/SQLiteException
    //   18	70	184	finally
    //   18	70	191	android/database/sqlite/SQLiteException
    //   74	82	241	finally
    //   99	134	241	finally
    //   138	148	241	finally
    //   152	169	241	finally
    //   200	227	241	finally
  }
  
  @X
  public final void zzag(String paramString1, String paramString2)
  {
    zzbp.zzgg(paramString1);
    zzbp.zzgg(paramString2);
    zzuj();
    zzwk();
    try
    {
      int i = getWritableDatabase().delete("user_attributes", "app_id=? and name=?", new String[] { paramString1, paramString2 });
      zzaul().zzayj().zzj("Deleted user attribute rows", Integer.valueOf(i));
      return;
    }
    catch (SQLiteException localSQLiteException)
    {
      zzaul().zzayd().zzd("Error deleting user attribute. appId", zzcbw.zzjf(paramString1), zzaug().zzje(paramString2), localSQLiteException);
    }
  }
  
  /* Error */
  @X
  public final zzcfv zzah(String paramString1, String paramString2)
  {
    // Byte code:
    //   0: aload_1
    //   1: invokestatic 263	com/google/android/gms/common/internal/zzbp:zzgg	(Ljava/lang/String;)Ljava/lang/String;
    //   4: pop
    //   5: aload_2
    //   6: invokestatic 263	com/google/android/gms/common/internal/zzbp:zzgg	(Ljava/lang/String;)Ljava/lang/String;
    //   9: pop
    //   10: aload_0
    //   11: invokevirtual 425	com/google/android/gms/internal/zzcdt:zzuj	()V
    //   14: aload_0
    //   15: invokevirtual 422	com/google/android/gms/internal/zzcdu:zzwk	()V
    //   18: aload_0
    //   19: invokevirtual 174	com/google/android/gms/internal/zzcay:getWritableDatabase	()Landroid/database/sqlite/SQLiteDatabase;
    //   22: ldc_w 1005
    //   25: iconst_3
    //   26: anewarray 269	java/lang/String
    //   29: dup
    //   30: iconst_0
    //   31: ldc_w 996
    //   34: aastore
    //   35: dup
    //   36: iconst_1
    //   37: ldc_w 903
    //   40: aastore
    //   41: dup
    //   42: iconst_2
    //   43: ldc 27
    //   45: aastore
    //   46: ldc_w 1030
    //   49: iconst_2
    //   50: anewarray 269	java/lang/String
    //   53: dup
    //   54: iconst_0
    //   55: aload_1
    //   56: aastore
    //   57: dup
    //   58: iconst_1
    //   59: aload_2
    //   60: aastore
    //   61: aconst_null
    //   62: aconst_null
    //   63: aconst_null
    //   64: invokevirtual 414	android/database/sqlite/SQLiteDatabase:query	(Ljava/lang/String;[Ljava/lang/String;Ljava/lang/String;[Ljava/lang/String;Ljava/lang/String;Ljava/lang/String;Ljava/lang/String;)Landroid/database/Cursor;
    //   67: astore 6
    //   69: aload 6
    //   71: invokeinterface 186 1 0
    //   76: istore_3
    //   77: iload_3
    //   78: ifne +12 -> 90
    //   81: aload 6
    //   83: invokeinterface 193 1 0
    //   88: aconst_null
    //   89: areturn
    //   90: aload 6
    //   92: iconst_0
    //   93: invokeinterface 190 2 0
    //   98: lstore 4
    //   100: aload 6
    //   102: astore 7
    //   104: aload_0
    //   105: aload 6
    //   107: iconst_1
    //   108: invokespecial 1062	com/google/android/gms/internal/zzcay:zza	(Landroid/database/Cursor;I)Ljava/lang/Object;
    //   111: astore 8
    //   113: aload 6
    //   115: astore 7
    //   117: new 973	com/google/android/gms/internal/zzcfv
    //   120: dup
    //   121: aload_1
    //   122: aload 6
    //   124: iconst_2
    //   125: invokeinterface 240 2 0
    //   130: aload_2
    //   131: lload 4
    //   133: aload 8
    //   135: invokespecial 1065	com/google/android/gms/internal/zzcfv:<init>	(Ljava/lang/String;Ljava/lang/String;Ljava/lang/String;JLjava/lang/Object;)V
    //   138: astore 8
    //   140: aload 6
    //   142: astore 7
    //   144: aload 6
    //   146: invokeinterface 1036 1 0
    //   151: ifeq +24 -> 175
    //   154: aload 6
    //   156: astore 7
    //   158: aload_0
    //   159: invokevirtual 197	com/google/android/gms/internal/zzcdt:zzaul	()Lcom/google/android/gms/internal/zzcbw;
    //   162: invokevirtual 203	com/google/android/gms/internal/zzcbw:zzayd	()Lcom/google/android/gms/internal/zzcby;
    //   165: ldc_w 1067
    //   168: aload_1
    //   169: invokestatic 440	com/google/android/gms/internal/zzcbw:zzjf	(Ljava/lang/String;)Ljava/lang/Object;
    //   172: invokevirtual 230	com/google/android/gms/internal/zzcby:zzj	(Ljava/lang/String;Ljava/lang/Object;)V
    //   175: aload 6
    //   177: invokeinterface 193 1 0
    //   182: aload 8
    //   184: areturn
    //   185: astore 8
    //   187: goto +24 -> 211
    //   190: astore_1
    //   191: goto +70 -> 261
    //   194: astore 8
    //   196: goto +15 -> 211
    //   199: astore_1
    //   200: aconst_null
    //   201: astore 6
    //   203: goto +58 -> 261
    //   206: astore 8
    //   208: aconst_null
    //   209: astore 6
    //   211: aload 6
    //   213: astore 7
    //   215: aload_0
    //   216: invokevirtual 197	com/google/android/gms/internal/zzcdt:zzaul	()Lcom/google/android/gms/internal/zzcbw;
    //   219: invokevirtual 203	com/google/android/gms/internal/zzcbw:zzayd	()Lcom/google/android/gms/internal/zzcby;
    //   222: ldc_w 1069
    //   225: aload_1
    //   226: invokestatic 440	com/google/android/gms/internal/zzcbw:zzjf	(Ljava/lang/String;)Ljava/lang/Object;
    //   229: aload_0
    //   230: invokevirtual 1044	com/google/android/gms/internal/zzcdt:zzaug	()Lcom/google/android/gms/internal/zzcbu;
    //   233: aload_2
    //   234: invokevirtual 1060	com/google/android/gms/internal/zzcbu:zzje	(Ljava/lang/String;)Ljava/lang/String;
    //   237: aload 8
    //   239: invokevirtual 451	com/google/android/gms/internal/zzcby:zzd	(Ljava/lang/String;Ljava/lang/Object;Ljava/lang/Object;Ljava/lang/Object;)V
    //   242: aload 6
    //   244: ifnull +10 -> 254
    //   247: aload 6
    //   249: invokeinterface 193 1 0
    //   254: aconst_null
    //   255: areturn
    //   256: astore_1
    //   257: aload 7
    //   259: astore 6
    //   261: aload 6
    //   263: ifnull +10 -> 273
    //   266: aload 6
    //   268: invokeinterface 193 1 0
    //   273: aload_1
    //   274: athrow
    // Local variable table:
    //   start	length	slot	name	signature
    //   0	275	0	this	zzcay
    //   0	275	1	paramString1	String
    //   0	275	2	paramString2	String
    //   76	2	3	bool	boolean
    //   98	34	4	l	long
    //   67	200	6	localObject1	Object
    //   102	156	7	localObject2	Object
    //   111	72	8	localObject3	Object
    //   185	1	8	localSQLiteException1	SQLiteException
    //   194	1	8	localSQLiteException2	SQLiteException
    //   206	32	8	localSQLiteException3	SQLiteException
    // Exception table:
    //   from	to	target	type
    //   104	113	185	android/database/sqlite/SQLiteException
    //   117	140	185	android/database/sqlite/SQLiteException
    //   144	154	185	android/database/sqlite/SQLiteException
    //   158	175	185	android/database/sqlite/SQLiteException
    //   69	77	190	finally
    //   90	100	190	finally
    //   69	77	194	android/database/sqlite/SQLiteException
    //   90	100	194	android/database/sqlite/SQLiteException
    //   18	69	199	finally
    //   18	69	206	android/database/sqlite/SQLiteException
    //   104	113	256	finally
    //   117	140	256	finally
    //   144	154	256	finally
    //   158	175	256	finally
    //   215	242	256	finally
  }
  
  /* Error */
  @X
  public final zzcav zzai(String paramString1, String paramString2)
  {
    // Byte code:
    //   0: aload_1
    //   1: invokestatic 263	com/google/android/gms/common/internal/zzbp:zzgg	(Ljava/lang/String;)Ljava/lang/String;
    //   4: pop
    //   5: aload_2
    //   6: invokestatic 263	com/google/android/gms/common/internal/zzbp:zzgg	(Ljava/lang/String;)Ljava/lang/String;
    //   9: pop
    //   10: aload_0
    //   11: invokevirtual 425	com/google/android/gms/internal/zzcdt:zzuj	()V
    //   14: aload_0
    //   15: invokevirtual 422	com/google/android/gms/internal/zzcdu:zzwk	()V
    //   18: aload_0
    //   19: invokevirtual 174	com/google/android/gms/internal/zzcay:getWritableDatabase	()Landroid/database/sqlite/SQLiteDatabase;
    //   22: ldc_w 958
    //   25: bipush 11
    //   27: anewarray 269	java/lang/String
    //   30: dup
    //   31: iconst_0
    //   32: ldc 27
    //   34: aastore
    //   35: dup
    //   36: iconst_1
    //   37: ldc_w 903
    //   40: aastore
    //   41: dup
    //   42: iconst_2
    //   43: ldc_w 908
    //   46: aastore
    //   47: dup
    //   48: iconst_3
    //   49: ldc_w 914
    //   52: aastore
    //   53: dup
    //   54: iconst_4
    //   55: ldc_w 919
    //   58: aastore
    //   59: dup
    //   60: iconst_5
    //   61: ldc_w 924
    //   64: aastore
    //   65: dup
    //   66: bipush 6
    //   68: ldc_w 933
    //   71: aastore
    //   72: dup
    //   73: bipush 7
    //   75: ldc_w 938
    //   78: aastore
    //   79: dup
    //   80: bipush 8
    //   82: ldc_w 943
    //   85: aastore
    //   86: dup
    //   87: bipush 9
    //   89: ldc_w 948
    //   92: aastore
    //   93: dup
    //   94: bipush 10
    //   96: ldc_w 953
    //   99: aastore
    //   100: ldc_w 1030
    //   103: iconst_2
    //   104: anewarray 269	java/lang/String
    //   107: dup
    //   108: iconst_0
    //   109: aload_1
    //   110: aastore
    //   111: dup
    //   112: iconst_1
    //   113: aload_2
    //   114: aastore
    //   115: aconst_null
    //   116: aconst_null
    //   117: aconst_null
    //   118: invokevirtual 414	android/database/sqlite/SQLiteDatabase:query	(Ljava/lang/String;[Ljava/lang/String;Ljava/lang/String;[Ljava/lang/String;Ljava/lang/String;Ljava/lang/String;Ljava/lang/String;)Landroid/database/Cursor;
    //   121: astore 12
    //   123: aload 12
    //   125: invokeinterface 186 1 0
    //   130: istore_3
    //   131: iload_3
    //   132: ifne +12 -> 144
    //   135: aload 12
    //   137: invokeinterface 193 1 0
    //   142: aconst_null
    //   143: areturn
    //   144: aload 12
    //   146: iconst_0
    //   147: invokeinterface 240 2 0
    //   152: astore 14
    //   154: aload 12
    //   156: astore 13
    //   158: aload_0
    //   159: aload 12
    //   161: iconst_1
    //   162: invokespecial 1062	com/google/android/gms/internal/zzcay:zza	(Landroid/database/Cursor;I)Ljava/lang/Object;
    //   165: astore 15
    //   167: aload 12
    //   169: astore 13
    //   171: aload 12
    //   173: iconst_2
    //   174: invokeinterface 1074 2 0
    //   179: ifeq +352 -> 531
    //   182: iconst_1
    //   183: istore_3
    //   184: goto +3 -> 187
    //   187: aload 12
    //   189: astore 13
    //   191: aload 12
    //   193: iconst_3
    //   194: invokeinterface 240 2 0
    //   199: astore 16
    //   201: aload 12
    //   203: astore 13
    //   205: aload 12
    //   207: iconst_4
    //   208: invokeinterface 190 2 0
    //   213: lstore 4
    //   215: aload 12
    //   217: astore 13
    //   219: aload_0
    //   220: invokevirtual 649	com/google/android/gms/internal/zzcdt:zzauh	()Lcom/google/android/gms/internal/zzcfw;
    //   223: aload 12
    //   225: iconst_5
    //   226: invokeinterface 1078 2 0
    //   231: getstatic 1084	com/google/android/gms/internal/zzcbk:CREATOR	Landroid/os/Parcelable$Creator;
    //   234: invokevirtual 1087	com/google/android/gms/internal/zzcfw:zzb	([BLandroid/os/Parcelable$Creator;)Landroid/os/Parcelable;
    //   237: checkcast 1080	com/google/android/gms/internal/zzcbk
    //   240: astore 17
    //   242: aload 12
    //   244: astore 13
    //   246: aload 12
    //   248: bipush 6
    //   250: invokeinterface 190 2 0
    //   255: lstore 6
    //   257: aload 12
    //   259: astore 13
    //   261: aload_0
    //   262: invokevirtual 649	com/google/android/gms/internal/zzcdt:zzauh	()Lcom/google/android/gms/internal/zzcfw;
    //   265: aload 12
    //   267: bipush 7
    //   269: invokeinterface 1078 2 0
    //   274: getstatic 1084	com/google/android/gms/internal/zzcbk:CREATOR	Landroid/os/Parcelable$Creator;
    //   277: invokevirtual 1087	com/google/android/gms/internal/zzcfw:zzb	([BLandroid/os/Parcelable$Creator;)Landroid/os/Parcelable;
    //   280: checkcast 1080	com/google/android/gms/internal/zzcbk
    //   283: astore 18
    //   285: aload 12
    //   287: astore 13
    //   289: aload 12
    //   291: bipush 8
    //   293: invokeinterface 190 2 0
    //   298: lstore 8
    //   300: aload 12
    //   302: astore 13
    //   304: aload 12
    //   306: bipush 9
    //   308: invokeinterface 190 2 0
    //   313: lstore 10
    //   315: aload 12
    //   317: astore 13
    //   319: aload_0
    //   320: invokevirtual 649	com/google/android/gms/internal/zzcdt:zzauh	()Lcom/google/android/gms/internal/zzcfw;
    //   323: aload 12
    //   325: bipush 10
    //   327: invokeinterface 1078 2 0
    //   332: getstatic 1084	com/google/android/gms/internal/zzcbk:CREATOR	Landroid/os/Parcelable$Creator;
    //   335: invokevirtual 1087	com/google/android/gms/internal/zzcfw:zzb	([BLandroid/os/Parcelable$Creator;)Landroid/os/Parcelable;
    //   338: checkcast 1080	com/google/android/gms/internal/zzcbk
    //   341: astore 19
    //   343: aload 12
    //   345: astore 13
    //   347: new 876	com/google/android/gms/internal/zzcav
    //   350: dup
    //   351: aload_1
    //   352: aload 14
    //   354: new 885	com/google/android/gms/internal/zzcft
    //   357: dup
    //   358: aload_2
    //   359: lload 8
    //   361: aload 15
    //   363: aload 14
    //   365: invokespecial 1090	com/google/android/gms/internal/zzcft:<init>	(Ljava/lang/String;JLjava/lang/Object;Ljava/lang/String;)V
    //   368: lload 6
    //   370: iload_3
    //   371: aload 16
    //   373: aload 17
    //   375: lload 4
    //   377: aload 18
    //   379: lload 10
    //   381: aload 19
    //   383: invokespecial 1093	com/google/android/gms/internal/zzcav:<init>	(Ljava/lang/String;Ljava/lang/String;Lcom/google/android/gms/internal/zzcft;JZLjava/lang/String;Lcom/google/android/gms/internal/zzcbk;JLcom/google/android/gms/internal/zzcbk;JLcom/google/android/gms/internal/zzcbk;)V
    //   386: astore 14
    //   388: aload 12
    //   390: astore 13
    //   392: aload 12
    //   394: invokeinterface 1036 1 0
    //   399: ifeq +32 -> 431
    //   402: aload 12
    //   404: astore 13
    //   406: aload_0
    //   407: invokevirtual 197	com/google/android/gms/internal/zzcdt:zzaul	()Lcom/google/android/gms/internal/zzcbw;
    //   410: invokevirtual 203	com/google/android/gms/internal/zzcbw:zzayd	()Lcom/google/android/gms/internal/zzcby;
    //   413: ldc_w 1095
    //   416: aload_1
    //   417: invokestatic 440	com/google/android/gms/internal/zzcbw:zzjf	(Ljava/lang/String;)Ljava/lang/Object;
    //   420: aload_0
    //   421: invokevirtual 1044	com/google/android/gms/internal/zzcdt:zzaug	()Lcom/google/android/gms/internal/zzcbu;
    //   424: aload_2
    //   425: invokevirtual 1060	com/google/android/gms/internal/zzcbu:zzje	(Ljava/lang/String;)Ljava/lang/String;
    //   428: invokevirtual 211	com/google/android/gms/internal/zzcby:zze	(Ljava/lang/String;Ljava/lang/Object;Ljava/lang/Object;)V
    //   431: aload 12
    //   433: invokeinterface 193 1 0
    //   438: aload 14
    //   440: areturn
    //   441: astore 14
    //   443: goto +24 -> 467
    //   446: astore_1
    //   447: goto +70 -> 517
    //   450: astore 14
    //   452: goto +15 -> 467
    //   455: astore_1
    //   456: aconst_null
    //   457: astore 12
    //   459: goto +58 -> 517
    //   462: astore 14
    //   464: aconst_null
    //   465: astore 12
    //   467: aload 12
    //   469: astore 13
    //   471: aload_0
    //   472: invokevirtual 197	com/google/android/gms/internal/zzcdt:zzaul	()Lcom/google/android/gms/internal/zzcbw;
    //   475: invokevirtual 203	com/google/android/gms/internal/zzcbw:zzayd	()Lcom/google/android/gms/internal/zzcby;
    //   478: ldc_w 1097
    //   481: aload_1
    //   482: invokestatic 440	com/google/android/gms/internal/zzcbw:zzjf	(Ljava/lang/String;)Ljava/lang/Object;
    //   485: aload_0
    //   486: invokevirtual 1044	com/google/android/gms/internal/zzcdt:zzaug	()Lcom/google/android/gms/internal/zzcbu;
    //   489: aload_2
    //   490: invokevirtual 1060	com/google/android/gms/internal/zzcbu:zzje	(Ljava/lang/String;)Ljava/lang/String;
    //   493: aload 14
    //   495: invokevirtual 451	com/google/android/gms/internal/zzcby:zzd	(Ljava/lang/String;Ljava/lang/Object;Ljava/lang/Object;Ljava/lang/Object;)V
    //   498: aload 12
    //   500: ifnull +10 -> 510
    //   503: aload 12
    //   505: invokeinterface 193 1 0
    //   510: aconst_null
    //   511: areturn
    //   512: astore_1
    //   513: aload 13
    //   515: astore 12
    //   517: aload 12
    //   519: ifnull +10 -> 529
    //   522: aload 12
    //   524: invokeinterface 193 1 0
    //   529: aload_1
    //   530: athrow
    //   531: iconst_0
    //   532: istore_3
    //   533: goto -346 -> 187
    // Local variable table:
    //   start	length	slot	name	signature
    //   0	536	0	this	zzcay
    //   0	536	1	paramString1	String
    //   0	536	2	paramString2	String
    //   130	403	3	bool	boolean
    //   213	163	4	l1	long
    //   255	114	6	l2	long
    //   298	62	8	l3	long
    //   313	67	10	l4	long
    //   121	402	12	localObject1	Object
    //   156	358	13	localObject2	Object
    //   152	287	14	localObject3	Object
    //   441	1	14	localSQLiteException1	SQLiteException
    //   450	1	14	localSQLiteException2	SQLiteException
    //   462	32	14	localSQLiteException3	SQLiteException
    //   165	197	15	localObject4	Object
    //   199	173	16	str	String
    //   240	134	17	localZzcbk1	zzcbk
    //   283	95	18	localZzcbk2	zzcbk
    //   341	41	19	localZzcbk3	zzcbk
    // Exception table:
    //   from	to	target	type
    //   158	167	441	android/database/sqlite/SQLiteException
    //   171	182	441	android/database/sqlite/SQLiteException
    //   191	201	441	android/database/sqlite/SQLiteException
    //   205	215	441	android/database/sqlite/SQLiteException
    //   219	242	441	android/database/sqlite/SQLiteException
    //   246	257	441	android/database/sqlite/SQLiteException
    //   261	285	441	android/database/sqlite/SQLiteException
    //   289	300	441	android/database/sqlite/SQLiteException
    //   304	315	441	android/database/sqlite/SQLiteException
    //   319	343	441	android/database/sqlite/SQLiteException
    //   347	388	441	android/database/sqlite/SQLiteException
    //   392	402	441	android/database/sqlite/SQLiteException
    //   406	431	441	android/database/sqlite/SQLiteException
    //   123	131	446	finally
    //   144	154	446	finally
    //   123	131	450	android/database/sqlite/SQLiteException
    //   144	154	450	android/database/sqlite/SQLiteException
    //   18	123	455	finally
    //   18	123	462	android/database/sqlite/SQLiteException
    //   158	167	512	finally
    //   171	182	512	finally
    //   191	201	512	finally
    //   205	215	512	finally
    //   219	242	512	finally
    //   246	257	512	finally
    //   261	285	512	finally
    //   289	300	512	finally
    //   304	315	512	finally
    //   319	343	512	finally
    //   347	388	512	finally
    //   392	402	512	finally
    //   406	431	512	finally
    //   471	498	512	finally
  }
  
  @X
  public final int zzaj(String paramString1, String paramString2)
  {
    zzbp.zzgg(paramString1);
    zzbp.zzgg(paramString2);
    zzuj();
    zzwk();
    try
    {
      int i = getWritableDatabase().delete("conditional_properties", "app_id=? and name=?", new String[] { paramString1, paramString2 });
      return i;
    }
    catch (SQLiteException localSQLiteException)
    {
      zzaul().zzayd().zzd("Error deleting conditional property", zzcbw.zzjf(paramString1), zzaug().zzje(paramString2), localSQLiteException);
    }
    return 0;
  }
  
  /* Error */
  public final Map<Integer, List<zzcfy>> zzak(String paramString1, String paramString2)
  {
    // Byte code:
    //   0: aload_0
    //   1: invokevirtual 422	com/google/android/gms/internal/zzcdu:zzwk	()V
    //   4: aload_0
    //   5: invokevirtual 425	com/google/android/gms/internal/zzcdt:zzuj	()V
    //   8: aload_1
    //   9: invokestatic 263	com/google/android/gms/common/internal/zzbp:zzgg	(Ljava/lang/String;)Ljava/lang/String;
    //   12: pop
    //   13: aload_2
    //   14: invokestatic 263	com/google/android/gms/common/internal/zzbp:zzgg	(Ljava/lang/String;)Ljava/lang/String;
    //   17: pop
    //   18: new 19	b/b/x/n/b
    //   21: dup
    //   22: invokespecial 1104	b/b/x/n/b:<init>	()V
    //   25: astore 8
    //   27: aload_0
    //   28: invokevirtual 174	com/google/android/gms/internal/zzcay:getWritableDatabase	()Landroid/database/sqlite/SQLiteDatabase;
    //   31: astore 5
    //   33: aload 5
    //   35: ldc_w 489
    //   38: iconst_2
    //   39: anewarray 269	java/lang/String
    //   42: dup
    //   43: iconst_0
    //   44: ldc_w 475
    //   47: aastore
    //   48: dup
    //   49: iconst_1
    //   50: ldc_w 484
    //   53: aastore
    //   54: ldc_w 1106
    //   57: iconst_2
    //   58: anewarray 269	java/lang/String
    //   61: dup
    //   62: iconst_0
    //   63: aload_1
    //   64: aastore
    //   65: dup
    //   66: iconst_1
    //   67: aload_2
    //   68: aastore
    //   69: aconst_null
    //   70: aconst_null
    //   71: aconst_null
    //   72: invokevirtual 414	android/database/sqlite/SQLiteDatabase:query	(Ljava/lang/String;[Ljava/lang/String;Ljava/lang/String;[Ljava/lang/String;Ljava/lang/String;Ljava/lang/String;Ljava/lang/String;)Landroid/database/Cursor;
    //   75: astore 5
    //   77: aload 5
    //   79: astore_2
    //   80: aload 5
    //   82: invokeinterface 186 1 0
    //   87: ifne +21 -> 108
    //   90: aload 5
    //   92: astore_2
    //   93: invokestatic 1109	java/util/Collections:emptyMap	()Ljava/util/Map;
    //   96: astore 6
    //   98: aload 5
    //   100: invokeinterface 193 1 0
    //   105: aload 6
    //   107: areturn
    //   108: aload 5
    //   110: astore_2
    //   111: aload 5
    //   113: iconst_1
    //   114: invokeinterface 1078 2 0
    //   119: astore 6
    //   121: aload 5
    //   123: astore_2
    //   124: aload 6
    //   126: iconst_0
    //   127: aload 6
    //   129: arraylength
    //   130: invokestatic 1115	com/google/android/gms/internal/zzeye:zzm	([BII)Lcom/google/android/gms/internal/zzeye;
    //   133: astore 6
    //   135: aload 5
    //   137: astore_2
    //   138: new 427	com/google/android/gms/internal/zzcfy
    //   141: dup
    //   142: invokespecial 1116	com/google/android/gms/internal/zzcfy:<init>	()V
    //   145: astore 9
    //   147: aload 5
    //   149: astore_2
    //   150: aload 9
    //   152: aload 6
    //   154: invokevirtual 1119	com/google/android/gms/internal/zzcfy:zza	(Lcom/google/android/gms/internal/zzeye;)Lcom/google/android/gms/internal/zzeyn;
    //   157: pop
    //   158: aload 5
    //   160: astore_2
    //   161: aload 5
    //   163: iconst_0
    //   164: invokeinterface 1074 2 0
    //   169: istore_3
    //   170: aload 5
    //   172: astore_2
    //   173: aload 8
    //   175: iload_3
    //   176: invokestatic 226	java/lang/Integer:valueOf	(I)Ljava/lang/Integer;
    //   179: invokeinterface 1121 2 0
    //   184: checkcast 594	java/util/List
    //   187: astore 7
    //   189: aload 7
    //   191: astore 6
    //   193: aload 7
    //   195: ifnonnull +32 -> 227
    //   198: aload 5
    //   200: astore_2
    //   201: new 591	java/util/ArrayList
    //   204: dup
    //   205: invokespecial 592	java/util/ArrayList:<init>	()V
    //   208: astore 6
    //   210: aload 5
    //   212: astore_2
    //   213: aload 8
    //   215: iload_3
    //   216: invokestatic 226	java/lang/Integer:valueOf	(I)Ljava/lang/Integer;
    //   219: aload 6
    //   221: invokeinterface 35 3 0
    //   226: pop
    //   227: aload 5
    //   229: astore_2
    //   230: aload 6
    //   232: aload 9
    //   234: invokeinterface 609 2 0
    //   239: pop
    //   240: goto +27 -> 267
    //   243: astore 6
    //   245: aload 5
    //   247: astore_2
    //   248: aload_0
    //   249: invokevirtual 197	com/google/android/gms/internal/zzcdt:zzaul	()Lcom/google/android/gms/internal/zzcbw;
    //   252: invokevirtual 203	com/google/android/gms/internal/zzcbw:zzayd	()Lcom/google/android/gms/internal/zzcby;
    //   255: ldc_w 1123
    //   258: aload_1
    //   259: invokestatic 440	com/google/android/gms/internal/zzcbw:zzjf	(Ljava/lang/String;)Ljava/lang/Object;
    //   262: aload 6
    //   264: invokevirtual 211	com/google/android/gms/internal/zzcby:zze	(Ljava/lang/String;Ljava/lang/Object;Ljava/lang/Object;)V
    //   267: aload 5
    //   269: astore_2
    //   270: aload 5
    //   272: invokeinterface 1036 1 0
    //   277: istore 4
    //   279: iload 4
    //   281: ifne -173 -> 108
    //   284: aload 5
    //   286: invokeinterface 193 1 0
    //   291: aload 8
    //   293: areturn
    //   294: astore 6
    //   296: goto +14 -> 310
    //   299: astore_1
    //   300: aconst_null
    //   301: astore_2
    //   302: goto +45 -> 347
    //   305: astore 6
    //   307: aconst_null
    //   308: astore 5
    //   310: aload 5
    //   312: astore_2
    //   313: aload_0
    //   314: invokevirtual 197	com/google/android/gms/internal/zzcdt:zzaul	()Lcom/google/android/gms/internal/zzcbw;
    //   317: invokevirtual 203	com/google/android/gms/internal/zzcbw:zzayd	()Lcom/google/android/gms/internal/zzcby;
    //   320: ldc_w 625
    //   323: aload_1
    //   324: invokestatic 440	com/google/android/gms/internal/zzcbw:zzjf	(Ljava/lang/String;)Ljava/lang/Object;
    //   327: aload 6
    //   329: invokevirtual 211	com/google/android/gms/internal/zzcby:zze	(Ljava/lang/String;Ljava/lang/Object;Ljava/lang/Object;)V
    //   332: aload 5
    //   334: ifnull +10 -> 344
    //   337: aload 5
    //   339: invokeinterface 193 1 0
    //   344: aconst_null
    //   345: areturn
    //   346: astore_1
    //   347: aload_2
    //   348: ifnull +9 -> 357
    //   351: aload_2
    //   352: invokeinterface 193 1 0
    //   357: goto +5 -> 362
    //   360: aload_1
    //   361: athrow
    //   362: goto -2 -> 360
    // Local variable table:
    //   start	length	slot	name	signature
    //   0	365	0	this	zzcay
    //   0	365	1	paramString1	String
    //   0	365	2	paramString2	String
    //   169	47	3	i	int
    //   277	3	4	bool	boolean
    //   31	307	5	localObject1	Object
    //   96	135	6	localObject2	Object
    //   243	20	6	localIOException	IOException
    //   294	1	6	localSQLiteException1	SQLiteException
    //   305	23	6	localSQLiteException2	SQLiteException
    //   187	7	7	localList	List
    //   25	267	8	localB	b
    //   145	88	9	localZzcfy	zzcfy
    // Exception table:
    //   from	to	target	type
    //   150	158	243	java/io/IOException
    //   80	90	294	android/database/sqlite/SQLiteException
    //   93	98	294	android/database/sqlite/SQLiteException
    //   111	121	294	android/database/sqlite/SQLiteException
    //   124	135	294	android/database/sqlite/SQLiteException
    //   138	147	294	android/database/sqlite/SQLiteException
    //   150	158	294	android/database/sqlite/SQLiteException
    //   161	170	294	android/database/sqlite/SQLiteException
    //   173	189	294	android/database/sqlite/SQLiteException
    //   201	210	294	android/database/sqlite/SQLiteException
    //   213	227	294	android/database/sqlite/SQLiteException
    //   230	240	294	android/database/sqlite/SQLiteException
    //   248	267	294	android/database/sqlite/SQLiteException
    //   270	279	294	android/database/sqlite/SQLiteException
    //   33	77	299	finally
    //   33	77	305	android/database/sqlite/SQLiteException
    //   80	90	346	finally
    //   93	98	346	finally
    //   111	121	346	finally
    //   124	135	346	finally
    //   138	147	346	finally
    //   150	158	346	finally
    //   161	170	346	finally
    //   173	189	346	finally
    //   201	210	346	finally
    //   213	227	346	finally
    //   230	240	346	finally
    //   248	267	346	finally
    //   270	279	346	finally
    //   313	332	346	finally
  }
  
  /* Error */
  public final Map<Integer, List<zzcgb>> zzal(String paramString1, String paramString2)
  {
    // Byte code:
    //   0: aload_0
    //   1: invokevirtual 422	com/google/android/gms/internal/zzcdu:zzwk	()V
    //   4: aload_0
    //   5: invokevirtual 425	com/google/android/gms/internal/zzcdt:zzuj	()V
    //   8: aload_1
    //   9: invokestatic 263	com/google/android/gms/common/internal/zzbp:zzgg	(Ljava/lang/String;)Ljava/lang/String;
    //   12: pop
    //   13: aload_2
    //   14: invokestatic 263	com/google/android/gms/common/internal/zzbp:zzgg	(Ljava/lang/String;)Ljava/lang/String;
    //   17: pop
    //   18: new 19	b/b/x/n/b
    //   21: dup
    //   22: invokespecial 1104	b/b/x/n/b:<init>	()V
    //   25: astore 8
    //   27: aload_0
    //   28: invokevirtual 174	com/google/android/gms/internal/zzcay:getWritableDatabase	()Landroid/database/sqlite/SQLiteDatabase;
    //   31: astore 5
    //   33: aload 5
    //   35: ldc_w 515
    //   38: iconst_2
    //   39: anewarray 269	java/lang/String
    //   42: dup
    //   43: iconst_0
    //   44: ldc_w 475
    //   47: aastore
    //   48: dup
    //   49: iconst_1
    //   50: ldc_w 484
    //   53: aastore
    //   54: ldc_w 1127
    //   57: iconst_2
    //   58: anewarray 269	java/lang/String
    //   61: dup
    //   62: iconst_0
    //   63: aload_1
    //   64: aastore
    //   65: dup
    //   66: iconst_1
    //   67: aload_2
    //   68: aastore
    //   69: aconst_null
    //   70: aconst_null
    //   71: aconst_null
    //   72: invokevirtual 414	android/database/sqlite/SQLiteDatabase:query	(Ljava/lang/String;[Ljava/lang/String;Ljava/lang/String;[Ljava/lang/String;Ljava/lang/String;Ljava/lang/String;Ljava/lang/String;)Landroid/database/Cursor;
    //   75: astore 5
    //   77: aload 5
    //   79: astore_2
    //   80: aload 5
    //   82: invokeinterface 186 1 0
    //   87: ifne +21 -> 108
    //   90: aload 5
    //   92: astore_2
    //   93: invokestatic 1109	java/util/Collections:emptyMap	()Ljava/util/Map;
    //   96: astore 6
    //   98: aload 5
    //   100: invokeinterface 193 1 0
    //   105: aload 6
    //   107: areturn
    //   108: aload 5
    //   110: astore_2
    //   111: aload 5
    //   113: iconst_1
    //   114: invokeinterface 1078 2 0
    //   119: astore 6
    //   121: aload 5
    //   123: astore_2
    //   124: aload 6
    //   126: iconst_0
    //   127: aload 6
    //   129: arraylength
    //   130: invokestatic 1115	com/google/android/gms/internal/zzeye:zzm	([BII)Lcom/google/android/gms/internal/zzeye;
    //   133: astore 6
    //   135: aload 5
    //   137: astore_2
    //   138: new 504	com/google/android/gms/internal/zzcgb
    //   141: dup
    //   142: invokespecial 1128	com/google/android/gms/internal/zzcgb:<init>	()V
    //   145: astore 9
    //   147: aload 5
    //   149: astore_2
    //   150: aload 9
    //   152: aload 6
    //   154: invokevirtual 1129	com/google/android/gms/internal/zzcgb:zza	(Lcom/google/android/gms/internal/zzeye;)Lcom/google/android/gms/internal/zzeyn;
    //   157: pop
    //   158: aload 5
    //   160: astore_2
    //   161: aload 5
    //   163: iconst_0
    //   164: invokeinterface 1074 2 0
    //   169: istore_3
    //   170: aload 5
    //   172: astore_2
    //   173: aload 8
    //   175: iload_3
    //   176: invokestatic 226	java/lang/Integer:valueOf	(I)Ljava/lang/Integer;
    //   179: invokeinterface 1121 2 0
    //   184: checkcast 594	java/util/List
    //   187: astore 7
    //   189: aload 7
    //   191: astore 6
    //   193: aload 7
    //   195: ifnonnull +32 -> 227
    //   198: aload 5
    //   200: astore_2
    //   201: new 591	java/util/ArrayList
    //   204: dup
    //   205: invokespecial 592	java/util/ArrayList:<init>	()V
    //   208: astore 6
    //   210: aload 5
    //   212: astore_2
    //   213: aload 8
    //   215: iload_3
    //   216: invokestatic 226	java/lang/Integer:valueOf	(I)Ljava/lang/Integer;
    //   219: aload 6
    //   221: invokeinterface 35 3 0
    //   226: pop
    //   227: aload 5
    //   229: astore_2
    //   230: aload 6
    //   232: aload 9
    //   234: invokeinterface 609 2 0
    //   239: pop
    //   240: goto +27 -> 267
    //   243: astore 6
    //   245: aload 5
    //   247: astore_2
    //   248: aload_0
    //   249: invokevirtual 197	com/google/android/gms/internal/zzcdt:zzaul	()Lcom/google/android/gms/internal/zzcbw;
    //   252: invokevirtual 203	com/google/android/gms/internal/zzcbw:zzayd	()Lcom/google/android/gms/internal/zzcby;
    //   255: ldc_w 1131
    //   258: aload_1
    //   259: invokestatic 440	com/google/android/gms/internal/zzcbw:zzjf	(Ljava/lang/String;)Ljava/lang/Object;
    //   262: aload 6
    //   264: invokevirtual 211	com/google/android/gms/internal/zzcby:zze	(Ljava/lang/String;Ljava/lang/Object;Ljava/lang/Object;)V
    //   267: aload 5
    //   269: astore_2
    //   270: aload 5
    //   272: invokeinterface 1036 1 0
    //   277: istore 4
    //   279: iload 4
    //   281: ifne -173 -> 108
    //   284: aload 5
    //   286: invokeinterface 193 1 0
    //   291: aload 8
    //   293: areturn
    //   294: astore 6
    //   296: goto +14 -> 310
    //   299: astore_1
    //   300: aconst_null
    //   301: astore_2
    //   302: goto +45 -> 347
    //   305: astore 6
    //   307: aconst_null
    //   308: astore 5
    //   310: aload 5
    //   312: astore_2
    //   313: aload_0
    //   314: invokevirtual 197	com/google/android/gms/internal/zzcdt:zzaul	()Lcom/google/android/gms/internal/zzcbw;
    //   317: invokevirtual 203	com/google/android/gms/internal/zzcbw:zzayd	()Lcom/google/android/gms/internal/zzcby;
    //   320: ldc_w 625
    //   323: aload_1
    //   324: invokestatic 440	com/google/android/gms/internal/zzcbw:zzjf	(Ljava/lang/String;)Ljava/lang/Object;
    //   327: aload 6
    //   329: invokevirtual 211	com/google/android/gms/internal/zzcby:zze	(Ljava/lang/String;Ljava/lang/Object;Ljava/lang/Object;)V
    //   332: aload 5
    //   334: ifnull +10 -> 344
    //   337: aload 5
    //   339: invokeinterface 193 1 0
    //   344: aconst_null
    //   345: areturn
    //   346: astore_1
    //   347: aload_2
    //   348: ifnull +9 -> 357
    //   351: aload_2
    //   352: invokeinterface 193 1 0
    //   357: goto +5 -> 362
    //   360: aload_1
    //   361: athrow
    //   362: goto -2 -> 360
    // Local variable table:
    //   start	length	slot	name	signature
    //   0	365	0	this	zzcay
    //   0	365	1	paramString1	String
    //   0	365	2	paramString2	String
    //   169	47	3	i	int
    //   277	3	4	bool	boolean
    //   31	307	5	localObject1	Object
    //   96	135	6	localObject2	Object
    //   243	20	6	localIOException	IOException
    //   294	1	6	localSQLiteException1	SQLiteException
    //   305	23	6	localSQLiteException2	SQLiteException
    //   187	7	7	localList	List
    //   25	267	8	localB	b
    //   145	88	9	localZzcgb	zzcgb
    // Exception table:
    //   from	to	target	type
    //   150	158	243	java/io/IOException
    //   80	90	294	android/database/sqlite/SQLiteException
    //   93	98	294	android/database/sqlite/SQLiteException
    //   111	121	294	android/database/sqlite/SQLiteException
    //   124	135	294	android/database/sqlite/SQLiteException
    //   138	147	294	android/database/sqlite/SQLiteException
    //   150	158	294	android/database/sqlite/SQLiteException
    //   161	170	294	android/database/sqlite/SQLiteException
    //   173	189	294	android/database/sqlite/SQLiteException
    //   201	210	294	android/database/sqlite/SQLiteException
    //   213	227	294	android/database/sqlite/SQLiteException
    //   230	240	294	android/database/sqlite/SQLiteException
    //   248	267	294	android/database/sqlite/SQLiteException
    //   270	279	294	android/database/sqlite/SQLiteException
    //   33	77	299	finally
    //   33	77	305	android/database/sqlite/SQLiteException
    //   80	90	346	finally
    //   93	98	346	finally
    //   111	121	346	finally
    //   124	135	346	finally
    //   138	147	346	finally
    //   150	158	346	finally
    //   161	170	346	finally
    //   173	189	346	finally
    //   201	210	346	finally
    //   213	227	346	finally
    //   230	240	346	finally
    //   248	267	346	finally
    //   270	279	346	finally
    //   313	332	346	finally
  }
  
  /* Error */
  @X
  public final long zzam(String paramString1, String paramString2)
  {
    // Byte code:
    //   0: aload_1
    //   1: invokestatic 263	com/google/android/gms/common/internal/zzbp:zzgg	(Ljava/lang/String;)Ljava/lang/String;
    //   4: pop
    //   5: aload_2
    //   6: invokestatic 263	com/google/android/gms/common/internal/zzbp:zzgg	(Ljava/lang/String;)Ljava/lang/String;
    //   9: pop
    //   10: aload_0
    //   11: invokevirtual 425	com/google/android/gms/internal/zzcdt:zzuj	()V
    //   14: aload_0
    //   15: invokevirtual 422	com/google/android/gms/internal/zzcdu:zzwk	()V
    //   18: aload_0
    //   19: invokevirtual 174	com/google/android/gms/internal/zzcay:getWritableDatabase	()Landroid/database/sqlite/SQLiteDatabase;
    //   22: astore 8
    //   24: aload 8
    //   26: invokevirtual 629	android/database/sqlite/SQLiteDatabase:beginTransaction	()V
    //   29: new 346	java/lang/StringBuilder
    //   32: dup
    //   33: aload_2
    //   34: invokestatic 447	java/lang/String:valueOf	(Ljava/lang/Object;)Ljava/lang/String;
    //   37: invokevirtual 1137	java/lang/String:length	()I
    //   40: bipush 32
    //   42: iadd
    //   43: invokespecial 353	java/lang/StringBuilder:<init>	(I)V
    //   46: astore 7
    //   48: aload 7
    //   50: ldc_w 1139
    //   53: invokevirtual 359	java/lang/StringBuilder:append	(Ljava/lang/String;)Ljava/lang/StringBuilder;
    //   56: pop
    //   57: aload 7
    //   59: aload_2
    //   60: invokevirtual 359	java/lang/StringBuilder:append	(Ljava/lang/String;)Ljava/lang/StringBuilder;
    //   63: pop
    //   64: aload 7
    //   66: ldc_w 1141
    //   69: invokevirtual 359	java/lang/StringBuilder:append	(Ljava/lang/String;)Ljava/lang/StringBuilder;
    //   72: pop
    //   73: aload 7
    //   75: invokevirtual 364	java/lang/StringBuilder:toString	()Ljava/lang/String;
    //   78: astore 7
    //   80: aload_0
    //   81: aload 7
    //   83: iconst_1
    //   84: anewarray 269	java/lang/String
    //   87: dup
    //   88: iconst_0
    //   89: aload_1
    //   90: aastore
    //   91: ldc2_w 494
    //   94: invokespecial 1143	com/google/android/gms/internal/zzcay:zza	(Ljava/lang/String;[Ljava/lang/String;J)J
    //   97: lstore 5
    //   99: lload 5
    //   101: lstore_3
    //   102: lload 5
    //   104: ldc2_w 494
    //   107: lcmp
    //   108: ifne +92 -> 200
    //   111: new 271	android/content/ContentValues
    //   114: dup
    //   115: invokespecial 471	android/content/ContentValues:<init>	()V
    //   118: astore 7
    //   120: aload 7
    //   122: ldc_w 473
    //   125: aload_1
    //   126: invokevirtual 274	android/content/ContentValues:put	(Ljava/lang/String;Ljava/lang/String;)V
    //   129: aload 7
    //   131: ldc_w 1145
    //   134: iconst_0
    //   135: invokestatic 226	java/lang/Integer:valueOf	(I)Ljava/lang/Integer;
    //   138: invokevirtual 478	android/content/ContentValues:put	(Ljava/lang/String;Ljava/lang/Integer;)V
    //   141: aload 7
    //   143: ldc -127
    //   145: iconst_0
    //   146: invokestatic 226	java/lang/Integer:valueOf	(I)Ljava/lang/Integer;
    //   149: invokevirtual 478	android/content/ContentValues:put	(Ljava/lang/String;Ljava/lang/Integer;)V
    //   152: aload 8
    //   154: ldc_w 1147
    //   157: aconst_null
    //   158: aload 7
    //   160: iconst_5
    //   161: invokevirtual 493	android/database/sqlite/SQLiteDatabase:insertWithOnConflict	(Ljava/lang/String;Ljava/lang/String;Landroid/content/ContentValues;I)J
    //   164: ldc2_w 494
    //   167: lcmp
    //   168: ifne +30 -> 198
    //   171: aload_0
    //   172: invokevirtual 197	com/google/android/gms/internal/zzcdt:zzaul	()Lcom/google/android/gms/internal/zzcbw;
    //   175: invokevirtual 203	com/google/android/gms/internal/zzcbw:zzayd	()Lcom/google/android/gms/internal/zzcby;
    //   178: ldc_w 1149
    //   181: aload_1
    //   182: invokestatic 440	com/google/android/gms/internal/zzcbw:zzjf	(Ljava/lang/String;)Ljava/lang/Object;
    //   185: aload_2
    //   186: invokevirtual 211	com/google/android/gms/internal/zzcby:zze	(Ljava/lang/String;Ljava/lang/Object;Ljava/lang/Object;)V
    //   189: aload 8
    //   191: invokevirtual 632	android/database/sqlite/SQLiteDatabase:endTransaction	()V
    //   194: ldc2_w 494
    //   197: lreturn
    //   198: lconst_0
    //   199: lstore_3
    //   200: new 271	android/content/ContentValues
    //   203: dup
    //   204: invokespecial 471	android/content/ContentValues:<init>	()V
    //   207: astore 7
    //   209: aload 7
    //   211: ldc_w 473
    //   214: aload_1
    //   215: invokevirtual 274	android/content/ContentValues:put	(Ljava/lang/String;Ljava/lang/String;)V
    //   218: aload 7
    //   220: aload_2
    //   221: lconst_1
    //   222: lload_3
    //   223: ladd
    //   224: invokestatic 254	java/lang/Long:valueOf	(J)Ljava/lang/Long;
    //   227: invokevirtual 277	android/content/ContentValues:put	(Ljava/lang/String;Ljava/lang/Long;)V
    //   230: aload 8
    //   232: ldc_w 1147
    //   235: aload 7
    //   237: ldc_w 809
    //   240: iconst_1
    //   241: anewarray 269	java/lang/String
    //   244: dup
    //   245: iconst_0
    //   246: aload_1
    //   247: aastore
    //   248: invokevirtual 711	android/database/sqlite/SQLiteDatabase:update	(Ljava/lang/String;Landroid/content/ContentValues;Ljava/lang/String;[Ljava/lang/String;)I
    //   251: i2l
    //   252: lconst_0
    //   253: lcmp
    //   254: ifne +30 -> 284
    //   257: aload_0
    //   258: invokevirtual 197	com/google/android/gms/internal/zzcdt:zzaul	()Lcom/google/android/gms/internal/zzcbw;
    //   261: invokevirtual 203	com/google/android/gms/internal/zzcbw:zzayd	()Lcom/google/android/gms/internal/zzcby;
    //   264: ldc_w 1151
    //   267: aload_1
    //   268: invokestatic 440	com/google/android/gms/internal/zzcbw:zzjf	(Ljava/lang/String;)Ljava/lang/Object;
    //   271: aload_2
    //   272: invokevirtual 211	com/google/android/gms/internal/zzcby:zze	(Ljava/lang/String;Ljava/lang/Object;Ljava/lang/Object;)V
    //   275: aload 8
    //   277: invokevirtual 632	android/database/sqlite/SQLiteDatabase:endTransaction	()V
    //   280: ldc2_w 494
    //   283: lreturn
    //   284: aload 8
    //   286: invokevirtual 638	android/database/sqlite/SQLiteDatabase:setTransactionSuccessful	()V
    //   289: goto +41 -> 330
    //   292: astore 7
    //   294: goto +16 -> 310
    //   297: astore 7
    //   299: goto +9 -> 308
    //   302: astore_1
    //   303: goto +35 -> 338
    //   306: astore 7
    //   308: lconst_0
    //   309: lstore_3
    //   310: aload_0
    //   311: invokevirtual 197	com/google/android/gms/internal/zzcdt:zzaul	()Lcom/google/android/gms/internal/zzcbw;
    //   314: invokevirtual 203	com/google/android/gms/internal/zzcbw:zzayd	()Lcom/google/android/gms/internal/zzcby;
    //   317: ldc_w 1153
    //   320: aload_1
    //   321: invokestatic 440	com/google/android/gms/internal/zzcbw:zzjf	(Ljava/lang/String;)Ljava/lang/Object;
    //   324: aload_2
    //   325: aload 7
    //   327: invokevirtual 451	com/google/android/gms/internal/zzcby:zzd	(Ljava/lang/String;Ljava/lang/Object;Ljava/lang/Object;Ljava/lang/Object;)V
    //   330: aload 8
    //   332: invokevirtual 632	android/database/sqlite/SQLiteDatabase:endTransaction	()V
    //   335: lload_3
    //   336: lreturn
    //   337: astore_1
    //   338: aload 8
    //   340: invokevirtual 632	android/database/sqlite/SQLiteDatabase:endTransaction	()V
    //   343: aload_1
    //   344: athrow
    // Local variable table:
    //   start	length	slot	name	signature
    //   0	345	0	this	zzcay
    //   0	345	1	paramString1	String
    //   0	345	2	paramString2	String
    //   101	235	3	l1	long
    //   97	6	5	l2	long
    //   46	190	7	localObject	Object
    //   292	1	7	localSQLiteException1	SQLiteException
    //   297	1	7	localSQLiteException2	SQLiteException
    //   306	20	7	localSQLiteException3	SQLiteException
    //   22	317	8	localSQLiteDatabase	SQLiteDatabase
    // Exception table:
    //   from	to	target	type
    //   200	275	292	android/database/sqlite/SQLiteException
    //   284	289	292	android/database/sqlite/SQLiteException
    //   80	99	297	android/database/sqlite/SQLiteException
    //   111	189	297	android/database/sqlite/SQLiteException
    //   29	80	302	finally
    //   29	80	306	android/database/sqlite/SQLiteException
    //   80	99	337	finally
    //   111	189	337	finally
    //   200	275	337	finally
    //   284	289	337	finally
    //   310	330	337	finally
  }
  
  /* Error */
  @X
  public final String zzaxi()
  {
    // Byte code:
    //   0: aload_0
    //   1: invokevirtual 174	com/google/android/gms/internal/zzcay:getWritableDatabase	()Landroid/database/sqlite/SQLiteDatabase;
    //   4: astore_1
    //   5: aload_1
    //   6: ldc_w 1156
    //   9: aconst_null
    //   10: invokevirtual 180	android/database/sqlite/SQLiteDatabase:rawQuery	(Ljava/lang/String;[Ljava/lang/String;)Landroid/database/Cursor;
    //   13: astore_2
    //   14: aload_2
    //   15: astore_1
    //   16: aload_2
    //   17: invokeinterface 186 1 0
    //   22: ifeq +21 -> 43
    //   25: aload_2
    //   26: astore_1
    //   27: aload_2
    //   28: iconst_0
    //   29: invokeinterface 240 2 0
    //   34: astore_3
    //   35: aload_2
    //   36: invokeinterface 193 1 0
    //   41: aload_3
    //   42: areturn
    //   43: aload_2
    //   44: invokeinterface 193 1 0
    //   49: aconst_null
    //   50: areturn
    //   51: astore_3
    //   52: goto +14 -> 66
    //   55: astore_1
    //   56: aconst_null
    //   57: astore_2
    //   58: aload_1
    //   59: astore_3
    //   60: goto +37 -> 97
    //   63: astore_3
    //   64: aconst_null
    //   65: astore_2
    //   66: aload_2
    //   67: astore_1
    //   68: aload_0
    //   69: invokevirtual 197	com/google/android/gms/internal/zzcdt:zzaul	()Lcom/google/android/gms/internal/zzcbw;
    //   72: invokevirtual 203	com/google/android/gms/internal/zzcbw:zzayd	()Lcom/google/android/gms/internal/zzcby;
    //   75: ldc_w 1158
    //   78: aload_3
    //   79: invokevirtual 230	com/google/android/gms/internal/zzcby:zzj	(Ljava/lang/String;Ljava/lang/Object;)V
    //   82: aload_2
    //   83: ifnull +9 -> 92
    //   86: aload_2
    //   87: invokeinterface 193 1 0
    //   92: aconst_null
    //   93: areturn
    //   94: astore_3
    //   95: aload_1
    //   96: astore_2
    //   97: aload_2
    //   98: ifnull +9 -> 107
    //   101: aload_2
    //   102: invokeinterface 193 1 0
    //   107: aload_3
    //   108: athrow
    // Local variable table:
    //   start	length	slot	name	signature
    //   0	109	0	this	zzcay
    //   4	23	1	localObject1	Object
    //   55	4	1	localObject2	Object
    //   67	29	1	localObject3	Object
    //   13	89	2	localObject4	Object
    //   34	8	3	str	String
    //   51	1	3	localSQLiteException1	SQLiteException
    //   59	1	3	localObject5	Object
    //   63	16	3	localSQLiteException2	SQLiteException
    //   94	14	3	localObject6	Object
    // Exception table:
    //   from	to	target	type
    //   16	25	51	android/database/sqlite/SQLiteException
    //   27	35	51	android/database/sqlite/SQLiteException
    //   5	14	55	finally
    //   5	14	63	android/database/sqlite/SQLiteException
    //   16	25	94	finally
    //   27	35	94	finally
    //   68	82	94	finally
  }
  
  public final boolean zzaxj()
  {
    return zzb("select count(1) > 0 from queue where has_realtime = 1", null) != 0L;
  }
  
  @X
  public final void zzaxk()
  {
    zzuj();
    zzwk();
    if (!zzaxq()) {
      return;
    }
    long l1 = zzaumzziqs.get();
    long l2 = zzvx().elapsedRealtime();
    if (Math.abs(l2 - l1) > zzcax.zzawn())
    {
      zzaumzziqs.set(l2);
      zzuj();
      zzwk();
      if (zzaxq())
      {
        int i = getWritableDatabase().delete("queue", "abs(bundle_end_timestamp - ?) > cast(? as integer)", new String[] { String.valueOf(zzvx().currentTimeMillis()), String.valueOf(zzcax.zzawm()) });
        if (i > 0) {
          zzaul().zzayj().zzj("Deleted stale rows. rowsDeleted", Integer.valueOf(i));
        }
      }
    }
  }
  
  @X
  public final long zzaxl()
  {
    return zza("select max(bundle_end_timestamp) from queue", null, 0L);
  }
  
  @X
  public final long zzaxm()
  {
    return zza("select max(timestamp) from raw_events", null, 0L);
  }
  
  public final boolean zzaxn()
  {
    return zzb("select count(1) > 0 from raw_events", null) != 0L;
  }
  
  public final boolean zzaxo()
  {
    return zzb("select count(1) > 0 from raw_events where realtime = 1", null) != 0L;
  }
  
  /* Error */
  public final long zzaxp()
  {
    // Byte code:
    //   0: aconst_null
    //   1: astore 5
    //   3: aconst_null
    //   4: astore 4
    //   6: aload_0
    //   7: invokevirtual 174	com/google/android/gms/internal/zzcay:getWritableDatabase	()Landroid/database/sqlite/SQLiteDatabase;
    //   10: ldc_w 1224
    //   13: aconst_null
    //   14: invokevirtual 180	android/database/sqlite/SQLiteDatabase:rawQuery	(Ljava/lang/String;[Ljava/lang/String;)Landroid/database/Cursor;
    //   17: astore 6
    //   19: aload 6
    //   21: astore 4
    //   23: aload 6
    //   25: astore 5
    //   27: aload 6
    //   29: invokeinterface 186 1 0
    //   34: istore_1
    //   35: iload_1
    //   36: ifne +14 -> 50
    //   39: aload 6
    //   41: invokeinterface 193 1 0
    //   46: ldc2_w 494
    //   49: lreturn
    //   50: aload 6
    //   52: astore 4
    //   54: aload 6
    //   56: astore 5
    //   58: aload 6
    //   60: iconst_0
    //   61: invokeinterface 190 2 0
    //   66: lstore_2
    //   67: aload 6
    //   69: invokeinterface 193 1 0
    //   74: lload_2
    //   75: lreturn
    //   76: astore 5
    //   78: goto +40 -> 118
    //   81: astore 6
    //   83: aload 5
    //   85: astore 4
    //   87: aload_0
    //   88: invokevirtual 197	com/google/android/gms/internal/zzcdt:zzaul	()Lcom/google/android/gms/internal/zzcbw;
    //   91: invokevirtual 203	com/google/android/gms/internal/zzcbw:zzayd	()Lcom/google/android/gms/internal/zzcby;
    //   94: ldc_w 1226
    //   97: aload 6
    //   99: invokevirtual 230	com/google/android/gms/internal/zzcby:zzj	(Ljava/lang/String;Ljava/lang/Object;)V
    //   102: aload 5
    //   104: ifnull +10 -> 114
    //   107: aload 5
    //   109: invokeinterface 193 1 0
    //   114: ldc2_w 494
    //   117: lreturn
    //   118: aload 4
    //   120: ifnull +10 -> 130
    //   123: aload 4
    //   125: invokeinterface 193 1 0
    //   130: aload 5
    //   132: athrow
    // Local variable table:
    //   start	length	slot	name	signature
    //   0	133	0	this	zzcay
    //   34	2	1	bool	boolean
    //   66	9	2	l	long
    //   4	120	4	localObject1	Object
    //   1	56	5	localObject2	Object
    //   76	55	5	localObject3	Object
    //   17	51	6	localCursor	Cursor
    //   81	17	6	localSQLiteException	SQLiteException
    // Exception table:
    //   from	to	target	type
    //   6	19	76	finally
    //   27	35	76	finally
    //   58	67	76	finally
    //   87	102	76	finally
    //   6	19	81	android/database/sqlite/SQLiteException
    //   27	35	81	android/database/sqlite/SQLiteException
    //   58	67	81	android/database/sqlite/SQLiteException
  }
  
  /* Error */
  public final String zzba(long paramLong)
  {
    // Byte code:
    //   0: aload_0
    //   1: invokevirtual 425	com/google/android/gms/internal/zzcdt:zzuj	()V
    //   4: aload_0
    //   5: invokevirtual 422	com/google/android/gms/internal/zzcdu:zzwk	()V
    //   8: aload_0
    //   9: invokevirtual 174	com/google/android/gms/internal/zzcay:getWritableDatabase	()Landroid/database/sqlite/SQLiteDatabase;
    //   12: ldc_w 1229
    //   15: iconst_1
    //   16: anewarray 269	java/lang/String
    //   19: dup
    //   20: iconst_0
    //   21: lload_1
    //   22: invokestatic 1204	java/lang/String:valueOf	(J)Ljava/lang/String;
    //   25: aastore
    //   26: invokevirtual 180	android/database/sqlite/SQLiteDatabase:rawQuery	(Ljava/lang/String;[Ljava/lang/String;)Landroid/database/Cursor;
    //   29: astore 4
    //   31: aload 4
    //   33: astore_3
    //   34: aload 4
    //   36: invokeinterface 186 1 0
    //   41: ifne +28 -> 69
    //   44: aload 4
    //   46: astore_3
    //   47: aload_0
    //   48: invokevirtual 197	com/google/android/gms/internal/zzcdt:zzaul	()Lcom/google/android/gms/internal/zzcbw;
    //   51: invokevirtual 1053	com/google/android/gms/internal/zzcbw:zzayj	()Lcom/google/android/gms/internal/zzcby;
    //   54: ldc_w 1231
    //   57: invokevirtual 236	com/google/android/gms/internal/zzcby:log	(Ljava/lang/String;)V
    //   60: aload 4
    //   62: invokeinterface 193 1 0
    //   67: aconst_null
    //   68: areturn
    //   69: aload 4
    //   71: astore_3
    //   72: aload 4
    //   74: iconst_0
    //   75: invokeinterface 240 2 0
    //   80: astore 5
    //   82: aload 4
    //   84: invokeinterface 193 1 0
    //   89: aload 5
    //   91: areturn
    //   92: astore 5
    //   94: goto +15 -> 109
    //   97: astore 4
    //   99: aconst_null
    //   100: astore_3
    //   101: goto +42 -> 143
    //   104: astore 5
    //   106: aconst_null
    //   107: astore 4
    //   109: aload 4
    //   111: astore_3
    //   112: aload_0
    //   113: invokevirtual 197	com/google/android/gms/internal/zzcdt:zzaul	()Lcom/google/android/gms/internal/zzcbw;
    //   116: invokevirtual 203	com/google/android/gms/internal/zzcbw:zzayd	()Lcom/google/android/gms/internal/zzcby;
    //   119: ldc_w 1233
    //   122: aload 5
    //   124: invokevirtual 230	com/google/android/gms/internal/zzcby:zzj	(Ljava/lang/String;Ljava/lang/Object;)V
    //   127: aload 4
    //   129: ifnull +10 -> 139
    //   132: aload 4
    //   134: invokeinterface 193 1 0
    //   139: aconst_null
    //   140: areturn
    //   141: astore 4
    //   143: aload_3
    //   144: ifnull +9 -> 153
    //   147: aload_3
    //   148: invokeinterface 193 1 0
    //   153: aload 4
    //   155: athrow
    // Local variable table:
    //   start	length	slot	name	signature
    //   0	156	0	this	zzcay
    //   0	156	1	paramLong	long
    //   33	115	3	localObject1	Object
    //   29	54	4	localCursor	Cursor
    //   97	1	4	localObject2	Object
    //   107	26	4	localObject3	Object
    //   141	13	4	localObject4	Object
    //   80	10	5	str	String
    //   92	1	5	localSQLiteException1	SQLiteException
    //   104	19	5	localSQLiteException2	SQLiteException
    // Exception table:
    //   from	to	target	type
    //   34	44	92	android/database/sqlite/SQLiteException
    //   47	60	92	android/database/sqlite/SQLiteException
    //   72	82	92	android/database/sqlite/SQLiteException
    //   8	31	97	finally
    //   8	31	104	android/database/sqlite/SQLiteException
    //   34	44	141	finally
    //   47	60	141	finally
    //   72	82	141	finally
    //   112	127	141	finally
  }
  
  /* Error */
  public final List<zzcav> zzc(String paramString, String[] paramArrayOfString)
  {
    // Byte code:
    //   0: aload_0
    //   1: invokevirtual 425	com/google/android/gms/internal/zzcdt:zzuj	()V
    //   4: aload_0
    //   5: invokevirtual 422	com/google/android/gms/internal/zzcdu:zzwk	()V
    //   8: new 591	java/util/ArrayList
    //   11: dup
    //   12: invokespecial 592	java/util/ArrayList:<init>	()V
    //   15: astore 17
    //   17: aconst_null
    //   18: astore 16
    //   20: aconst_null
    //   21: astore 15
    //   23: aload 15
    //   25: astore 13
    //   27: aload 16
    //   29: astore 14
    //   31: aload_0
    //   32: invokevirtual 174	com/google/android/gms/internal/zzcay:getWritableDatabase	()Landroid/database/sqlite/SQLiteDatabase;
    //   35: astore 18
    //   37: aload 15
    //   39: astore 13
    //   41: aload 16
    //   43: astore 14
    //   45: invokestatic 896	com/google/android/gms/internal/zzcax:zzawb	()I
    //   48: pop
    //   49: aload 15
    //   51: astore 13
    //   53: aload 16
    //   55: astore 14
    //   57: aload 18
    //   59: ldc_w 958
    //   62: bipush 13
    //   64: anewarray 269	java/lang/String
    //   67: dup
    //   68: iconst_0
    //   69: ldc_w 473
    //   72: aastore
    //   73: dup
    //   74: iconst_1
    //   75: ldc 27
    //   77: aastore
    //   78: dup
    //   79: iconst_2
    //   80: ldc_w 408
    //   83: aastore
    //   84: dup
    //   85: iconst_3
    //   86: ldc_w 903
    //   89: aastore
    //   90: dup
    //   91: iconst_4
    //   92: ldc_w 908
    //   95: aastore
    //   96: dup
    //   97: iconst_5
    //   98: ldc_w 914
    //   101: aastore
    //   102: dup
    //   103: bipush 6
    //   105: ldc_w 919
    //   108: aastore
    //   109: dup
    //   110: bipush 7
    //   112: ldc_w 924
    //   115: aastore
    //   116: dup
    //   117: bipush 8
    //   119: ldc_w 933
    //   122: aastore
    //   123: dup
    //   124: bipush 9
    //   126: ldc_w 938
    //   129: aastore
    //   130: dup
    //   131: bipush 10
    //   133: ldc_w 943
    //   136: aastore
    //   137: dup
    //   138: bipush 11
    //   140: ldc_w 948
    //   143: aastore
    //   144: dup
    //   145: bipush 12
    //   147: ldc_w 953
    //   150: aastore
    //   151: aload_1
    //   152: aload_2
    //   153: aconst_null
    //   154: aconst_null
    //   155: ldc_w 1236
    //   158: ldc_w 1238
    //   161: invokevirtual 1241	android/database/sqlite/SQLiteDatabase:query	(Ljava/lang/String;[Ljava/lang/String;Ljava/lang/String;[Ljava/lang/String;Ljava/lang/String;Ljava/lang/String;Ljava/lang/String;Ljava/lang/String;)Landroid/database/Cursor;
    //   164: astore_1
    //   165: aload_1
    //   166: astore 13
    //   168: aload_1
    //   169: astore 14
    //   171: aload_1
    //   172: invokeinterface 186 1 0
    //   177: istore 4
    //   179: iload 4
    //   181: ifne +12 -> 193
    //   184: aload_1
    //   185: invokeinterface 193 1 0
    //   190: aload 17
    //   192: areturn
    //   193: aload_1
    //   194: astore 13
    //   196: aload_1
    //   197: astore 14
    //   199: aload 17
    //   201: invokeinterface 597 1 0
    //   206: istore_3
    //   207: aload_1
    //   208: astore 13
    //   210: aload_1
    //   211: astore 14
    //   213: invokestatic 896	com/google/android/gms/internal/zzcax:zzawb	()I
    //   216: pop
    //   217: iload_3
    //   218: sipush 1000
    //   221: if_icmplt +49 -> 270
    //   224: aload_1
    //   225: astore 13
    //   227: aload_1
    //   228: astore 14
    //   230: aload_0
    //   231: invokevirtual 197	com/google/android/gms/internal/zzcdt:zzaul	()Lcom/google/android/gms/internal/zzcbw;
    //   234: invokevirtual 203	com/google/android/gms/internal/zzcbw:zzayd	()Lcom/google/android/gms/internal/zzcby;
    //   237: astore_2
    //   238: aload_1
    //   239: astore 13
    //   241: aload_1
    //   242: astore 14
    //   244: invokestatic 896	com/google/android/gms/internal/zzcax:zzawb	()I
    //   247: pop
    //   248: aload_1
    //   249: astore 13
    //   251: aload_1
    //   252: astore 14
    //   254: aload_2
    //   255: ldc_w 1243
    //   258: sipush 1000
    //   261: invokestatic 226	java/lang/Integer:valueOf	(I)Ljava/lang/Integer;
    //   264: invokevirtual 230	com/google/android/gms/internal/zzcby:zzj	(Ljava/lang/String;Ljava/lang/Object;)V
    //   267: goto +323 -> 590
    //   270: iconst_0
    //   271: istore 4
    //   273: aload_1
    //   274: astore 13
    //   276: aload_1
    //   277: astore 14
    //   279: aload_1
    //   280: iconst_0
    //   281: invokeinterface 240 2 0
    //   286: astore_2
    //   287: aload_1
    //   288: astore 13
    //   290: aload_1
    //   291: astore 14
    //   293: aload_1
    //   294: iconst_1
    //   295: invokeinterface 240 2 0
    //   300: astore 15
    //   302: aload_1
    //   303: astore 13
    //   305: aload_1
    //   306: astore 14
    //   308: aload_1
    //   309: iconst_2
    //   310: invokeinterface 240 2 0
    //   315: astore 16
    //   317: aload_1
    //   318: astore 13
    //   320: aload_1
    //   321: astore 14
    //   323: aload_0
    //   324: aload_1
    //   325: iconst_3
    //   326: invokespecial 1062	com/google/android/gms/internal/zzcay:zza	(Landroid/database/Cursor;I)Ljava/lang/Object;
    //   329: astore 18
    //   331: aload_1
    //   332: astore 13
    //   334: aload_1
    //   335: astore 14
    //   337: aload_1
    //   338: iconst_4
    //   339: invokeinterface 1074 2 0
    //   344: ifeq +6 -> 350
    //   347: iconst_1
    //   348: istore 4
    //   350: aload_1
    //   351: astore 13
    //   353: aload_1
    //   354: astore 14
    //   356: aload_1
    //   357: iconst_5
    //   358: invokeinterface 240 2 0
    //   363: astore 19
    //   365: aload_1
    //   366: astore 13
    //   368: aload_1
    //   369: astore 14
    //   371: aload_1
    //   372: bipush 6
    //   374: invokeinterface 190 2 0
    //   379: lstore 5
    //   381: aload_1
    //   382: astore 13
    //   384: aload_1
    //   385: astore 14
    //   387: aload_0
    //   388: invokevirtual 649	com/google/android/gms/internal/zzcdt:zzauh	()Lcom/google/android/gms/internal/zzcfw;
    //   391: aload_1
    //   392: bipush 7
    //   394: invokeinterface 1078 2 0
    //   399: getstatic 1084	com/google/android/gms/internal/zzcbk:CREATOR	Landroid/os/Parcelable$Creator;
    //   402: invokevirtual 1087	com/google/android/gms/internal/zzcfw:zzb	([BLandroid/os/Parcelable$Creator;)Landroid/os/Parcelable;
    //   405: checkcast 1080	com/google/android/gms/internal/zzcbk
    //   408: astore 20
    //   410: aload_1
    //   411: astore 13
    //   413: aload_1
    //   414: astore 14
    //   416: aload_1
    //   417: bipush 8
    //   419: invokeinterface 190 2 0
    //   424: lstore 7
    //   426: aload_1
    //   427: astore 13
    //   429: aload_1
    //   430: astore 14
    //   432: aload_0
    //   433: invokevirtual 649	com/google/android/gms/internal/zzcdt:zzauh	()Lcom/google/android/gms/internal/zzcfw;
    //   436: aload_1
    //   437: bipush 9
    //   439: invokeinterface 1078 2 0
    //   444: getstatic 1084	com/google/android/gms/internal/zzcbk:CREATOR	Landroid/os/Parcelable$Creator;
    //   447: invokevirtual 1087	com/google/android/gms/internal/zzcfw:zzb	([BLandroid/os/Parcelable$Creator;)Landroid/os/Parcelable;
    //   450: checkcast 1080	com/google/android/gms/internal/zzcbk
    //   453: astore 21
    //   455: aload_1
    //   456: astore 13
    //   458: aload_1
    //   459: astore 14
    //   461: aload_1
    //   462: bipush 10
    //   464: invokeinterface 190 2 0
    //   469: lstore 9
    //   471: aload_1
    //   472: astore 13
    //   474: aload_1
    //   475: astore 14
    //   477: aload_1
    //   478: bipush 11
    //   480: invokeinterface 190 2 0
    //   485: lstore 11
    //   487: aload_1
    //   488: astore 13
    //   490: aload_1
    //   491: astore 14
    //   493: aload_0
    //   494: invokevirtual 649	com/google/android/gms/internal/zzcdt:zzauh	()Lcom/google/android/gms/internal/zzcfw;
    //   497: aload_1
    //   498: bipush 12
    //   500: invokeinterface 1078 2 0
    //   505: getstatic 1084	com/google/android/gms/internal/zzcbk:CREATOR	Landroid/os/Parcelable$Creator;
    //   508: invokevirtual 1087	com/google/android/gms/internal/zzcfw:zzb	([BLandroid/os/Parcelable$Creator;)Landroid/os/Parcelable;
    //   511: checkcast 1080	com/google/android/gms/internal/zzcbk
    //   514: astore 22
    //   516: aload_1
    //   517: astore 13
    //   519: aload_1
    //   520: astore 14
    //   522: aload 17
    //   524: new 876	com/google/android/gms/internal/zzcav
    //   527: dup
    //   528: aload_2
    //   529: aload 15
    //   531: new 885	com/google/android/gms/internal/zzcft
    //   534: dup
    //   535: aload 16
    //   537: lload 9
    //   539: aload 18
    //   541: aload 15
    //   543: invokespecial 1090	com/google/android/gms/internal/zzcft:<init>	(Ljava/lang/String;JLjava/lang/Object;Ljava/lang/String;)V
    //   546: lload 7
    //   548: iload 4
    //   550: aload 19
    //   552: aload 20
    //   554: lload 5
    //   556: aload 21
    //   558: lload 11
    //   560: aload 22
    //   562: invokespecial 1093	com/google/android/gms/internal/zzcav:<init>	(Ljava/lang/String;Ljava/lang/String;Lcom/google/android/gms/internal/zzcft;JZLjava/lang/String;Lcom/google/android/gms/internal/zzcbk;JLcom/google/android/gms/internal/zzcbk;JLcom/google/android/gms/internal/zzcbk;)V
    //   565: invokeinterface 609 2 0
    //   570: pop
    //   571: aload_1
    //   572: astore 13
    //   574: aload_1
    //   575: astore 14
    //   577: aload_1
    //   578: invokeinterface 1036 1 0
    //   583: istore 4
    //   585: iload 4
    //   587: ifne -394 -> 193
    //   590: aload_1
    //   591: invokeinterface 193 1 0
    //   596: aload 17
    //   598: areturn
    //   599: astore_1
    //   600: goto +44 -> 644
    //   603: astore_1
    //   604: aload 14
    //   606: astore 13
    //   608: aload_0
    //   609: invokevirtual 197	com/google/android/gms/internal/zzcdt:zzaul	()Lcom/google/android/gms/internal/zzcbw;
    //   612: invokevirtual 203	com/google/android/gms/internal/zzcbw:zzayd	()Lcom/google/android/gms/internal/zzcby;
    //   615: ldc_w 1245
    //   618: aload_1
    //   619: invokevirtual 230	com/google/android/gms/internal/zzcby:zzj	(Ljava/lang/String;Ljava/lang/Object;)V
    //   622: aload 14
    //   624: astore 13
    //   626: invokestatic 1249	java/util/Collections:emptyList	()Ljava/util/List;
    //   629: astore_1
    //   630: aload 14
    //   632: ifnull +10 -> 642
    //   635: aload 14
    //   637: invokeinterface 193 1 0
    //   642: aload_1
    //   643: areturn
    //   644: aload 13
    //   646: ifnull +10 -> 656
    //   649: aload 13
    //   651: invokeinterface 193 1 0
    //   656: goto +5 -> 661
    //   659: aload_1
    //   660: athrow
    //   661: goto -2 -> 659
    // Local variable table:
    //   start	length	slot	name	signature
    //   0	664	0	this	zzcay
    //   0	664	1	paramString	String
    //   0	664	2	paramArrayOfString	String[]
    //   206	16	3	i	int
    //   177	409	4	bool	boolean
    //   379	176	5	l1	long
    //   424	123	7	l2	long
    //   469	69	9	l3	long
    //   485	74	11	l4	long
    //   25	625	13	localObject1	Object
    //   29	607	14	str1	String
    //   21	521	15	str2	String
    //   18	518	16	str3	String
    //   15	582	17	localArrayList	ArrayList
    //   35	505	18	localObject2	Object
    //   363	188	19	str4	String
    //   408	145	20	localZzcbk1	zzcbk
    //   453	104	21	localZzcbk2	zzcbk
    //   514	47	22	localZzcbk3	zzcbk
    // Exception table:
    //   from	to	target	type
    //   31	37	599	finally
    //   45	49	599	finally
    //   57	165	599	finally
    //   171	179	599	finally
    //   199	207	599	finally
    //   213	217	599	finally
    //   230	238	599	finally
    //   244	248	599	finally
    //   254	267	599	finally
    //   279	287	599	finally
    //   293	302	599	finally
    //   308	317	599	finally
    //   323	331	599	finally
    //   337	347	599	finally
    //   356	365	599	finally
    //   371	381	599	finally
    //   387	410	599	finally
    //   416	426	599	finally
    //   432	455	599	finally
    //   461	471	599	finally
    //   477	487	599	finally
    //   493	516	599	finally
    //   522	571	599	finally
    //   577	585	599	finally
    //   608	622	599	finally
    //   626	630	599	finally
    //   31	37	603	android/database/sqlite/SQLiteException
    //   45	49	603	android/database/sqlite/SQLiteException
    //   57	165	603	android/database/sqlite/SQLiteException
    //   171	179	603	android/database/sqlite/SQLiteException
    //   199	207	603	android/database/sqlite/SQLiteException
    //   213	217	603	android/database/sqlite/SQLiteException
    //   230	238	603	android/database/sqlite/SQLiteException
    //   244	248	603	android/database/sqlite/SQLiteException
    //   254	267	603	android/database/sqlite/SQLiteException
    //   279	287	603	android/database/sqlite/SQLiteException
    //   293	302	603	android/database/sqlite/SQLiteException
    //   308	317	603	android/database/sqlite/SQLiteException
    //   323	331	603	android/database/sqlite/SQLiteException
    //   337	347	603	android/database/sqlite/SQLiteException
    //   356	365	603	android/database/sqlite/SQLiteException
    //   371	381	603	android/database/sqlite/SQLiteException
    //   387	410	603	android/database/sqlite/SQLiteException
    //   416	426	603	android/database/sqlite/SQLiteException
    //   432	455	603	android/database/sqlite/SQLiteException
    //   461	471	603	android/database/sqlite/SQLiteException
    //   477	487	603	android/database/sqlite/SQLiteException
    //   493	516	603	android/database/sqlite/SQLiteException
    //   522	571	603	android/database/sqlite/SQLiteException
    //   577	585	603	android/database/sqlite/SQLiteException
  }
  
  /* Error */
  @X
  public final List<zzcfv> zzg(String paramString1, String paramString2, String paramString3)
  {
    // Byte code:
    //   0: aload_1
    //   1: invokestatic 263	com/google/android/gms/common/internal/zzbp:zzgg	(Ljava/lang/String;)Ljava/lang/String;
    //   4: pop
    //   5: aload_0
    //   6: invokevirtual 425	com/google/android/gms/internal/zzcdt:zzuj	()V
    //   9: aload_0
    //   10: invokevirtual 422	com/google/android/gms/internal/zzcdu:zzwk	()V
    //   13: new 591	java/util/ArrayList
    //   16: dup
    //   17: invokespecial 592	java/util/ArrayList:<init>	()V
    //   20: astore 11
    //   22: aconst_null
    //   23: astore 10
    //   25: new 591	java/util/ArrayList
    //   28: dup
    //   29: iconst_3
    //   30: invokespecial 1253	java/util/ArrayList:<init>	(I)V
    //   33: astore 12
    //   35: aload 12
    //   37: aload_1
    //   38: invokeinterface 609 2 0
    //   43: pop
    //   44: new 346	java/lang/StringBuilder
    //   47: dup
    //   48: ldc_w 689
    //   51: invokespecial 1015	java/lang/StringBuilder:<init>	(Ljava/lang/String;)V
    //   54: astore 8
    //   56: aload_2
    //   57: invokestatic 434	android/text/TextUtils:isEmpty	(Ljava/lang/CharSequence;)Z
    //   60: istore 5
    //   62: iload 5
    //   64: ifne +495 -> 559
    //   67: aload 12
    //   69: aload_2
    //   70: invokeinterface 609 2 0
    //   75: pop
    //   76: aload 8
    //   78: ldc_w 1255
    //   81: invokevirtual 359	java/lang/StringBuilder:append	(Ljava/lang/String;)Ljava/lang/StringBuilder;
    //   84: pop
    //   85: goto +3 -> 88
    //   88: aload_2
    //   89: astore 9
    //   91: aload_3
    //   92: invokestatic 434	android/text/TextUtils:isEmpty	(Ljava/lang/CharSequence;)Z
    //   95: ifne +30 -> 125
    //   98: aload 12
    //   100: aload_3
    //   101: invokestatic 447	java/lang/String:valueOf	(Ljava/lang/Object;)Ljava/lang/String;
    //   104: ldc_w 1257
    //   107: invokevirtual 1260	java/lang/String:concat	(Ljava/lang/String;)Ljava/lang/String;
    //   110: invokeinterface 609 2 0
    //   115: pop
    //   116: aload 8
    //   118: ldc_w 1262
    //   121: invokevirtual 359	java/lang/StringBuilder:append	(Ljava/lang/String;)Ljava/lang/StringBuilder;
    //   124: pop
    //   125: aload 12
    //   127: aload 12
    //   129: invokeinterface 597 1 0
    //   134: anewarray 269	java/lang/String
    //   137: invokeinterface 1266 2 0
    //   142: checkcast 1268	[Ljava/lang/String;
    //   145: astore 12
    //   147: aload_0
    //   148: invokevirtual 174	com/google/android/gms/internal/zzcay:getWritableDatabase	()Landroid/database/sqlite/SQLiteDatabase;
    //   151: astore 13
    //   153: aload 8
    //   155: invokevirtual 364	java/lang/StringBuilder:toString	()Ljava/lang/String;
    //   158: astore 8
    //   160: invokestatic 1271	com/google/android/gms/internal/zzcax:zzavz	()I
    //   163: pop
    //   164: aload 13
    //   166: ldc_w 1005
    //   169: iconst_4
    //   170: anewarray 269	java/lang/String
    //   173: dup
    //   174: iconst_0
    //   175: ldc_w 408
    //   178: aastore
    //   179: dup
    //   180: iconst_1
    //   181: ldc_w 996
    //   184: aastore
    //   185: dup
    //   186: iconst_2
    //   187: ldc_w 903
    //   190: aastore
    //   191: dup
    //   192: iconst_3
    //   193: ldc 27
    //   195: aastore
    //   196: aload 8
    //   198: aload 12
    //   200: aconst_null
    //   201: aconst_null
    //   202: ldc_w 1236
    //   205: ldc_w 1238
    //   208: invokevirtual 1241	android/database/sqlite/SQLiteDatabase:query	(Ljava/lang/String;[Ljava/lang/String;Ljava/lang/String;[Ljava/lang/String;Ljava/lang/String;Ljava/lang/String;Ljava/lang/String;Ljava/lang/String;)Landroid/database/Cursor;
    //   211: astore 8
    //   213: aload 9
    //   215: astore 10
    //   217: aload 8
    //   219: invokeinterface 186 1 0
    //   224: istore 5
    //   226: aload 9
    //   228: astore_2
    //   229: iload 5
    //   231: ifne +13 -> 244
    //   234: aload 8
    //   236: invokeinterface 193 1 0
    //   241: aload 11
    //   243: areturn
    //   244: aload_2
    //   245: astore 10
    //   247: aload 11
    //   249: invokeinterface 597 1 0
    //   254: istore 4
    //   256: aload_2
    //   257: astore 10
    //   259: invokestatic 1271	com/google/android/gms/internal/zzcax:zzavz	()I
    //   262: pop
    //   263: iload 4
    //   265: sipush 1000
    //   268: if_icmplt +40 -> 308
    //   271: aload_2
    //   272: astore 10
    //   274: aload_0
    //   275: invokevirtual 197	com/google/android/gms/internal/zzcdt:zzaul	()Lcom/google/android/gms/internal/zzcbw;
    //   278: invokevirtual 203	com/google/android/gms/internal/zzcbw:zzayd	()Lcom/google/android/gms/internal/zzcby;
    //   281: astore_3
    //   282: aload_2
    //   283: astore 10
    //   285: invokestatic 1271	com/google/android/gms/internal/zzcax:zzavz	()I
    //   288: pop
    //   289: aload_2
    //   290: astore 10
    //   292: aload_3
    //   293: ldc_w 1273
    //   296: sipush 1000
    //   299: invokestatic 226	java/lang/Integer:valueOf	(I)Ljava/lang/Integer;
    //   302: invokevirtual 230	com/google/android/gms/internal/zzcby:zzj	(Ljava/lang/String;Ljava/lang/Object;)V
    //   305: goto +134 -> 439
    //   308: aload_2
    //   309: astore 10
    //   311: aload 8
    //   313: iconst_0
    //   314: invokeinterface 240 2 0
    //   319: astore 12
    //   321: aload_2
    //   322: astore 10
    //   324: aload 8
    //   326: iconst_1
    //   327: invokeinterface 190 2 0
    //   332: lstore 6
    //   334: aload 8
    //   336: astore 9
    //   338: aload_0
    //   339: aload 8
    //   341: iconst_2
    //   342: invokespecial 1062	com/google/android/gms/internal/zzcay:zza	(Landroid/database/Cursor;I)Ljava/lang/Object;
    //   345: astore 13
    //   347: aload 8
    //   349: astore 9
    //   351: aload 8
    //   353: iconst_3
    //   354: invokeinterface 240 2 0
    //   359: astore 10
    //   361: aload 13
    //   363: ifnonnull +30 -> 393
    //   366: aload 8
    //   368: astore 9
    //   370: aload_0
    //   371: invokevirtual 197	com/google/android/gms/internal/zzcdt:zzaul	()Lcom/google/android/gms/internal/zzcbw;
    //   374: invokevirtual 203	com/google/android/gms/internal/zzcbw:zzayd	()Lcom/google/android/gms/internal/zzcby;
    //   377: ldc_w 1275
    //   380: aload_1
    //   381: invokestatic 440	com/google/android/gms/internal/zzcbw:zzjf	(Ljava/lang/String;)Ljava/lang/Object;
    //   384: aload 10
    //   386: aload_3
    //   387: invokevirtual 451	com/google/android/gms/internal/zzcby:zzd	(Ljava/lang/String;Ljava/lang/Object;Ljava/lang/Object;Ljava/lang/Object;)V
    //   390: goto +31 -> 421
    //   393: aload 8
    //   395: astore 9
    //   397: aload 11
    //   399: new 973	com/google/android/gms/internal/zzcfv
    //   402: dup
    //   403: aload_1
    //   404: aload 10
    //   406: aload 12
    //   408: lload 6
    //   410: aload 13
    //   412: invokespecial 1065	com/google/android/gms/internal/zzcfv:<init>	(Ljava/lang/String;Ljava/lang/String;Ljava/lang/String;JLjava/lang/Object;)V
    //   415: invokeinterface 609 2 0
    //   420: pop
    //   421: aload 8
    //   423: astore 9
    //   425: aload 8
    //   427: invokeinterface 1036 1 0
    //   432: istore 5
    //   434: iload 5
    //   436: ifne +13 -> 449
    //   439: aload 8
    //   441: invokeinterface 193 1 0
    //   446: aload 11
    //   448: areturn
    //   449: aload 10
    //   451: astore_2
    //   452: goto -208 -> 244
    //   455: astore_3
    //   456: aload 10
    //   458: astore_2
    //   459: goto +37 -> 496
    //   462: astore_3
    //   463: goto +33 -> 496
    //   466: astore_1
    //   467: goto +71 -> 538
    //   470: astore_3
    //   471: aload 10
    //   473: astore_2
    //   474: goto +22 -> 496
    //   477: astore_3
    //   478: goto +15 -> 493
    //   481: astore_3
    //   482: goto +11 -> 493
    //   485: astore_1
    //   486: aload 10
    //   488: astore_2
    //   489: goto +52 -> 541
    //   492: astore_3
    //   493: aconst_null
    //   494: astore 8
    //   496: aload 8
    //   498: astore 9
    //   500: aload_0
    //   501: invokevirtual 197	com/google/android/gms/internal/zzcdt:zzaul	()Lcom/google/android/gms/internal/zzcbw;
    //   504: invokevirtual 203	com/google/android/gms/internal/zzcbw:zzayd	()Lcom/google/android/gms/internal/zzcby;
    //   507: ldc_w 1277
    //   510: aload_1
    //   511: invokestatic 440	com/google/android/gms/internal/zzcbw:zzjf	(Ljava/lang/String;)Ljava/lang/Object;
    //   514: aload_2
    //   515: aload_3
    //   516: invokevirtual 451	com/google/android/gms/internal/zzcby:zzd	(Ljava/lang/String;Ljava/lang/Object;Ljava/lang/Object;Ljava/lang/Object;)V
    //   519: aload 8
    //   521: ifnull +10 -> 531
    //   524: aload 8
    //   526: invokeinterface 193 1 0
    //   531: aconst_null
    //   532: areturn
    //   533: astore_1
    //   534: aload 9
    //   536: astore 8
    //   538: aload 8
    //   540: astore_2
    //   541: aload_2
    //   542: ifnull +9 -> 551
    //   545: aload_2
    //   546: invokeinterface 193 1 0
    //   551: goto +5 -> 556
    //   554: aload_1
    //   555: athrow
    //   556: goto -2 -> 554
    //   559: goto -471 -> 88
    // Local variable table:
    //   start	length	slot	name	signature
    //   0	562	0	this	zzcay
    //   0	562	1	paramString1	String
    //   0	562	2	paramString2	String
    //   0	562	3	paramString3	String
    //   254	15	4	i	int
    //   60	375	5	bool	boolean
    //   332	77	6	l	long
    //   54	485	8	localObject1	Object
    //   89	446	9	localObject2	Object
    //   23	464	10	localObject3	Object
    //   20	427	11	localArrayList	ArrayList
    //   33	374	12	localObject4	Object
    //   151	260	13	localObject5	Object
    // Exception table:
    //   from	to	target	type
    //   370	390	455	android/database/sqlite/SQLiteException
    //   397	421	455	android/database/sqlite/SQLiteException
    //   425	434	455	android/database/sqlite/SQLiteException
    //   338	347	462	android/database/sqlite/SQLiteException
    //   351	361	462	android/database/sqlite/SQLiteException
    //   217	226	466	finally
    //   247	256	466	finally
    //   259	263	466	finally
    //   274	282	466	finally
    //   285	289	466	finally
    //   292	305	466	finally
    //   311	321	466	finally
    //   324	334	466	finally
    //   217	226	470	android/database/sqlite/SQLiteException
    //   247	256	470	android/database/sqlite/SQLiteException
    //   259	263	470	android/database/sqlite/SQLiteException
    //   274	282	470	android/database/sqlite/SQLiteException
    //   285	289	470	android/database/sqlite/SQLiteException
    //   292	305	470	android/database/sqlite/SQLiteException
    //   311	321	470	android/database/sqlite/SQLiteException
    //   324	334	470	android/database/sqlite/SQLiteException
    //   67	85	477	android/database/sqlite/SQLiteException
    //   91	125	477	android/database/sqlite/SQLiteException
    //   125	213	477	android/database/sqlite/SQLiteException
    //   35	62	481	android/database/sqlite/SQLiteException
    //   25	35	485	finally
    //   35	62	485	finally
    //   67	85	485	finally
    //   91	125	485	finally
    //   125	213	485	finally
    //   25	35	492	android/database/sqlite/SQLiteException
    //   338	347	533	finally
    //   351	361	533	finally
    //   370	390	533	finally
    //   397	421	533	finally
    //   425	434	533	finally
    //   500	519	533	finally
  }
  
  @X
  public final List<zzcav> zzh(String paramString1, String paramString2, String paramString3)
  {
    zzbp.zzgg(paramString1);
    zzuj();
    zzwk();
    ArrayList localArrayList = new ArrayList(3);
    localArrayList.add(paramString1);
    paramString1 = new StringBuilder("app_id=?");
    if (!TextUtils.isEmpty(paramString2))
    {
      localArrayList.add(paramString2);
      paramString1.append(" and origin=?");
    }
    if (!TextUtils.isEmpty(paramString3))
    {
      localArrayList.add(String.valueOf(paramString3).concat("*"));
      paramString1.append(" and name glob ?");
    }
    paramString2 = (String[])localArrayList.toArray(new String[localArrayList.size()]);
    return zzc(paramString1.toString(), paramString2);
  }
  
  /* Error */
  @X
  public final List<zzcfv> zziv(String paramString)
  {
    // Byte code:
    //   0: aload_1
    //   1: invokestatic 263	com/google/android/gms/common/internal/zzbp:zzgg	(Ljava/lang/String;)Ljava/lang/String;
    //   4: pop
    //   5: aload_0
    //   6: invokevirtual 425	com/google/android/gms/internal/zzcdt:zzuj	()V
    //   9: aload_0
    //   10: invokevirtual 422	com/google/android/gms/internal/zzcdu:zzwk	()V
    //   13: new 591	java/util/ArrayList
    //   16: dup
    //   17: invokespecial 592	java/util/ArrayList:<init>	()V
    //   20: astore 9
    //   22: aload_0
    //   23: invokevirtual 174	com/google/android/gms/internal/zzcay:getWritableDatabase	()Landroid/database/sqlite/SQLiteDatabase;
    //   26: astore 5
    //   28: invokestatic 1271	com/google/android/gms/internal/zzcax:zzavz	()I
    //   31: pop
    //   32: aload 5
    //   34: ldc_w 1005
    //   37: iconst_4
    //   38: anewarray 269	java/lang/String
    //   41: dup
    //   42: iconst_0
    //   43: ldc_w 408
    //   46: aastore
    //   47: dup
    //   48: iconst_1
    //   49: ldc 27
    //   51: aastore
    //   52: dup
    //   53: iconst_2
    //   54: ldc_w 996
    //   57: aastore
    //   58: dup
    //   59: iconst_3
    //   60: ldc_w 903
    //   63: aastore
    //   64: ldc_w 689
    //   67: iconst_1
    //   68: anewarray 269	java/lang/String
    //   71: dup
    //   72: iconst_0
    //   73: aload_1
    //   74: aastore
    //   75: aconst_null
    //   76: aconst_null
    //   77: ldc_w 1236
    //   80: sipush 1000
    //   83: invokestatic 871	java/lang/String:valueOf	(I)Ljava/lang/String;
    //   86: invokevirtual 1241	android/database/sqlite/SQLiteDatabase:query	(Ljava/lang/String;[Ljava/lang/String;Ljava/lang/String;[Ljava/lang/String;Ljava/lang/String;Ljava/lang/String;Ljava/lang/String;Ljava/lang/String;)Landroid/database/Cursor;
    //   89: astore 6
    //   91: aload 6
    //   93: astore 5
    //   95: aload 6
    //   97: invokeinterface 186 1 0
    //   102: istore_2
    //   103: iload_2
    //   104: ifne +13 -> 117
    //   107: aload 6
    //   109: invokeinterface 193 1 0
    //   114: aload 9
    //   116: areturn
    //   117: aload 6
    //   119: astore 5
    //   121: aload 6
    //   123: iconst_0
    //   124: invokeinterface 240 2 0
    //   129: astore 10
    //   131: aload 6
    //   133: astore 5
    //   135: aload 6
    //   137: iconst_1
    //   138: invokeinterface 240 2 0
    //   143: astore 8
    //   145: aload 8
    //   147: astore 7
    //   149: aload 8
    //   151: ifnonnull +8 -> 159
    //   154: ldc_w 1286
    //   157: astore 7
    //   159: aload 6
    //   161: astore 5
    //   163: aload 6
    //   165: iconst_2
    //   166: invokeinterface 190 2 0
    //   171: lstore_3
    //   172: aload 6
    //   174: astore 5
    //   176: aload_0
    //   177: aload 6
    //   179: iconst_3
    //   180: invokespecial 1062	com/google/android/gms/internal/zzcay:zza	(Landroid/database/Cursor;I)Ljava/lang/Object;
    //   183: astore 8
    //   185: aload 8
    //   187: ifnonnull +27 -> 214
    //   190: aload 6
    //   192: astore 5
    //   194: aload_0
    //   195: invokevirtual 197	com/google/android/gms/internal/zzcdt:zzaul	()Lcom/google/android/gms/internal/zzcbw;
    //   198: invokevirtual 203	com/google/android/gms/internal/zzcbw:zzayd	()Lcom/google/android/gms/internal/zzcby;
    //   201: ldc_w 1288
    //   204: aload_1
    //   205: invokestatic 440	com/google/android/gms/internal/zzcbw:zzjf	(Ljava/lang/String;)Ljava/lang/Object;
    //   208: invokevirtual 230	com/google/android/gms/internal/zzcby:zzj	(Ljava/lang/String;Ljava/lang/Object;)V
    //   211: goto +30 -> 241
    //   214: aload 6
    //   216: astore 5
    //   218: aload 9
    //   220: new 973	com/google/android/gms/internal/zzcfv
    //   223: dup
    //   224: aload_1
    //   225: aload 7
    //   227: aload 10
    //   229: lload_3
    //   230: aload 8
    //   232: invokespecial 1065	com/google/android/gms/internal/zzcfv:<init>	(Ljava/lang/String;Ljava/lang/String;Ljava/lang/String;JLjava/lang/Object;)V
    //   235: invokeinterface 609 2 0
    //   240: pop
    //   241: aload 6
    //   243: astore 5
    //   245: aload 6
    //   247: invokeinterface 1036 1 0
    //   252: istore_2
    //   253: iload_2
    //   254: ifne -137 -> 117
    //   257: aload 6
    //   259: invokeinterface 193 1 0
    //   264: aload 9
    //   266: areturn
    //   267: astore 7
    //   269: goto +15 -> 284
    //   272: astore_1
    //   273: aconst_null
    //   274: astore 5
    //   276: goto +46 -> 322
    //   279: astore 7
    //   281: aconst_null
    //   282: astore 6
    //   284: aload 6
    //   286: astore 5
    //   288: aload_0
    //   289: invokevirtual 197	com/google/android/gms/internal/zzcdt:zzaul	()Lcom/google/android/gms/internal/zzcbw;
    //   292: invokevirtual 203	com/google/android/gms/internal/zzcbw:zzayd	()Lcom/google/android/gms/internal/zzcby;
    //   295: ldc_w 1290
    //   298: aload_1
    //   299: invokestatic 440	com/google/android/gms/internal/zzcbw:zzjf	(Ljava/lang/String;)Ljava/lang/Object;
    //   302: aload 7
    //   304: invokevirtual 211	com/google/android/gms/internal/zzcby:zze	(Ljava/lang/String;Ljava/lang/Object;Ljava/lang/Object;)V
    //   307: aload 6
    //   309: ifnull +10 -> 319
    //   312: aload 6
    //   314: invokeinterface 193 1 0
    //   319: aconst_null
    //   320: areturn
    //   321: astore_1
    //   322: aload 5
    //   324: ifnull +10 -> 334
    //   327: aload 5
    //   329: invokeinterface 193 1 0
    //   334: goto +5 -> 339
    //   337: aload_1
    //   338: athrow
    //   339: goto -2 -> 337
    // Local variable table:
    //   start	length	slot	name	signature
    //   0	342	0	this	zzcay
    //   0	342	1	paramString	String
    //   102	152	2	bool	boolean
    //   171	59	3	l	long
    //   26	302	5	localObject1	Object
    //   89	224	6	localCursor	Cursor
    //   147	79	7	localObject2	Object
    //   267	1	7	localSQLiteException1	SQLiteException
    //   279	24	7	localSQLiteException2	SQLiteException
    //   143	88	8	localObject3	Object
    //   20	245	9	localArrayList	ArrayList
    //   129	99	10	str	String
    // Exception table:
    //   from	to	target	type
    //   95	103	267	android/database/sqlite/SQLiteException
    //   121	131	267	android/database/sqlite/SQLiteException
    //   135	145	267	android/database/sqlite/SQLiteException
    //   163	172	267	android/database/sqlite/SQLiteException
    //   176	185	267	android/database/sqlite/SQLiteException
    //   194	211	267	android/database/sqlite/SQLiteException
    //   218	241	267	android/database/sqlite/SQLiteException
    //   245	253	267	android/database/sqlite/SQLiteException
    //   22	91	272	finally
    //   22	91	279	android/database/sqlite/SQLiteException
    //   95	103	321	finally
    //   121	131	321	finally
    //   135	145	321	finally
    //   163	172	321	finally
    //   176	185	321	finally
    //   194	211	321	finally
    //   218	241	321	finally
    //   245	253	321	finally
    //   288	307	321	finally
  }
  
  /* Error */
  @X
  public final zzcar zziw(String paramString)
  {
    // Byte code:
    //   0: aload_1
    //   1: invokestatic 263	com/google/android/gms/common/internal/zzbp:zzgg	(Ljava/lang/String;)Ljava/lang/String;
    //   4: pop
    //   5: aload_0
    //   6: invokevirtual 425	com/google/android/gms/internal/zzcdt:zzuj	()V
    //   9: aload_0
    //   10: invokevirtual 422	com/google/android/gms/internal/zzcdu:zzwk	()V
    //   13: aload_0
    //   14: invokevirtual 174	com/google/android/gms/internal/zzcay:getWritableDatabase	()Landroid/database/sqlite/SQLiteDatabase;
    //   17: astore 7
    //   19: iconst_1
    //   20: istore_3
    //   21: aload 7
    //   23: ldc_w 687
    //   26: bipush 23
    //   28: anewarray 269	java/lang/String
    //   31: dup
    //   32: iconst_0
    //   33: ldc_w 721
    //   36: aastore
    //   37: dup
    //   38: iconst_1
    //   39: ldc_w 726
    //   42: aastore
    //   43: dup
    //   44: iconst_2
    //   45: ldc_w 731
    //   48: aastore
    //   49: dup
    //   50: iconst_3
    //   51: ldc_w 736
    //   54: aastore
    //   55: dup
    //   56: iconst_4
    //   57: ldc 59
    //   59: aastore
    //   60: dup
    //   61: iconst_5
    //   62: ldc_w 745
    //   65: aastore
    //   66: dup
    //   67: bipush 6
    //   69: ldc 39
    //   71: aastore
    //   72: dup
    //   73: bipush 7
    //   75: ldc 43
    //   77: aastore
    //   78: dup
    //   79: bipush 8
    //   81: ldc 47
    //   83: aastore
    //   84: dup
    //   85: bipush 9
    //   87: ldc 51
    //   89: aastore
    //   90: dup
    //   91: bipush 10
    //   93: ldc 55
    //   95: aastore
    //   96: dup
    //   97: bipush 11
    //   99: ldc 63
    //   101: aastore
    //   102: dup
    //   103: bipush 12
    //   105: ldc 67
    //   107: aastore
    //   108: dup
    //   109: bipush 13
    //   111: ldc 71
    //   113: aastore
    //   114: dup
    //   115: bipush 14
    //   117: ldc 75
    //   119: aastore
    //   120: dup
    //   121: bipush 15
    //   123: ldc 83
    //   125: aastore
    //   126: dup
    //   127: bipush 16
    //   129: ldc 87
    //   131: aastore
    //   132: dup
    //   133: bipush 17
    //   135: ldc 91
    //   137: aastore
    //   138: dup
    //   139: bipush 18
    //   141: ldc 95
    //   143: aastore
    //   144: dup
    //   145: bipush 19
    //   147: ldc 99
    //   149: aastore
    //   150: dup
    //   151: bipush 20
    //   153: ldc 103
    //   155: aastore
    //   156: dup
    //   157: bipush 21
    //   159: ldc 107
    //   161: aastore
    //   162: dup
    //   163: bipush 22
    //   165: ldc 111
    //   167: aastore
    //   168: ldc_w 689
    //   171: iconst_1
    //   172: anewarray 269	java/lang/String
    //   175: dup
    //   176: iconst_0
    //   177: aload_1
    //   178: aastore
    //   179: aconst_null
    //   180: aconst_null
    //   181: aconst_null
    //   182: invokevirtual 414	android/database/sqlite/SQLiteDatabase:query	(Ljava/lang/String;[Ljava/lang/String;Ljava/lang/String;[Ljava/lang/String;Ljava/lang/String;Ljava/lang/String;Ljava/lang/String;)Landroid/database/Cursor;
    //   185: astore 7
    //   187: aload 7
    //   189: invokeinterface 186 1 0
    //   194: istore 4
    //   196: iload 4
    //   198: ifne +12 -> 210
    //   201: aload 7
    //   203: invokeinterface 193 1 0
    //   208: aconst_null
    //   209: areturn
    //   210: aload 7
    //   212: astore 8
    //   214: new 716	com/google/android/gms/internal/zzcar
    //   217: dup
    //   218: aload_0
    //   219: getfield 1297	com/google/android/gms/internal/zzcdt:zziki	Lcom/google/android/gms/internal/zzccw;
    //   222: aload_1
    //   223: invokespecial 1300	com/google/android/gms/internal/zzcar:<init>	(Lcom/google/android/gms/internal/zzccw;Ljava/lang/String;)V
    //   226: astore 9
    //   228: aload 7
    //   230: astore 8
    //   232: aload 9
    //   234: aload 7
    //   236: iconst_0
    //   237: invokeinterface 240 2 0
    //   242: invokevirtual 1303	com/google/android/gms/internal/zzcar:zzim	(Ljava/lang/String;)V
    //   245: aload 7
    //   247: astore 8
    //   249: aload 9
    //   251: aload 7
    //   253: iconst_1
    //   254: invokeinterface 240 2 0
    //   259: invokevirtual 1306	com/google/android/gms/internal/zzcar:zzin	(Ljava/lang/String;)V
    //   262: aload 7
    //   264: astore 8
    //   266: aload 9
    //   268: aload 7
    //   270: iconst_2
    //   271: invokeinterface 240 2 0
    //   276: invokevirtual 1309	com/google/android/gms/internal/zzcar:zzio	(Ljava/lang/String;)V
    //   279: aload 7
    //   281: astore 8
    //   283: aload 9
    //   285: aload 7
    //   287: iconst_3
    //   288: invokeinterface 190 2 0
    //   293: invokevirtual 1312	com/google/android/gms/internal/zzcar:zzaq	(J)V
    //   296: aload 7
    //   298: astore 8
    //   300: aload 9
    //   302: aload 7
    //   304: iconst_4
    //   305: invokeinterface 190 2 0
    //   310: invokevirtual 1314	com/google/android/gms/internal/zzcar:zzal	(J)V
    //   313: aload 7
    //   315: astore 8
    //   317: aload 9
    //   319: aload 7
    //   321: iconst_5
    //   322: invokeinterface 190 2 0
    //   327: invokevirtual 1316	com/google/android/gms/internal/zzcar:zzam	(J)V
    //   330: aload 7
    //   332: astore 8
    //   334: aload 9
    //   336: aload 7
    //   338: bipush 6
    //   340: invokeinterface 240 2 0
    //   345: invokevirtual 1319	com/google/android/gms/internal/zzcar:setAppVersion	(Ljava/lang/String;)V
    //   348: aload 7
    //   350: astore 8
    //   352: aload 9
    //   354: aload 7
    //   356: bipush 7
    //   358: invokeinterface 240 2 0
    //   363: invokevirtual 1322	com/google/android/gms/internal/zzcar:zziq	(Ljava/lang/String;)V
    //   366: aload 7
    //   368: astore 8
    //   370: aload 9
    //   372: aload 7
    //   374: bipush 8
    //   376: invokeinterface 190 2 0
    //   381: invokevirtual 1325	com/google/android/gms/internal/zzcar:zzao	(J)V
    //   384: aload 7
    //   386: astore 8
    //   388: aload 9
    //   390: aload 7
    //   392: bipush 9
    //   394: invokeinterface 190 2 0
    //   399: invokevirtual 1328	com/google/android/gms/internal/zzcar:zzap	(J)V
    //   402: aload 7
    //   404: astore 8
    //   406: aload 7
    //   408: bipush 10
    //   410: invokeinterface 1332 2 0
    //   415: ifeq +8 -> 423
    //   418: iconst_1
    //   419: istore_2
    //   420: goto +445 -> 865
    //   423: aload 7
    //   425: astore 8
    //   427: aload 7
    //   429: bipush 10
    //   431: invokeinterface 1074 2 0
    //   436: istore_2
    //   437: goto +428 -> 865
    //   440: aload 7
    //   442: astore 8
    //   444: aload 9
    //   446: iload_3
    //   447: invokevirtual 1336	com/google/android/gms/internal/zzcar:setMeasurementEnabled	(Z)V
    //   450: aload 7
    //   452: astore 8
    //   454: aload 9
    //   456: aload 7
    //   458: bipush 11
    //   460: invokeinterface 190 2 0
    //   465: invokevirtual 1339	com/google/android/gms/internal/zzcar:zzat	(J)V
    //   468: aload 7
    //   470: astore 8
    //   472: aload 9
    //   474: aload 7
    //   476: bipush 12
    //   478: invokeinterface 190 2 0
    //   483: invokevirtual 1342	com/google/android/gms/internal/zzcar:zzau	(J)V
    //   486: aload 7
    //   488: astore 8
    //   490: aload 9
    //   492: aload 7
    //   494: bipush 13
    //   496: invokeinterface 190 2 0
    //   501: invokevirtual 1345	com/google/android/gms/internal/zzcar:zzav	(J)V
    //   504: aload 7
    //   506: astore 8
    //   508: aload 9
    //   510: aload 7
    //   512: bipush 14
    //   514: invokeinterface 190 2 0
    //   519: invokevirtual 1348	com/google/android/gms/internal/zzcar:zzaw	(J)V
    //   522: aload 7
    //   524: astore 8
    //   526: aload 9
    //   528: aload 7
    //   530: bipush 15
    //   532: invokeinterface 190 2 0
    //   537: invokevirtual 1351	com/google/android/gms/internal/zzcar:zzar	(J)V
    //   540: aload 7
    //   542: astore 8
    //   544: aload 9
    //   546: aload 7
    //   548: bipush 16
    //   550: invokeinterface 190 2 0
    //   555: invokevirtual 1354	com/google/android/gms/internal/zzcar:zzas	(J)V
    //   558: aload 7
    //   560: astore 8
    //   562: aload 7
    //   564: bipush 17
    //   566: invokeinterface 1332 2 0
    //   571: ifeq +11 -> 582
    //   574: ldc2_w 1355
    //   577: lstore 5
    //   579: goto +19 -> 598
    //   582: aload 7
    //   584: astore 8
    //   586: aload 7
    //   588: bipush 17
    //   590: invokeinterface 1074 2 0
    //   595: i2l
    //   596: lstore 5
    //   598: aload 7
    //   600: astore 8
    //   602: aload 9
    //   604: lload 5
    //   606: invokevirtual 1359	com/google/android/gms/internal/zzcar:zzan	(J)V
    //   609: aload 7
    //   611: astore 8
    //   613: aload 9
    //   615: aload 7
    //   617: bipush 18
    //   619: invokeinterface 240 2 0
    //   624: invokevirtual 1362	com/google/android/gms/internal/zzcar:zzip	(Ljava/lang/String;)V
    //   627: aload 7
    //   629: astore 8
    //   631: aload 9
    //   633: aload 7
    //   635: bipush 19
    //   637: invokeinterface 190 2 0
    //   642: invokevirtual 1365	com/google/android/gms/internal/zzcar:zzay	(J)V
    //   645: aload 7
    //   647: astore 8
    //   649: aload 9
    //   651: aload 7
    //   653: bipush 20
    //   655: invokeinterface 190 2 0
    //   660: invokevirtual 1368	com/google/android/gms/internal/zzcar:zzax	(J)V
    //   663: aload 7
    //   665: astore 8
    //   667: aload 9
    //   669: aload 7
    //   671: bipush 21
    //   673: invokeinterface 240 2 0
    //   678: invokevirtual 1371	com/google/android/gms/internal/zzcar:zzir	(Ljava/lang/String;)V
    //   681: aload 7
    //   683: astore 8
    //   685: aload 7
    //   687: bipush 22
    //   689: invokeinterface 1332 2 0
    //   694: ifeq +9 -> 703
    //   697: lconst_0
    //   698: lstore 5
    //   700: goto +18 -> 718
    //   703: aload 7
    //   705: astore 8
    //   707: aload 7
    //   709: bipush 22
    //   711: invokeinterface 190 2 0
    //   716: lstore 5
    //   718: aload 7
    //   720: astore 8
    //   722: aload 9
    //   724: lload 5
    //   726: invokevirtual 1374	com/google/android/gms/internal/zzcar:zzaz	(J)V
    //   729: aload 7
    //   731: astore 8
    //   733: aload 9
    //   735: invokevirtual 1377	com/google/android/gms/internal/zzcar:zzauo	()V
    //   738: aload 7
    //   740: astore 8
    //   742: aload 7
    //   744: invokeinterface 1036 1 0
    //   749: ifeq +24 -> 773
    //   752: aload 7
    //   754: astore 8
    //   756: aload_0
    //   757: invokevirtual 197	com/google/android/gms/internal/zzcdt:zzaul	()Lcom/google/android/gms/internal/zzcbw;
    //   760: invokevirtual 203	com/google/android/gms/internal/zzcbw:zzayd	()Lcom/google/android/gms/internal/zzcby;
    //   763: ldc_w 1379
    //   766: aload_1
    //   767: invokestatic 440	com/google/android/gms/internal/zzcbw:zzjf	(Ljava/lang/String;)Ljava/lang/Object;
    //   770: invokevirtual 230	com/google/android/gms/internal/zzcby:zzj	(Ljava/lang/String;Ljava/lang/Object;)V
    //   773: aload 7
    //   775: invokeinterface 193 1 0
    //   780: aload 9
    //   782: areturn
    //   783: astore 9
    //   785: goto +24 -> 809
    //   788: astore_1
    //   789: goto +62 -> 851
    //   792: astore 9
    //   794: goto +15 -> 809
    //   797: astore_1
    //   798: aconst_null
    //   799: astore 7
    //   801: goto +50 -> 851
    //   804: astore 9
    //   806: aconst_null
    //   807: astore 7
    //   809: aload 7
    //   811: astore 8
    //   813: aload_0
    //   814: invokevirtual 197	com/google/android/gms/internal/zzcdt:zzaul	()Lcom/google/android/gms/internal/zzcbw;
    //   817: invokevirtual 203	com/google/android/gms/internal/zzcbw:zzayd	()Lcom/google/android/gms/internal/zzcby;
    //   820: ldc_w 1381
    //   823: aload_1
    //   824: invokestatic 440	com/google/android/gms/internal/zzcbw:zzjf	(Ljava/lang/String;)Ljava/lang/Object;
    //   827: aload 9
    //   829: invokevirtual 211	com/google/android/gms/internal/zzcby:zze	(Ljava/lang/String;Ljava/lang/Object;Ljava/lang/Object;)V
    //   832: aload 7
    //   834: ifnull +10 -> 844
    //   837: aload 7
    //   839: invokeinterface 193 1 0
    //   844: aconst_null
    //   845: areturn
    //   846: astore_1
    //   847: aload 8
    //   849: astore 7
    //   851: aload 7
    //   853: ifnull +10 -> 863
    //   856: aload 7
    //   858: invokeinterface 193 1 0
    //   863: aload_1
    //   864: athrow
    //   865: iload_2
    //   866: ifeq +6 -> 872
    //   869: goto -429 -> 440
    //   872: iconst_0
    //   873: istore_3
    //   874: goto -434 -> 440
    // Local variable table:
    //   start	length	slot	name	signature
    //   0	877	0	this	zzcay
    //   0	877	1	paramString	String
    //   419	447	2	i	int
    //   20	854	3	bool1	boolean
    //   194	3	4	bool2	boolean
    //   577	148	5	l	long
    //   17	840	7	localObject1	Object
    //   212	636	8	localObject2	Object
    //   226	555	9	localZzcar	zzcar
    //   783	1	9	localSQLiteException1	SQLiteException
    //   792	1	9	localSQLiteException2	SQLiteException
    //   804	24	9	localSQLiteException3	SQLiteException
    // Exception table:
    //   from	to	target	type
    //   214	228	783	android/database/sqlite/SQLiteException
    //   232	245	783	android/database/sqlite/SQLiteException
    //   249	262	783	android/database/sqlite/SQLiteException
    //   266	279	783	android/database/sqlite/SQLiteException
    //   283	296	783	android/database/sqlite/SQLiteException
    //   300	313	783	android/database/sqlite/SQLiteException
    //   317	330	783	android/database/sqlite/SQLiteException
    //   334	348	783	android/database/sqlite/SQLiteException
    //   352	366	783	android/database/sqlite/SQLiteException
    //   370	384	783	android/database/sqlite/SQLiteException
    //   388	402	783	android/database/sqlite/SQLiteException
    //   406	418	783	android/database/sqlite/SQLiteException
    //   427	437	783	android/database/sqlite/SQLiteException
    //   444	450	783	android/database/sqlite/SQLiteException
    //   454	468	783	android/database/sqlite/SQLiteException
    //   472	486	783	android/database/sqlite/SQLiteException
    //   490	504	783	android/database/sqlite/SQLiteException
    //   508	522	783	android/database/sqlite/SQLiteException
    //   526	540	783	android/database/sqlite/SQLiteException
    //   544	558	783	android/database/sqlite/SQLiteException
    //   562	574	783	android/database/sqlite/SQLiteException
    //   586	598	783	android/database/sqlite/SQLiteException
    //   602	609	783	android/database/sqlite/SQLiteException
    //   613	627	783	android/database/sqlite/SQLiteException
    //   631	645	783	android/database/sqlite/SQLiteException
    //   649	663	783	android/database/sqlite/SQLiteException
    //   667	681	783	android/database/sqlite/SQLiteException
    //   685	697	783	android/database/sqlite/SQLiteException
    //   707	718	783	android/database/sqlite/SQLiteException
    //   722	729	783	android/database/sqlite/SQLiteException
    //   733	738	783	android/database/sqlite/SQLiteException
    //   742	752	783	android/database/sqlite/SQLiteException
    //   756	773	783	android/database/sqlite/SQLiteException
    //   187	196	788	finally
    //   187	196	792	android/database/sqlite/SQLiteException
    //   13	19	797	finally
    //   21	187	797	finally
    //   13	19	804	android/database/sqlite/SQLiteException
    //   21	187	804	android/database/sqlite/SQLiteException
    //   214	228	846	finally
    //   232	245	846	finally
    //   249	262	846	finally
    //   266	279	846	finally
    //   283	296	846	finally
    //   300	313	846	finally
    //   317	330	846	finally
    //   334	348	846	finally
    //   352	366	846	finally
    //   370	384	846	finally
    //   388	402	846	finally
    //   406	418	846	finally
    //   427	437	846	finally
    //   444	450	846	finally
    //   454	468	846	finally
    //   472	486	846	finally
    //   490	504	846	finally
    //   508	522	846	finally
    //   526	540	846	finally
    //   544	558	846	finally
    //   562	574	846	finally
    //   586	598	846	finally
    //   602	609	846	finally
    //   613	627	846	finally
    //   631	645	846	finally
    //   649	663	846	finally
    //   667	681	846	finally
    //   685	697	846	finally
    //   707	718	846	finally
    //   722	729	846	finally
    //   733	738	846	finally
    //   742	752	846	finally
    //   756	773	846	finally
    //   813	832	846	finally
  }
  
  public final long zzix(String paramString)
  {
    zzbp.zzgg(paramString);
    zzuj();
    zzwk();
    try
    {
      int i = getWritableDatabase().delete("raw_events", "rowid in (select rowid from raw_events where app_id=? order by rowid desc limit -1 offset ?)", new String[] { paramString, String.valueOf(Math.max(0, Math.min(1000000, zzaun().zzb(paramString, zzcbm.zzioq)))) });
      return i;
    }
    catch (SQLiteException localSQLiteException)
    {
      zzaul().zzayd().zze("Error deleting over the limit events. appId", zzcbw.zzjf(paramString), localSQLiteException);
    }
    return 0L;
  }
  
  /* Error */
  @X
  public final byte[] zziy(String paramString)
  {
    // Byte code:
    //   0: aload_1
    //   1: invokestatic 263	com/google/android/gms/common/internal/zzbp:zzgg	(Ljava/lang/String;)Ljava/lang/String;
    //   4: pop
    //   5: aload_0
    //   6: invokevirtual 425	com/google/android/gms/internal/zzcdt:zzuj	()V
    //   9: aload_0
    //   10: invokevirtual 422	com/google/android/gms/internal/zzcdu:zzwk	()V
    //   13: aload_0
    //   14: invokevirtual 174	com/google/android/gms/internal/zzcay:getWritableDatabase	()Landroid/database/sqlite/SQLiteDatabase;
    //   17: ldc_w 687
    //   20: iconst_1
    //   21: anewarray 269	java/lang/String
    //   24: dup
    //   25: iconst_0
    //   26: ldc 79
    //   28: aastore
    //   29: ldc_w 689
    //   32: iconst_1
    //   33: anewarray 269	java/lang/String
    //   36: dup
    //   37: iconst_0
    //   38: aload_1
    //   39: aastore
    //   40: aconst_null
    //   41: aconst_null
    //   42: aconst_null
    //   43: invokevirtual 414	android/database/sqlite/SQLiteDatabase:query	(Ljava/lang/String;[Ljava/lang/String;Ljava/lang/String;[Ljava/lang/String;Ljava/lang/String;Ljava/lang/String;Ljava/lang/String;)Landroid/database/Cursor;
    //   46: astore 4
    //   48: aload 4
    //   50: astore_3
    //   51: aload 4
    //   53: invokeinterface 186 1 0
    //   58: istore_2
    //   59: iload_2
    //   60: ifne +12 -> 72
    //   63: aload 4
    //   65: invokeinterface 193 1 0
    //   70: aconst_null
    //   71: areturn
    //   72: aload 4
    //   74: astore_3
    //   75: aload 4
    //   77: iconst_0
    //   78: invokeinterface 1078 2 0
    //   83: astore 5
    //   85: aload 4
    //   87: astore_3
    //   88: aload 4
    //   90: invokeinterface 1036 1 0
    //   95: ifeq +23 -> 118
    //   98: aload 4
    //   100: astore_3
    //   101: aload_0
    //   102: invokevirtual 197	com/google/android/gms/internal/zzcdt:zzaul	()Lcom/google/android/gms/internal/zzcbw;
    //   105: invokevirtual 203	com/google/android/gms/internal/zzcbw:zzayd	()Lcom/google/android/gms/internal/zzcby;
    //   108: ldc_w 1395
    //   111: aload_1
    //   112: invokestatic 440	com/google/android/gms/internal/zzcbw:zzjf	(Ljava/lang/String;)Ljava/lang/Object;
    //   115: invokevirtual 230	com/google/android/gms/internal/zzcby:zzj	(Ljava/lang/String;Ljava/lang/Object;)V
    //   118: aload 4
    //   120: invokeinterface 193 1 0
    //   125: aload 5
    //   127: areturn
    //   128: astore 5
    //   130: goto +14 -> 144
    //   133: astore_1
    //   134: aconst_null
    //   135: astore_3
    //   136: goto +45 -> 181
    //   139: astore 5
    //   141: aconst_null
    //   142: astore 4
    //   144: aload 4
    //   146: astore_3
    //   147: aload_0
    //   148: invokevirtual 197	com/google/android/gms/internal/zzcdt:zzaul	()Lcom/google/android/gms/internal/zzcbw;
    //   151: invokevirtual 203	com/google/android/gms/internal/zzcbw:zzayd	()Lcom/google/android/gms/internal/zzcby;
    //   154: ldc_w 1397
    //   157: aload_1
    //   158: invokestatic 440	com/google/android/gms/internal/zzcbw:zzjf	(Ljava/lang/String;)Ljava/lang/Object;
    //   161: aload 5
    //   163: invokevirtual 211	com/google/android/gms/internal/zzcby:zze	(Ljava/lang/String;Ljava/lang/Object;Ljava/lang/Object;)V
    //   166: aload 4
    //   168: ifnull +10 -> 178
    //   171: aload 4
    //   173: invokeinterface 193 1 0
    //   178: aconst_null
    //   179: areturn
    //   180: astore_1
    //   181: aload_3
    //   182: ifnull +9 -> 191
    //   185: aload_3
    //   186: invokeinterface 193 1 0
    //   191: aload_1
    //   192: athrow
    // Local variable table:
    //   start	length	slot	name	signature
    //   0	193	0	this	zzcay
    //   0	193	1	paramString	String
    //   58	2	2	bool	boolean
    //   50	136	3	localCursor1	Cursor
    //   46	126	4	localCursor2	Cursor
    //   83	43	5	arrayOfByte	byte[]
    //   128	1	5	localSQLiteException1	SQLiteException
    //   139	23	5	localSQLiteException2	SQLiteException
    // Exception table:
    //   from	to	target	type
    //   51	59	128	android/database/sqlite/SQLiteException
    //   75	85	128	android/database/sqlite/SQLiteException
    //   88	98	128	android/database/sqlite/SQLiteException
    //   101	118	128	android/database/sqlite/SQLiteException
    //   13	48	133	finally
    //   13	48	139	android/database/sqlite/SQLiteException
    //   51	59	180	finally
    //   75	85	180	finally
    //   88	98	180	finally
    //   101	118	180	finally
    //   147	166	180	finally
  }
  
  /* Error */
  public final Map<Integer, zzcgl> zziz(String paramString)
  {
    // Byte code:
    //   0: aload_0
    //   1: invokevirtual 422	com/google/android/gms/internal/zzcdu:zzwk	()V
    //   4: aload_0
    //   5: invokevirtual 425	com/google/android/gms/internal/zzcdt:zzuj	()V
    //   8: aload_1
    //   9: invokestatic 263	com/google/android/gms/common/internal/zzbp:zzgg	(Ljava/lang/String;)Ljava/lang/String;
    //   12: pop
    //   13: aload_0
    //   14: invokevirtual 174	com/google/android/gms/internal/zzcay:getWritableDatabase	()Landroid/database/sqlite/SQLiteDatabase;
    //   17: astore 4
    //   19: aload 4
    //   21: ldc_w 615
    //   24: iconst_2
    //   25: anewarray 269	java/lang/String
    //   28: dup
    //   29: iconst_0
    //   30: ldc_w 475
    //   33: aastore
    //   34: dup
    //   35: iconst_1
    //   36: ldc_w 1401
    //   39: aastore
    //   40: ldc_w 689
    //   43: iconst_1
    //   44: anewarray 269	java/lang/String
    //   47: dup
    //   48: iconst_0
    //   49: aload_1
    //   50: aastore
    //   51: aconst_null
    //   52: aconst_null
    //   53: aconst_null
    //   54: invokevirtual 414	android/database/sqlite/SQLiteDatabase:query	(Ljava/lang/String;[Ljava/lang/String;Ljava/lang/String;[Ljava/lang/String;Ljava/lang/String;Ljava/lang/String;Ljava/lang/String;)Landroid/database/Cursor;
    //   57: astore 5
    //   59: aload 5
    //   61: astore 4
    //   63: aload 5
    //   65: invokeinterface 186 1 0
    //   70: istore_3
    //   71: iload_3
    //   72: ifne +12 -> 84
    //   75: aload 5
    //   77: invokeinterface 193 1 0
    //   82: aconst_null
    //   83: areturn
    //   84: aload 5
    //   86: astore 4
    //   88: new 19	b/b/x/n/b
    //   91: dup
    //   92: invokespecial 1104	b/b/x/n/b:<init>	()V
    //   95: astore 6
    //   97: aload 5
    //   99: astore 4
    //   101: aload 5
    //   103: iconst_0
    //   104: invokeinterface 1074 2 0
    //   109: istore_2
    //   110: aload 5
    //   112: astore 4
    //   114: aload 5
    //   116: iconst_1
    //   117: invokeinterface 1078 2 0
    //   122: astore 7
    //   124: aload 5
    //   126: astore 4
    //   128: aload 7
    //   130: iconst_0
    //   131: aload 7
    //   133: arraylength
    //   134: invokestatic 1115	com/google/android/gms/internal/zzeye:zzm	([BII)Lcom/google/android/gms/internal/zzeye;
    //   137: astore 7
    //   139: aload 5
    //   141: astore 4
    //   143: new 1403	com/google/android/gms/internal/zzcgl
    //   146: dup
    //   147: invokespecial 1404	com/google/android/gms/internal/zzcgl:<init>	()V
    //   150: astore 8
    //   152: aload 5
    //   154: astore 4
    //   156: aload 8
    //   158: aload 7
    //   160: invokevirtual 1405	com/google/android/gms/internal/zzcgl:zza	(Lcom/google/android/gms/internal/zzeye;)Lcom/google/android/gms/internal/zzeyn;
    //   163: pop
    //   164: aload 5
    //   166: astore 4
    //   168: aload 6
    //   170: iload_2
    //   171: invokestatic 226	java/lang/Integer:valueOf	(I)Ljava/lang/Integer;
    //   174: aload 8
    //   176: invokeinterface 35 3 0
    //   181: pop
    //   182: goto +32 -> 214
    //   185: astore 7
    //   187: aload 5
    //   189: astore 4
    //   191: aload_0
    //   192: invokevirtual 197	com/google/android/gms/internal/zzcdt:zzaul	()Lcom/google/android/gms/internal/zzcbw;
    //   195: invokevirtual 203	com/google/android/gms/internal/zzcbw:zzayd	()Lcom/google/android/gms/internal/zzcby;
    //   198: ldc_w 1407
    //   201: aload_1
    //   202: invokestatic 440	com/google/android/gms/internal/zzcbw:zzjf	(Ljava/lang/String;)Ljava/lang/Object;
    //   205: iload_2
    //   206: invokestatic 226	java/lang/Integer:valueOf	(I)Ljava/lang/Integer;
    //   209: aload 7
    //   211: invokevirtual 451	com/google/android/gms/internal/zzcby:zzd	(Ljava/lang/String;Ljava/lang/Object;Ljava/lang/Object;Ljava/lang/Object;)V
    //   214: aload 5
    //   216: astore 4
    //   218: aload 5
    //   220: invokeinterface 1036 1 0
    //   225: istore_3
    //   226: iload_3
    //   227: ifne -130 -> 97
    //   230: aload 5
    //   232: invokeinterface 193 1 0
    //   237: aload 6
    //   239: areturn
    //   240: astore 6
    //   242: goto +15 -> 257
    //   245: astore_1
    //   246: aconst_null
    //   247: astore 4
    //   249: goto +46 -> 295
    //   252: astore 6
    //   254: aconst_null
    //   255: astore 5
    //   257: aload 5
    //   259: astore 4
    //   261: aload_0
    //   262: invokevirtual 197	com/google/android/gms/internal/zzcdt:zzaul	()Lcom/google/android/gms/internal/zzcbw;
    //   265: invokevirtual 203	com/google/android/gms/internal/zzcbw:zzayd	()Lcom/google/android/gms/internal/zzcby;
    //   268: ldc_w 1409
    //   271: aload_1
    //   272: invokestatic 440	com/google/android/gms/internal/zzcbw:zzjf	(Ljava/lang/String;)Ljava/lang/Object;
    //   275: aload 6
    //   277: invokevirtual 211	com/google/android/gms/internal/zzcby:zze	(Ljava/lang/String;Ljava/lang/Object;Ljava/lang/Object;)V
    //   280: aload 5
    //   282: ifnull +10 -> 292
    //   285: aload 5
    //   287: invokeinterface 193 1 0
    //   292: aconst_null
    //   293: areturn
    //   294: astore_1
    //   295: aload 4
    //   297: ifnull +10 -> 307
    //   300: aload 4
    //   302: invokeinterface 193 1 0
    //   307: goto +5 -> 312
    //   310: aload_1
    //   311: athrow
    //   312: goto -2 -> 310
    // Local variable table:
    //   start	length	slot	name	signature
    //   0	315	0	this	zzcay
    //   0	315	1	paramString	String
    //   109	97	2	i	int
    //   70	157	3	bool	boolean
    //   17	284	4	localObject1	Object
    //   57	229	5	localCursor	Cursor
    //   95	143	6	localB	b
    //   240	1	6	localSQLiteException1	SQLiteException
    //   252	24	6	localSQLiteException2	SQLiteException
    //   122	37	7	localObject2	Object
    //   185	25	7	localIOException	IOException
    //   150	25	8	localZzcgl	zzcgl
    // Exception table:
    //   from	to	target	type
    //   156	164	185	java/io/IOException
    //   63	71	240	android/database/sqlite/SQLiteException
    //   88	97	240	android/database/sqlite/SQLiteException
    //   101	110	240	android/database/sqlite/SQLiteException
    //   114	124	240	android/database/sqlite/SQLiteException
    //   128	139	240	android/database/sqlite/SQLiteException
    //   143	152	240	android/database/sqlite/SQLiteException
    //   156	164	240	android/database/sqlite/SQLiteException
    //   168	182	240	android/database/sqlite/SQLiteException
    //   191	214	240	android/database/sqlite/SQLiteException
    //   218	226	240	android/database/sqlite/SQLiteException
    //   19	59	245	finally
    //   19	59	252	android/database/sqlite/SQLiteException
    //   63	71	294	finally
    //   88	97	294	finally
    //   101	110	294	finally
    //   114	124	294	finally
    //   128	139	294	finally
    //   143	152	294	finally
    //   156	164	294	finally
    //   168	182	294	finally
    //   191	214	294	finally
    //   218	226	294	finally
    //   261	280	294	finally
  }
  
  public final long zzja(String paramString)
  {
    zzbp.zzgg(paramString);
    return zza("select count(1) from events where app_id=? and name not like '!_%' escape '!'", new String[] { paramString }, 0L);
  }
  
  /* Error */
  @X
  public final List<android.util.Pair<zzcgk, Long>> zzl(String paramString, int paramInt1, int paramInt2)
  {
    // Byte code:
    //   0: aload_0
    //   1: invokevirtual 425	com/google/android/gms/internal/zzcdt:zzuj	()V
    //   4: aload_0
    //   5: invokevirtual 422	com/google/android/gms/internal/zzcdu:zzwk	()V
    //   8: iload_2
    //   9: ifle +9 -> 18
    //   12: iconst_1
    //   13: istore 5
    //   15: goto +6 -> 21
    //   18: iconst_0
    //   19: istore 5
    //   21: iload 5
    //   23: invokestatic 1418	com/google/android/gms/common/internal/zzbp:zzbh	(Z)V
    //   26: iload_3
    //   27: ifle +9 -> 36
    //   30: iconst_1
    //   31: istore 5
    //   33: goto +6 -> 39
    //   36: iconst_0
    //   37: istore 5
    //   39: iload 5
    //   41: invokestatic 1418	com/google/android/gms/common/internal/zzbp:zzbh	(Z)V
    //   44: aload_1
    //   45: invokestatic 263	com/google/android/gms/common/internal/zzbp:zzgg	(Ljava/lang/String;)Ljava/lang/String;
    //   48: pop
    //   49: aconst_null
    //   50: astore 9
    //   52: aconst_null
    //   53: astore 8
    //   55: aload_0
    //   56: invokevirtual 174	com/google/android/gms/internal/zzcay:getWritableDatabase	()Landroid/database/sqlite/SQLiteDatabase;
    //   59: ldc_w 1196
    //   62: iconst_2
    //   63: anewarray 269	java/lang/String
    //   66: dup
    //   67: iconst_0
    //   68: ldc_w 1236
    //   71: aastore
    //   72: dup
    //   73: iconst_1
    //   74: ldc_w 484
    //   77: aastore
    //   78: ldc_w 689
    //   81: iconst_1
    //   82: anewarray 269	java/lang/String
    //   85: dup
    //   86: iconst_0
    //   87: aload_1
    //   88: aastore
    //   89: aconst_null
    //   90: aconst_null
    //   91: ldc_w 1236
    //   94: iload_2
    //   95: invokestatic 871	java/lang/String:valueOf	(I)Ljava/lang/String;
    //   98: invokevirtual 1241	android/database/sqlite/SQLiteDatabase:query	(Ljava/lang/String;[Ljava/lang/String;Ljava/lang/String;[Ljava/lang/String;Ljava/lang/String;Ljava/lang/String;Ljava/lang/String;Ljava/lang/String;)Landroid/database/Cursor;
    //   101: astore 10
    //   103: aload 10
    //   105: astore 8
    //   107: aload 10
    //   109: astore 9
    //   111: aload 10
    //   113: invokeinterface 186 1 0
    //   118: ifne +26 -> 144
    //   121: aload 10
    //   123: astore 8
    //   125: aload 10
    //   127: astore 9
    //   129: invokestatic 1249	java/util/Collections:emptyList	()Ljava/util/List;
    //   132: astore 11
    //   134: aload 10
    //   136: invokeinterface 193 1 0
    //   141: aload 11
    //   143: areturn
    //   144: aload 10
    //   146: astore 8
    //   148: aload 10
    //   150: astore 9
    //   152: new 591	java/util/ArrayList
    //   155: dup
    //   156: invokespecial 592	java/util/ArrayList:<init>	()V
    //   159: astore 15
    //   161: iconst_0
    //   162: istore_2
    //   163: aload 10
    //   165: astore 8
    //   167: aload 10
    //   169: astore 9
    //   171: aload 10
    //   173: iconst_0
    //   174: invokeinterface 190 2 0
    //   179: lstore 6
    //   181: aload 10
    //   183: astore 8
    //   185: aload 10
    //   187: astore 9
    //   189: aload 10
    //   191: iconst_1
    //   192: invokeinterface 1078 2 0
    //   197: astore 11
    //   199: aload 10
    //   201: astore 8
    //   203: aload 10
    //   205: astore 9
    //   207: aload_0
    //   208: invokevirtual 649	com/google/android/gms/internal/zzcdt:zzauh	()Lcom/google/android/gms/internal/zzcfw;
    //   211: aload 11
    //   213: invokevirtual 1421	com/google/android/gms/internal/zzcfw:zzq	([B)[B
    //   216: astore 11
    //   218: aload 10
    //   220: astore 8
    //   222: aload 10
    //   224: astore 9
    //   226: aload 15
    //   228: invokeinterface 1422 1 0
    //   233: ifne +20 -> 253
    //   236: aload 10
    //   238: astore 8
    //   240: aload 10
    //   242: astore 9
    //   244: aload 11
    //   246: arraylength
    //   247: iload_2
    //   248: iadd
    //   249: iload_3
    //   250: if_icmpgt +234 -> 484
    //   253: aload 10
    //   255: astore 8
    //   257: aload 10
    //   259: astore 9
    //   261: aload 11
    //   263: iconst_0
    //   264: aload 11
    //   266: arraylength
    //   267: invokestatic 1115	com/google/android/gms/internal/zzeye:zzm	([BII)Lcom/google/android/gms/internal/zzeye;
    //   270: astore 12
    //   272: aload 10
    //   274: astore 8
    //   276: aload 10
    //   278: astore 9
    //   280: new 641	com/google/android/gms/internal/zzcgk
    //   283: dup
    //   284: invokespecial 1423	com/google/android/gms/internal/zzcgk:<init>	()V
    //   287: astore 13
    //   289: aload 10
    //   291: astore 8
    //   293: aload 10
    //   295: astore 9
    //   297: aload 13
    //   299: aload 12
    //   301: invokevirtual 1424	com/google/android/gms/internal/zzcgk:zza	(Lcom/google/android/gms/internal/zzeye;)Lcom/google/android/gms/internal/zzeyn;
    //   304: pop
    //   305: aload 10
    //   307: astore 8
    //   309: aload 10
    //   311: astore 9
    //   313: iload_2
    //   314: aload 11
    //   316: arraylength
    //   317: iadd
    //   318: istore 4
    //   320: aload 10
    //   322: astore 8
    //   324: aload 10
    //   326: astore 9
    //   328: aload 15
    //   330: aload 13
    //   332: lload 6
    //   334: invokestatic 254	java/lang/Long:valueOf	(J)Ljava/lang/Long;
    //   337: invokestatic 1430	android/util/Pair:create	(Ljava/lang/Object;Ljava/lang/Object;)Landroid/util/Pair;
    //   340: invokeinterface 609 2 0
    //   345: pop
    //   346: goto +107 -> 453
    //   349: astore 11
    //   351: aload 10
    //   353: astore 8
    //   355: aload 10
    //   357: astore 9
    //   359: aload_0
    //   360: invokevirtual 197	com/google/android/gms/internal/zzcdt:zzaul	()Lcom/google/android/gms/internal/zzcbw;
    //   363: invokevirtual 203	com/google/android/gms/internal/zzcbw:zzayd	()Lcom/google/android/gms/internal/zzcby;
    //   366: astore 12
    //   368: ldc_w 1432
    //   371: astore 13
    //   373: aload 10
    //   375: astore 8
    //   377: aload 10
    //   379: astore 9
    //   381: aload_1
    //   382: invokestatic 440	com/google/android/gms/internal/zzcbw:zzjf	(Ljava/lang/String;)Ljava/lang/Object;
    //   385: astore 14
    //   387: aload 10
    //   389: astore 8
    //   391: aload 10
    //   393: astore 9
    //   395: aload 12
    //   397: aload 13
    //   399: aload 14
    //   401: aload 11
    //   403: invokevirtual 211	com/google/android/gms/internal/zzcby:zze	(Ljava/lang/String;Ljava/lang/Object;Ljava/lang/Object;)V
    //   406: iload_2
    //   407: istore 4
    //   409: goto +44 -> 453
    //   412: astore 11
    //   414: aload 10
    //   416: astore 8
    //   418: aload 10
    //   420: astore 9
    //   422: aload_0
    //   423: invokevirtual 197	com/google/android/gms/internal/zzcdt:zzaul	()Lcom/google/android/gms/internal/zzcbw;
    //   426: invokevirtual 203	com/google/android/gms/internal/zzcbw:zzayd	()Lcom/google/android/gms/internal/zzcby;
    //   429: astore 12
    //   431: ldc_w 1434
    //   434: astore 13
    //   436: aload 10
    //   438: astore 8
    //   440: aload 10
    //   442: astore 9
    //   444: aload_1
    //   445: invokestatic 440	com/google/android/gms/internal/zzcbw:zzjf	(Ljava/lang/String;)Ljava/lang/Object;
    //   448: astore 14
    //   450: goto -63 -> 387
    //   453: aload 10
    //   455: astore 8
    //   457: aload 10
    //   459: astore 9
    //   461: aload 10
    //   463: invokeinterface 1036 1 0
    //   468: istore 5
    //   470: iload 5
    //   472: ifeq +12 -> 484
    //   475: iload 4
    //   477: istore_2
    //   478: iload 4
    //   480: iload_3
    //   481: if_icmple -318 -> 163
    //   484: aload 10
    //   486: invokeinterface 193 1 0
    //   491: aload 15
    //   493: areturn
    //   494: astore_1
    //   495: goto +50 -> 545
    //   498: astore 10
    //   500: aload 9
    //   502: astore 8
    //   504: aload_0
    //   505: invokevirtual 197	com/google/android/gms/internal/zzcdt:zzaul	()Lcom/google/android/gms/internal/zzcbw;
    //   508: invokevirtual 203	com/google/android/gms/internal/zzcbw:zzayd	()Lcom/google/android/gms/internal/zzcby;
    //   511: ldc_w 1436
    //   514: aload_1
    //   515: invokestatic 440	com/google/android/gms/internal/zzcbw:zzjf	(Ljava/lang/String;)Ljava/lang/Object;
    //   518: aload 10
    //   520: invokevirtual 211	com/google/android/gms/internal/zzcby:zze	(Ljava/lang/String;Ljava/lang/Object;Ljava/lang/Object;)V
    //   523: aload 9
    //   525: astore 8
    //   527: invokestatic 1249	java/util/Collections:emptyList	()Ljava/util/List;
    //   530: astore_1
    //   531: aload 9
    //   533: ifnull +10 -> 543
    //   536: aload 9
    //   538: invokeinterface 193 1 0
    //   543: aload_1
    //   544: areturn
    //   545: aload 8
    //   547: ifnull +10 -> 557
    //   550: aload 8
    //   552: invokeinterface 193 1 0
    //   557: goto +5 -> 562
    //   560: aload_1
    //   561: athrow
    //   562: goto -2 -> 560
    // Local variable table:
    //   start	length	slot	name	signature
    //   0	565	0	this	zzcay
    //   0	565	1	paramString	String
    //   0	565	2	paramInt1	int
    //   0	565	3	paramInt2	int
    //   318	164	4	i	int
    //   13	458	5	bool	boolean
    //   179	154	6	l	long
    //   53	498	8	localObject1	Object
    //   50	487	9	localObject2	Object
    //   101	384	10	localCursor	Cursor
    //   498	21	10	localSQLiteException	SQLiteException
    //   132	183	11	localObject3	Object
    //   349	53	11	localIOException1	IOException
    //   412	1	11	localIOException2	IOException
    //   270	160	12	localObject4	Object
    //   287	148	13	localObject5	Object
    //   385	64	14	localObject6	Object
    //   159	333	15	localArrayList	ArrayList
    // Exception table:
    //   from	to	target	type
    //   297	305	349	java/io/IOException
    //   189	199	412	java/io/IOException
    //   207	218	412	java/io/IOException
    //   55	103	494	finally
    //   111	121	494	finally
    //   129	134	494	finally
    //   152	161	494	finally
    //   171	181	494	finally
    //   189	199	494	finally
    //   207	218	494	finally
    //   226	236	494	finally
    //   244	253	494	finally
    //   261	272	494	finally
    //   280	289	494	finally
    //   297	305	494	finally
    //   313	320	494	finally
    //   328	346	494	finally
    //   359	368	494	finally
    //   381	387	494	finally
    //   395	406	494	finally
    //   422	431	494	finally
    //   444	450	494	finally
    //   461	470	494	finally
    //   504	523	494	finally
    //   527	531	494	finally
    //   55	103	498	android/database/sqlite/SQLiteException
    //   111	121	498	android/database/sqlite/SQLiteException
    //   129	134	498	android/database/sqlite/SQLiteException
    //   152	161	498	android/database/sqlite/SQLiteException
    //   171	181	498	android/database/sqlite/SQLiteException
    //   189	199	498	android/database/sqlite/SQLiteException
    //   207	218	498	android/database/sqlite/SQLiteException
    //   226	236	498	android/database/sqlite/SQLiteException
    //   244	253	498	android/database/sqlite/SQLiteException
    //   261	272	498	android/database/sqlite/SQLiteException
    //   280	289	498	android/database/sqlite/SQLiteException
    //   297	305	498	android/database/sqlite/SQLiteException
    //   313	320	498	android/database/sqlite/SQLiteException
    //   328	346	498	android/database/sqlite/SQLiteException
    //   359	368	498	android/database/sqlite/SQLiteException
    //   381	387	498	android/database/sqlite/SQLiteException
    //   395	406	498	android/database/sqlite/SQLiteException
    //   422	431	498	android/database/sqlite/SQLiteException
    //   444	450	498	android/database/sqlite/SQLiteException
    //   461	470	498	android/database/sqlite/SQLiteException
  }
  
  public final void zzuk() {}
}
