package com.google.android.gms.internal;

import android.app.Application;
import android.content.Context;
import android.content.pm.ApplicationInfo;
import android.content.pm.PackageInfo;
import android.content.pm.PackageManager.NameNotFoundException;
import android.database.sqlite.SQLiteDatabase;
import android.database.sqlite.SQLiteException;
import android.net.Uri;
import android.net.Uri.Builder;
import android.os.Build;
import android.os.Build.VERSION;
import android.os.Bundle;
import android.provider.Settings.Secure;
import android.text.TextUtils;
import android.util.Pair;
import b.b.a.F;
import b.b.a.O;
import b.b.a.X;
import b.b.x.n.b;
import com.google.android.gms.common.internal.zzbp;
import com.google.android.gms.common.util.zzd;
import com.google.android.gms.common.util.zzh;
import com.google.android.gms.measurement.AppMeasurement;
import com.google.firebase.analytics.FirebaseAnalytics;
import java.io.File;
import java.io.FileNotFoundException;
import java.io.IOException;
import java.io.RandomAccessFile;
import java.net.MalformedURLException;
import java.net.URL;
import java.nio.ByteBuffer;
import java.nio.channels.FileChannel;
import java.nio.channels.FileLock;
import java.security.SecureRandom;
import java.util.ArrayList;
import java.util.Collection;
import java.util.Collections;
import java.util.Iterator;
import java.util.List;
import java.util.Locale;
import java.util.Map;
import java.util.concurrent.ExecutionException;
import java.util.concurrent.Future;
import java.util.concurrent.TimeUnit;
import java.util.concurrent.TimeoutException;
import java.util.concurrent.atomic.AtomicReference;

public class zzccw
{
  public static volatile zzccw zzisr;
  public final Context mContext;
  public final zzd zzasc;
  public final boolean zzdoe;
  public final zzcax zziss;
  public final zzcch zzist;
  public final zzcbw zzisu;
  public final zzccr zzisv;
  public final zzcfl zzisw;
  public final zzccq zzisx;
  public final AppMeasurement zzisy;
  public final FirebaseAnalytics zzisz;
  public final zzcfw zzita;
  public final zzcbu zzitb;
  public final zzcay zzitc;
  public final zzcbs zzitd;
  public final zzcca zzite;
  public final zzcek zzitf;
  public final zzceo zzitg;
  public final zzcbe zzith;
  public final zzcdw zziti;
  public final zzcbr zzitj;
  public final zzccf zzitk;
  public final zzcfr zzitl;
  public final zzcau zzitm;
  public final zzcan zzitn;
  public boolean zzito;
  public Boolean zzitp;
  public long zzitq;
  public FileLock zzitr;
  public FileChannel zzits;
  public List<Long> zzitt;
  public List<Runnable> zzitu;
  public int zzitv;
  public int zzitw;
  public long zzitx;
  public long zzity;
  public boolean zzitz;
  public boolean zziua;
  public boolean zziub;
  public final long zziuc;
  
  public zzccw(zzcdv paramZzcdv)
  {
    zzbp.zzu(paramZzcdv);
    mContext = mContext;
    zzitx = -1L;
    zzasc = zzh.zzfyr;
    zziuc = zzasc.currentTimeMillis();
    zziss = new zzcax(this);
    paramZzcdv = new zzcch(this);
    paramZzcdv.initialize();
    zzist = paramZzcdv;
    paramZzcdv = new zzcbw(this);
    paramZzcdv.initialize();
    zzisu = paramZzcdv;
    paramZzcdv = zzaul().zzayh();
    zzcax.zzauv();
    paramZzcdv.zzj("App measurement is starting up, version", Long.valueOf(11400L));
    zzcax.zzawk();
    zzaul().zzayh().log("To enable debug logging run: adb shell setprop log.tag.FA VERBOSE");
    paramZzcdv = new zzcfw(this);
    paramZzcdv.initialize();
    zzita = paramZzcdv;
    paramZzcdv = new zzcbu(this);
    paramZzcdv.initialize();
    zzitb = paramZzcdv;
    paramZzcdv = new zzcbe(this);
    paramZzcdv.initialize();
    zzith = paramZzcdv;
    paramZzcdv = new zzcbr(this);
    paramZzcdv.initialize();
    zzitj = paramZzcdv;
    zzcax.zzawk();
    paramZzcdv = paramZzcdv.getAppId();
    Object localObject;
    if (zzauh().zzke(paramZzcdv))
    {
      localObject = zzaul().zzayh();
      paramZzcdv = "Faster debug mode event logging enabled. To disable, run:\n  adb shell setprop debug.firebase.analytics.app .none.";
    }
    else
    {
      localObject = zzaul().zzayh();
      paramZzcdv = String.valueOf(paramZzcdv);
      if (paramZzcdv.length() != 0) {
        paramZzcdv = "To enable faster debug mode event logging run:\n  adb shell setprop debug.firebase.analytics.app ".concat(paramZzcdv);
      } else {
        paramZzcdv = new String("To enable faster debug mode event logging run:\n  adb shell setprop debug.firebase.analytics.app ");
      }
    }
    ((zzcby)localObject).log(paramZzcdv);
    zzaul().zzayi().log("Debug-level message logging enabled");
    paramZzcdv = new zzcay(this);
    paramZzcdv.initialize();
    zzitc = paramZzcdv;
    paramZzcdv = new zzcbs(this);
    paramZzcdv.initialize();
    zzitd = paramZzcdv;
    paramZzcdv = new zzcau(this);
    paramZzcdv.initialize();
    zzitm = paramZzcdv;
    zzitn = new zzcan(this);
    paramZzcdv = new zzcca(this);
    paramZzcdv.initialize();
    zzite = paramZzcdv;
    paramZzcdv = new zzcek(this);
    paramZzcdv.initialize();
    zzitf = paramZzcdv;
    paramZzcdv = new zzceo(this);
    paramZzcdv.initialize();
    zzitg = paramZzcdv;
    paramZzcdv = new zzcdw(this);
    paramZzcdv.initialize();
    zziti = paramZzcdv;
    paramZzcdv = new zzcfr(this);
    paramZzcdv.initialize();
    zzitl = paramZzcdv;
    zzitk = new zzccf(this);
    zzisy = new AppMeasurement(this);
    zzisz = new FirebaseAnalytics(this);
    paramZzcdv = new zzcfl(this);
    paramZzcdv.initialize();
    zzisw = paramZzcdv;
    paramZzcdv = new zzccq(this);
    paramZzcdv.initialize();
    zzisx = paramZzcdv;
    paramZzcdv = new zzccr(this);
    paramZzcdv.initialize();
    zzisv = paramZzcdv;
    if (zzitv != zzitw) {
      zzaul().zzayd().zze("Not all components initialized", Integer.valueOf(zzitv), Integer.valueOf(zzitw));
    }
    zzdoe = true;
    zzcax.zzawk();
    if ((mContext.getApplicationContext() instanceof Application))
    {
      paramZzcdv = zzatz();
      if (!(paramZzcdv.getContext().getApplicationContext() instanceof Application)) {
        break label698;
      }
      localObject = (Application)paramZzcdv.getContext().getApplicationContext();
      if (zziut == null) {
        zziut = new zzcej(paramZzcdv, null);
      }
      ((Application)localObject).unregisterActivityLifecycleCallbacks(zziut);
      ((Application)localObject).registerActivityLifecycleCallbacks(zziut);
      localObject = paramZzcdv.zzaul().zzayj();
      paramZzcdv = "Registered activity lifecycle callback";
    }
    else
    {
      localObject = zzaul().zzayf();
      paramZzcdv = "Application context is not an Application";
    }
    ((zzcby)localObject).log(paramZzcdv);
    label698:
    zzisv.zzg(new zzccx(this));
  }
  
  @X
  private final int zza(FileChannel paramFileChannel)
  {
    zzauk().zzuj();
    if ((paramFileChannel != null) && (paramFileChannel.isOpen()))
    {
      ByteBuffer localByteBuffer = ByteBuffer.allocate(4);
      try
      {
        paramFileChannel.position(0L);
        int i = paramFileChannel.read(localByteBuffer);
        if (i != 4)
        {
          if (i == -1) {
            break label111;
          }
          zzaul().zzayf().zzj("Unexpected data length. Bytes read", Integer.valueOf(i));
          return 0;
        }
        localByteBuffer.flip();
        i = localByteBuffer.getInt();
        return i;
      }
      catch (IOException paramFileChannel)
      {
        zzaul().zzayd().zzj("Failed to read from channel", paramFileChannel);
        return 0;
      }
    }
    zzaul().zzayd().log("Bad chanel to read from");
    return 0;
    label111:
    return 0;
  }
  
  private final void zza(zzcbf paramZzcbf, zzcas paramZzcas)
  {
    zzauk().zzuj();
    zzwk();
    zzbp.zzu(paramZzcbf);
    zzbp.zzu(paramZzcas);
    zzbp.zzgg(mAppId);
    zzbp.zzbh(mAppId.equals(packageName));
    zzcgk localZzcgk = new zzcgk();
    boolean bool1 = true;
    zzize = Integer.valueOf(1);
    zzizm = "android";
    zzci = packageName;
    zzilv = zzilv;
    zzhtt = zzhtt;
    long l = zzimb;
    if (l == -2147483648L) {
      localObject1 = null;
    } else {
      localObject1 = Integer.valueOf((int)l);
    }
    zzizz = ((Integer)localObject1);
    zzizq = Long.valueOf(zzilw);
    zzilu = zzilu;
    l = zzilx;
    if (l == 0L) {
      localObject1 = null;
    } else {
      localObject1 = Long.valueOf(l);
    }
    zzizv = ((Long)localObject1);
    Object localObject1 = zzaum().zzjh(packageName);
    if ((localObject1 != null) && (!TextUtils.isEmpty((CharSequence)first)))
    {
      zzizs = ((String)first);
      zzizt = ((Boolean)second);
    }
    else if (!zzaub().zzdm(mContext))
    {
      localObject2 = Settings.Secure.getString(mContext.getContentResolver(), "android_id");
      if (localObject2 == null)
      {
        zzaul().zzayf().zzj("null secure ID. appId", zzcbw.zzjf(zzci));
        localObject1 = "null";
      }
      else
      {
        localObject1 = localObject2;
        if (((String)localObject2).isEmpty())
        {
          zzaul().zzayf().zzj("empty secure ID. appId", zzcbw.zzjf(zzci));
          localObject1 = localObject2;
        }
      }
      zzjac = ((String)localObject1);
    }
    zzaub().zzwk();
    zzizn = Build.MODEL;
    zzaub().zzwk();
    zzcw = Build.VERSION.RELEASE;
    zzizp = Integer.valueOf((int)zzaub().zzaxw());
    zzizo = zzaub().zzaxx();
    zzizr = null;
    zzizh = null;
    zzizi = null;
    zzizj = null;
    zzjae = Long.valueOf(zzimd);
    if ((isEnabled()) && (zzcax.zzaxh()))
    {
      zzaua();
      zzjaf = null;
    }
    Object localObject2 = zzauf().zziw(packageName);
    localObject1 = localObject2;
    if (localObject2 == null)
    {
      localObject1 = new zzcar(this, packageName);
      ((zzcar)localObject1).zzim(zzaua().zzaya());
      ((zzcar)localObject1).zzip(zzimc);
      ((zzcar)localObject1).zzin(zzilu);
      ((zzcar)localObject1).zzio(zzaum().zzji(packageName));
      ((zzcar)localObject1).zzaq(0L);
      ((zzcar)localObject1).zzal(0L);
      ((zzcar)localObject1).zzam(0L);
      ((zzcar)localObject1).setAppVersion(zzhtt);
      ((zzcar)localObject1).zzan(zzimb);
      ((zzcar)localObject1).zziq(zzilv);
      ((zzcar)localObject1).zzao(zzilw);
      ((zzcar)localObject1).zzap(zzilx);
      ((zzcar)localObject1).setMeasurementEnabled(zzilz);
      ((zzcar)localObject1).zzaz(zzimd);
      zzauf().zza((zzcar)localObject1);
    }
    zzizu = ((zzcar)localObject1).getAppInstanceId();
    zzimc = ((zzcar)localObject1).zzauq();
    paramZzcas = zzauf().zziv(packageName);
    zzizg = new zzcgm[paramZzcas.size()];
    int i = 0;
    while (i < paramZzcas.size())
    {
      localObject1 = new zzcgm();
      zzizg[i] = localObject1;
      name = getmName;
      zzjaj = Long.valueOf(getzzixd);
      zzauh().zza((zzcgm)localObject1, getmValue);
      i += 1;
    }
    try
    {
      l = zzauf().zza(localZzcgk);
      paramZzcas = zzauf();
      localObject1 = zzink;
      if (localObject1 != null)
      {
        localObject1 = ((zzcbh)localObject1).iterator();
        while (((Iterator)localObject1).hasNext()) {
          if ("_r".equals((String)((Iterator)localObject1).next())) {
            break label928;
          }
        }
        boolean bool2 = zzaui().zzap(mAppId, mName);
        localObject1 = zzauf().zza(zzazf(), mAppId, false, false, false, false, false);
        if ((bool2) && (zzinc < zziss.zzis(mAppId))) {}
      }
      else
      {
        bool1 = false;
      }
      label928:
      if (paramZzcas.zza(paramZzcbf, l, bool1)) {
        zzity = 0L;
      }
      return;
    }
    catch (IOException paramZzcbf)
    {
      zzaul().zzayd().zze("Data loss. Failed to insert raw event metadata. appId", zzcbw.zzjf(zzci), paramZzcbf);
    }
  }
  
  public static void zza(zzcdt paramZzcdt)
  {
    if (paramZzcdt != null) {
      return;
    }
    throw new IllegalStateException("Component not created");
  }
  
  public static void zza(zzcdu paramZzcdu)
  {
    if (paramZzcdu != null)
    {
      if (paramZzcdu.isInitialized()) {
        return;
      }
      throw new IllegalStateException("Component not initialized");
    }
    throw new IllegalStateException("Component not created");
  }
  
  @X
  private final boolean zza(int paramInt, FileChannel paramFileChannel)
  {
    zzauk().zzuj();
    if ((paramFileChannel != null) && (paramFileChannel.isOpen()))
    {
      ByteBuffer localByteBuffer = ByteBuffer.allocate(4);
      localByteBuffer.putInt(paramInt);
      localByteBuffer.flip();
      try
      {
        paramFileChannel.truncate(0L);
        paramFileChannel.write(localByteBuffer);
        paramFileChannel.force(true);
        if (paramFileChannel.size() != 4L) {
          zzaul().zzayd().zzj("Error writing to channel. Bytes written", Long.valueOf(paramFileChannel.size()));
        }
        return true;
      }
      catch (IOException paramFileChannel)
      {
        zzaul().zzayd().zzj("Failed to write to channel", paramFileChannel);
        return false;
      }
    }
    zzaul().zzayd().log("Bad chanel to read from");
    return false;
  }
  
  private final zzcgg[] zza(String paramString, zzcgm[] paramArrayOfZzcgm, zzcgh[] paramArrayOfZzcgh)
  {
    zzbp.zzgg(paramString);
    return zzaty().zza(paramString, paramArrayOfZzcgh, paramArrayOfZzcgm);
  }
  
  public static void zzatu()
  {
    zzcax.zzawk();
    throw new IllegalStateException("Unexpected call on client side");
  }
  
  private final zzccf zzazb()
  {
    zzccf localZzccf = zzitk;
    if (localZzccf != null) {
      return localZzccf;
    }
    throw new IllegalStateException("Network broadcast receiver not created");
  }
  
  private final zzcfr zzazc()
  {
    zza(zzitl);
    return zzitl;
  }
  
  @X
  private final boolean zzazd()
  {
    zzauk().zzuj();
    Object localObject = zzcax.zzawi();
    localObject = new File(mContext.getFilesDir(), (String)localObject);
    zzcby localZzcby;
    String str;
    try
    {
      zzits = new RandomAccessFile((File)localObject, "rw").getChannel();
      zzitr = zzits.tryLock();
      if (zzitr != null)
      {
        zzaul().zzayj().log("Storage concurrent access okay");
        return true;
      }
      zzaul().zzayd().log("Storage concurrent data access panic");
    }
    catch (IOException localIOException)
    {
      localZzcby = zzaul().zzayd();
      str = "Failed to access storage lock file";
    }
    catch (FileNotFoundException localFileNotFoundException)
    {
      localZzcby = zzaul().zzayd();
      str = "Failed to acquire storage lock";
    }
    localZzcby.zzj(str, localFileNotFoundException);
    return false;
  }
  
  private final long zzazf()
  {
    long l3 = zzasc.currentTimeMillis();
    zzcch localZzcch = zzaum();
    localZzcch.zzwk();
    localZzcch.zzuj();
    long l2 = zziqt.get();
    long l1 = l2;
    if (l2 == 0L)
    {
      l1 = localZzcch.zzauh().zzazy().nextInt(86400000) + 1;
      zziqt.set(l1);
    }
    return (l3 + l1) / 1000L / 60L / 60L / 24L;
  }
  
  private final boolean zzazh()
  {
    zzauk().zzuj();
    zzwk();
    return (zzauf().zzaxn()) || (!TextUtils.isEmpty(zzauf().zzaxi()));
  }
  
  @X
  private final void zzazi()
  {
    zzauk().zzuj();
    zzwk();
    if (!zzazl()) {
      return;
    }
    long l1;
    if (zzity > 0L)
    {
      l1 = 3600000L - Math.abs(zzasc.elapsedRealtime() - zzity);
      if (l1 > 0L)
      {
        zzaul().zzayj().zzj("Upload has been suspended. Will update scheduling later in approximately ms", Long.valueOf(l1));
        zzazb().unregister();
        zzazc().cancel();
        return;
      }
      zzity = 0L;
    }
    if ((zzayv()) && (zzazh()))
    {
      long l3 = zzasc.currentTimeMillis();
      long l2 = zzcax.zzaxd();
      int i;
      if ((!zzauf().zzaxo()) && (!zzauf().zzaxj())) {
        i = 0;
      } else {
        i = 1;
      }
      if (i != 0)
      {
        String str = zziss.zzaxg();
        if ((!TextUtils.isEmpty(str)) && (!".none.".equals(str))) {
          l1 = zzcax.zzawz();
        } else {
          l1 = zzcax.zzawy();
        }
      }
      else
      {
        l1 = zzcax.zzawx();
      }
      long l6 = zzaumzziqp.get();
      long l4 = zzaumzziqq.get();
      long l5 = Math.max(zzauf().zzaxl(), zzauf().zzaxm());
      if (l5 == 0L) {}
      for (;;)
      {
        l1 = 0L;
        break;
        l5 = l3 - Math.abs(l5 - l3);
        l6 = Math.abs(l6 - l3);
        l4 = l3 - Math.abs(l4 - l3);
        l6 = Math.max(l3 - l6, l4);
        l3 = l2 + l5;
        l2 = l3;
        if (i != 0)
        {
          l2 = l3;
          if (l6 > 0L) {
            l2 = Math.min(l5, l6) + l1;
          }
        }
        if (!zzauh().zzf(l6, l1)) {
          l2 = l6 + l1;
        }
        l1 = l2;
        if (l4 == 0L) {
          break;
        }
        l1 = l2;
        if (l4 < l5) {
          break;
        }
        l1 = l2;
        i = 0;
        while (i < zzcax.zzaxf())
        {
          l2 = 1 << i;
          l1 += zzcax.zzaxe() * l2;
          if (l1 > l4) {
            break label430;
          }
          i += 1;
        }
      }
      label430:
      if (l1 == 0L)
      {
        zzaul().zzayj().log("Next upload time is 0");
        zzazb().unregister();
        zzazc().cancel();
        return;
      }
      if (!zzaza().zzyx())
      {
        zzaul().zzayj().log("No network");
        zzazb().zzyu();
        zzazc().cancel();
        return;
      }
      l3 = zzaumzziqr.get();
      l4 = zzcax.zzaww();
      l2 = l1;
      if (!zzauh().zzf(l3, l4)) {
        l2 = Math.max(l1, l3 + l4);
      }
      zzazb().unregister();
      l2 -= zzasc.currentTimeMillis();
      l1 = l2;
      if (l2 <= 0L)
      {
        l1 = zzcax.zzaxa();
        zzaumzziqp.set(zzasc.currentTimeMillis());
      }
      zzaul().zzayj().zzj("Upload scheduled in approximately ms", Long.valueOf(l1));
      zzazc().zzs(l1);
      return;
    }
    zzaul().zzayj().log("Nothing to upload or uploading impossible");
    zzazb().unregister();
    zzazc().cancel();
  }
  
  @X
  private final boolean zzazl()
  {
    zzauk().zzuj();
    zzwk();
    return zzito;
  }
  
  @X
  private final void zzazm()
  {
    zzauk().zzuj();
    if ((!zzitz) && (!zziua) && (!zziub))
    {
      zzaul().zzayj().log("Stopping uploading service(s)");
      Object localObject = zzitu;
      if (localObject == null) {
        return;
      }
      localObject = ((List)localObject).iterator();
      while (((Iterator)localObject).hasNext()) {
        ((Runnable)((Iterator)localObject).next()).run();
      }
      zzitu.clear();
      return;
    }
    zzaul().zzayj().zzd("Not stopping services. fetch, network, upload", Boolean.valueOf(zzitz), Boolean.valueOf(zziua), Boolean.valueOf(zziub));
  }
  
  @X
  private final void zzb(zzcar paramZzcar)
  {
    zzauk().zzuj();
    if (TextUtils.isEmpty(paramZzcar.getGmpAppId()))
    {
      zzb(paramZzcar.getAppId(), 204, null, null, null);
      return;
    }
    Object localObject1 = paramZzcar.getGmpAppId();
    String str1 = paramZzcar.getAppInstanceId();
    Object localObject3 = new Uri.Builder();
    Object localObject4 = ((Uri.Builder)localObject3).scheme((String)zzcbm.zziof.get()).encodedAuthority((String)zzcbm.zziog.get());
    localObject1 = String.valueOf(localObject1);
    if (((String)localObject1).length() != 0) {
      localObject1 = "config/app/".concat((String)localObject1);
    } else {
      localObject1 = new String("config/app/");
    }
    ((Uri.Builder)localObject4).path((String)localObject1).appendQueryParameter("app_instance_id", str1).appendQueryParameter("platform", "android").appendQueryParameter("gmp_version", "11400");
    str1 = ((Uri.Builder)localObject3).build().toString();
    try
    {
      localObject3 = new URL(str1);
      zzaul().zzayj().zzj("Fetching remote configuration", paramZzcar.getAppId());
      localObject1 = zzaui().zzjn(paramZzcar.getAppId());
      localObject4 = zzaui().zzjo(paramZzcar.getAppId());
      if ((localObject1 == null) || (TextUtils.isEmpty((CharSequence)localObject4))) {
        break label342;
      }
      localObject1 = new b();
      ((Map)localObject1).put("If-Modified-Since", localObject4);
    }
    catch (MalformedURLException localMalformedURLException)
    {
      for (;;)
      {
        String str2;
        zzcda localZzcda;
        continue;
        Object localObject2 = null;
      }
    }
    zzitz = true;
    localObject4 = zzaza();
    str2 = paramZzcar.getAppId();
    localZzcda = new zzcda(this);
    ((zzcca)localObject4).zzuj();
    ((zzcdu)localObject4).zzwk();
    zzbp.zzu(localObject3);
    zzbp.zzu(localZzcda);
    ((zzcca)localObject4).zzauk().zzh(new zzcce((zzcca)localObject4, str2, (URL)localObject3, null, (Map)localObject1, localZzcda));
    return;
    zzaul().zzayd().zze("Failed to parse config URL. Not fetching. appId", zzcbw.zzjf(paramZzcar.getAppId()), str1);
  }
  
  @X
  private final void zzc(zzcbk paramZzcbk, zzcas paramZzcas)
  {
    zzbp.zzu(paramZzcas);
    zzbp.zzgg(packageName);
    long l2 = System.nanoTime();
    zzauk().zzuj();
    zzwk();
    String str = packageName;
    zzauh();
    if (!zzcfw.zzd(paramZzcbk, paramZzcas)) {
      return;
    }
    if (!zzilz)
    {
      zzf(paramZzcas);
      return;
    }
    boolean bool1 = zzaui().zzao(str, name);
    int i = 0;
    if (bool1)
    {
      zzaul().zzayf().zze("Dropping blacklisted event. appId", zzcbw.zzjf(str), zzaug().zzjc(name));
      if ((zzauh().zzkg(str)) || (zzauh().zzkh(str))) {
        i = 1;
      }
      if ((i == 0) && (!"_err".equals(name))) {
        zzauh().zza(str, 11, "_ev", name, 0);
      }
      if (i != 0)
      {
        paramZzcbk = zzauf().zziw(str);
        if (paramZzcbk != null)
        {
          l1 = Math.max(paramZzcbk.zzava(), paramZzcbk.zzauz());
          if (Math.abs(zzasc.currentTimeMillis() - l1) > zzcax.zzawo())
          {
            zzaul().zzayi().log("Fetching config for blacklisted app");
            zzb(paramZzcbk);
          }
        }
      }
      return;
    }
    if (zzaul().zzad(2)) {
      zzaul().zzayj().zzj("Logging event", zzaug().zzb(paramZzcbk));
    }
    zzauf().beginTransaction();
    try
    {
      localBundle = zzinr.zzaxz();
      zzf(paramZzcas);
      bool1 = "_iap".equals(name);
      if (!bool1) {
        if (!"ecommerce_purchase".equals(name)) {
          break label1526;
        }
      }
      localObject1 = localBundle.getString("currency");
      bool1 = "ecommerce_purchase".equals(name);
      if (bool1)
      {
        double d2 = localBundle.getDouble("value") * 1000000.0D;
        double d1 = d2;
        if (d2 == 0.0D)
        {
          l1 = localBundle.getLong("value");
          d1 = l1;
          Double.isNaN(d1);
          d1 *= 1000000.0D;
        }
        if ((d1 <= 9.223372036854776E18D) && (d1 >= -9.223372036854776E18D))
        {
          l1 = Math.round(d1);
        }
        else
        {
          zzaul().zzayf().zze("Data lost. Currency value is too big. appId", zzcbw.zzjf(str), Double.valueOf(d1));
          zzauf().setTransactionSuccessful();
          zzauf().endTransaction();
        }
      }
      else
      {
        l1 = localBundle.getLong("value");
      }
      if (TextUtils.isEmpty((CharSequence)localObject1)) {
        break label1526;
      }
      localObject1 = ((String)localObject1).toUpperCase(Locale.US);
      if (!((String)localObject1).matches("[A-Z]{3}")) {
        break label1526;
      }
      if (((String)localObject1).length() != 0) {
        localObject1 = "_ltv_".concat((String)localObject1);
      } else {
        localObject1 = new String("_ltv_");
      }
      Object localObject2 = zzauf().zzah(str, (String)localObject1);
      if (localObject2 != null)
      {
        localObject2 = mValue;
        if ((localObject2 instanceof Long))
        {
          long l3 = ((Long)localObject2).longValue();
          localObject1 = new zzcfv(str, zzimg, (String)localObject1, zzasc.currentTimeMillis(), Long.valueOf(l3 + l1));
          break label767;
        }
      }
      zzcay localZzcay = zzauf();
      i = zziss.zzb(str, zzcbm.zzipf);
      zzbp.zzgg(str);
      localZzcay.zzuj();
      localZzcay.zzwk();
      try
      {
        localObject2 = localZzcay.getWritableDatabase();
        try
        {
          ((SQLiteDatabase)localObject2).execSQL("delete from user_attributes where app_id=? and name in (select name from user_attributes where app_id=? and name like '_ltv_%' order by set_timestamp desc limit ?,10);", new String[] { str, str, String.valueOf(i - 1) });
        }
        catch (SQLiteException localSQLiteException1) {}
        localZzcay.zzaul().zzayd().zze("Error pruning currencies. appId", zzcbw.zzjf(str), localSQLiteException2);
      }
      catch (SQLiteException localSQLiteException2) {}
      localObject1 = new zzcfv(str, zzimg, (String)localObject1, zzasc.currentTimeMillis(), Long.valueOf(l1));
      label767:
      if (!zzauf().zza((zzcfv)localObject1))
      {
        zzaul().zzayd().zzd("Too many unique user properties are set. Ignoring user property. appId", zzcbw.zzjf(str), zzaug().zzje(mName), mValue);
        zzauh().zza(str, 9, null, null, 0);
      }
    }
    finally
    {
      for (;;)
      {
        Bundle localBundle;
        Object localObject1;
        boolean bool2;
        zzauf().endTransaction();
        for (;;)
        {
          throw paramZzcbk;
        }
      }
    }
    bool1 = zzcfw.zzju(name);
    bool2 = "_err".equals(name);
    localObject1 = zzauf().zza(zzazf(), str, true, bool1, false, bool2, false);
    long l1 = zzimz - zzcax.zzavw();
    if (l1 > 0L)
    {
      if (l1 % 1000L == 1L) {
        zzaul().zzayd().zze("Data loss. Too many events logged. appId, count", zzcbw.zzjf(str), Long.valueOf(zzimz));
      }
      zzauf().setTransactionSuccessful();
      zzauf().endTransaction();
      return;
    }
    if (bool1)
    {
      l1 = zzimy - zzcax.zzavx();
      if (l1 > 0L)
      {
        if (l1 % 1000L == 1L) {
          zzaul().zzayd().zze("Data loss. Too many public events logged. appId, count", zzcbw.zzjf(str), Long.valueOf(zzimy));
        }
        zzauh().zza(str, 16, "_ev", name, 0);
        zzauf().setTransactionSuccessful();
        zzauf().endTransaction();
        return;
      }
    }
    if (bool2)
    {
      l1 = zzinb - Math.max(0, Math.min(1000000, zziss.zzb(packageName, zzcbm.zziom)));
      if (l1 > 0L)
      {
        if (l1 == 1L) {
          zzaul().zzayd().zze("Too many error events logged. appId, count", zzcbw.zzjf(str), Long.valueOf(zzinb));
        }
        zzauf().setTransactionSuccessful();
        zzauf().endTransaction();
        return;
      }
    }
    zzauh().zza(localBundle, "_o", zzimg);
    if (zzauh().zzke(str))
    {
      zzauh().zza(localBundle, "_dbg", Long.valueOf(1L));
      zzauh().zza(localBundle, "_r", Long.valueOf(1L));
    }
    l1 = zzauf().zzix(str);
    if (l1 > 0L) {
      zzaul().zzayf().zze("Data lost. Too many events stored on disk, deleted. appId", zzcbw.zzjf(str), Long.valueOf(l1));
    }
    paramZzcbk = new zzcbf(this, zzimg, str, name, zzins, 0L, localBundle);
    localObject1 = zzauf().zzaf(str, mName);
    if (localObject1 == null)
    {
      l1 = zzauf().zzja(str);
      zzcax.zzavv();
      if (l1 >= 500L)
      {
        paramZzcas = zzaul().zzayd();
        localObject1 = zzcbw.zzjf(str);
        paramZzcbk = zzaug().zzjc(mName);
        zzcax.zzavv();
        paramZzcas.zzd("Too many event names used, ignoring event. appId, name, supported count", localObject1, paramZzcbk, Integer.valueOf(500));
        zzauh().zza(str, 8, null, null, 0);
        zzauf().endTransaction();
        return;
      }
      localObject1 = new zzcbg(str, mName, 0L, 0L, zzfdc);
    }
    else
    {
      paramZzcbk = paramZzcbk.zza(this, zzinn);
      localObject1 = ((zzcbg)localObject1).zzbb(zzfdc);
    }
    zzauf().zza((zzcbg)localObject1);
    zza(paramZzcbk, paramZzcas);
    zzauf().setTransactionSuccessful();
    if (zzaul().zzad(2)) {
      zzaul().zzayj().zzj("Event recorded", zzaug().zza(paramZzcbk));
    }
    zzauf().endTransaction();
    zzazi();
    zzaul().zzayj().zzj("Background event processing time, ms", Long.valueOf((System.nanoTime() - l2 + 500000L) / 1000000L));
  }
  
  public static zzccw zzdn(Context paramContext)
  {
    zzbp.zzu(paramContext);
    zzbp.zzu(paramContext.getApplicationContext());
    if (zzisr == null) {
      try
      {
        if (zzisr == null) {
          zzisr = new zzccw(new zzcdv(paramContext));
        }
      }
      finally {}
    }
    return zzisr;
  }
  
  @X
  private final void zzf(zzcas paramZzcas)
  {
    zzauk().zzuj();
    zzwk();
    zzbp.zzu(paramZzcas);
    zzbp.zzgg(packageName);
    zzcar localZzcar = zzauf().zziw(packageName);
    String str = zzaum().zzji(packageName);
    if (localZzcar == null)
    {
      localZzcar = new zzcar(this, packageName);
      localZzcar.zzim(zzaua().zzaya());
      localZzcar.zzio(str);
    }
    for (;;)
    {
      j = 1;
      break label130;
      if (str.equals(localZzcar.zzaup())) {
        break;
      }
      localZzcar.zzio(str);
      localZzcar.zzim(zzaua().zzaya());
    }
    int j = 0;
    label130:
    int i = j;
    if (!TextUtils.isEmpty(zzilu))
    {
      i = j;
      if (!zzilu.equals(localZzcar.getGmpAppId()))
      {
        localZzcar.zzin(zzilu);
        i = 1;
      }
    }
    j = i;
    if (!TextUtils.isEmpty(zzimc))
    {
      j = i;
      if (!zzimc.equals(localZzcar.zzauq()))
      {
        localZzcar.zzip(zzimc);
        j = 1;
      }
    }
    long l = zzilw;
    i = j;
    if (l != 0L)
    {
      i = j;
      if (l != localZzcar.zzauv())
      {
        localZzcar.zzao(zzilw);
        i = 1;
      }
    }
    j = i;
    if (!TextUtils.isEmpty(zzhtt))
    {
      j = i;
      if (!zzhtt.equals(localZzcar.zzuo()))
      {
        localZzcar.setAppVersion(zzhtt);
        j = 1;
      }
    }
    if (zzimb != localZzcar.zzaut())
    {
      localZzcar.zzan(zzimb);
      j = 1;
    }
    str = zzilv;
    i = j;
    if (str != null)
    {
      i = j;
      if (!str.equals(localZzcar.zzauu()))
      {
        localZzcar.zziq(zzilv);
        i = 1;
      }
    }
    if (zzilx != localZzcar.zzauw())
    {
      localZzcar.zzap(zzilx);
      i = 1;
    }
    if (zzilz != localZzcar.zzaux())
    {
      localZzcar.setMeasurementEnabled(zzilz);
      i = 1;
    }
    j = i;
    if (!TextUtils.isEmpty(zzily))
    {
      j = i;
      if (!zzily.equals(localZzcar.zzavi()))
      {
        localZzcar.zzir(zzily);
        j = 1;
      }
    }
    if (zzimd != localZzcar.zzavk())
    {
      localZzcar.zzaz(zzimd);
      j = 1;
    }
    if (j != 0) {
      zzauf().zza(localZzcar);
    }
  }
  
  /* Error */
  private final boolean zzg(String arg1, long arg2)
  {
    // Byte code:
    //   0: aload_0
    //   1: invokevirtual 628	com/google/android/gms/internal/zzccw:zzauf	()Lcom/google/android/gms/internal/zzcay;
    //   4: invokevirtual 1239	com/google/android/gms/internal/zzcay:beginTransaction	()V
    //   7: aconst_null
    //   8: astore 17
    //   10: new 6	com/google/android/gms/internal/zzccw$zza
    //   13: dup
    //   14: aload_0
    //   15: aconst_null
    //   16: invokespecial 1500	com/google/android/gms/internal/zzccw$zza:<init>	(Lcom/google/android/gms/internal/zzccw;Lcom/google/android/gms/internal/zzccx;)V
    //   19: astore 20
    //   21: aload_0
    //   22: invokevirtual 628	com/google/android/gms/internal/zzccw:zzauf	()Lcom/google/android/gms/internal/zzcay;
    //   25: astore 21
    //   27: aload_0
    //   28: getfield 102	com/google/android/gms/internal/zzccw:zzitx	J
    //   31: lstore 11
    //   33: aload 20
    //   35: invokestatic 93	com/google/android/gms/common/internal/zzbp:zzu	(Ljava/lang/Object;)Ljava/lang/Object;
    //   38: pop
    //   39: aload 21
    //   41: invokevirtual 894	com/google/android/gms/internal/zzcdt:zzuj	()V
    //   44: aload 21
    //   46: invokevirtual 565	com/google/android/gms/internal/zzcdu:zzwk	()V
    //   49: aload 21
    //   51: invokevirtual 1333	com/google/android/gms/internal/zzcay:getWritableDatabase	()Landroid/database/sqlite/SQLiteDatabase;
    //   54: astore 22
    //   56: aconst_null
    //   57: invokestatic 518	android/text/TextUtils:isEmpty	(Ljava/lang/CharSequence;)Z
    //   60: istore 13
    //   62: ldc_w 1502
    //   65: astore_1
    //   66: iload 13
    //   68: ifeq +247 -> 315
    //   71: lload 11
    //   73: ldc2_w 99
    //   76: lcmp
    //   77: ifeq +64 -> 141
    //   80: aload 17
    //   82: astore 16
    //   84: iconst_2
    //   85: anewarray 213	java/lang/String
    //   88: astore 18
    //   90: aload 17
    //   92: astore 16
    //   94: aload 18
    //   96: iconst_0
    //   97: lload 11
    //   99: invokestatic 1505	java/lang/String:valueOf	(J)Ljava/lang/String;
    //   102: aastore
    //   103: aload 17
    //   105: astore 16
    //   107: aload 18
    //   109: iconst_1
    //   110: lload_2
    //   111: invokestatic 1505	java/lang/String:valueOf	(J)Ljava/lang/String;
    //   114: aastore
    //   115: aload 18
    //   117: astore 16
    //   119: goto +36 -> 155
    //   122: astore_1
    //   123: goto +2942 -> 3065
    //   126: astore_1
    //   127: aconst_null
    //   128: astore 16
    //   130: aload 16
    //   132: astore 17
    //   134: aload 17
    //   136: astore 18
    //   138: goto +957 -> 1095
    //   141: iconst_1
    //   142: anewarray 213	java/lang/String
    //   145: astore 16
    //   147: aload 16
    //   149: iconst_0
    //   150: lload_2
    //   151: invokestatic 1505	java/lang/String:valueOf	(J)Ljava/lang/String;
    //   154: aastore
    //   155: lload 11
    //   157: ldc2_w 99
    //   160: lcmp
    //   161: ifeq +7 -> 168
    //   164: ldc_w 1507
    //   167: astore_1
    //   168: new 1509	java/lang/StringBuilder
    //   171: dup
    //   172: aload_1
    //   173: invokevirtual 220	java/lang/String:length	()I
    //   176: sipush 148
    //   179: iadd
    //   180: invokespecial 1512	java/lang/StringBuilder:<init>	(I)V
    //   183: astore 17
    //   185: aload 17
    //   187: ldc_w 1514
    //   190: invokevirtual 1518	java/lang/StringBuilder:append	(Ljava/lang/String;)Ljava/lang/StringBuilder;
    //   193: pop
    //   194: aload 17
    //   196: aload_1
    //   197: invokevirtual 1518	java/lang/StringBuilder:append	(Ljava/lang/String;)Ljava/lang/StringBuilder;
    //   200: pop
    //   201: aload 17
    //   203: ldc_w 1520
    //   206: invokevirtual 1518	java/lang/StringBuilder:append	(Ljava/lang/String;)Ljava/lang/StringBuilder;
    //   209: pop
    //   210: aload 22
    //   212: aload 17
    //   214: invokevirtual 1521	java/lang/StringBuilder:toString	()Ljava/lang/String;
    //   217: aload 16
    //   219: invokevirtual 1525	android/database/sqlite/SQLiteDatabase:rawQuery	(Ljava/lang/String;[Ljava/lang/String;)Landroid/database/Cursor;
    //   222: astore_1
    //   223: aload_1
    //   224: astore 16
    //   226: aload_1
    //   227: astore 17
    //   229: aload_1
    //   230: invokeinterface 1530 1 0
    //   235: istore 13
    //   237: iload 13
    //   239: ifne +12 -> 251
    //   242: aload_1
    //   243: invokeinterface 1533 1 0
    //   248: goto +879 -> 1127
    //   251: aload_1
    //   252: astore 16
    //   254: aload_1
    //   255: astore 17
    //   257: aload_1
    //   258: iconst_0
    //   259: invokeinterface 1535 2 0
    //   264: astore 18
    //   266: aload_1
    //   267: astore 16
    //   269: aload_1
    //   270: iconst_1
    //   271: invokeinterface 1535 2 0
    //   276: astore 19
    //   278: aload_1
    //   279: astore 16
    //   281: aload_1
    //   282: invokeinterface 1533 1 0
    //   287: aload_1
    //   288: astore 17
    //   290: aload 18
    //   292: astore_1
    //   293: aload 19
    //   295: astore 18
    //   297: goto +179 -> 476
    //   300: astore 17
    //   302: aload_1
    //   303: astore 16
    //   305: aload 17
    //   307: astore_1
    //   308: aload 18
    //   310: astore 17
    //   312: goto -178 -> 134
    //   315: lload 11
    //   317: ldc2_w 99
    //   320: lcmp
    //   321: ifeq +24 -> 345
    //   324: iconst_2
    //   325: anewarray 213	java/lang/String
    //   328: dup
    //   329: iconst_0
    //   330: aconst_null
    //   331: aastore
    //   332: dup
    //   333: iconst_1
    //   334: lload 11
    //   336: invokestatic 1505	java/lang/String:valueOf	(J)Ljava/lang/String;
    //   339: aastore
    //   340: astore 16
    //   342: goto +13 -> 355
    //   345: iconst_1
    //   346: anewarray 213	java/lang/String
    //   349: dup
    //   350: iconst_0
    //   351: aconst_null
    //   352: aastore
    //   353: astore 16
    //   355: lload 11
    //   357: ldc2_w 99
    //   360: lcmp
    //   361: ifeq +7 -> 368
    //   364: ldc_w 1537
    //   367: astore_1
    //   368: new 1509	java/lang/StringBuilder
    //   371: dup
    //   372: aload_1
    //   373: invokevirtual 220	java/lang/String:length	()I
    //   376: bipush 84
    //   378: iadd
    //   379: invokespecial 1512	java/lang/StringBuilder:<init>	(I)V
    //   382: astore 17
    //   384: aload 17
    //   386: ldc_w 1539
    //   389: invokevirtual 1518	java/lang/StringBuilder:append	(Ljava/lang/String;)Ljava/lang/StringBuilder;
    //   392: pop
    //   393: aload 17
    //   395: aload_1
    //   396: invokevirtual 1518	java/lang/StringBuilder:append	(Ljava/lang/String;)Ljava/lang/StringBuilder;
    //   399: pop
    //   400: aload 17
    //   402: ldc_w 1541
    //   405: invokevirtual 1518	java/lang/StringBuilder:append	(Ljava/lang/String;)Ljava/lang/StringBuilder;
    //   408: pop
    //   409: aload 22
    //   411: aload 17
    //   413: invokevirtual 1521	java/lang/StringBuilder:toString	()Ljava/lang/String;
    //   416: aload 16
    //   418: invokevirtual 1525	android/database/sqlite/SQLiteDatabase:rawQuery	(Ljava/lang/String;[Ljava/lang/String;)Landroid/database/Cursor;
    //   421: astore_1
    //   422: aload_1
    //   423: astore 16
    //   425: aload_1
    //   426: astore 17
    //   428: aload_1
    //   429: invokeinterface 1530 1 0
    //   434: ifne +6 -> 440
    //   437: goto -195 -> 242
    //   440: aload_1
    //   441: astore 16
    //   443: aload_1
    //   444: astore 17
    //   446: aload_1
    //   447: iconst_0
    //   448: invokeinterface 1535 2 0
    //   453: astore 18
    //   455: aload_1
    //   456: astore 16
    //   458: aload_1
    //   459: astore 17
    //   461: aload_1
    //   462: invokeinterface 1533 1 0
    //   467: aconst_null
    //   468: astore 16
    //   470: aload_1
    //   471: astore 17
    //   473: aload 16
    //   475: astore_1
    //   476: aload 22
    //   478: ldc_w 1543
    //   481: iconst_1
    //   482: anewarray 213	java/lang/String
    //   485: dup
    //   486: iconst_0
    //   487: ldc_w 1545
    //   490: aastore
    //   491: ldc_w 1547
    //   494: iconst_2
    //   495: anewarray 213	java/lang/String
    //   498: dup
    //   499: iconst_0
    //   500: aload_1
    //   501: aastore
    //   502: dup
    //   503: iconst_1
    //   504: aload 18
    //   506: aastore
    //   507: aconst_null
    //   508: aconst_null
    //   509: ldc_w 1549
    //   512: ldc_w 1551
    //   515: invokevirtual 1555	android/database/sqlite/SQLiteDatabase:query	(Ljava/lang/String;[Ljava/lang/String;Ljava/lang/String;[Ljava/lang/String;Ljava/lang/String;Ljava/lang/String;Ljava/lang/String;Ljava/lang/String;)Landroid/database/Cursor;
    //   518: astore 16
    //   520: aload 16
    //   522: invokeinterface 1530 1 0
    //   527: istore 13
    //   529: iload 13
    //   531: ifne +46 -> 577
    //   534: aload 21
    //   536: invokevirtual 1345	com/google/android/gms/internal/zzcdt:zzaul	()Lcom/google/android/gms/internal/zzcbw;
    //   539: invokevirtual 315	com/google/android/gms/internal/zzcbw:zzayd	()Lcom/google/android/gms/internal/zzcby;
    //   542: ldc_w 1557
    //   545: aload_1
    //   546: invokestatic 555	com/google/android/gms/internal/zzcbw:zzjf	(Ljava/lang/String;)Ljava/lang/Object;
    //   549: invokevirtual 167	com/google/android/gms/internal/zzcby:zzj	(Ljava/lang/String;Ljava/lang/Object;)V
    //   552: aload 16
    //   554: invokeinterface 1533 1 0
    //   559: goto +568 -> 1127
    //   562: astore_1
    //   563: goto +2502 -> 3065
    //   566: astore 18
    //   568: aload_1
    //   569: astore 17
    //   571: aload 18
    //   573: astore_1
    //   574: goto -440 -> 134
    //   577: aload 16
    //   579: iconst_0
    //   580: invokeinterface 1561 2 0
    //   585: astore 17
    //   587: aload 17
    //   589: iconst_0
    //   590: aload 17
    //   592: arraylength
    //   593: invokestatic 1567	com/google/android/gms/internal/zzeye:zzm	([BII)Lcom/google/android/gms/internal/zzeye;
    //   596: astore 17
    //   598: new 450	com/google/android/gms/internal/zzcgk
    //   601: dup
    //   602: invokespecial 451	com/google/android/gms/internal/zzcgk:<init>	()V
    //   605: astore 19
    //   607: aload 19
    //   609: aload 17
    //   611: invokevirtual 1570	com/google/android/gms/internal/zzcgk:zza	(Lcom/google/android/gms/internal/zzeye;)Lcom/google/android/gms/internal/zzeyn;
    //   614: pop
    //   615: aload 16
    //   617: invokeinterface 1573 1 0
    //   622: istore 13
    //   624: iload 13
    //   626: ifeq +21 -> 647
    //   629: aload 21
    //   631: invokevirtual 1345	com/google/android/gms/internal/zzcdt:zzaul	()Lcom/google/android/gms/internal/zzcbw;
    //   634: invokevirtual 368	com/google/android/gms/internal/zzcbw:zzayf	()Lcom/google/android/gms/internal/zzcby;
    //   637: ldc_w 1575
    //   640: aload_1
    //   641: invokestatic 555	com/google/android/gms/internal/zzcbw:zzjf	(Ljava/lang/String;)Ljava/lang/Object;
    //   644: invokevirtual 167	com/google/android/gms/internal/zzcby:zzj	(Ljava/lang/String;Ljava/lang/Object;)V
    //   647: aload 16
    //   649: invokeinterface 1533 1 0
    //   654: aload 20
    //   656: aload 19
    //   658: invokeinterface 1580 2 0
    //   663: lload 11
    //   665: ldc2_w 99
    //   668: lcmp
    //   669: ifeq +38 -> 707
    //   672: ldc_w 1582
    //   675: astore 17
    //   677: iconst_3
    //   678: anewarray 213	java/lang/String
    //   681: dup
    //   682: iconst_0
    //   683: aload_1
    //   684: aastore
    //   685: dup
    //   686: iconst_1
    //   687: aload 18
    //   689: aastore
    //   690: dup
    //   691: iconst_2
    //   692: lload 11
    //   694: invokestatic 1505	java/lang/String:valueOf	(J)Ljava/lang/String;
    //   697: aastore
    //   698: astore 19
    //   700: aload 17
    //   702: astore 18
    //   704: goto +27 -> 731
    //   707: ldc_w 1547
    //   710: astore 17
    //   712: iconst_2
    //   713: anewarray 213	java/lang/String
    //   716: dup
    //   717: iconst_0
    //   718: aload_1
    //   719: aastore
    //   720: dup
    //   721: iconst_1
    //   722: aload 18
    //   724: aastore
    //   725: astore 19
    //   727: aload 17
    //   729: astore 18
    //   731: aload 16
    //   733: astore 17
    //   735: aload 22
    //   737: ldc_w 1584
    //   740: iconst_4
    //   741: anewarray 213	java/lang/String
    //   744: dup
    //   745: iconst_0
    //   746: ldc_w 1549
    //   749: aastore
    //   750: dup
    //   751: iconst_1
    //   752: ldc_w 1585
    //   755: aastore
    //   756: dup
    //   757: iconst_2
    //   758: ldc_w 1587
    //   761: aastore
    //   762: dup
    //   763: iconst_3
    //   764: ldc_w 1589
    //   767: aastore
    //   768: aload 18
    //   770: aload 19
    //   772: aconst_null
    //   773: aconst_null
    //   774: ldc_w 1549
    //   777: aconst_null
    //   778: invokevirtual 1555	android/database/sqlite/SQLiteDatabase:query	(Ljava/lang/String;[Ljava/lang/String;Ljava/lang/String;[Ljava/lang/String;Ljava/lang/String;Ljava/lang/String;Ljava/lang/String;Ljava/lang/String;)Landroid/database/Cursor;
    //   781: astore 18
    //   783: aload 18
    //   785: invokeinterface 1530 1 0
    //   790: ifne +31 -> 821
    //   793: aload 21
    //   795: invokevirtual 1345	com/google/android/gms/internal/zzcdt:zzaul	()Lcom/google/android/gms/internal/zzcbw;
    //   798: invokevirtual 368	com/google/android/gms/internal/zzcbw:zzayf	()Lcom/google/android/gms/internal/zzcby;
    //   801: ldc_w 1591
    //   804: aload_1
    //   805: invokestatic 555	com/google/android/gms/internal/zzcbw:zzjf	(Ljava/lang/String;)Ljava/lang/Object;
    //   808: invokevirtual 167	com/google/android/gms/internal/zzcby:zzj	(Ljava/lang/String;Ljava/lang/Object;)V
    //   811: aload 18
    //   813: invokeinterface 1533 1 0
    //   818: goto +309 -> 1127
    //   821: aload 18
    //   823: iconst_0
    //   824: invokeinterface 1594 2 0
    //   829: lstore_2
    //   830: aload 18
    //   832: iconst_3
    //   833: invokeinterface 1561 2 0
    //   838: astore 16
    //   840: aload 16
    //   842: iconst_0
    //   843: aload 16
    //   845: arraylength
    //   846: invokestatic 1567	com/google/android/gms/internal/zzeye:zzm	([BII)Lcom/google/android/gms/internal/zzeye;
    //   849: astore 16
    //   851: new 1596	com/google/android/gms/internal/zzcgh
    //   854: dup
    //   855: invokespecial 1597	com/google/android/gms/internal/zzcgh:<init>	()V
    //   858: astore 17
    //   860: aload 17
    //   862: aload 16
    //   864: invokevirtual 1598	com/google/android/gms/internal/zzcgh:zza	(Lcom/google/android/gms/internal/zzeye;)Lcom/google/android/gms/internal/zzeyn;
    //   867: pop
    //   868: aload 17
    //   870: aload 18
    //   872: iconst_1
    //   873: invokeinterface 1535 2 0
    //   878: putfield 1599	com/google/android/gms/internal/zzcgh:name	Ljava/lang/String;
    //   881: aload 17
    //   883: aload 18
    //   885: iconst_2
    //   886: invokeinterface 1594 2 0
    //   891: invokestatic 161	java/lang/Long:valueOf	(J)Ljava/lang/Long;
    //   894: putfield 1602	com/google/android/gms/internal/zzcgh:zziyy	Ljava/lang/Long;
    //   897: aload 20
    //   899: lload_2
    //   900: aload 17
    //   902: invokeinterface 1605 4 0
    //   907: ifne +28 -> 935
    //   910: goto -99 -> 811
    //   913: astore 16
    //   915: aload 21
    //   917: invokevirtual 1345	com/google/android/gms/internal/zzcdt:zzaul	()Lcom/google/android/gms/internal/zzcbw;
    //   920: invokevirtual 315	com/google/android/gms/internal/zzcbw:zzayd	()Lcom/google/android/gms/internal/zzcby;
    //   923: ldc_w 1607
    //   926: aload_1
    //   927: invokestatic 555	com/google/android/gms/internal/zzcbw:zzjf	(Ljava/lang/String;)Ljava/lang/Object;
    //   930: aload 16
    //   932: invokevirtual 326	com/google/android/gms/internal/zzcby:zze	(Ljava/lang/String;Ljava/lang/Object;Ljava/lang/Object;)V
    //   935: aload 18
    //   937: invokeinterface 1573 1 0
    //   942: istore 13
    //   944: iload 13
    //   946: ifne -125 -> 821
    //   949: goto -138 -> 811
    //   952: astore_1
    //   953: aload 18
    //   955: astore 16
    //   957: goto +2108 -> 3065
    //   960: astore 19
    //   962: aload_1
    //   963: astore 17
    //   965: aload 18
    //   967: astore 16
    //   969: aload 19
    //   971: astore_1
    //   972: goto -838 -> 134
    //   975: astore 19
    //   977: aload 16
    //   979: astore 18
    //   981: aload 18
    //   983: astore 17
    //   985: aload 21
    //   987: invokevirtual 1345	com/google/android/gms/internal/zzcdt:zzaul	()Lcom/google/android/gms/internal/zzcbw;
    //   990: invokevirtual 315	com/google/android/gms/internal/zzcbw:zzayd	()Lcom/google/android/gms/internal/zzcby;
    //   993: ldc_w 1609
    //   996: aload_1
    //   997: invokestatic 555	com/google/android/gms/internal/zzcbw:zzjf	(Ljava/lang/String;)Ljava/lang/Object;
    //   1000: aload 19
    //   1002: invokevirtual 326	com/google/android/gms/internal/zzcby:zze	(Ljava/lang/String;Ljava/lang/Object;Ljava/lang/Object;)V
    //   1005: aload 18
    //   1007: astore 16
    //   1009: aload 16
    //   1011: invokeinterface 1533 1 0
    //   1016: goto +111 -> 1127
    //   1019: astore 17
    //   1021: goto +9 -> 1030
    //   1024: astore_1
    //   1025: goto +2040 -> 3065
    //   1028: astore 17
    //   1030: aload_1
    //   1031: astore 18
    //   1033: aload 17
    //   1035: astore_1
    //   1036: aload 18
    //   1038: astore 17
    //   1040: goto -906 -> 134
    //   1043: astore_1
    //   1044: aload 17
    //   1046: astore 16
    //   1048: goto +2017 -> 3065
    //   1051: astore 19
    //   1053: aload_1
    //   1054: astore 18
    //   1056: aload 17
    //   1058: astore 16
    //   1060: aload 19
    //   1062: astore_1
    //   1063: aload 18
    //   1065: astore 17
    //   1067: goto -933 -> 134
    //   1070: astore_1
    //   1071: aload 17
    //   1073: astore 16
    //   1075: aconst_null
    //   1076: astore 17
    //   1078: goto -944 -> 134
    //   1081: astore_1
    //   1082: aconst_null
    //   1083: astore 16
    //   1085: goto +1980 -> 3065
    //   1088: astore_1
    //   1089: aconst_null
    //   1090: astore 16
    //   1092: aconst_null
    //   1093: astore 18
    //   1095: aload 16
    //   1097: astore 17
    //   1099: aload 21
    //   1101: invokevirtual 1345	com/google/android/gms/internal/zzcdt:zzaul	()Lcom/google/android/gms/internal/zzcbw;
    //   1104: invokevirtual 315	com/google/android/gms/internal/zzcbw:zzayd	()Lcom/google/android/gms/internal/zzcby;
    //   1107: ldc_w 1611
    //   1110: aload 18
    //   1112: invokestatic 555	com/google/android/gms/internal/zzcbw:zzjf	(Ljava/lang/String;)Ljava/lang/Object;
    //   1115: aload_1
    //   1116: invokevirtual 326	com/google/android/gms/internal/zzcby:zze	(Ljava/lang/String;Ljava/lang/Object;Ljava/lang/Object;)V
    //   1119: aload 16
    //   1121: ifnull +6 -> 1127
    //   1124: goto -115 -> 1009
    //   1127: aload 20
    //   1129: getfield 1614	com/google/android/gms/internal/zzccw$zza:zzaoc	Ljava/util/List;
    //   1132: ifnull +1969 -> 3101
    //   1135: aload 20
    //   1137: getfield 1614	com/google/android/gms/internal/zzccw$zza:zzaoc	Ljava/util/List;
    //   1140: invokeinterface 1615 1 0
    //   1145: ifeq +1950 -> 3095
    //   1148: goto +1953 -> 3101
    //   1151: iload 4
    //   1153: ifne +1891 -> 3044
    //   1156: aload 20
    //   1158: getfield 1619	com/google/android/gms/internal/zzccw$zza:zziue	Lcom/google/android/gms/internal/zzcgk;
    //   1161: astore 18
    //   1163: aload 18
    //   1165: aload 20
    //   1167: getfield 1614	com/google/android/gms/internal/zzccw$zza:zzaoc	Ljava/util/List;
    //   1170: invokeinterface 714 1 0
    //   1175: anewarray 1596	com/google/android/gms/internal/zzcgh
    //   1178: putfield 1623	com/google/android/gms/internal/zzcgk:zzizf	[Lcom/google/android/gms/internal/zzcgh;
    //   1181: iconst_0
    //   1182: istore 4
    //   1184: iconst_0
    //   1185: istore 5
    //   1187: iconst_0
    //   1188: istore 13
    //   1190: iload 4
    //   1192: aload 20
    //   1194: getfield 1614	com/google/android/gms/internal/zzccw$zza:zzaoc	Ljava/util/List;
    //   1197: invokeinterface 714 1 0
    //   1202: if_icmpge +1256 -> 2458
    //   1205: aload_0
    //   1206: invokevirtual 773	com/google/android/gms/internal/zzccw:zzaui	()Lcom/google/android/gms/internal/zzccq;
    //   1209: aload 20
    //   1211: getfield 1619	com/google/android/gms/internal/zzccw$zza:zziue	Lcom/google/android/gms/internal/zzcgk;
    //   1214: getfield 463	com/google/android/gms/internal/zzcgk:zzci	Ljava/lang/String;
    //   1217: aload 20
    //   1219: getfield 1614	com/google/android/gms/internal/zzccw$zza:zzaoc	Ljava/util/List;
    //   1222: iload 4
    //   1224: invokeinterface 725 2 0
    //   1229: checkcast 1596	com/google/android/gms/internal/zzcgh
    //   1232: getfield 1599	com/google/android/gms/internal/zzcgh:name	Ljava/lang/String;
    //   1235: invokevirtual 1192	com/google/android/gms/internal/zzccq:zzao	(Ljava/lang/String;Ljava/lang/String;)Z
    //   1238: istore 14
    //   1240: iload 14
    //   1242: ifeq +189 -> 1431
    //   1245: aload_0
    //   1246: invokevirtual 144	com/google/android/gms/internal/zzccw:zzaul	()Lcom/google/android/gms/internal/zzcbw;
    //   1249: invokevirtual 368	com/google/android/gms/internal/zzcbw:zzayf	()Lcom/google/android/gms/internal/zzcby;
    //   1252: ldc_w 1625
    //   1255: aload 20
    //   1257: getfield 1619	com/google/android/gms/internal/zzccw$zza:zziue	Lcom/google/android/gms/internal/zzcgk;
    //   1260: getfield 463	com/google/android/gms/internal/zzcgk:zzci	Ljava/lang/String;
    //   1263: invokestatic 555	com/google/android/gms/internal/zzcbw:zzjf	(Ljava/lang/String;)Ljava/lang/Object;
    //   1266: aload_0
    //   1267: invokevirtual 1198	com/google/android/gms/internal/zzccw:zzaug	()Lcom/google/android/gms/internal/zzcbu;
    //   1270: aload 20
    //   1272: getfield 1614	com/google/android/gms/internal/zzccw$zza:zzaoc	Ljava/util/List;
    //   1275: iload 4
    //   1277: invokeinterface 725 2 0
    //   1282: checkcast 1596	com/google/android/gms/internal/zzcgh
    //   1285: getfield 1599	com/google/android/gms/internal/zzcgh:name	Ljava/lang/String;
    //   1288: invokevirtual 1201	com/google/android/gms/internal/zzcbu:zzjc	(Ljava/lang/String;)Ljava/lang/String;
    //   1291: invokevirtual 326	com/google/android/gms/internal/zzcby:zze	(Ljava/lang/String;Ljava/lang/Object;Ljava/lang/Object;)V
    //   1294: aload_0
    //   1295: invokevirtual 205	com/google/android/gms/internal/zzccw:zzauh	()Lcom/google/android/gms/internal/zzcfw;
    //   1298: aload 20
    //   1300: getfield 1619	com/google/android/gms/internal/zzccw$zza:zziue	Lcom/google/android/gms/internal/zzcgk;
    //   1303: getfield 463	com/google/android/gms/internal/zzcgk:zzci	Ljava/lang/String;
    //   1306: invokevirtual 1204	com/google/android/gms/internal/zzcfw:zzkg	(Ljava/lang/String;)Z
    //   1309: ifne +1804 -> 3113
    //   1312: aload_0
    //   1313: invokevirtual 205	com/google/android/gms/internal/zzccw:zzauh	()Lcom/google/android/gms/internal/zzcfw;
    //   1316: aload 20
    //   1318: getfield 1619	com/google/android/gms/internal/zzccw$zza:zziue	Lcom/google/android/gms/internal/zzcgk;
    //   1321: getfield 463	com/google/android/gms/internal/zzcgk:zzci	Ljava/lang/String;
    //   1324: invokevirtual 1207	com/google/android/gms/internal/zzcfw:zzkh	(Ljava/lang/String;)Z
    //   1327: ifeq +1780 -> 3107
    //   1330: goto +1783 -> 3113
    //   1333: iload 5
    //   1335: istore 6
    //   1337: iload 13
    //   1339: istore 14
    //   1341: iload 7
    //   1343: ifne +1877 -> 3220
    //   1346: iload 5
    //   1348: istore 6
    //   1350: iload 13
    //   1352: istore 14
    //   1354: ldc_w 1209
    //   1357: aload 20
    //   1359: getfield 1614	com/google/android/gms/internal/zzccw$zza:zzaoc	Ljava/util/List;
    //   1362: iload 4
    //   1364: invokeinterface 725 2 0
    //   1369: checkcast 1596	com/google/android/gms/internal/zzcgh
    //   1372: getfield 1599	com/google/android/gms/internal/zzcgh:name	Ljava/lang/String;
    //   1375: invokevirtual 444	java/lang/String:equals	(Ljava/lang/Object;)Z
    //   1378: ifne +1842 -> 3220
    //   1381: aload_0
    //   1382: invokevirtual 205	com/google/android/gms/internal/zzccw:zzauh	()Lcom/google/android/gms/internal/zzcfw;
    //   1385: aload 20
    //   1387: getfield 1619	com/google/android/gms/internal/zzccw$zza:zziue	Lcom/google/android/gms/internal/zzcgk;
    //   1390: getfield 463	com/google/android/gms/internal/zzcgk:zzci	Ljava/lang/String;
    //   1393: bipush 11
    //   1395: ldc_w 1211
    //   1398: aload 20
    //   1400: getfield 1614	com/google/android/gms/internal/zzccw$zza:zzaoc	Ljava/util/List;
    //   1403: iload 4
    //   1405: invokeinterface 725 2 0
    //   1410: checkcast 1596	com/google/android/gms/internal/zzcgh
    //   1413: getfield 1599	com/google/android/gms/internal/zzcgh:name	Ljava/lang/String;
    //   1416: iconst_0
    //   1417: invokevirtual 1214	com/google/android/gms/internal/zzcfw:zza	(Ljava/lang/String;ILjava/lang/String;Ljava/lang/String;I)V
    //   1420: iload 5
    //   1422: istore 6
    //   1424: iload 13
    //   1426: istore 14
    //   1428: goto +1792 -> 3220
    //   1431: aload_0
    //   1432: invokevirtual 773	com/google/android/gms/internal/zzccw:zzaui	()Lcom/google/android/gms/internal/zzccq;
    //   1435: aload 20
    //   1437: getfield 1619	com/google/android/gms/internal/zzccw$zza:zziue	Lcom/google/android/gms/internal/zzcgk;
    //   1440: getfield 463	com/google/android/gms/internal/zzcgk:zzci	Ljava/lang/String;
    //   1443: aload 20
    //   1445: getfield 1614	com/google/android/gms/internal/zzccw$zza:zzaoc	Ljava/util/List;
    //   1448: iload 4
    //   1450: invokeinterface 725 2 0
    //   1455: checkcast 1596	com/google/android/gms/internal/zzcgh
    //   1458: getfield 1599	com/google/android/gms/internal/zzcgh:name	Ljava/lang/String;
    //   1461: invokevirtual 777	com/google/android/gms/internal/zzccq:zzap	(Ljava/lang/String;Ljava/lang/String;)Z
    //   1464: istore 15
    //   1466: iload 15
    //   1468: ifne +36 -> 1504
    //   1471: aload_0
    //   1472: invokevirtual 205	com/google/android/gms/internal/zzccw:zzauh	()Lcom/google/android/gms/internal/zzcfw;
    //   1475: pop
    //   1476: iload 13
    //   1478: istore 14
    //   1480: aload 20
    //   1482: getfield 1614	com/google/android/gms/internal/zzccw$zza:zzaoc	Ljava/util/List;
    //   1485: iload 4
    //   1487: invokeinterface 725 2 0
    //   1492: checkcast 1596	com/google/android/gms/internal/zzcgh
    //   1495: getfield 1599	com/google/android/gms/internal/zzcgh:name	Ljava/lang/String;
    //   1498: invokestatic 1628	com/google/android/gms/internal/zzcfw:zzki	(Ljava/lang/String;)Z
    //   1501: ifeq +925 -> 2426
    //   1504: aload 20
    //   1506: getfield 1614	com/google/android/gms/internal/zzccw$zza:zzaoc	Ljava/util/List;
    //   1509: iload 4
    //   1511: invokeinterface 725 2 0
    //   1516: checkcast 1596	com/google/android/gms/internal/zzcgh
    //   1519: getfield 1632	com/google/android/gms/internal/zzcgh:zziyx	[Lcom/google/android/gms/internal/zzcgi;
    //   1522: ifnonnull +25 -> 1547
    //   1525: aload 20
    //   1527: getfield 1614	com/google/android/gms/internal/zzccw$zza:zzaoc	Ljava/util/List;
    //   1530: iload 4
    //   1532: invokeinterface 725 2 0
    //   1537: checkcast 1596	com/google/android/gms/internal/zzcgh
    //   1540: iconst_0
    //   1541: anewarray 1634	com/google/android/gms/internal/zzcgi
    //   1544: putfield 1632	com/google/android/gms/internal/zzcgh:zziyx	[Lcom/google/android/gms/internal/zzcgi;
    //   1547: aload 20
    //   1549: getfield 1614	com/google/android/gms/internal/zzccw$zza:zzaoc	Ljava/util/List;
    //   1552: iload 4
    //   1554: invokeinterface 725 2 0
    //   1559: checkcast 1596	com/google/android/gms/internal/zzcgh
    //   1562: getfield 1632	com/google/android/gms/internal/zzcgh:zziyx	[Lcom/google/android/gms/internal/zzcgi;
    //   1565: astore_1
    //   1566: aload_1
    //   1567: arraylength
    //   1568: istore 6
    //   1570: iconst_0
    //   1571: istore 7
    //   1573: iconst_0
    //   1574: istore 8
    //   1576: iconst_0
    //   1577: istore 9
    //   1579: iload 7
    //   1581: iload 6
    //   1583: if_icmpge +75 -> 1658
    //   1586: aload_1
    //   1587: iload 7
    //   1589: aaload
    //   1590: astore 16
    //   1592: ldc_w 1636
    //   1595: aload 16
    //   1597: getfield 1637	com/google/android/gms/internal/zzcgi:name	Ljava/lang/String;
    //   1600: invokevirtual 444	java/lang/String:equals	(Ljava/lang/Object;)Z
    //   1603: ifeq +18 -> 1621
    //   1606: aload 16
    //   1608: lconst_1
    //   1609: invokestatic 161	java/lang/Long:valueOf	(J)Ljava/lang/Long;
    //   1612: putfield 1640	com/google/android/gms/internal/zzcgi:zzizb	Ljava/lang/Long;
    //   1615: iconst_1
    //   1616: istore 10
    //   1618: goto +1501 -> 3119
    //   1621: iload 8
    //   1623: istore 10
    //   1625: ldc_w 765
    //   1628: aload 16
    //   1630: getfield 1637	com/google/android/gms/internal/zzcgi:name	Ljava/lang/String;
    //   1633: invokevirtual 444	java/lang/String:equals	(Ljava/lang/Object;)Z
    //   1636: ifeq +1483 -> 3119
    //   1639: aload 16
    //   1641: lconst_1
    //   1642: invokestatic 161	java/lang/Long:valueOf	(J)Ljava/lang/Long;
    //   1645: putfield 1640	com/google/android/gms/internal/zzcgi:zzizb	Ljava/lang/Long;
    //   1648: iconst_1
    //   1649: istore 9
    //   1651: iload 8
    //   1653: istore 10
    //   1655: goto +1464 -> 3119
    //   1658: iload 8
    //   1660: ifne +145 -> 1805
    //   1663: iload 15
    //   1665: ifeq +140 -> 1805
    //   1668: aload_0
    //   1669: invokevirtual 144	com/google/android/gms/internal/zzccw:zzaul	()Lcom/google/android/gms/internal/zzcbw;
    //   1672: invokevirtual 363	com/google/android/gms/internal/zzcbw:zzayj	()Lcom/google/android/gms/internal/zzcby;
    //   1675: ldc_w 1642
    //   1678: aload_0
    //   1679: invokevirtual 1198	com/google/android/gms/internal/zzccw:zzaug	()Lcom/google/android/gms/internal/zzcbu;
    //   1682: aload 20
    //   1684: getfield 1614	com/google/android/gms/internal/zzccw$zza:zzaoc	Ljava/util/List;
    //   1687: iload 4
    //   1689: invokeinterface 725 2 0
    //   1694: checkcast 1596	com/google/android/gms/internal/zzcgh
    //   1697: getfield 1599	com/google/android/gms/internal/zzcgh:name	Ljava/lang/String;
    //   1700: invokevirtual 1201	com/google/android/gms/internal/zzcbu:zzjc	(Ljava/lang/String;)Ljava/lang/String;
    //   1703: invokevirtual 167	com/google/android/gms/internal/zzcby:zzj	(Ljava/lang/String;Ljava/lang/Object;)V
    //   1706: aload 20
    //   1708: getfield 1614	com/google/android/gms/internal/zzccw$zza:zzaoc	Ljava/util/List;
    //   1711: iload 4
    //   1713: invokeinterface 725 2 0
    //   1718: checkcast 1596	com/google/android/gms/internal/zzcgh
    //   1721: getfield 1632	com/google/android/gms/internal/zzcgh:zziyx	[Lcom/google/android/gms/internal/zzcgi;
    //   1724: aload 20
    //   1726: getfield 1614	com/google/android/gms/internal/zzccw$zza:zzaoc	Ljava/util/List;
    //   1729: iload 4
    //   1731: invokeinterface 725 2 0
    //   1736: checkcast 1596	com/google/android/gms/internal/zzcgh
    //   1739: getfield 1632	com/google/android/gms/internal/zzcgh:zziyx	[Lcom/google/android/gms/internal/zzcgi;
    //   1742: arraylength
    //   1743: iconst_1
    //   1744: iadd
    //   1745: invokestatic 1648	java/util/Arrays:copyOf	([Ljava/lang/Object;I)[Ljava/lang/Object;
    //   1748: checkcast 1649	[Lcom/google/android/gms/internal/zzcgi;
    //   1751: astore_1
    //   1752: new 1634	com/google/android/gms/internal/zzcgi
    //   1755: dup
    //   1756: invokespecial 1650	com/google/android/gms/internal/zzcgi:<init>	()V
    //   1759: astore 16
    //   1761: aload 16
    //   1763: ldc_w 1636
    //   1766: putfield 1637	com/google/android/gms/internal/zzcgi:name	Ljava/lang/String;
    //   1769: aload 16
    //   1771: lconst_1
    //   1772: invokestatic 161	java/lang/Long:valueOf	(J)Ljava/lang/Long;
    //   1775: putfield 1640	com/google/android/gms/internal/zzcgi:zzizb	Ljava/lang/Long;
    //   1778: aload_1
    //   1779: aload_1
    //   1780: arraylength
    //   1781: iconst_1
    //   1782: isub
    //   1783: aload 16
    //   1785: aastore
    //   1786: aload 20
    //   1788: getfield 1614	com/google/android/gms/internal/zzccw$zza:zzaoc	Ljava/util/List;
    //   1791: iload 4
    //   1793: invokeinterface 725 2 0
    //   1798: checkcast 1596	com/google/android/gms/internal/zzcgh
    //   1801: aload_1
    //   1802: putfield 1632	com/google/android/gms/internal/zzcgh:zziyx	[Lcom/google/android/gms/internal/zzcgi;
    //   1805: iload 9
    //   1807: ifne +140 -> 1947
    //   1810: aload_0
    //   1811: invokevirtual 144	com/google/android/gms/internal/zzccw:zzaul	()Lcom/google/android/gms/internal/zzcbw;
    //   1814: invokevirtual 363	com/google/android/gms/internal/zzcbw:zzayj	()Lcom/google/android/gms/internal/zzcby;
    //   1817: ldc_w 1652
    //   1820: aload_0
    //   1821: invokevirtual 1198	com/google/android/gms/internal/zzccw:zzaug	()Lcom/google/android/gms/internal/zzcbu;
    //   1824: aload 20
    //   1826: getfield 1614	com/google/android/gms/internal/zzccw$zza:zzaoc	Ljava/util/List;
    //   1829: iload 4
    //   1831: invokeinterface 725 2 0
    //   1836: checkcast 1596	com/google/android/gms/internal/zzcgh
    //   1839: getfield 1599	com/google/android/gms/internal/zzcgh:name	Ljava/lang/String;
    //   1842: invokevirtual 1201	com/google/android/gms/internal/zzcbu:zzjc	(Ljava/lang/String;)Ljava/lang/String;
    //   1845: invokevirtual 167	com/google/android/gms/internal/zzcby:zzj	(Ljava/lang/String;Ljava/lang/Object;)V
    //   1848: aload 20
    //   1850: getfield 1614	com/google/android/gms/internal/zzccw$zza:zzaoc	Ljava/util/List;
    //   1853: iload 4
    //   1855: invokeinterface 725 2 0
    //   1860: checkcast 1596	com/google/android/gms/internal/zzcgh
    //   1863: getfield 1632	com/google/android/gms/internal/zzcgh:zziyx	[Lcom/google/android/gms/internal/zzcgi;
    //   1866: aload 20
    //   1868: getfield 1614	com/google/android/gms/internal/zzccw$zza:zzaoc	Ljava/util/List;
    //   1871: iload 4
    //   1873: invokeinterface 725 2 0
    //   1878: checkcast 1596	com/google/android/gms/internal/zzcgh
    //   1881: getfield 1632	com/google/android/gms/internal/zzcgh:zziyx	[Lcom/google/android/gms/internal/zzcgi;
    //   1884: arraylength
    //   1885: iconst_1
    //   1886: iadd
    //   1887: invokestatic 1648	java/util/Arrays:copyOf	([Ljava/lang/Object;I)[Ljava/lang/Object;
    //   1890: checkcast 1649	[Lcom/google/android/gms/internal/zzcgi;
    //   1893: astore_1
    //   1894: new 1634	com/google/android/gms/internal/zzcgi
    //   1897: dup
    //   1898: invokespecial 1650	com/google/android/gms/internal/zzcgi:<init>	()V
    //   1901: astore 16
    //   1903: aload 16
    //   1905: ldc_w 765
    //   1908: putfield 1637	com/google/android/gms/internal/zzcgi:name	Ljava/lang/String;
    //   1911: aload 16
    //   1913: lconst_1
    //   1914: invokestatic 161	java/lang/Long:valueOf	(J)Ljava/lang/Long;
    //   1917: putfield 1640	com/google/android/gms/internal/zzcgi:zzizb	Ljava/lang/Long;
    //   1920: aload_1
    //   1921: aload_1
    //   1922: arraylength
    //   1923: iconst_1
    //   1924: isub
    //   1925: aload 16
    //   1927: aastore
    //   1928: aload 20
    //   1930: getfield 1614	com/google/android/gms/internal/zzccw$zza:zzaoc	Ljava/util/List;
    //   1933: iload 4
    //   1935: invokeinterface 725 2 0
    //   1940: checkcast 1596	com/google/android/gms/internal/zzcgh
    //   1943: aload_1
    //   1944: putfield 1632	com/google/android/gms/internal/zzcgh:zziyx	[Lcom/google/android/gms/internal/zzcgi;
    //   1947: aload_0
    //   1948: invokevirtual 628	com/google/android/gms/internal/zzccw:zzauf	()Lcom/google/android/gms/internal/zzcay;
    //   1951: aload_0
    //   1952: invokespecial 780	com/google/android/gms/internal/zzccw:zzazf	()J
    //   1955: aload 20
    //   1957: getfield 1619	com/google/android/gms/internal/zzccw$zza:zziue	Lcom/google/android/gms/internal/zzcgk;
    //   1960: getfield 463	com/google/android/gms/internal/zzcgk:zzci	Ljava/lang/String;
    //   1963: iconst_0
    //   1964: iconst_0
    //   1965: iconst_0
    //   1966: iconst_0
    //   1967: iconst_1
    //   1968: invokevirtual 783	com/google/android/gms/internal/zzcay:zza	(JLjava/lang/String;ZZZZZ)Lcom/google/android/gms/internal/zzcaz;
    //   1971: getfield 788	com/google/android/gms/internal/zzcaz:zzinc	J
    //   1974: aload_0
    //   1975: getfield 125	com/google/android/gms/internal/zzccw:zziss	Lcom/google/android/gms/internal/zzcax;
    //   1978: aload 20
    //   1980: getfield 1619	com/google/android/gms/internal/zzccw$zza:zziue	Lcom/google/android/gms/internal/zzcgk;
    //   1983: getfield 463	com/google/android/gms/internal/zzcgk:zzci	Ljava/lang/String;
    //   1986: invokevirtual 792	com/google/android/gms/internal/zzcax:zzis	(Ljava/lang/String;)I
    //   1989: i2l
    //   1990: lcmp
    //   1991: ifle +1150 -> 3141
    //   1994: aload 20
    //   1996: getfield 1614	com/google/android/gms/internal/zzccw$zza:zzaoc	Ljava/util/List;
    //   1999: iload 4
    //   2001: invokeinterface 725 2 0
    //   2006: checkcast 1596	com/google/android/gms/internal/zzcgh
    //   2009: astore_1
    //   2010: iconst_0
    //   2011: istore 6
    //   2013: iload 13
    //   2015: istore 14
    //   2017: iload 6
    //   2019: aload_1
    //   2020: getfield 1632	com/google/android/gms/internal/zzcgh:zziyx	[Lcom/google/android/gms/internal/zzcgi;
    //   2023: arraylength
    //   2024: if_icmpge +96 -> 2120
    //   2027: ldc_w 765
    //   2030: aload_1
    //   2031: getfield 1632	com/google/android/gms/internal/zzcgh:zziyx	[Lcom/google/android/gms/internal/zzcgi;
    //   2034: iload 6
    //   2036: aaload
    //   2037: getfield 1637	com/google/android/gms/internal/zzcgi:name	Ljava/lang/String;
    //   2040: invokevirtual 444	java/lang/String:equals	(Ljava/lang/Object;)Z
    //   2043: ifeq +1089 -> 3132
    //   2046: aload_1
    //   2047: getfield 1632	com/google/android/gms/internal/zzcgh:zziyx	[Lcom/google/android/gms/internal/zzcgi;
    //   2050: astore 16
    //   2052: aload 16
    //   2054: arraylength
    //   2055: iconst_1
    //   2056: isub
    //   2057: anewarray 1634	com/google/android/gms/internal/zzcgi
    //   2060: astore 17
    //   2062: iload 6
    //   2064: ifle +14 -> 2078
    //   2067: aload 16
    //   2069: iconst_0
    //   2070: aload 17
    //   2072: iconst_0
    //   2073: iload 6
    //   2075: invokestatic 1656	java/lang/System:arraycopy	(Ljava/lang/Object;ILjava/lang/Object;II)V
    //   2078: iload 6
    //   2080: aload 17
    //   2082: arraylength
    //   2083: if_icmpge +24 -> 2107
    //   2086: aload_1
    //   2087: getfield 1632	com/google/android/gms/internal/zzcgh:zziyx	[Lcom/google/android/gms/internal/zzcgi;
    //   2090: iload 6
    //   2092: iconst_1
    //   2093: iadd
    //   2094: aload 17
    //   2096: iload 6
    //   2098: aload 17
    //   2100: arraylength
    //   2101: iload 6
    //   2103: isub
    //   2104: invokestatic 1656	java/lang/System:arraycopy	(Ljava/lang/Object;ILjava/lang/Object;II)V
    //   2107: aload_1
    //   2108: aload 17
    //   2110: putfield 1632	com/google/android/gms/internal/zzcgh:zziyx	[Lcom/google/android/gms/internal/zzcgi;
    //   2113: iload 13
    //   2115: istore 14
    //   2117: goto +3 -> 2120
    //   2120: aload 20
    //   2122: getfield 1614	com/google/android/gms/internal/zzccw$zza:zzaoc	Ljava/util/List;
    //   2125: iload 4
    //   2127: invokeinterface 725 2 0
    //   2132: checkcast 1596	com/google/android/gms/internal/zzcgh
    //   2135: getfield 1599	com/google/android/gms/internal/zzcgh:name	Ljava/lang/String;
    //   2138: invokestatic 1358	com/google/android/gms/internal/zzcfw:zzju	(Ljava/lang/String;)Z
    //   2141: ifeq +1068 -> 3209
    //   2144: iload 15
    //   2146: ifeq +1063 -> 3209
    //   2149: aload_0
    //   2150: invokevirtual 628	com/google/android/gms/internal/zzccw:zzauf	()Lcom/google/android/gms/internal/zzcay;
    //   2153: aload_0
    //   2154: invokespecial 780	com/google/android/gms/internal/zzccw:zzazf	()J
    //   2157: aload 20
    //   2159: getfield 1619	com/google/android/gms/internal/zzccw$zza:zziue	Lcom/google/android/gms/internal/zzcgk;
    //   2162: getfield 463	com/google/android/gms/internal/zzcgk:zzci	Ljava/lang/String;
    //   2165: iconst_0
    //   2166: iconst_0
    //   2167: iconst_1
    //   2168: iconst_0
    //   2169: iconst_0
    //   2170: invokevirtual 783	com/google/android/gms/internal/zzcay:zza	(JLjava/lang/String;ZZZZZ)Lcom/google/android/gms/internal/zzcaz;
    //   2173: getfield 1659	com/google/android/gms/internal/zzcaz:zzina	J
    //   2176: aload_0
    //   2177: getfield 125	com/google/android/gms/internal/zzccw:zziss	Lcom/google/android/gms/internal/zzcax;
    //   2180: aload 20
    //   2182: getfield 1619	com/google/android/gms/internal/zzccw$zza:zziue	Lcom/google/android/gms/internal/zzcgk;
    //   2185: getfield 463	com/google/android/gms/internal/zzcgk:zzci	Ljava/lang/String;
    //   2188: getstatic 1662	com/google/android/gms/internal/zzcbm:zzioo	Lcom/google/android/gms/internal/zzcbn;
    //   2191: invokevirtual 1329	com/google/android/gms/internal/zzcax:zzb	(Ljava/lang/String;Lcom/google/android/gms/internal/zzcbn;)I
    //   2194: i2l
    //   2195: lcmp
    //   2196: ifle +1013 -> 3209
    //   2199: aload_0
    //   2200: invokevirtual 144	com/google/android/gms/internal/zzccw:zzaul	()Lcom/google/android/gms/internal/zzcbw;
    //   2203: invokevirtual 368	com/google/android/gms/internal/zzcbw:zzayf	()Lcom/google/android/gms/internal/zzcby;
    //   2206: ldc_w 1664
    //   2209: aload 20
    //   2211: getfield 1619	com/google/android/gms/internal/zzccw$zza:zziue	Lcom/google/android/gms/internal/zzcgk;
    //   2214: getfield 463	com/google/android/gms/internal/zzcgk:zzci	Ljava/lang/String;
    //   2217: invokestatic 555	com/google/android/gms/internal/zzcbw:zzjf	(Ljava/lang/String;)Ljava/lang/Object;
    //   2220: invokevirtual 167	com/google/android/gms/internal/zzcby:zzj	(Ljava/lang/String;Ljava/lang/Object;)V
    //   2223: aload 20
    //   2225: getfield 1614	com/google/android/gms/internal/zzccw$zza:zzaoc	Ljava/util/List;
    //   2228: iload 4
    //   2230: invokeinterface 725 2 0
    //   2235: checkcast 1596	com/google/android/gms/internal/zzcgh
    //   2238: astore 19
    //   2240: aload 19
    //   2242: getfield 1632	com/google/android/gms/internal/zzcgh:zziyx	[Lcom/google/android/gms/internal/zzcgi;
    //   2245: astore 21
    //   2247: aload 21
    //   2249: arraylength
    //   2250: istore 8
    //   2252: iconst_0
    //   2253: istore 6
    //   2255: iconst_0
    //   2256: istore 7
    //   2258: aconst_null
    //   2259: astore_1
    //   2260: iload 6
    //   2262: iload 8
    //   2264: if_icmpge +57 -> 2321
    //   2267: aload 21
    //   2269: iload 6
    //   2271: aaload
    //   2272: astore 17
    //   2274: ldc_w 1636
    //   2277: aload 17
    //   2279: getfield 1637	com/google/android/gms/internal/zzcgi:name	Ljava/lang/String;
    //   2282: invokevirtual 444	java/lang/String:equals	(Ljava/lang/Object;)Z
    //   2285: ifeq +10 -> 2295
    //   2288: aload 17
    //   2290: astore 16
    //   2292: goto +855 -> 3147
    //   2295: aload_1
    //   2296: astore 16
    //   2298: ldc_w 1209
    //   2301: aload 17
    //   2303: getfield 1637	com/google/android/gms/internal/zzcgi:name	Ljava/lang/String;
    //   2306: invokevirtual 444	java/lang/String:equals	(Ljava/lang/Object;)Z
    //   2309: ifeq +838 -> 3147
    //   2312: iconst_1
    //   2313: istore 7
    //   2315: aload_1
    //   2316: astore 16
    //   2318: goto +829 -> 3147
    //   2321: iload 14
    //   2323: istore 13
    //   2325: iload 7
    //   2327: ifeq +48 -> 2375
    //   2330: aload_1
    //   2331: ifnull +44 -> 2375
    //   2334: aload 19
    //   2336: getfield 1632	com/google/android/gms/internal/zzcgh:zziyx	[Lcom/google/android/gms/internal/zzcgi;
    //   2339: astore 16
    //   2341: aload 16
    //   2343: arraylength
    //   2344: iconst_1
    //   2345: isub
    //   2346: anewarray 1634	com/google/android/gms/internal/zzcgi
    //   2349: astore 17
    //   2351: aload 16
    //   2353: arraylength
    //   2354: istore 9
    //   2356: iconst_0
    //   2357: istore 6
    //   2359: iconst_0
    //   2360: istore 8
    //   2362: goto +797 -> 3159
    //   2365: aload 19
    //   2367: aload 17
    //   2369: putfield 1632	com/google/android/gms/internal/zzcgh:zziyx	[Lcom/google/android/gms/internal/zzcgi;
    //   2372: goto +841 -> 3213
    //   2375: aload_1
    //   2376: ifnull +23 -> 2399
    //   2379: aload_1
    //   2380: ldc_w 1209
    //   2383: putfield 1637	com/google/android/gms/internal/zzcgi:name	Ljava/lang/String;
    //   2386: aload_1
    //   2387: ldc2_w 1665
    //   2390: invokestatic 161	java/lang/Long:valueOf	(J)Ljava/lang/Long;
    //   2393: putfield 1640	com/google/android/gms/internal/zzcgi:zzizb	Ljava/lang/Long;
    //   2396: goto +817 -> 3213
    //   2399: aload_0
    //   2400: invokevirtual 144	com/google/android/gms/internal/zzccw:zzaul	()Lcom/google/android/gms/internal/zzcbw;
    //   2403: invokevirtual 315	com/google/android/gms/internal/zzcbw:zzayd	()Lcom/google/android/gms/internal/zzcby;
    //   2406: ldc_w 1668
    //   2409: aload 20
    //   2411: getfield 1619	com/google/android/gms/internal/zzccw$zza:zziue	Lcom/google/android/gms/internal/zzcgk;
    //   2414: getfield 463	com/google/android/gms/internal/zzcgk:zzci	Ljava/lang/String;
    //   2417: invokestatic 555	com/google/android/gms/internal/zzcbw:zzjf	(Ljava/lang/String;)Ljava/lang/Object;
    //   2420: invokevirtual 167	com/google/android/gms/internal/zzcby:zzj	(Ljava/lang/String;Ljava/lang/Object;)V
    //   2423: goto +790 -> 3213
    //   2426: aload 18
    //   2428: getfield 1623	com/google/android/gms/internal/zzcgk:zzizf	[Lcom/google/android/gms/internal/zzcgh;
    //   2431: iload 5
    //   2433: aload 20
    //   2435: getfield 1614	com/google/android/gms/internal/zzccw$zza:zzaoc	Ljava/util/List;
    //   2438: iload 4
    //   2440: invokeinterface 725 2 0
    //   2445: checkcast 1596	com/google/android/gms/internal/zzcgh
    //   2448: aastore
    //   2449: iload 5
    //   2451: iconst_1
    //   2452: iadd
    //   2453: istore 6
    //   2455: goto +765 -> 3220
    //   2458: iload 5
    //   2460: aload 20
    //   2462: getfield 1614	com/google/android/gms/internal/zzccw$zza:zzaoc	Ljava/util/List;
    //   2465: invokeinterface 714 1 0
    //   2470: if_icmpge +21 -> 2491
    //   2473: aload 18
    //   2475: aload 18
    //   2477: getfield 1623	com/google/android/gms/internal/zzcgk:zzizf	[Lcom/google/android/gms/internal/zzcgh;
    //   2480: iload 5
    //   2482: invokestatic 1648	java/util/Arrays:copyOf	([Ljava/lang/Object;I)[Ljava/lang/Object;
    //   2485: checkcast 1669	[Lcom/google/android/gms/internal/zzcgh;
    //   2488: putfield 1623	com/google/android/gms/internal/zzcgk:zzizf	[Lcom/google/android/gms/internal/zzcgh;
    //   2491: aload 18
    //   2493: aload_0
    //   2494: aload 20
    //   2496: getfield 1619	com/google/android/gms/internal/zzccw$zza:zziue	Lcom/google/android/gms/internal/zzcgk;
    //   2499: getfield 463	com/google/android/gms/internal/zzcgk:zzci	Ljava/lang/String;
    //   2502: aload 20
    //   2504: getfield 1619	com/google/android/gms/internal/zzccw$zza:zziue	Lcom/google/android/gms/internal/zzcgk;
    //   2507: getfield 720	com/google/android/gms/internal/zzcgk:zzizg	[Lcom/google/android/gms/internal/zzcgm;
    //   2510: aload 18
    //   2512: getfield 1623	com/google/android/gms/internal/zzcgk:zzizf	[Lcom/google/android/gms/internal/zzcgh;
    //   2515: invokespecial 1671	com/google/android/gms/internal/zzccw:zza	(Ljava/lang/String;[Lcom/google/android/gms/internal/zzcgm;[Lcom/google/android/gms/internal/zzcgh;)[Lcom/google/android/gms/internal/zzcgg;
    //   2518: putfield 1675	com/google/android/gms/internal/zzcgk:zzizy	[Lcom/google/android/gms/internal/zzcgg;
    //   2521: aload 18
    //   2523: ldc2_w 1676
    //   2526: invokestatic 161	java/lang/Long:valueOf	(J)Ljava/lang/Long;
    //   2529: putfield 602	com/google/android/gms/internal/zzcgk:zzizi	Ljava/lang/Long;
    //   2532: aload 18
    //   2534: ldc2_w 1678
    //   2537: invokestatic 161	java/lang/Long:valueOf	(J)Ljava/lang/Long;
    //   2540: putfield 605	com/google/android/gms/internal/zzcgk:zzizj	Ljava/lang/Long;
    //   2543: iconst_0
    //   2544: istore 4
    //   2546: aload 18
    //   2548: getfield 1623	com/google/android/gms/internal/zzcgk:zzizf	[Lcom/google/android/gms/internal/zzcgh;
    //   2551: astore_1
    //   2552: iload 4
    //   2554: aload_1
    //   2555: arraylength
    //   2556: if_icmpge +67 -> 2623
    //   2559: aload_1
    //   2560: iload 4
    //   2562: aaload
    //   2563: astore_1
    //   2564: aload_1
    //   2565: getfield 1602	com/google/android/gms/internal/zzcgh:zziyy	Ljava/lang/Long;
    //   2568: invokevirtual 1317	java/lang/Long:longValue	()J
    //   2571: aload 18
    //   2573: getfield 602	com/google/android/gms/internal/zzcgk:zzizi	Ljava/lang/Long;
    //   2576: invokevirtual 1317	java/lang/Long:longValue	()J
    //   2579: lcmp
    //   2580: ifge +12 -> 2592
    //   2583: aload 18
    //   2585: aload_1
    //   2586: getfield 1602	com/google/android/gms/internal/zzcgh:zziyy	Ljava/lang/Long;
    //   2589: putfield 602	com/google/android/gms/internal/zzcgk:zzizi	Ljava/lang/Long;
    //   2592: aload_1
    //   2593: getfield 1602	com/google/android/gms/internal/zzcgh:zziyy	Ljava/lang/Long;
    //   2596: invokevirtual 1317	java/lang/Long:longValue	()J
    //   2599: aload 18
    //   2601: getfield 605	com/google/android/gms/internal/zzcgk:zzizj	Ljava/lang/Long;
    //   2604: invokevirtual 1317	java/lang/Long:longValue	()J
    //   2607: lcmp
    //   2608: ifle +629 -> 3237
    //   2611: aload 18
    //   2613: aload_1
    //   2614: getfield 1602	com/google/android/gms/internal/zzcgh:zziyy	Ljava/lang/Long;
    //   2617: putfield 605	com/google/android/gms/internal/zzcgk:zzizj	Ljava/lang/Long;
    //   2620: goto +617 -> 3237
    //   2623: aload 20
    //   2625: getfield 1619	com/google/android/gms/internal/zzccw$zza:zziue	Lcom/google/android/gms/internal/zzcgk;
    //   2628: getfield 463	com/google/android/gms/internal/zzcgk:zzci	Ljava/lang/String;
    //   2631: astore 17
    //   2633: aload_0
    //   2634: invokevirtual 628	com/google/android/gms/internal/zzccw:zzauf	()Lcom/google/android/gms/internal/zzcay;
    //   2637: aload 17
    //   2639: invokevirtual 632	com/google/android/gms/internal/zzcay:zziw	(Ljava/lang/String;)Lcom/google/android/gms/internal/zzcar;
    //   2642: astore 16
    //   2644: aload 16
    //   2646: ifnonnull +30 -> 2676
    //   2649: aload_0
    //   2650: invokevirtual 144	com/google/android/gms/internal/zzccw:zzaul	()Lcom/google/android/gms/internal/zzcbw;
    //   2653: invokevirtual 315	com/google/android/gms/internal/zzcbw:zzayd	()Lcom/google/android/gms/internal/zzcby;
    //   2656: ldc_w 1681
    //   2659: aload 20
    //   2661: getfield 1619	com/google/android/gms/internal/zzccw$zza:zziue	Lcom/google/android/gms/internal/zzcgk;
    //   2664: getfield 463	com/google/android/gms/internal/zzcgk:zzci	Ljava/lang/String;
    //   2667: invokestatic 555	com/google/android/gms/internal/zzcbw:zzjf	(Ljava/lang/String;)Ljava/lang/Object;
    //   2670: invokevirtual 167	com/google/android/gms/internal/zzcby:zzj	(Ljava/lang/String;Ljava/lang/Object;)V
    //   2673: goto +139 -> 2812
    //   2676: aload 18
    //   2678: getfield 1623	com/google/android/gms/internal/zzcgk:zzizf	[Lcom/google/android/gms/internal/zzcgh;
    //   2681: arraylength
    //   2682: ifle +130 -> 2812
    //   2685: aload 16
    //   2687: invokevirtual 1684	com/google/android/gms/internal/zzcar:zzaus	()J
    //   2690: lstore_2
    //   2691: lload_2
    //   2692: lconst_0
    //   2693: lcmp
    //   2694: ifeq +552 -> 3246
    //   2697: lload_2
    //   2698: invokestatic 161	java/lang/Long:valueOf	(J)Ljava/lang/Long;
    //   2701: astore_1
    //   2702: goto +3 -> 2705
    //   2705: aload 18
    //   2707: aload_1
    //   2708: putfield 1687	com/google/android/gms/internal/zzcgk:zzizl	Ljava/lang/Long;
    //   2711: aload 16
    //   2713: invokevirtual 1690	com/google/android/gms/internal/zzcar:zzaur	()J
    //   2716: lstore 11
    //   2718: lload 11
    //   2720: lconst_0
    //   2721: lcmp
    //   2722: ifne +529 -> 3251
    //   2725: goto +3 -> 2728
    //   2728: lload_2
    //   2729: lconst_0
    //   2730: lcmp
    //   2731: ifeq +526 -> 3257
    //   2734: lload_2
    //   2735: invokestatic 161	java/lang/Long:valueOf	(J)Ljava/lang/Long;
    //   2738: astore_1
    //   2739: goto +3 -> 2742
    //   2742: aload 18
    //   2744: aload_1
    //   2745: putfield 1693	com/google/android/gms/internal/zzcgk:zzizk	Ljava/lang/Long;
    //   2748: aload 16
    //   2750: invokevirtual 1696	com/google/android/gms/internal/zzcar:zzavb	()V
    //   2753: aload 18
    //   2755: aload 16
    //   2757: invokevirtual 1699	com/google/android/gms/internal/zzcar:zzauy	()J
    //   2760: l2i
    //   2761: invokestatic 322	java/lang/Integer:valueOf	(I)Ljava/lang/Integer;
    //   2764: putfield 1702	com/google/android/gms/internal/zzcgk:zzizw	Ljava/lang/Integer;
    //   2767: aload 16
    //   2769: aload 18
    //   2771: getfield 602	com/google/android/gms/internal/zzcgk:zzizi	Ljava/lang/Long;
    //   2774: invokevirtual 1317	java/lang/Long:longValue	()J
    //   2777: invokevirtual 665	com/google/android/gms/internal/zzcar:zzal	(J)V
    //   2780: aload 16
    //   2782: aload 18
    //   2784: getfield 605	com/google/android/gms/internal/zzcgk:zzizj	Ljava/lang/Long;
    //   2787: invokevirtual 1317	java/lang/Long:longValue	()J
    //   2790: invokevirtual 668	com/google/android/gms/internal/zzcar:zzam	(J)V
    //   2793: aload 18
    //   2795: aload 16
    //   2797: invokevirtual 1705	com/google/android/gms/internal/zzcar:zzavj	()Ljava/lang/String;
    //   2800: putfield 1706	com/google/android/gms/internal/zzcgk:zzily	Ljava/lang/String;
    //   2803: aload_0
    //   2804: invokevirtual 628	com/google/android/gms/internal/zzccw:zzauf	()Lcom/google/android/gms/internal/zzcay;
    //   2807: aload 16
    //   2809: invokevirtual 695	com/google/android/gms/internal/zzcay:zza	(Lcom/google/android/gms/internal/zzcar;)V
    //   2812: aload 18
    //   2814: getfield 1623	com/google/android/gms/internal/zzcgk:zzizf	[Lcom/google/android/gms/internal/zzcgh;
    //   2817: arraylength
    //   2818: ifle +113 -> 2931
    //   2821: invokestatic 171	com/google/android/gms/internal/zzcax:zzawk	()Z
    //   2824: pop
    //   2825: aload_0
    //   2826: invokevirtual 773	com/google/android/gms/internal/zzccw:zzaui	()Lcom/google/android/gms/internal/zzccq;
    //   2829: aload 20
    //   2831: getfield 1619	com/google/android/gms/internal/zzccw$zza:zziue	Lcom/google/android/gms/internal/zzcgk;
    //   2834: getfield 463	com/google/android/gms/internal/zzcgk:zzci	Ljava/lang/String;
    //   2837: invokevirtual 1143	com/google/android/gms/internal/zzccq:zzjn	(Ljava/lang/String;)Lcom/google/android/gms/internal/zzcge;
    //   2840: astore_1
    //   2841: aload_1
    //   2842: ifnull +29 -> 2871
    //   2845: aload_1
    //   2846: getfield 1711	com/google/android/gms/internal/zzcge:zziym	Ljava/lang/Long;
    //   2849: astore 16
    //   2851: aload 16
    //   2853: astore_1
    //   2854: aload 16
    //   2856: ifnonnull +6 -> 2862
    //   2859: goto +12 -> 2871
    //   2862: aload 18
    //   2864: aload_1
    //   2865: putfield 1714	com/google/android/gms/internal/zzcgk:zzjad	Ljava/lang/Long;
    //   2868: goto +51 -> 2919
    //   2871: aload 20
    //   2873: getfield 1619	com/google/android/gms/internal/zzccw$zza:zziue	Lcom/google/android/gms/internal/zzcgk;
    //   2876: getfield 490	com/google/android/gms/internal/zzcgk:zzilu	Ljava/lang/String;
    //   2879: invokestatic 518	android/text/TextUtils:isEmpty	(Ljava/lang/CharSequence;)Z
    //   2882: ifeq +13 -> 2895
    //   2885: ldc2_w 99
    //   2888: invokestatic 161	java/lang/Long:valueOf	(J)Ljava/lang/Long;
    //   2891: astore_1
    //   2892: goto -30 -> 2862
    //   2895: aload_0
    //   2896: invokevirtual 144	com/google/android/gms/internal/zzccw:zzaul	()Lcom/google/android/gms/internal/zzcbw;
    //   2899: invokevirtual 368	com/google/android/gms/internal/zzcbw:zzayf	()Lcom/google/android/gms/internal/zzcby;
    //   2902: ldc_w 1716
    //   2905: aload 20
    //   2907: getfield 1619	com/google/android/gms/internal/zzccw$zza:zziue	Lcom/google/android/gms/internal/zzcgk;
    //   2910: getfield 463	com/google/android/gms/internal/zzcgk:zzci	Ljava/lang/String;
    //   2913: invokestatic 555	com/google/android/gms/internal/zzcbw:zzjf	(Ljava/lang/String;)Ljava/lang/Object;
    //   2916: invokevirtual 167	com/google/android/gms/internal/zzcby:zzj	(Ljava/lang/String;Ljava/lang/Object;)V
    //   2919: aload_0
    //   2920: invokevirtual 628	com/google/android/gms/internal/zzccw:zzauf	()Lcom/google/android/gms/internal/zzcay;
    //   2923: aload 18
    //   2925: iload 13
    //   2927: invokevirtual 1719	com/google/android/gms/internal/zzcay:zza	(Lcom/google/android/gms/internal/zzcgk;Z)Z
    //   2930: pop
    //   2931: aload_0
    //   2932: invokevirtual 628	com/google/android/gms/internal/zzccw:zzauf	()Lcom/google/android/gms/internal/zzcay;
    //   2935: aload 20
    //   2937: getfield 1722	com/google/android/gms/internal/zzccw$zza:zziuf	Ljava/util/List;
    //   2940: invokevirtual 1726	com/google/android/gms/internal/zzcay:zzae	(Ljava/util/List;)V
    //   2943: aload_0
    //   2944: invokevirtual 628	com/google/android/gms/internal/zzccw:zzauf	()Lcom/google/android/gms/internal/zzcay;
    //   2947: astore 16
    //   2949: aload 16
    //   2951: invokevirtual 1333	com/google/android/gms/internal/zzcay:getWritableDatabase	()Landroid/database/sqlite/SQLiteDatabase;
    //   2954: astore_1
    //   2955: aload_1
    //   2956: ldc_w 1728
    //   2959: iconst_2
    //   2960: anewarray 213	java/lang/String
    //   2963: dup
    //   2964: iconst_0
    //   2965: aload 17
    //   2967: aastore
    //   2968: dup
    //   2969: iconst_1
    //   2970: aload 17
    //   2972: aastore
    //   2973: invokevirtual 1344	android/database/sqlite/SQLiteDatabase:execSQL	(Ljava/lang/String;[Ljava/lang/Object;)V
    //   2976: goto +29 -> 3005
    //   2979: astore_1
    //   2980: goto +5 -> 2985
    //   2983: astore 19
    //   2985: aload 16
    //   2987: invokevirtual 1345	com/google/android/gms/internal/zzcdt:zzaul	()Lcom/google/android/gms/internal/zzcbw;
    //   2990: invokevirtual 315	com/google/android/gms/internal/zzcbw:zzayd	()Lcom/google/android/gms/internal/zzcby;
    //   2993: ldc_w 1730
    //   2996: aload 17
    //   2998: invokestatic 555	com/google/android/gms/internal/zzcbw:zzjf	(Ljava/lang/String;)Ljava/lang/Object;
    //   3001: aload_1
    //   3002: invokevirtual 326	com/google/android/gms/internal/zzcby:zze	(Ljava/lang/String;Ljava/lang/Object;Ljava/lang/Object;)V
    //   3005: iconst_1
    //   3006: istore 13
    //   3008: aload_0
    //   3009: invokevirtual 628	com/google/android/gms/internal/zzccw:zzauf	()Lcom/google/android/gms/internal/zzcay;
    //   3012: invokevirtual 1290	com/google/android/gms/internal/zzcay:setTransactionSuccessful	()V
    //   3015: aload 18
    //   3017: getfield 1623	com/google/android/gms/internal/zzcgk:zzizf	[Lcom/google/android/gms/internal/zzcgh;
    //   3020: arraylength
    //   3021: istore 4
    //   3023: iload 4
    //   3025: ifle +6 -> 3031
    //   3028: goto +6 -> 3034
    //   3031: iconst_0
    //   3032: istore 13
    //   3034: aload_0
    //   3035: invokevirtual 628	com/google/android/gms/internal/zzccw:zzauf	()Lcom/google/android/gms/internal/zzcay;
    //   3038: invokevirtual 1293	com/google/android/gms/internal/zzcay:endTransaction	()V
    //   3041: iload 13
    //   3043: ireturn
    //   3044: aload_0
    //   3045: invokevirtual 628	com/google/android/gms/internal/zzccw:zzauf	()Lcom/google/android/gms/internal/zzcay;
    //   3048: invokevirtual 1290	com/google/android/gms/internal/zzcay:setTransactionSuccessful	()V
    //   3051: aload_0
    //   3052: invokevirtual 628	com/google/android/gms/internal/zzccw:zzauf	()Lcom/google/android/gms/internal/zzcay;
    //   3055: invokevirtual 1293	com/google/android/gms/internal/zzcay:endTransaction	()V
    //   3058: iconst_0
    //   3059: ireturn
    //   3060: astore_1
    //   3061: aload 17
    //   3063: astore 16
    //   3065: aload 16
    //   3067: ifnull +10 -> 3077
    //   3070: aload 16
    //   3072: invokeinterface 1533 1 0
    //   3077: aload_1
    //   3078: athrow
    //   3079: astore_1
    //   3080: aload_0
    //   3081: invokevirtual 628	com/google/android/gms/internal/zzccw:zzauf	()Lcom/google/android/gms/internal/zzcay;
    //   3084: invokevirtual 1293	com/google/android/gms/internal/zzcay:endTransaction	()V
    //   3087: goto +5 -> 3092
    //   3090: aload_1
    //   3091: athrow
    //   3092: goto -2 -> 3090
    //   3095: iconst_0
    //   3096: istore 4
    //   3098: goto -1947 -> 1151
    //   3101: iconst_1
    //   3102: istore 4
    //   3104: goto -1953 -> 1151
    //   3107: iconst_0
    //   3108: istore 7
    //   3110: goto -1777 -> 1333
    //   3113: iconst_1
    //   3114: istore 7
    //   3116: goto -1783 -> 1333
    //   3119: iload 7
    //   3121: iconst_1
    //   3122: iadd
    //   3123: istore 7
    //   3125: iload 10
    //   3127: istore 8
    //   3129: goto -1550 -> 1579
    //   3132: iload 6
    //   3134: iconst_1
    //   3135: iadd
    //   3136: istore 6
    //   3138: goto -1125 -> 2013
    //   3141: iconst_1
    //   3142: istore 14
    //   3144: goto -1024 -> 2120
    //   3147: iload 6
    //   3149: iconst_1
    //   3150: iadd
    //   3151: istore 6
    //   3153: aload 16
    //   3155: astore_1
    //   3156: goto -896 -> 2260
    //   3159: iload 6
    //   3161: iload 9
    //   3163: if_icmpge -798 -> 2365
    //   3166: aload 16
    //   3168: iload 6
    //   3170: aaload
    //   3171: astore 21
    //   3173: iload 8
    //   3175: istore 7
    //   3177: aload 21
    //   3179: aload_1
    //   3180: if_acmpeq +16 -> 3196
    //   3183: aload 17
    //   3185: iload 8
    //   3187: aload 21
    //   3189: aastore
    //   3190: iload 8
    //   3192: iconst_1
    //   3193: iadd
    //   3194: istore 7
    //   3196: iload 6
    //   3198: iconst_1
    //   3199: iadd
    //   3200: istore 6
    //   3202: iload 7
    //   3204: istore 8
    //   3206: goto -47 -> 3159
    //   3209: iload 14
    //   3211: istore 13
    //   3213: iload 13
    //   3215: istore 14
    //   3217: goto -791 -> 2426
    //   3220: iload 4
    //   3222: iconst_1
    //   3223: iadd
    //   3224: istore 4
    //   3226: iload 6
    //   3228: istore 5
    //   3230: iload 14
    //   3232: istore 13
    //   3234: goto -2044 -> 1190
    //   3237: iload 4
    //   3239: iconst_1
    //   3240: iadd
    //   3241: istore 4
    //   3243: goto -697 -> 2546
    //   3246: aconst_null
    //   3247: astore_1
    //   3248: goto -543 -> 2705
    //   3251: lload 11
    //   3253: lstore_2
    //   3254: goto -526 -> 2728
    //   3257: aconst_null
    //   3258: astore_1
    //   3259: goto -517 -> 2742
    // Exception table:
    //   from	to	target	type
    //   84	90	122	finally
    //   94	103	122	finally
    //   107	115	122	finally
    //   229	237	122	finally
    //   257	266	122	finally
    //   269	278	122	finally
    //   281	287	122	finally
    //   428	437	122	finally
    //   446	455	122	finally
    //   461	467	122	finally
    //   84	90	126	android/database/sqlite/SQLiteException
    //   94	103	126	android/database/sqlite/SQLiteException
    //   107	115	126	android/database/sqlite/SQLiteException
    //   269	278	300	android/database/sqlite/SQLiteException
    //   281	287	300	android/database/sqlite/SQLiteException
    //   534	552	562	finally
    //   629	647	562	finally
    //   534	552	566	android/database/sqlite/SQLiteException
    //   629	647	566	android/database/sqlite/SQLiteException
    //   860	868	913	java/io/IOException
    //   783	811	952	finally
    //   821	860	952	finally
    //   860	868	952	finally
    //   868	910	952	finally
    //   915	935	952	finally
    //   935	944	952	finally
    //   783	811	960	android/database/sqlite/SQLiteException
    //   821	860	960	android/database/sqlite/SQLiteException
    //   860	868	960	android/database/sqlite/SQLiteException
    //   868	910	960	android/database/sqlite/SQLiteException
    //   915	935	960	android/database/sqlite/SQLiteException
    //   935	944	960	android/database/sqlite/SQLiteException
    //   607	615	975	java/io/IOException
    //   735	783	1019	android/database/sqlite/SQLiteException
    //   985	1005	1019	android/database/sqlite/SQLiteException
    //   520	529	1024	finally
    //   577	607	1024	finally
    //   607	615	1024	finally
    //   615	624	1024	finally
    //   647	663	1024	finally
    //   712	727	1024	finally
    //   520	529	1028	android/database/sqlite/SQLiteException
    //   577	607	1028	android/database/sqlite/SQLiteException
    //   607	615	1028	android/database/sqlite/SQLiteException
    //   615	624	1028	android/database/sqlite/SQLiteException
    //   647	663	1028	android/database/sqlite/SQLiteException
    //   712	727	1028	android/database/sqlite/SQLiteException
    //   476	520	1043	finally
    //   476	520	1051	android/database/sqlite/SQLiteException
    //   229	237	1070	android/database/sqlite/SQLiteException
    //   257	266	1070	android/database/sqlite/SQLiteException
    //   428	437	1070	android/database/sqlite/SQLiteException
    //   446	455	1070	android/database/sqlite/SQLiteException
    //   461	467	1070	android/database/sqlite/SQLiteException
    //   49	62	1081	finally
    //   141	155	1081	finally
    //   168	223	1081	finally
    //   324	342	1081	finally
    //   345	355	1081	finally
    //   368	422	1081	finally
    //   49	62	1088	android/database/sqlite/SQLiteException
    //   141	155	1088	android/database/sqlite/SQLiteException
    //   168	223	1088	android/database/sqlite/SQLiteException
    //   324	342	1088	android/database/sqlite/SQLiteException
    //   345	355	1088	android/database/sqlite/SQLiteException
    //   368	422	1088	android/database/sqlite/SQLiteException
    //   2955	2976	2979	android/database/sqlite/SQLiteException
    //   735	783	3060	finally
    //   985	1005	3060	finally
    //   1099	1119	3060	finally
    //   10	49	3079	finally
    //   242	248	3079	finally
    //   552	559	3079	finally
    //   811	818	3079	finally
    //   1009	1016	3079	finally
    //   1127	1148	3079	finally
    //   1156	1181	3079	finally
    //   1190	1240	3079	finally
    //   1245	1330	3079	finally
    //   1354	1420	3079	finally
    //   1431	1466	3079	finally
    //   1471	1476	3079	finally
    //   1480	1504	3079	finally
    //   1504	1547	3079	finally
    //   1547	1570	3079	finally
    //   1592	1615	3079	finally
    //   1625	1648	3079	finally
    //   1668	1805	3079	finally
    //   1810	1947	3079	finally
    //   1947	2010	3079	finally
    //   2017	2062	3079	finally
    //   2067	2078	3079	finally
    //   2078	2107	3079	finally
    //   2107	2113	3079	finally
    //   2120	2144	3079	finally
    //   2149	2252	3079	finally
    //   2274	2288	3079	finally
    //   2298	2312	3079	finally
    //   2334	2356	3079	finally
    //   2365	2372	3079	finally
    //   2379	2396	3079	finally
    //   2399	2423	3079	finally
    //   2426	2449	3079	finally
    //   2458	2491	3079	finally
    //   2491	2543	3079	finally
    //   2546	2559	3079	finally
    //   2564	2592	3079	finally
    //   2592	2620	3079	finally
    //   2623	2644	3079	finally
    //   2649	2673	3079	finally
    //   2676	2691	3079	finally
    //   2697	2702	3079	finally
    //   2705	2718	3079	finally
    //   2734	2739	3079	finally
    //   2742	2812	3079	finally
    //   2812	2841	3079	finally
    //   2845	2851	3079	finally
    //   2862	2868	3079	finally
    //   2871	2892	3079	finally
    //   2895	2919	3079	finally
    //   2919	2931	3079	finally
    //   2931	2955	3079	finally
    //   2955	2976	3079	finally
    //   2985	3005	3079	finally
    //   3008	3023	3079	finally
    //   3044	3051	3079	finally
    //   3070	3077	3079	finally
    //   3077	3079	3079	finally
  }
  
  @X
  private final zzcas zzjr(String paramString)
  {
    zzcar localZzcar = zzauf().zziw(paramString);
    if ((localZzcar != null) && (!TextUtils.isEmpty(localZzcar.zzuo()))) {}
    try
    {
      String str = zzcrmContext).getPackageInfo(paramString, 0).versionName;
      if ((localZzcar.zzuo() != null) && (!localZzcar.zzuo().equals(str)))
      {
        zzaul().zzayf().zzj("App version does not match; dropping. appId", zzcbw.zzjf(paramString));
        return null;
      }
    }
    catch (PackageManager.NameNotFoundException localNameNotFoundException)
    {
      for (;;) {}
    }
    return new zzcas(paramString, localZzcar.getGmpAppId(), localZzcar.zzuo(), localZzcar.zzaut(), localZzcar.zzauu(), localZzcar.zzauv(), localZzcar.zzauw(), null, localZzcar.zzaux(), false, localZzcar.zzauq(), localZzcar.zzavk(), 0L, 0);
    zzaul().zzayi().zzj("No app data available; dropping", paramString);
    return null;
  }
  
  public final Context getContext()
  {
    return mContext;
  }
  
  @X
  public final boolean isEnabled()
  {
    zzauk().zzuj();
    zzwk();
    boolean bool2 = zziss.zzawl();
    boolean bool1 = false;
    if (bool2) {
      return false;
    }
    Boolean localBoolean = zziss.zzit("firebase_analytics_collection_enabled");
    if (localBoolean != null) {
      bool1 = localBoolean.booleanValue();
    } else if (!zzcax.zzaif()) {
      bool1 = true;
    }
    return zzaum().zzbn(bool1);
  }
  
  @X
  public final void start()
  {
    zzauk().zzuj();
    zzauf().zzaxk();
    if (zzaumzziqp.get() == 0L) {
      zzaumzziqp.set(zzasc.currentTimeMillis());
    }
    if (Long.valueOf(zzaumzziqu.get()).longValue() == 0L)
    {
      zzaul().zzayj().zzj("Persisting first open", Long.valueOf(zziuc));
      zzaumzziqu.set(zziuc);
    }
    if (!zzayv())
    {
      if (isEnabled())
      {
        if (!zzauh().zzdt("android.permission.INTERNET")) {
          zzaul().zzayd().log("App is missing INTERNET permission");
        }
        if (!zzauh().zzdt("android.permission.ACCESS_NETWORK_STATE")) {
          zzaul().zzayd().log("App is missing ACCESS_NETWORK_STATE permission");
        }
        zzcax.zzawk();
        if (!zzbed.zzcr(mContext).zzalq())
        {
          if (!zzccn.zzj(mContext, false)) {
            zzaul().zzayd().log("AppMeasurementReceiver not registered/enabled");
          }
          if (!zzcfh.zzk(mContext, false)) {
            zzaul().zzayd().log("AppMeasurementService not registered/enabled");
          }
        }
        zzaul().zzayd().log("Uploading is not possible. App measurement disabled");
      }
    }
    else
    {
      zzcax.zzawk();
      Object localObject;
      if (!TextUtils.isEmpty(zzaua().getGmpAppId()))
      {
        localObject = zzaum().zzaym();
        if (localObject == null)
        {
          zzaum().zzjj(zzaua().getGmpAppId());
        }
        else if (!((String)localObject).equals(zzaua().getGmpAppId()))
        {
          zzaul().zzayh().log("Rechecking which service to use due to a GMP App Id change");
          zzaum().zzayp();
          zzitg.disconnect();
          zzitg.zzxh();
          zzaum().zzjj(zzaua().getGmpAppId());
          zzaumzziqu.set(zziuc);
          zzaumzziqv.zzjl(null);
        }
      }
      zzatz().zzjk(zzaumzziqv.zzayr());
      zzcax.zzawk();
      if (!TextUtils.isEmpty(zzaua().getGmpAppId()))
      {
        localObject = zzatz();
        ((zzcdw)localObject).zzuj();
        ((zzcdw)localObject).zzatv();
        ((zzcdu)localObject).zzwk();
        if (zziki.zzayv())
        {
          ((zzcdw)localObject).zzauc().zzazq();
          String str = ((zzcdw)localObject).zzaum().zzayq();
          if (!TextUtils.isEmpty(str))
          {
            ((zzcdw)localObject).zzaub().zzwk();
            if (!str.equals(Build.VERSION.RELEASE))
            {
              Bundle localBundle = new Bundle();
              localBundle.putString("_po", str);
              ((zzcdw)localObject).zzc("auto", "_ou", localBundle);
            }
          }
        }
        zzauc().zza(new AtomicReference());
      }
    }
    zzazi();
  }
  
  @X
  public final void zza(int paramInt, Throwable paramThrowable, byte[] paramArrayOfByte)
  {
    zzauk().zzuj();
    zzwk();
    Object localObject = paramArrayOfByte;
    if (paramArrayOfByte == null) {}
    try
    {
      localObject = new byte[0];
      paramArrayOfByte = zzitt;
      zzitt = null;
      int j = 1;
      if (((paramInt == 200) || (paramInt == 204)) && (paramThrowable == null)) {
        try
        {
          zzaumzziqp.set(zzasc.currentTimeMillis());
          zzaumzziqq.set(0L);
          zzazi();
          zzaul().zzayj().zze("Successful upload. Got network response. code, size", Integer.valueOf(paramInt), Integer.valueOf(localObject.length));
          zzauf().beginTransaction();
          try
          {
            paramArrayOfByte = paramArrayOfByte.iterator();
            while (paramArrayOfByte.hasNext())
            {
              localObject = (Long)paramArrayOfByte.next();
              paramThrowable = zzauf();
              long l = ((Long)localObject).longValue();
              paramThrowable.zzuj();
              paramThrowable.zzwk();
              localObject = paramThrowable.getWritableDatabase();
              try
              {
                if (((SQLiteDatabase)localObject).delete("queue", "rowid=?", new String[] { String.valueOf(l) }) != 1) {
                  throw new SQLiteException("Deleted fewer rows from queue than expected");
                }
              }
              catch (SQLiteException paramArrayOfByte)
              {
                paramThrowable.zzaul().zzayd().zzj("Failed to delete a bundle in a queue table", paramArrayOfByte);
                throw paramArrayOfByte;
              }
            }
            zzauf().setTransactionSuccessful();
            zzauf().endTransaction();
            if ((zzaza().zzyx()) && (zzazh()))
            {
              zzazg();
            }
            else
            {
              zzitx = -1L;
              zzazi();
            }
            zzity = 0L;
          }
          finally
          {
            zzauf().endTransaction();
          }
          zzaul().zzayj().zze("Network upload failed. Will retry later. code, error", Integer.valueOf(paramInt), paramThrowable);
        }
        catch (SQLiteException paramThrowable)
        {
          zzaul().zzayd().zzj("Database error while trying to delete uploaded bundles", paramThrowable);
          zzity = zzasc.elapsedRealtime();
          zzaul().zzayj().zzj("Disable upload, time", Long.valueOf(zzity));
        }
      }
      zzaumzziqq.set(zzasc.currentTimeMillis());
      i = j;
      if (paramInt != 503)
      {
        if (paramInt != 429) {
          break label465;
        }
        i = j;
      }
    }
    finally
    {
      for (;;)
      {
        zziua = false;
        zzazm();
        for (;;)
        {
          throw paramThrowable;
        }
        int i = 0;
      }
    }
    if (i != 0) {
      zzaumzziqr.set(zzasc.currentTimeMillis());
    }
    zzazi();
    zziua = false;
    zzazm();
  }
  
  @X
  public final byte[] zza(@F zzcbk paramZzcbk, @O(min=1L) String paramString)
  {
    zzwk();
    zzauk().zzuj();
    zzatu();
    throw null;
  }
  
  public final zzcan zzatx()
  {
    zza(zzitn);
    return zzitn;
  }
  
  public final zzcau zzaty()
  {
    zza(zzitm);
    return zzitm;
  }
  
  public final zzcdw zzatz()
  {
    zza(zziti);
    return zziti;
  }
  
  public final zzcbr zzaua()
  {
    zza(zzitj);
    return zzitj;
  }
  
  public final zzcbe zzaub()
  {
    zza(zzith);
    return zzith;
  }
  
  public final zzceo zzauc()
  {
    zza(zzitg);
    return zzitg;
  }
  
  public final zzcek zzaud()
  {
    zza(zzitf);
    return zzitf;
  }
  
  public final zzcbs zzaue()
  {
    zza(zzitd);
    return zzitd;
  }
  
  public final zzcay zzauf()
  {
    zza(zzitc);
    return zzitc;
  }
  
  public final zzcbu zzaug()
  {
    zza(zzitb);
    return zzitb;
  }
  
  public final zzcfw zzauh()
  {
    zza(zzita);
    return zzita;
  }
  
  public final zzccq zzaui()
  {
    zza(zzisx);
    return zzisx;
  }
  
  public final zzcfl zzauj()
  {
    zza(zzisw);
    return zzisw;
  }
  
  public final zzccr zzauk()
  {
    zza(zzisv);
    return zzisv;
  }
  
  public final zzcbw zzaul()
  {
    zza(zzisu);
    return zzisu;
  }
  
  public final zzcch zzaum()
  {
    zza(zzist);
    return zzist;
  }
  
  public final zzcax zzaun()
  {
    return zziss;
  }
  
  @X
  public final boolean zzayv()
  {
    zzwk();
    zzauk().zzuj();
    Boolean localBoolean = zzitp;
    if ((localBoolean == null) || (zzitq == 0L) || ((localBoolean != null) && (!localBoolean.booleanValue()) && (Math.abs(zzasc.elapsedRealtime() - zzitq) > 1000L)))
    {
      zzitq = zzasc.elapsedRealtime();
      zzcax.zzawk();
      boolean bool3 = zzauh().zzdt("android.permission.INTERNET");
      boolean bool2 = false;
      boolean bool1 = bool2;
      if (bool3)
      {
        bool1 = bool2;
        if (zzauh().zzdt("android.permission.ACCESS_NETWORK_STATE")) {
          if (!zzbed.zzcr(mContext).zzalq())
          {
            bool1 = bool2;
            if (zzccn.zzj(mContext, false))
            {
              bool1 = bool2;
              if (!zzcfh.zzk(mContext, false)) {}
            }
          }
          else
          {
            bool1 = true;
          }
        }
      }
      zzitp = Boolean.valueOf(bool1);
      if (zzitp.booleanValue()) {
        zzitp = Boolean.valueOf(zzauh().zzkb(zzaua().getGmpAppId()));
      }
    }
    return zzitp.booleanValue();
  }
  
  public final zzcbw zzayw()
  {
    zzcbw localZzcbw = zzisu;
    if ((localZzcbw != null) && (localZzcbw.isInitialized())) {
      return zzisu;
    }
    return null;
  }
  
  public final zzccr zzayx()
  {
    return zzisv;
  }
  
  public final AppMeasurement zzayy()
  {
    return zzisy;
  }
  
  public final FirebaseAnalytics zzayz()
  {
    return zzisz;
  }
  
  public final zzcca zzaza()
  {
    zza(zzite);
    return zzite;
  }
  
  public final long zzaze()
  {
    Long localLong = Long.valueOf(zzaumzziqu.get());
    if (localLong.longValue() == 0L) {
      return zziuc;
    }
    return Math.min(zziuc, localLong.longValue());
  }
  
  @X
  public final void zzazg()
  {
    zzauk().zzuj();
    zzwk();
    zziub = true;
    for (;;)
    {
      try
      {
        zzcax.zzawk();
        localObject1 = zzaum().zzayo();
        if (localObject1 == null)
        {
          localObject1 = zzaul().zzayf();
          localObject4 = "Upload data called on the client side before use of service was decided";
          ((zzcby)localObject1).log((String)localObject4);
          zziub = false;
          zzazm();
          return;
        }
        if (((Boolean)localObject1).booleanValue())
        {
          localObject1 = zzaul().zzayd();
          localObject4 = "Upload called in the client side when service should be used";
          continue;
        }
        if (zzity > 0L)
        {
          zzazi();
          continue;
        }
        zzauk().zzuj();
        if (zzitt == null) {
          continue;
        }
        i = 1;
      }
      finally
      {
        Object localObject1;
        long l1;
        long l2;
        String str1;
        String str2;
        Object localObject5;
        Object localObject6;
        zziub = false;
        zzazm();
        continue;
        throw localObject2;
        continue;
        int i = 0;
        continue;
        Object localObject4 = null;
        Object localObject3 = localObject5;
        if (localObject4 == null) {
          continue;
        }
        i = 0;
        continue;
        i += 1;
        continue;
        i = 0;
        int j = 0;
        continue;
        j += 1;
        continue;
        boolean bool = false;
        continue;
      }
      if (i != 0)
      {
        localObject1 = zzaul().zzayj();
        localObject4 = "Uploading requested multiple times";
      }
      else if (!zzaza().zzyx())
      {
        zzaul().zzayj().log("Network not connected, ignoring upload request");
      }
      else
      {
        l1 = zzasc.currentTimeMillis();
        l2 = zzcax.zzawv();
        str1 = null;
        zzg(null, l1 - l2);
        l2 = zzaumzziqp.get();
        if (l2 != 0L) {
          zzaul().zzayi().zzj("Uploading events. Elapsed time since last upload attempt (ms)", Long.valueOf(Math.abs(l1 - l2)));
        }
        str2 = zzauf().zzaxi();
        if (!TextUtils.isEmpty(str2))
        {
          if (zzitx == -1L) {
            zzitx = zzauf().zzaxp();
          }
          i = zziss.zzb(str2, zzcbm.zzioh);
          j = Math.max(0, zziss.zzb(str2, zzcbm.zzioi));
          localObject5 = zzauf().zzl(str2, i, j);
          if (((List)localObject5).isEmpty()) {
            continue;
          }
          localObject1 = ((List)localObject5).iterator();
          if (!((Iterator)localObject1).hasNext()) {
            continue;
          }
          localObject4 = (zzcgk)nextfirst;
          if (TextUtils.isEmpty(zzizs)) {
            continue;
          }
          localObject4 = zzizs;
          continue;
          localObject1 = localObject5;
          if (i < ((List)localObject5).size())
          {
            localObject1 = (zzcgk)getfirst;
            if ((TextUtils.isEmpty(zzizs)) || (zzizs.equals(localObject4))) {
              continue;
            }
            localObject1 = ((List)localObject5).subList(0, i);
          }
          localObject5 = new zzcgj();
          zzizc = new zzcgk[((List)localObject1).size()];
          localObject4 = new ArrayList(((List)localObject1).size());
          if ((!zzcax.zzaxh()) || (!zziss.zziu(str2))) {
            continue;
          }
          i = 1;
          continue;
          if (j < zzizc.length)
          {
            zzizc[j] = ((zzcgk)getfirst);
            ((List)localObject4).add((Long)getsecond);
            localObject6 = zzizc[j];
            zzcax.zzauv();
            zzizr = Long.valueOf(11400L);
            zzizc[j].zzizh = Long.valueOf(l1);
            localObject6 = zzizc[j];
            zzcax.zzawk();
            zzizx = Boolean.valueOf(false);
            if (i != 0) {
              continue;
            }
            zzizc[j].zzjaf = null;
            continue;
          }
          localObject1 = str1;
          if (zzaul().zzad(2)) {
            localObject1 = zzaug().zza((zzcgj)localObject5);
          }
          localObject6 = zzauh().zzb((zzcgj)localObject5);
          str1 = zzcax.zzawu();
        }
      }
      try
      {
        URL localURL = new URL(str1);
        if (((List)localObject4).isEmpty()) {
          continue;
        }
        bool = true;
        zzbp.zzbh(bool);
        if (zzitt != null) {
          zzaul().zzayd().log("Set uploading progress before finishing the previous upload");
        } else {
          zzitt = new ArrayList((Collection)localObject4);
        }
        zzaumzziqq.set(l1);
        localObject4 = "?";
        if (zzizc.length > 0) {
          localObject4 = zzizc[0].zzci;
        }
        zzaul().zzayj().zzd("Uploading data. app, uncompressed size, data", localObject4, Integer.valueOf(localObject6.length), localObject1);
        zziua = true;
        localObject1 = zzaza();
        localObject4 = new zzccz(this);
        ((zzcca)localObject1).zzuj();
        ((zzcdu)localObject1).zzwk();
        zzbp.zzu(localURL);
        zzbp.zzu(localObject6);
        zzbp.zzu(localObject4);
        ((zzcca)localObject1).zzauk().zzh(new zzcce((zzcca)localObject1, str2, localURL, (byte[])localObject6, null, (zzccc)localObject4));
      }
      catch (MalformedURLException localMalformedURLException)
      {
        continue;
      }
      zzaul().zzayd().zze("Failed to parse upload URL. Not uploading. appId", zzcbw.zzjf(str2), str1);
      continue;
      zzitx = -1L;
      localObject1 = zzauf().zzba(l1 - zzcax.zzawv());
      if (!TextUtils.isEmpty((CharSequence)localObject1))
      {
        localObject1 = zzauf().zziw((String)localObject1);
        if (localObject1 != null) {
          zzb((zzcar)localObject1);
        }
      }
    }
  }
  
  public final void zzazj()
  {
    zzitw += 1;
  }
  
  @X
  public final void zzazk()
  {
    zzauk().zzuj();
    zzwk();
    if (!zzito)
    {
      zzaul().zzayh().log("This instance being marked as an uploader");
      zzauk().zzuj();
      zzwk();
      if ((zzazl()) && (zzazd()))
      {
        int i = zza(zzits);
        int j = zzaua().zzayb();
        zzauk().zzuj();
        zzcby localZzcby;
        Integer localInteger1;
        Integer localInteger2;
        String str;
        if (i > j)
        {
          localZzcby = zzaul().zzayd();
          localInteger1 = Integer.valueOf(i);
          localInteger2 = Integer.valueOf(j);
          str = "Panic: can't downgrade version. Previous, current version";
        }
        for (;;)
        {
          localZzcby.zze(str, localInteger1, localInteger2);
          break;
          if (i >= j) {
            break;
          }
          if (zza(j, zzits))
          {
            localZzcby = zzaul().zzayj();
            localInteger1 = Integer.valueOf(i);
            localInteger2 = Integer.valueOf(j);
            str = "Storage version upgraded. Previous, current version";
          }
          else
          {
            localZzcby = zzaul().zzayd();
            localInteger1 = Integer.valueOf(i);
            localInteger2 = Integer.valueOf(j);
            str = "Storage version upgrade failed. Previous, current version";
          }
        }
      }
      zzito = true;
      zzazi();
    }
  }
  
  @X
  public final void zzb(zzcav paramZzcav, zzcas paramZzcas)
  {
    zzbp.zzu(paramZzcav);
    zzbp.zzgg(packageName);
    zzbp.zzu(zzimg);
    zzbp.zzu(zzimh);
    zzbp.zzgg(zzimh.name);
    zzauk().zzuj();
    zzwk();
    if (TextUtils.isEmpty(zzilu)) {
      return;
    }
    if (!zzilz)
    {
      zzf(paramZzcas);
      return;
    }
    zzcav localZzcav = new zzcav(paramZzcav);
    int i = 0;
    zzimj = false;
    zzauf().beginTransaction();
    try
    {
      paramZzcav = zzauf().zzai(packageName, zzimh.name);
      if ((paramZzcav != null) && (!zzimg.equals(zzimg))) {
        zzaul().zzayf().zzd("Updating a conditional user property with different origin. name, origin, origin (from DB)", zzaug().zzje(zzimh.name), zzimg, zzimg);
      }
      if (paramZzcav != null)
      {
        boolean bool = zzimj;
        if (bool)
        {
          zzimg = zzimg;
          zzimi = zzimi;
          zzimm = zzimm;
          zzimk = zzimk;
          zzimn = zzimn;
          zzimj = bool;
          zzimh = new zzcft(zzimh.name, zzimh.zziwz, zzimh.getValue(), zzimh.zzimg);
          break label349;
        }
      }
      if (TextUtils.isEmpty(zzimk))
      {
        zzimh = new zzcft(zzimh.name, zzimi, zzimh.getValue(), zzimh.zzimg);
        zzimj = true;
        i = 1;
      }
      label349:
      String str1;
      Object localObject1;
      String str2;
      if (zzimj)
      {
        paramZzcav = zzimh;
        Object localObject2 = new zzcfv(packageName, zzimg, name, zziwz, paramZzcav.getValue());
        if (zzauf().zza((zzcfv)localObject2))
        {
          paramZzcav = zzaul().zzayi();
          str1 = "User property updated immediately";
          localObject1 = packageName;
          str2 = zzaug().zzje(mName);
        }
        for (localObject2 = mValue;; localObject2 = mValue)
        {
          paramZzcav.zzd(str1, localObject1, str2, localObject2);
          break;
          paramZzcav = zzaul().zzayd();
          str1 = "(2)Too many active user properties, ignoring";
          localObject1 = zzcbw.zzjf(packageName);
          str2 = zzaug().zzje(mName);
        }
        if ((i != 0) && (zzimn != null)) {
          zzc(new zzcbk(zzimn, zzimi), paramZzcas);
        }
      }
      if (zzauf().zza(localZzcav))
      {
        localObject1 = zzaul().zzayi();
        str2 = "Conditional property added";
        paramZzcas = packageName;
        str1 = zzaug().zzje(zzimh.name);
      }
      for (paramZzcav = zzimh.getValue();; paramZzcav = zzimh.getValue())
      {
        ((zzcby)localObject1).zzd(str2, paramZzcas, str1, paramZzcav);
        break;
        localObject1 = zzaul().zzayd();
        str2 = "Too many conditional properties, ignoring";
        paramZzcas = zzcbw.zzjf(packageName);
        str1 = zzaug().zzje(zzimh.name);
      }
      zzauf().setTransactionSuccessful();
      zzauf().endTransaction();
      return;
    }
    finally
    {
      zzauf().endTransaction();
    }
    for (;;)
    {
      throw paramZzcav;
    }
  }
  
  @X
  public final void zzb(zzcbk paramZzcbk, zzcas paramZzcas)
  {
    zzbp.zzu(paramZzcas);
    zzbp.zzgg(packageName);
    zzauk().zzuj();
    zzwk();
    String str = packageName;
    long l = zzins;
    zzauh();
    if (!zzcfw.zzd(paramZzcbk, paramZzcas)) {
      return;
    }
    if (!zzilz)
    {
      zzf(paramZzcas);
      return;
    }
    zzauf().beginTransaction();
    try
    {
      Object localObject1 = zzauf();
      zzbp.zzgg(str);
      ((zzcdt)localObject1).zzuj();
      ((zzcdu)localObject1).zzwk();
      if (l < 0L)
      {
        ((zzcdt)localObject1).zzaul().zzayf().zze("Invalid time querying timed out conditional properties", zzcbw.zzjf(str), Long.valueOf(l));
        localObject1 = Collections.emptyList();
      }
      else
      {
        localObject1 = ((zzcay)localObject1).zzc("active=0 and app_id=? and abs(? - creation_timestamp) > trigger_timeout", new String[] { str, String.valueOf(l) });
      }
      localObject1 = ((List)localObject1).iterator();
      Object localObject3;
      while (((Iterator)localObject1).hasNext())
      {
        localObject2 = (zzcav)((Iterator)localObject1).next();
        if (localObject2 != null)
        {
          zzaul().zzayi().zzd("User property timed out", packageName, zzaug().zzje(zzimh.name), zzimh.getValue());
          localObject3 = zziml;
          if (localObject3 != null) {
            zzc(new zzcbk((zzcbk)localObject3, l), paramZzcas);
          }
          zzauf().zzaj(str, zzimh.name);
        }
      }
      localObject1 = zzauf();
      zzbp.zzgg(str);
      ((zzcdt)localObject1).zzuj();
      ((zzcdu)localObject1).zzwk();
      if (l < 0L)
      {
        ((zzcdt)localObject1).zzaul().zzayf().zze("Invalid time querying expired conditional properties", zzcbw.zzjf(str), Long.valueOf(l));
        localObject1 = Collections.emptyList();
      }
      else
      {
        localObject1 = ((zzcay)localObject1).zzc("active<>0 and app_id=? and abs(? - triggered_timestamp) > time_to_live", new String[] { str, String.valueOf(l) });
      }
      Object localObject2 = new ArrayList(((List)localObject1).size());
      localObject1 = ((List)localObject1).iterator();
      Object localObject4;
      while (((Iterator)localObject1).hasNext())
      {
        localObject3 = (zzcav)((Iterator)localObject1).next();
        if (localObject3 != null)
        {
          zzaul().zzayi().zzd("User property expired", packageName, zzaug().zzje(zzimh.name), zzimh.getValue());
          zzauf().zzag(str, zzimh.name);
          localObject4 = zzimp;
          if (localObject4 != null) {
            ((List)localObject2).add(localObject4);
          }
          zzauf().zzaj(str, zzimh.name);
        }
      }
      int j = ((ArrayList)localObject2).size();
      int i = 0;
      while (i < j)
      {
        localObject1 = ((ArrayList)localObject2).get(i);
        i += 1;
        zzc(new zzcbk((zzcbk)localObject1, l), paramZzcas);
      }
      localObject1 = zzauf();
      localObject2 = name;
      zzbp.zzgg(str);
      zzbp.zzgg((String)localObject2);
      ((zzcdt)localObject1).zzuj();
      ((zzcdu)localObject1).zzwk();
      if (l < 0L)
      {
        ((zzcdt)localObject1).zzaul().zzayf().zzd("Invalid time querying triggered conditional properties", zzcbw.zzjf(str), ((zzcdt)localObject1).zzaug().zzjc((String)localObject2), Long.valueOf(l));
        localObject1 = Collections.emptyList();
      }
      else
      {
        localObject1 = ((zzcay)localObject1).zzc("active=0 and app_id=? and trigger_event_name=? and abs(? - creation_timestamp) <= trigger_timeout", new String[] { str, localObject2, String.valueOf(l) });
      }
      ArrayList localArrayList = new ArrayList(((List)localObject1).size());
      Iterator localIterator = ((List)localObject1).iterator();
      while (localIterator.hasNext())
      {
        zzcav localZzcav = (zzcav)localIterator.next();
        if (localZzcav != null)
        {
          localObject1 = zzimh;
          zzcfv localZzcfv = new zzcfv(packageName, zzimg, name, l, ((zzcft)localObject1).getValue());
          if (zzauf().zza(localZzcfv))
          {
            localObject1 = zzaul().zzayi();
            str = "User property triggered";
            localObject2 = packageName;
            localObject3 = zzaug().zzje(mName);
          }
          for (localObject4 = mValue;; localObject4 = mValue)
          {
            ((zzcby)localObject1).zzd(str, localObject2, localObject3, localObject4);
            break;
            localObject1 = zzaul().zzayd();
            str = "Too many active user properties, ignoring";
            localObject2 = zzcbw.zzjf(packageName);
            localObject3 = zzaug().zzje(mName);
          }
          localObject1 = zzimn;
          if (localObject1 != null) {
            localArrayList.add(localObject1);
          }
          zzimh = new zzcft(localZzcfv);
          zzimj = true;
          zzauf().zza(localZzcav);
        }
      }
      zzc(paramZzcbk, paramZzcas);
      j = localArrayList.size();
      i = 0;
      while (i < j)
      {
        paramZzcbk = localArrayList.get(i);
        i += 1;
        zzc(new zzcbk((zzcbk)paramZzcbk, l), paramZzcas);
      }
      zzauf().setTransactionSuccessful();
      zzauf().endTransaction();
      return;
    }
    finally
    {
      zzauf().endTransaction();
    }
    for (;;)
    {
      throw paramZzcbk;
    }
  }
  
  @X
  public final void zzb(zzcbk paramZzcbk, String paramString)
  {
    zzcar localZzcar = zzauf().zziw(paramString);
    if ((localZzcar != null) && (!TextUtils.isEmpty(localZzcar.zzuo()))) {}
    try
    {
      String str = zzcrmContext).getPackageInfo(paramString, 0).versionName;
      if ((localZzcar.zzuo() == null) || (localZzcar.zzuo().equals(str))) {
        break label110;
      }
      zzaul().zzayf().zzj("App version does not match; dropping event. appId", zzcbw.zzjf(paramString));
      return;
    }
    catch (PackageManager.NameNotFoundException localNameNotFoundException)
    {
      for (;;) {}
    }
    if (!"_ui".equals(name)) {
      zzaul().zzayf().zzj("Could not find package. appId", zzcbw.zzjf(paramString));
    }
    label110:
    zzb(paramZzcbk, new zzcas(paramString, localZzcar.getGmpAppId(), localZzcar.zzuo(), localZzcar.zzaut(), localZzcar.zzauu(), localZzcar.zzauv(), localZzcar.zzauw(), null, localZzcar.zzaux(), false, localZzcar.zzauq(), localZzcar.zzavk(), 0L, 0));
    return;
    zzaul().zzayi().zzj("No app data available; dropping event", paramString);
  }
  
  public final void zzb(zzcdu paramZzcdu)
  {
    zzitv += 1;
  }
  
  @X
  public final void zzb(zzcft paramZzcft, zzcas paramZzcas)
  {
    zzauk().zzuj();
    zzwk();
    if (TextUtils.isEmpty(zzilu)) {
      return;
    }
    if (!zzilz)
    {
      zzf(paramZzcas);
      return;
    }
    int j = zzauh().zzjy(name);
    int i;
    if (j != 0)
    {
      zzauh();
      localObject = name;
      zzcax.zzavo();
      localObject = zzcfw.zza((String)localObject, 24, true);
      paramZzcft = name;
      if (paramZzcft != null) {
        i = paramZzcft.length();
      } else {
        i = 0;
      }
      zzauh().zza(packageName, j, "_ev", (String)localObject, i);
      return;
    }
    j = zzauh().zzl(name, paramZzcft.getValue());
    if (j != 0)
    {
      zzauh();
      localObject = name;
      zzcax.zzavo();
      localObject = zzcfw.zza((String)localObject, 24, true);
      paramZzcft = paramZzcft.getValue();
      if ((paramZzcft != null) && (((paramZzcft instanceof String)) || ((paramZzcft instanceof CharSequence)))) {
        i = String.valueOf(paramZzcft).length();
      } else {
        i = 0;
      }
      zzauh().zza(packageName, j, "_ev", (String)localObject, i);
      return;
    }
    Object localObject = zzauh().zzm(name, paramZzcft.getValue());
    if (localObject == null) {
      return;
    }
    paramZzcft = new zzcfv(packageName, zzimg, name, zziwz, localObject);
    zzaul().zzayi().zze("Setting user property", zzaug().zzje(mName), localObject);
    zzauf().beginTransaction();
    try
    {
      zzf(paramZzcas);
      boolean bool = zzauf().zza(paramZzcft);
      zzauf().setTransactionSuccessful();
      if (bool)
      {
        zzaul().zzayi().zze("User property set", zzaug().zzje(mName), mValue);
      }
      else
      {
        zzaul().zzayd().zze("Too many unique user properties are set. Ignoring user property", zzaug().zzje(mName), mValue);
        zzauh().zza(packageName, 9, null, null, 0);
      }
      return;
    }
    finally
    {
      zzauf().endTransaction();
    }
  }
  
  @X
  public final void zzb(String paramString, int paramInt, Throwable paramThrowable, byte[] paramArrayOfByte, Map<String, List<String>> paramMap)
  {
    zzauk().zzuj();
    zzwk();
    zzbp.zzgg(paramString);
    byte[] arrayOfByte = paramArrayOfByte;
    if (paramArrayOfByte == null) {}
    for (;;)
    {
      try
      {
        arrayOfByte = new byte[0];
        zzaul().zzayj().zzj("onConfigFetched. Response size", Integer.valueOf(arrayOfByte.length));
        zzauf().beginTransaction();
      }
      finally
      {
        int j;
        boolean bool;
        label455:
        zzitz = false;
        zzazm();
        continue;
        throw paramString;
        continue;
        if (paramThrowable != null) {
          continue;
        }
        int i = 1;
        continue;
        i = 0;
        continue;
        if (i != 0) {
          continue;
        }
        if (paramInt != 404) {
          continue;
        }
        continue;
        i = 0;
        continue;
        paramThrowable = null;
        continue;
        paramThrowable = null;
        if (paramInt == 404) {
          continue;
        }
        if (paramInt != 304) {
          continue;
        }
        continue;
      }
      try
      {
        paramArrayOfByte = zzauf().zziw(paramString);
        j = 1;
        if ((paramInt == 200) || (paramInt == 204)) {
          continue;
        }
        if (paramInt != 304) {
          continue;
        }
      }
      finally
      {
        zzauf().endTransaction();
      }
    }
    if (paramArrayOfByte == null)
    {
      zzaul().zzayf().zzj("App does not exist in onConfigFetched. appId", zzcbw.zzjf(paramString));
      break label455;
      paramArrayOfByte.zzas(zzasc.currentTimeMillis());
      zzauf().zza(paramArrayOfByte);
      zzaul().zzayj().zze("Fetching config failed. code, error", Integer.valueOf(paramInt), paramThrowable);
      zzaui().zzjp(paramString);
      zzaumzziqq.set(zzasc.currentTimeMillis());
      i = j;
      if (paramInt != 503)
      {
        if (paramInt != 429) {
          break label529;
        }
        i = j;
      }
      if (i != 0) {
        zzaumzziqr.set(zzasc.currentTimeMillis());
      }
      zzazi();
      break label455;
      if (paramMap == null) {
        break label535;
      }
      paramThrowable = (List)paramMap.get("Last-Modified");
      if ((paramThrowable == null) || (paramThrowable.size() <= 0)) {
        break label540;
      }
      paramThrowable = (String)paramThrowable.get(0);
      break label542;
      bool = zzaui().zzb(paramString, arrayOfByte, paramThrowable);
      if (!bool) {
        paramString = zzauf();
      }
      for (;;)
      {
        paramString.endTransaction();
        zzitz = false;
        zzazm();
        return;
        if (zzaui().zzjn(paramString) == null)
        {
          bool = zzaui().zzb(paramString, null, null);
          if (!bool)
          {
            paramString = zzauf();
            continue;
          }
        }
        paramArrayOfByte.zzar(zzasc.currentTimeMillis());
        zzauf().zza(paramArrayOfByte);
        if (paramInt == 404) {
          zzaul().zzayg().zzj("Config not found. Using empty config. appId", paramString);
        } else {
          zzaul().zzayj().zze("Successfully fetched config. Got network response. code, size", Integer.valueOf(paramInt), Integer.valueOf(arrayOfByte.length));
        }
        if ((!zzaza().zzyx()) || (!zzazh())) {
          break;
        }
        zzazg();
        zzauf().setTransactionSuccessful();
        paramString = zzauf();
      }
    }
  }
  
  public final void zzbo(boolean paramBoolean)
  {
    zzazi();
  }
  
  @X
  public final void zzc(zzcav paramZzcav, zzcas paramZzcas)
  {
    zzbp.zzu(paramZzcav);
    zzbp.zzgg(packageName);
    zzbp.zzu(zzimh);
    zzbp.zzgg(zzimh.name);
    zzauk().zzuj();
    zzwk();
    if (TextUtils.isEmpty(zzilu)) {
      return;
    }
    if (!zzilz)
    {
      zzf(paramZzcas);
      return;
    }
    zzauf().beginTransaction();
    try
    {
      zzf(paramZzcas);
      zzcav localZzcav = zzauf().zzai(packageName, zzimh.name);
      if (localZzcav != null)
      {
        zzaul().zzayi().zze("Removing conditional user property", packageName, zzaug().zzje(zzimh.name));
        zzauf().zzaj(packageName, zzimh.name);
        if (zzimj) {
          zzauf().zzag(packageName, zzimh.name);
        }
        Object localObject = zzimp;
        if (localObject != null)
        {
          Bundle localBundle = null;
          if (zzinr != null) {
            localBundle = zzinr.zzaxz();
          }
          localObject = zzauh();
          paramZzcav = zzimp;
          zzc(((zzcfw)localObject).zza(name, localBundle, zzimg, zzins, true, false), paramZzcas);
        }
      }
      else
      {
        zzaul().zzayf().zze("Conditional user property doesn't exist", zzcbw.zzjf(packageName), zzaug().zzje(zzimh.name));
      }
      zzauf().setTransactionSuccessful();
      return;
    }
    finally
    {
      zzauf().endTransaction();
    }
  }
  
  @X
  public final void zzc(zzcft paramZzcft, zzcas paramZzcas)
  {
    zzauk().zzuj();
    zzwk();
    if (TextUtils.isEmpty(zzilu)) {
      return;
    }
    if (!zzilz)
    {
      zzf(paramZzcas);
      return;
    }
    zzaul().zzayi().zzj("Removing user property", zzaug().zzje(name));
    zzauf().beginTransaction();
    try
    {
      zzf(paramZzcas);
      zzauf().zzag(packageName, name);
      zzauf().setTransactionSuccessful();
      zzaul().zzayi().zzj("User property removed", zzaug().zzje(name));
      return;
    }
    finally
    {
      zzauf().endTransaction();
    }
  }
  
  public final void zzd(zzcas paramZzcas)
  {
    zzauk().zzuj();
    zzwk();
    zzbp.zzgg(packageName);
    zzf(paramZzcas);
  }
  
  @X
  public final void zzd(zzcav paramZzcav)
  {
    zzcas localZzcas = zzjr(packageName);
    if (localZzcas != null) {
      zzb(paramZzcav, localZzcas);
    }
  }
  
  @X
  public final void zze(zzcas paramZzcas)
  {
    zzauk().zzuj();
    zzwk();
    zzbp.zzu(paramZzcas);
    zzbp.zzgg(packageName);
    if (TextUtils.isEmpty(zzilu)) {
      return;
    }
    Object localObject1 = zzauf().zziw(packageName);
    if ((localObject1 != null) && (TextUtils.isEmpty(((zzcar)localObject1).getGmpAppId())) && (!TextUtils.isEmpty(zzilu)))
    {
      ((zzcar)localObject1).zzar(0L);
      zzauf().zza((zzcar)localObject1);
      zzaui().zzjq(packageName);
    }
    if (!zzilz)
    {
      zzf(paramZzcas);
      return;
    }
    l2 = zzime;
    long l1 = l2;
    if (l2 == 0L) {
      l1 = zzasc.currentTimeMillis();
    }
    int j = zzimf;
    i = j;
    if (j != 0)
    {
      i = j;
      if (j != 1)
      {
        zzaul().zzayf().zze("Incorrect app type, assuming installed app. appId, appType", zzcbw.zzjf(packageName), Integer.valueOf(j));
        i = 0;
      }
    }
    zzauf().beginTransaction();
    try
    {
      localObject3 = zzauf().zziw(packageName);
      localObject1 = localObject3;
      if (localObject3 != null)
      {
        localObject1 = localObject3;
        if (((zzcar)localObject3).getGmpAppId() != null)
        {
          localObject1 = localObject3;
          if (!((zzcar)localObject3).getGmpAppId().equals(zzilu))
          {
            zzaul().zzayf().zzj("New GMP App Id passed in. Removing cached database data. appId", zzcbw.zzjf(((zzcar)localObject3).getAppId()));
            localObject1 = zzauf();
            localObject3 = ((zzcar)localObject3).getAppId();
            ((zzcdu)localObject1).zzwk();
            ((zzcdt)localObject1).zzuj();
            zzbp.zzgg((String)localObject3);
            try
            {
              SQLiteDatabase localSQLiteDatabase = ((zzcay)localObject1).getWritableDatabase();
              String[] arrayOfString = new String[1];
              arrayOfString[0] = localObject3;
              j = localSQLiteDatabase.delete("events", "app_id=?", arrayOfString) + 0 + localSQLiteDatabase.delete("user_attributes", "app_id=?", arrayOfString) + localSQLiteDatabase.delete("conditional_properties", "app_id=?", arrayOfString) + localSQLiteDatabase.delete("apps", "app_id=?", arrayOfString) + localSQLiteDatabase.delete("raw_events", "app_id=?", arrayOfString) + localSQLiteDatabase.delete("raw_events_metadata", "app_id=?", arrayOfString) + localSQLiteDatabase.delete("event_filters", "app_id=?", arrayOfString) + localSQLiteDatabase.delete("property_filters", "app_id=?", arrayOfString) + localSQLiteDatabase.delete("audience_filter_values", "app_id=?", arrayOfString);
              if (j <= 0) {
                break label1351;
              }
              ((zzcdt)localObject1).zzaul().zzayj().zze("Deleted application data. app, records", localObject3, Integer.valueOf(j));
            }
            catch (SQLiteException localSQLiteException)
            {
              ((zzcdt)localObject1).zzaul().zzayd().zze("Error deleting application data. appId, error", zzcbw.zzjf((String)localObject3), localSQLiteException);
            }
          }
        }
      }
    }
    finally
    {
      for (;;)
      {
        Object localObject3;
        String str;
        ApplicationInfo localApplicationInfo;
        zzauf().endTransaction();
        for (;;)
        {
          throw paramZzcas;
        }
        Object localObject2 = null;
        continue;
        continue;
        localObject2 = null;
        continue;
        i = 1;
        continue;
        l2 = 0L;
      }
    }
    if ((localObject1 != null) && (((zzcar)localObject1).zzuo() != null) && (!((zzcar)localObject1).zzuo().equals(zzhtt)))
    {
      localObject3 = new Bundle();
      ((Bundle)localObject3).putString("_pv", ((zzcar)localObject1).zzuo());
      zzb(new zzcbk("_au", new zzcbh((Bundle)localObject3), "auto", l1), paramZzcas);
      zzf(paramZzcas);
      if (i == 0)
      {
        localObject1 = zzauf();
        localObject3 = packageName;
      }
      for (str = "_f";; str = "_v")
      {
        localObject1 = ((zzcay)localObject1).zzaf((String)localObject3, str);
        break;
        if (i != 1) {
          break label1360;
        }
        localObject1 = zzauf();
        localObject3 = packageName;
      }
      if (localObject1 == null)
      {
        l2 = l1 / 3600000L;
        l2 = (l2 + 1L) * 3600000L;
        if (i == 0)
        {
          zzb(new zzcft("_fot", l1, Long.valueOf(l2), "auto"), paramZzcas);
          zzauk().zzuj();
          zzwk();
          localObject3 = new Bundle();
          ((Bundle)localObject3).putLong("_c", 1L);
          ((Bundle)localObject3).putLong("_r", 1L);
          ((Bundle)localObject3).putLong("_uwa", 0L);
          ((Bundle)localObject3).putLong("_pfo", 0L);
          ((Bundle)localObject3).putLong("_sys", 0L);
          ((Bundle)localObject3).putLong("_sysu", 0L);
          if (mContext.getPackageManager() == null)
          {
            zzaul().zzayd().zzj("PackageManager is null, first open report might be inaccurate. appId", zzcbw.zzjf(packageName));
          }
          else
          {
            try
            {
              localObject1 = zzbed.zzcr(mContext);
              str = packageName;
              try
              {
                localObject1 = ((zzbec)localObject1).getPackageInfo(str, 0);
              }
              catch (PackageManager.NameNotFoundException localNameNotFoundException1) {}
              zzaul().zzayd().zze("Package info is null, first open report might be inaccurate. appId", zzcbw.zzjf(packageName), localNameNotFoundException2);
            }
            catch (PackageManager.NameNotFoundException localNameNotFoundException2) {}
            localApplicationInfo = null;
            if (localApplicationInfo != null)
            {
              l2 = firstInstallTime;
              if (l2 != 0L)
              {
                if (l2 == lastUpdateTime) {
                  break label1366;
                }
                ((Bundle)localObject3).putLong("_uwa", 1L);
                i = 0;
                if (i == 0) {
                  break label1371;
                }
                l2 = 1L;
                zzb(new zzcft("_fi", l1, Long.valueOf(l2), "auto"), paramZzcas);
              }
            }
            try
            {
              localApplicationInfo = zzbed.zzcr(mContext).getApplicationInfo(packageName, 0);
            }
            catch (PackageManager.NameNotFoundException localNameNotFoundException3)
            {
              zzaul().zzayd().zze("Application info is null, first open report might be inaccurate. appId", zzcbw.zzjf(packageName), localNameNotFoundException3);
              localObject2 = null;
            }
            if (localObject2 != null)
            {
              if ((flags & 0x1) != 0) {
                ((Bundle)localObject3).putLong("_sys", 1L);
              }
              if ((flags & 0x80) != 0) {
                ((Bundle)localObject3).putLong("_sysu", 1L);
              }
            }
          }
          localObject2 = zzauf();
          str = packageName;
          zzbp.zzgg(str);
          ((zzcdt)localObject2).zzuj();
          ((zzcdu)localObject2).zzwk();
          l2 = ((zzcay)localObject2).zzam(str, "first_open_count");
          if (l2 >= 0L) {
            ((Bundle)localObject3).putLong("_pfo", l2);
          }
        }
        for (localObject2 = new zzcbk("_f", new zzcbh((Bundle)localObject3), "auto", l1);; localObject2 = new zzcbk("_v", new zzcbh((Bundle)localObject2), "auto", l1))
        {
          zzb((zzcbk)localObject2, paramZzcas);
          break;
          if (i != 1) {
            break;
          }
          zzb(new zzcft("_fvt", l1, Long.valueOf(l2), "auto"), paramZzcas);
          zzauk().zzuj();
          zzwk();
          localObject2 = new Bundle();
          ((Bundle)localObject2).putLong("_c", 1L);
          ((Bundle)localObject2).putLong("_r", 1L);
        }
        localObject2 = new Bundle();
        ((Bundle)localObject2).putLong("_et", 1L);
      }
      for (localObject2 = new zzcbk("_e", new zzcbh((Bundle)localObject2), "auto", l1);; localObject2 = new zzcbk("_cd", new zzcbh(new Bundle()), "auto", l1))
      {
        zzb((zzcbk)localObject2, paramZzcas);
        break;
        if (!zzima) {
          break;
        }
      }
      zzauf().setTransactionSuccessful();
      zzauf().endTransaction();
    }
  }
  
  @X
  public final void zze(zzcav paramZzcav)
  {
    zzcas localZzcas = zzjr(packageName);
    if (localZzcas != null) {
      zzc(paramZzcav, localZzcas);
    }
  }
  
  @X
  public final void zzi(Runnable paramRunnable)
  {
    zzauk().zzuj();
    if (zzitu == null) {
      zzitu = new ArrayList();
    }
    zzitu.add(paramRunnable);
  }
  
  public final String zzjs(String paramString)
  {
    Object localObject = zzauk().zzd(new zzccy(this, paramString));
    try
    {
      localObject = (String)((Future)localObject).get(30000L, TimeUnit.MILLISECONDS);
      return localObject;
    }
    catch (ExecutionException localExecutionException) {}catch (InterruptedException localInterruptedException) {}catch (TimeoutException localTimeoutException) {}
    zzaul().zzayd().zze("Failed to get app instance id. appId", zzcbw.zzjf(paramString), localTimeoutException);
    return null;
  }
  
  public final zzd zzvx()
  {
    return zzasc;
  }
  
  public final void zzwk()
  {
    if (zzdoe) {
      return;
    }
    throw new IllegalStateException("AppMeasurement is not initialized");
  }
  
  public final class zza
    implements zzcba
  {
    public List<zzcgh> zzaoc;
    public zzcgk zziue;
    public List<Long> zziuf;
    public long zziug;
    
    public zza() {}
    
    public static long zza(zzcgh paramZzcgh)
    {
      return zziyy.longValue() / 1000L / 60L / 60L;
    }
    
    public final boolean zza(long paramLong, zzcgh paramZzcgh)
    {
      zzbp.zzu(paramZzcgh);
      if (zzaoc == null) {
        zzaoc = new ArrayList();
      }
      if (zziuf == null) {
        zziuf = new ArrayList();
      }
      if ((zzaoc.size() > 0) && (zza((zzcgh)zzaoc.get(0)) != zza(paramZzcgh))) {
        return false;
      }
      long l = zziug + paramZzcgh.zzhi();
      if (l >= zzcax.zzawr()) {
        return false;
      }
      zziug = l;
      zzaoc.add(paramZzcgh);
      zziuf.add(Long.valueOf(paramLong));
      return zzaoc.size() < zzcax.zzaws();
    }
    
    public final void zzb(zzcgk paramZzcgk)
    {
      zzbp.zzu(paramZzcgk);
      zziue = paramZzcgk;
    }
  }
}
