package com.google.android.gms.internal;

import java.util.concurrent.atomic.AtomicReference;

public final class zzceq
  implements Runnable
{
  public zzceq(zzceo paramZzceo, AtomicReference paramAtomicReference, zzcas paramZzcas) {}
  
  /* Error */
  public final void run()
  {
    // Byte code:
    //   0: aload_0
    //   1: getfield 18	com/google/android/gms/internal/zzceq:zziwg	Ljava/util/concurrent/atomic/AtomicReference;
    //   4: astore_2
    //   5: aload_2
    //   6: monitorenter
    //   7: aload_0
    //   8: getfield 16	com/google/android/gms/internal/zzceq:zziwf	Lcom/google/android/gms/internal/zzceo;
    //   11: getfield 33	com/google/android/gms/internal/zzceo:zzivz	Lcom/google/android/gms/internal/zzcbo;
    //   14: astore_1
    //   15: aload_1
    //   16: ifnonnull +28 -> 44
    //   19: aload_0
    //   20: getfield 16	com/google/android/gms/internal/zzceq:zziwf	Lcom/google/android/gms/internal/zzceo;
    //   23: invokevirtual 37	com/google/android/gms/internal/zzceo:zzaul	()Lcom/google/android/gms/internal/zzcbw;
    //   26: invokevirtual 43	com/google/android/gms/internal/zzcbw:zzayd	()Lcom/google/android/gms/internal/zzcby;
    //   29: ldc 45
    //   31: invokevirtual 51	com/google/android/gms/internal/zzcby:log	(Ljava/lang/String;)V
    //   34: aload_0
    //   35: getfield 18	com/google/android/gms/internal/zzceq:zziwg	Ljava/util/concurrent/atomic/AtomicReference;
    //   38: invokevirtual 54	java/lang/Object:notify	()V
    //   41: aload_2
    //   42: monitorexit
    //   43: return
    //   44: aload_0
    //   45: getfield 18	com/google/android/gms/internal/zzceq:zziwg	Ljava/util/concurrent/atomic/AtomicReference;
    //   48: aload_1
    //   49: aload_0
    //   50: getfield 20	com/google/android/gms/internal/zzceq:zziuj	Lcom/google/android/gms/internal/zzcas;
    //   53: invokeinterface 60 2 0
    //   58: invokevirtual 66	java/util/concurrent/atomic/AtomicReference:set	(Ljava/lang/Object;)V
    //   61: aload_0
    //   62: getfield 18	com/google/android/gms/internal/zzceq:zziwg	Ljava/util/concurrent/atomic/AtomicReference;
    //   65: invokevirtual 70	java/util/concurrent/atomic/AtomicReference:get	()Ljava/lang/Object;
    //   68: checkcast 72	java/lang/String
    //   71: astore_1
    //   72: aload_1
    //   73: ifnull +28 -> 101
    //   76: aload_0
    //   77: getfield 16	com/google/android/gms/internal/zzceq:zziwf	Lcom/google/android/gms/internal/zzceo;
    //   80: invokevirtual 76	com/google/android/gms/internal/zzceo:zzatz	()Lcom/google/android/gms/internal/zzcdw;
    //   83: aload_1
    //   84: invokevirtual 81	com/google/android/gms/internal/zzcdw:zzjk	(Ljava/lang/String;)V
    //   87: aload_0
    //   88: getfield 16	com/google/android/gms/internal/zzceq:zziwf	Lcom/google/android/gms/internal/zzceo;
    //   91: invokevirtual 85	com/google/android/gms/internal/zzceo:zzaum	()Lcom/google/android/gms/internal/zzcch;
    //   94: getfield 91	com/google/android/gms/internal/zzcch:zziqv	Lcom/google/android/gms/internal/zzccm;
    //   97: aload_1
    //   98: invokevirtual 96	com/google/android/gms/internal/zzccm:zzjl	(Ljava/lang/String;)V
    //   101: aload_0
    //   102: getfield 16	com/google/android/gms/internal/zzceq:zziwf	Lcom/google/android/gms/internal/zzceo;
    //   105: invokestatic 100	com/google/android/gms/internal/zzceo:zze	(Lcom/google/android/gms/internal/zzceo;)V
    //   108: aload_0
    //   109: getfield 18	com/google/android/gms/internal/zzceq:zziwg	Ljava/util/concurrent/atomic/AtomicReference;
    //   112: astore_1
    //   113: aload_1
    //   114: invokevirtual 54	java/lang/Object:notify	()V
    //   117: goto +32 -> 149
    //   120: astore_1
    //   121: goto +31 -> 152
    //   124: astore_1
    //   125: aload_0
    //   126: getfield 16	com/google/android/gms/internal/zzceq:zziwf	Lcom/google/android/gms/internal/zzceo;
    //   129: invokevirtual 37	com/google/android/gms/internal/zzceo:zzaul	()Lcom/google/android/gms/internal/zzcbw;
    //   132: invokevirtual 43	com/google/android/gms/internal/zzcbw:zzayd	()Lcom/google/android/gms/internal/zzcby;
    //   135: ldc 45
    //   137: aload_1
    //   138: invokevirtual 104	com/google/android/gms/internal/zzcby:zzj	(Ljava/lang/String;Ljava/lang/Object;)V
    //   141: aload_0
    //   142: getfield 18	com/google/android/gms/internal/zzceq:zziwg	Ljava/util/concurrent/atomic/AtomicReference;
    //   145: astore_1
    //   146: goto -33 -> 113
    //   149: aload_2
    //   150: monitorexit
    //   151: return
    //   152: aload_0
    //   153: getfield 18	com/google/android/gms/internal/zzceq:zziwg	Ljava/util/concurrent/atomic/AtomicReference;
    //   156: invokevirtual 54	java/lang/Object:notify	()V
    //   159: aload_1
    //   160: athrow
    //   161: astore_1
    //   162: aload_2
    //   163: monitorexit
    //   164: goto +5 -> 169
    //   167: aload_1
    //   168: athrow
    //   169: goto -2 -> 167
    // Local variable table:
    //   start	length	slot	name	signature
    //   0	172	0	this	zzceq
    //   14	100	1	localObject1	Object
    //   120	1	1	localObject2	Object
    //   124	14	1	localRemoteException	android.os.RemoteException
    //   145	15	1	localAtomicReference1	AtomicReference
    //   161	7	1	localObject3	Object
    // Exception table:
    //   from	to	target	type
    //   7	15	120	finally
    //   19	34	120	finally
    //   44	72	120	finally
    //   76	101	120	finally
    //   101	108	120	finally
    //   125	141	120	finally
    //   7	15	124	android/os/RemoteException
    //   19	34	124	android/os/RemoteException
    //   44	72	124	android/os/RemoteException
    //   76	101	124	android/os/RemoteException
    //   101	108	124	android/os/RemoteException
    //   34	43	161	finally
    //   108	113	161	finally
    //   113	117	161	finally
    //   141	146	161	finally
    //   149	151	161	finally
    //   152	161	161	finally
    //   162	164	161	finally
  }
}
