package b.b.r;

import android.content.Context;
import android.content.SharedPreferences;
import android.content.SharedPreferences.Editor;
import android.os.Build.VERSION;
import f.a.a.a.a;
import java.io.Closeable;
import java.io.File;
import java.io.IOException;
import java.util.ArrayList;
import java.util.Iterator;
import java.util.List;

public final class d
{
  public static final String a = "MultiDex";
  public static final String b = "classes";
  public static final String c = ".dex";
  public static final String d = ".classes";
  public static final String e = ".zip";
  public static final int f = 3;
  public static final String g = "multidex.version";
  public static final String h = "timestamp";
  public static final String i = "crc";
  public static final String j = "dex.number";
  public static final String k = "dex.crc.";
  public static final String l = "dex.time.";
  public static final int m = 16384;
  public static final long n = -1L;
  public static final String o = "MultiDex.lock";
  
  public d() {}
  
  public static long a(File paramFile)
  {
    long l2 = paramFile.lastModified();
    long l1 = l2;
    if (l2 == -1L) {
      l1 = l2 - 1L;
    }
    return l1;
  }
  
  public static SharedPreferences a(Context paramContext)
  {
    int i1 = Build.VERSION.SDK_INT;
    return paramContext.getSharedPreferences("multidex.version", 4);
  }
  
  public static List<a> a(Context paramContext, File paramFile1, File paramFile2, String paramString)
    throws IOException
  {
    Object localObject = new StringBuilder();
    ((StringBuilder)localObject).append(paramFile1.getName());
    ((StringBuilder)localObject).append(".classes");
    localObject = ((StringBuilder)localObject).toString();
    paramFile1 = a(paramContext);
    paramContext = new StringBuilder();
    paramContext.append(paramString);
    paramContext.append("dex.number");
    int i2 = paramFile1.getInt(paramContext.toString(), 1);
    ArrayList localArrayList = new ArrayList(i2 - 1);
    int i1 = 2;
    paramContext = (Context)localObject;
    while (i1 <= i2)
    {
      localObject = new a(paramFile2, a.a(paramContext, i1, ".zip"));
      if (((File)localObject).isFile())
      {
        a = b((File)localObject);
        StringBuilder localStringBuilder = new StringBuilder();
        localStringBuilder.append(paramString);
        localStringBuilder.append("dex.crc.");
        localStringBuilder.append(i1);
        long l1 = paramFile1.getLong(localStringBuilder.toString(), -1L);
        localStringBuilder = new StringBuilder();
        localStringBuilder.append(paramString);
        localStringBuilder.append("dex.time.");
        localStringBuilder.append(i1);
        long l2 = paramFile1.getLong(localStringBuilder.toString(), -1L);
        long l3 = ((File)localObject).lastModified();
        if ((l2 == l3) && (l1 == a))
        {
          localArrayList.add(localObject);
          i1 += 1;
        }
        else
        {
          paramContext = new StringBuilder();
          paramContext.append("Invalid extracted dex: ");
          paramContext.append(localObject);
          paramContext.append(" (key \"");
          paramContext.append(paramString);
          paramContext.append("\"), expected modification time: ");
          paramContext.append(l2);
          paramContext.append(", modification time: ");
          paramContext.append(l3);
          paramContext.append(", expected crc: ");
          paramContext.append(l1);
          paramContext.append(", file crc: ");
          paramContext.append(a);
          throw new IOException(paramContext.toString());
        }
      }
      else
      {
        paramContext = a.b("Missing extracted secondary dex file '");
        paramContext.append(((File)localObject).getPath());
        paramContext.append("'");
        throw new IOException(paramContext.toString());
      }
    }
    return localArrayList;
  }
  
  /* Error */
  public static List<? extends File> a(Context paramContext, File paramFile1, File paramFile2, String paramString, boolean paramBoolean)
    throws IOException
  {
    // Byte code:
    //   0: ldc -83
    //   2: invokestatic 162	f/a/a/a/a:b	(Ljava/lang/String;)Ljava/lang/StringBuilder;
    //   5: astore 7
    //   7: aload 7
    //   9: aload_1
    //   10: invokevirtual 165	java/io/File:getPath	()Ljava/lang/String;
    //   13: invokevirtual 92	java/lang/StringBuilder:append	(Ljava/lang/String;)Ljava/lang/StringBuilder;
    //   16: pop
    //   17: aload 7
    //   19: ldc -81
    //   21: invokevirtual 92	java/lang/StringBuilder:append	(Ljava/lang/String;)Ljava/lang/StringBuilder;
    //   24: pop
    //   25: aload 7
    //   27: iload 4
    //   29: invokevirtual 178	java/lang/StringBuilder:append	(Z)Ljava/lang/StringBuilder;
    //   32: pop
    //   33: aload 7
    //   35: ldc -81
    //   37: invokevirtual 92	java/lang/StringBuilder:append	(Ljava/lang/String;)Ljava/lang/StringBuilder;
    //   40: pop
    //   41: aload 7
    //   43: aload_3
    //   44: invokevirtual 92	java/lang/StringBuilder:append	(Ljava/lang/String;)Ljava/lang/StringBuilder;
    //   47: pop
    //   48: aload 7
    //   50: ldc -76
    //   52: invokevirtual 92	java/lang/StringBuilder:append	(Ljava/lang/String;)Ljava/lang/StringBuilder;
    //   55: pop
    //   56: aload 7
    //   58: invokevirtual 95	java/lang/StringBuilder:toString	()Ljava/lang/String;
    //   61: pop
    //   62: aload_1
    //   63: invokestatic 122	b/b/r/d:b	(Ljava/io/File;)J
    //   66: lstore 5
    //   68: new 62	java/io/File
    //   71: dup
    //   72: aload_2
    //   73: ldc 54
    //   75: invokespecial 181	java/io/File:<init>	(Ljava/io/File;Ljava/lang/String;)V
    //   78: astore 12
    //   80: new 183	java/io/RandomAccessFile
    //   83: dup
    //   84: aload 12
    //   86: ldc -71
    //   88: invokespecial 186	java/io/RandomAccessFile:<init>	(Ljava/io/File;Ljava/lang/String;)V
    //   91: astore 11
    //   93: aconst_null
    //   94: astore 10
    //   96: aconst_null
    //   97: astore 8
    //   99: aload 11
    //   101: invokevirtual 190	java/io/RandomAccessFile:getChannel	()Ljava/nio/channels/FileChannel;
    //   104: astore 7
    //   106: new 83	java/lang/StringBuilder
    //   109: dup
    //   110: invokespecial 84	java/lang/StringBuilder:<init>	()V
    //   113: astore 9
    //   115: aload 9
    //   117: ldc -64
    //   119: invokevirtual 92	java/lang/StringBuilder:append	(Ljava/lang/String;)Ljava/lang/StringBuilder;
    //   122: pop
    //   123: aload 9
    //   125: aload 12
    //   127: invokevirtual 165	java/io/File:getPath	()Ljava/lang/String;
    //   130: invokevirtual 92	java/lang/StringBuilder:append	(Ljava/lang/String;)Ljava/lang/StringBuilder;
    //   133: pop
    //   134: aload 9
    //   136: invokevirtual 95	java/lang/StringBuilder:toString	()Ljava/lang/String;
    //   139: pop
    //   140: aload 7
    //   142: invokevirtual 198	java/nio/channels/FileChannel:lock	()Ljava/nio/channels/FileLock;
    //   145: astore 9
    //   147: new 83	java/lang/StringBuilder
    //   150: dup
    //   151: invokespecial 84	java/lang/StringBuilder:<init>	()V
    //   154: astore 10
    //   156: aload 10
    //   158: aload 12
    //   160: invokevirtual 165	java/io/File:getPath	()Ljava/lang/String;
    //   163: invokevirtual 92	java/lang/StringBuilder:append	(Ljava/lang/String;)Ljava/lang/StringBuilder;
    //   166: pop
    //   167: aload 10
    //   169: ldc -56
    //   171: invokevirtual 92	java/lang/StringBuilder:append	(Ljava/lang/String;)Ljava/lang/StringBuilder;
    //   174: pop
    //   175: aload 10
    //   177: invokevirtual 95	java/lang/StringBuilder:toString	()Ljava/lang/String;
    //   180: pop
    //   181: iload 4
    //   183: ifne +270 -> 453
    //   186: aload_0
    //   187: aload_1
    //   188: lload 5
    //   190: aload_3
    //   191: invokestatic 203	b/b/r/d:a	(Landroid/content/Context;Ljava/io/File;JLjava/lang/String;)Z
    //   194: istore 4
    //   196: iload 4
    //   198: ifne +41 -> 239
    //   201: aload_0
    //   202: aload_1
    //   203: aload_2
    //   204: aload_3
    //   205: invokestatic 205	b/b/r/d:a	(Landroid/content/Context;Ljava/io/File;Ljava/io/File;Ljava/lang/String;)Ljava/util/List;
    //   208: astore 10
    //   210: aload 10
    //   212: astore_0
    //   213: goto +46 -> 259
    //   216: aload_1
    //   217: aload_2
    //   218: invokestatic 208	b/b/r/d:a	(Ljava/io/File;Ljava/io/File;)Ljava/util/List;
    //   221: astore_2
    //   222: aload_0
    //   223: aload_3
    //   224: aload_1
    //   225: invokestatic 210	b/b/r/d:a	(Ljava/io/File;)J
    //   228: lload 5
    //   230: aload_2
    //   231: invokestatic 213	b/b/r/d:a	(Landroid/content/Context;Ljava/lang/String;JJLjava/util/List;)V
    //   234: aload_2
    //   235: astore_0
    //   236: goto +23 -> 259
    //   239: aload_1
    //   240: aload_2
    //   241: invokestatic 208	b/b/r/d:a	(Ljava/io/File;Ljava/io/File;)Ljava/util/List;
    //   244: astore_2
    //   245: aload_0
    //   246: aload_3
    //   247: aload_1
    //   248: invokestatic 210	b/b/r/d:a	(Ljava/io/File;)J
    //   251: lload 5
    //   253: aload_2
    //   254: invokestatic 213	b/b/r/d:a	(Landroid/content/Context;Ljava/lang/String;JJLjava/util/List;)V
    //   257: aload_2
    //   258: astore_0
    //   259: aload 8
    //   261: astore_1
    //   262: aload 9
    //   264: ifnull +36 -> 300
    //   267: aload 9
    //   269: invokevirtual 218	java/nio/channels/FileLock:release	()V
    //   272: aload 8
    //   274: astore_1
    //   275: goto +25 -> 300
    //   278: astore_1
    //   279: ldc -36
    //   281: invokestatic 162	f/a/a/a/a:b	(Ljava/lang/String;)Ljava/lang/StringBuilder;
    //   284: astore_2
    //   285: aload_2
    //   286: aload 12
    //   288: invokevirtual 165	java/io/File:getPath	()Ljava/lang/String;
    //   291: invokevirtual 92	java/lang/StringBuilder:append	(Ljava/lang/String;)Ljava/lang/StringBuilder;
    //   294: pop
    //   295: aload_2
    //   296: invokevirtual 95	java/lang/StringBuilder:toString	()Ljava/lang/String;
    //   299: pop
    //   300: aload 7
    //   302: invokeinterface 225 1 0
    //   307: aload 11
    //   309: invokeinterface 225 1 0
    //   314: aload_1
    //   315: ifnonnull +34 -> 349
    //   318: ldc -29
    //   320: invokestatic 162	f/a/a/a/a:b	(Ljava/lang/String;)Ljava/lang/StringBuilder;
    //   323: astore_1
    //   324: aload_1
    //   325: aload_0
    //   326: invokeinterface 231 1 0
    //   331: invokevirtual 127	java/lang/StringBuilder:append	(I)Ljava/lang/StringBuilder;
    //   334: pop
    //   335: aload_1
    //   336: ldc -23
    //   338: invokevirtual 92	java/lang/StringBuilder:append	(Ljava/lang/String;)Ljava/lang/StringBuilder;
    //   341: pop
    //   342: aload_1
    //   343: invokevirtual 95	java/lang/StringBuilder:toString	()Ljava/lang/String;
    //   346: pop
    //   347: aload_0
    //   348: areturn
    //   349: aload_1
    //   350: athrow
    //   351: astore_0
    //   352: aload 9
    //   354: astore_2
    //   355: aload 7
    //   357: astore_1
    //   358: goto +19 -> 377
    //   361: astore_0
    //   362: aload 10
    //   364: astore_2
    //   365: aload 7
    //   367: astore_1
    //   368: goto +9 -> 377
    //   371: astore_0
    //   372: aconst_null
    //   373: astore_1
    //   374: aload 10
    //   376: astore_2
    //   377: aload_2
    //   378: ifnull +31 -> 409
    //   381: aload_2
    //   382: invokevirtual 218	java/nio/channels/FileLock:release	()V
    //   385: goto +24 -> 409
    //   388: ldc -36
    //   390: invokestatic 162	f/a/a/a/a:b	(Ljava/lang/String;)Ljava/lang/StringBuilder;
    //   393: astore_2
    //   394: aload_2
    //   395: aload 12
    //   397: invokevirtual 165	java/io/File:getPath	()Ljava/lang/String;
    //   400: invokevirtual 92	java/lang/StringBuilder:append	(Ljava/lang/String;)Ljava/lang/StringBuilder;
    //   403: pop
    //   404: aload_2
    //   405: invokevirtual 95	java/lang/StringBuilder:toString	()Ljava/lang/String;
    //   408: pop
    //   409: aload_1
    //   410: ifnull +9 -> 419
    //   413: aload_1
    //   414: invokeinterface 225 1 0
    //   419: aload 11
    //   421: invokeinterface 225 1 0
    //   426: aload_0
    //   427: athrow
    //   428: astore 10
    //   430: goto -214 -> 216
    //   433: astore_2
    //   434: goto -127 -> 307
    //   437: astore_2
    //   438: goto -124 -> 314
    //   441: astore_2
    //   442: goto -54 -> 388
    //   445: astore_1
    //   446: goto -27 -> 419
    //   449: astore_1
    //   450: goto -24 -> 426
    //   453: goto -214 -> 239
    // Local variable table:
    //   start	length	slot	name	signature
    //   0	456	0	paramContext	Context
    //   0	456	1	paramFile1	File
    //   0	456	2	paramFile2	File
    //   0	456	3	paramString	String
    //   0	456	4	paramBoolean	boolean
    //   66	186	5	l1	long
    //   5	361	7	localObject1	Object
    //   97	176	8	localObject2	Object
    //   113	240	9	localObject3	Object
    //   94	281	10	localObject4	Object
    //   428	1	10	localIOException	IOException
    //   91	329	11	localRandomAccessFile	java.io.RandomAccessFile
    //   78	318	12	localFile	File
    // Exception table:
    //   from	to	target	type
    //   267	272	278	java/io/IOException
    //   147	181	351	finally
    //   186	196	351	finally
    //   201	210	351	finally
    //   216	234	351	finally
    //   239	257	351	finally
    //   106	147	361	finally
    //   99	106	371	finally
    //   201	210	428	java/io/IOException
    //   300	307	433	java/io/IOException
    //   307	314	437	java/io/IOException
    //   381	385	441	java/io/IOException
    //   413	419	445	java/io/IOException
    //   419	426	449	java/io/IOException
  }
  
  /* Error */
  public static List<a> a(File paramFile1, File paramFile2)
    throws IOException
  {
    // Byte code:
    //   0: new 83	java/lang/StringBuilder
    //   3: dup
    //   4: invokespecial 84	java/lang/StringBuilder:<init>	()V
    //   7: astore 7
    //   9: aload 7
    //   11: aload_0
    //   12: invokevirtual 88	java/io/File:getName	()Ljava/lang/String;
    //   15: invokevirtual 92	java/lang/StringBuilder:append	(Ljava/lang/String;)Ljava/lang/StringBuilder;
    //   18: pop
    //   19: aload 7
    //   21: ldc 21
    //   23: invokevirtual 92	java/lang/StringBuilder:append	(Ljava/lang/String;)Ljava/lang/StringBuilder;
    //   26: pop
    //   27: aload 7
    //   29: invokevirtual 95	java/lang/StringBuilder:toString	()Ljava/lang/String;
    //   32: astore 10
    //   34: aload_1
    //   35: aload 10
    //   37: invokestatic 236	b/b/r/d:a	(Ljava/io/File;Ljava/lang/String;)V
    //   40: new 105	java/util/ArrayList
    //   43: dup
    //   44: invokespecial 237	java/util/ArrayList:<init>	()V
    //   47: astore 8
    //   49: new 239	java/util/zip/ZipFile
    //   52: dup
    //   53: aload_0
    //   54: invokespecial 242	java/util/zip/ZipFile:<init>	(Ljava/io/File;)V
    //   57: astore 9
    //   59: iconst_2
    //   60: istore_3
    //   61: new 83	java/lang/StringBuilder
    //   64: dup
    //   65: invokespecial 84	java/lang/StringBuilder:<init>	()V
    //   68: astore_0
    //   69: aload_0
    //   70: ldc 15
    //   72: invokevirtual 92	java/lang/StringBuilder:append	(Ljava/lang/String;)Ljava/lang/StringBuilder;
    //   75: pop
    //   76: aload_0
    //   77: iconst_2
    //   78: invokevirtual 127	java/lang/StringBuilder:append	(I)Ljava/lang/StringBuilder;
    //   81: pop
    //   82: aload_0
    //   83: ldc 18
    //   85: invokevirtual 92	java/lang/StringBuilder:append	(Ljava/lang/String;)Ljava/lang/StringBuilder;
    //   88: pop
    //   89: aload 9
    //   91: aload_0
    //   92: invokevirtual 95	java/lang/StringBuilder:toString	()Ljava/lang/String;
    //   95: invokevirtual 246	java/util/zip/ZipFile:getEntry	(Ljava/lang/String;)Ljava/util/zip/ZipEntry;
    //   98: astore_0
    //   99: aload_0
    //   100: ifnull +473 -> 573
    //   103: new 83	java/lang/StringBuilder
    //   106: dup
    //   107: invokespecial 84	java/lang/StringBuilder:<init>	()V
    //   110: astore 7
    //   112: aload 7
    //   114: aload 10
    //   116: invokevirtual 92	java/lang/StringBuilder:append	(Ljava/lang/String;)Ljava/lang/StringBuilder;
    //   119: pop
    //   120: aload 7
    //   122: iload_3
    //   123: invokevirtual 127	java/lang/StringBuilder:append	(I)Ljava/lang/StringBuilder;
    //   126: pop
    //   127: aload 7
    //   129: ldc 24
    //   131: invokevirtual 92	java/lang/StringBuilder:append	(Ljava/lang/String;)Ljava/lang/StringBuilder;
    //   134: pop
    //   135: new 8	b/b/r/d$a
    //   138: dup
    //   139: aload_1
    //   140: aload 7
    //   142: invokevirtual 95	java/lang/StringBuilder:toString	()Ljava/lang/String;
    //   145: invokespecial 116	b/b/r/d$a:<init>	(Ljava/io/File;Ljava/lang/String;)V
    //   148: astore 11
    //   150: aload 8
    //   152: aload 11
    //   154: invokeinterface 137 2 0
    //   159: pop
    //   160: new 83	java/lang/StringBuilder
    //   163: dup
    //   164: invokespecial 84	java/lang/StringBuilder:<init>	()V
    //   167: astore 7
    //   169: aload 7
    //   171: ldc -8
    //   173: invokevirtual 92	java/lang/StringBuilder:append	(Ljava/lang/String;)Ljava/lang/StringBuilder;
    //   176: pop
    //   177: aload 7
    //   179: aload 11
    //   181: invokevirtual 142	java/lang/StringBuilder:append	(Ljava/lang/Object;)Ljava/lang/StringBuilder;
    //   184: pop
    //   185: aload 7
    //   187: invokevirtual 95	java/lang/StringBuilder:toString	()Ljava/lang/String;
    //   190: pop
    //   191: iconst_0
    //   192: istore 5
    //   194: iconst_0
    //   195: istore 4
    //   197: iload 5
    //   199: iconst_3
    //   200: if_icmpge +264 -> 464
    //   203: iload 4
    //   205: ifne +259 -> 464
    //   208: iload 5
    //   210: iconst_1
    //   211: iadd
    //   212: istore 6
    //   214: aload 9
    //   216: aload_0
    //   217: aload 11
    //   219: aload 10
    //   221: invokestatic 251	b/b/r/d:a	(Ljava/util/zip/ZipFile;Ljava/util/zip/ZipEntry;Ljava/io/File;Ljava/lang/String;)V
    //   224: aload 11
    //   226: aload 11
    //   228: invokestatic 122	b/b/r/d:b	(Ljava/io/File;)J
    //   231: putfield 124	b/b/r/d$a:a	J
    //   234: iconst_1
    //   235: istore_2
    //   236: goto +39 -> 275
    //   239: new 83	java/lang/StringBuilder
    //   242: dup
    //   243: invokespecial 84	java/lang/StringBuilder:<init>	()V
    //   246: astore 7
    //   248: aload 7
    //   250: ldc -3
    //   252: invokevirtual 92	java/lang/StringBuilder:append	(Ljava/lang/String;)Ljava/lang/StringBuilder;
    //   255: pop
    //   256: aload 7
    //   258: aload 11
    //   260: invokevirtual 256	java/io/File:getAbsolutePath	()Ljava/lang/String;
    //   263: invokevirtual 92	java/lang/StringBuilder:append	(Ljava/lang/String;)Ljava/lang/StringBuilder;
    //   266: pop
    //   267: aload 7
    //   269: invokevirtual 95	java/lang/StringBuilder:toString	()Ljava/lang/String;
    //   272: pop
    //   273: iconst_0
    //   274: istore_2
    //   275: new 83	java/lang/StringBuilder
    //   278: dup
    //   279: invokespecial 84	java/lang/StringBuilder:<init>	()V
    //   282: astore 12
    //   284: aload 12
    //   286: ldc_w 258
    //   289: invokevirtual 92	java/lang/StringBuilder:append	(Ljava/lang/String;)Ljava/lang/StringBuilder;
    //   292: pop
    //   293: iload_2
    //   294: ifeq +314 -> 608
    //   297: ldc_w 260
    //   300: astore 7
    //   302: goto +3 -> 305
    //   305: aload 12
    //   307: aload 7
    //   309: invokevirtual 92	java/lang/StringBuilder:append	(Ljava/lang/String;)Ljava/lang/StringBuilder;
    //   312: pop
    //   313: aload 12
    //   315: ldc_w 262
    //   318: invokevirtual 92	java/lang/StringBuilder:append	(Ljava/lang/String;)Ljava/lang/StringBuilder;
    //   321: pop
    //   322: aload 12
    //   324: aload 11
    //   326: invokevirtual 256	java/io/File:getAbsolutePath	()Ljava/lang/String;
    //   329: invokevirtual 92	java/lang/StringBuilder:append	(Ljava/lang/String;)Ljava/lang/StringBuilder;
    //   332: pop
    //   333: aload 12
    //   335: ldc_w 264
    //   338: invokevirtual 92	java/lang/StringBuilder:append	(Ljava/lang/String;)Ljava/lang/StringBuilder;
    //   341: pop
    //   342: aload 12
    //   344: aload 11
    //   346: invokevirtual 267	java/io/File:length	()J
    //   349: invokevirtual 149	java/lang/StringBuilder:append	(J)Ljava/lang/StringBuilder;
    //   352: pop
    //   353: aload 12
    //   355: ldc_w 269
    //   358: invokevirtual 92	java/lang/StringBuilder:append	(Ljava/lang/String;)Ljava/lang/StringBuilder;
    //   361: pop
    //   362: aload 12
    //   364: aload 11
    //   366: getfield 124	b/b/r/d$a:a	J
    //   369: invokevirtual 149	java/lang/StringBuilder:append	(J)Ljava/lang/StringBuilder;
    //   372: pop
    //   373: aload 12
    //   375: invokevirtual 95	java/lang/StringBuilder:toString	()Ljava/lang/String;
    //   378: pop
    //   379: iload 6
    //   381: istore 5
    //   383: iload_2
    //   384: istore 4
    //   386: iload_2
    //   387: ifne -190 -> 197
    //   390: aload 11
    //   392: invokevirtual 272	java/io/File:delete	()Z
    //   395: pop
    //   396: iload 6
    //   398: istore 5
    //   400: iload_2
    //   401: istore 4
    //   403: aload 11
    //   405: invokevirtual 275	java/io/File:exists	()Z
    //   408: ifeq -211 -> 197
    //   411: new 83	java/lang/StringBuilder
    //   414: dup
    //   415: invokespecial 84	java/lang/StringBuilder:<init>	()V
    //   418: astore 7
    //   420: aload 7
    //   422: ldc_w 277
    //   425: invokevirtual 92	java/lang/StringBuilder:append	(Ljava/lang/String;)Ljava/lang/StringBuilder;
    //   428: pop
    //   429: aload 7
    //   431: aload 11
    //   433: invokevirtual 165	java/io/File:getPath	()Ljava/lang/String;
    //   436: invokevirtual 92	java/lang/StringBuilder:append	(Ljava/lang/String;)Ljava/lang/StringBuilder;
    //   439: pop
    //   440: aload 7
    //   442: ldc -89
    //   444: invokevirtual 92	java/lang/StringBuilder:append	(Ljava/lang/String;)Ljava/lang/StringBuilder;
    //   447: pop
    //   448: aload 7
    //   450: invokevirtual 95	java/lang/StringBuilder:toString	()Ljava/lang/String;
    //   453: pop
    //   454: iload 6
    //   456: istore 5
    //   458: iload_2
    //   459: istore 4
    //   461: goto -264 -> 197
    //   464: iload 4
    //   466: ifeq +48 -> 514
    //   469: iload_3
    //   470: iconst_1
    //   471: iadd
    //   472: istore_3
    //   473: new 83	java/lang/StringBuilder
    //   476: dup
    //   477: invokespecial 84	java/lang/StringBuilder:<init>	()V
    //   480: astore_0
    //   481: aload_0
    //   482: ldc 15
    //   484: invokevirtual 92	java/lang/StringBuilder:append	(Ljava/lang/String;)Ljava/lang/StringBuilder;
    //   487: pop
    //   488: aload_0
    //   489: iload_3
    //   490: invokevirtual 127	java/lang/StringBuilder:append	(I)Ljava/lang/StringBuilder;
    //   493: pop
    //   494: aload_0
    //   495: ldc 18
    //   497: invokevirtual 92	java/lang/StringBuilder:append	(Ljava/lang/String;)Ljava/lang/StringBuilder;
    //   500: pop
    //   501: aload 9
    //   503: aload_0
    //   504: invokevirtual 95	java/lang/StringBuilder:toString	()Ljava/lang/String;
    //   507: invokevirtual 246	java/util/zip/ZipFile:getEntry	(Ljava/lang/String;)Ljava/util/zip/ZipEntry;
    //   510: astore_0
    //   511: goto -412 -> 99
    //   514: new 83	java/lang/StringBuilder
    //   517: dup
    //   518: invokespecial 84	java/lang/StringBuilder:<init>	()V
    //   521: astore_0
    //   522: aload_0
    //   523: ldc_w 279
    //   526: invokevirtual 92	java/lang/StringBuilder:append	(Ljava/lang/String;)Ljava/lang/StringBuilder;
    //   529: pop
    //   530: aload_0
    //   531: aload 11
    //   533: invokevirtual 256	java/io/File:getAbsolutePath	()Ljava/lang/String;
    //   536: invokevirtual 92	java/lang/StringBuilder:append	(Ljava/lang/String;)Ljava/lang/StringBuilder;
    //   539: pop
    //   540: aload_0
    //   541: ldc_w 281
    //   544: invokevirtual 92	java/lang/StringBuilder:append	(Ljava/lang/String;)Ljava/lang/StringBuilder;
    //   547: pop
    //   548: aload_0
    //   549: iload_3
    //   550: invokevirtual 127	java/lang/StringBuilder:append	(I)Ljava/lang/StringBuilder;
    //   553: pop
    //   554: aload_0
    //   555: ldc -76
    //   557: invokevirtual 92	java/lang/StringBuilder:append	(Ljava/lang/String;)Ljava/lang/StringBuilder;
    //   560: pop
    //   561: new 81	java/io/IOException
    //   564: dup
    //   565: aload_0
    //   566: invokevirtual 95	java/lang/StringBuilder:toString	()Ljava/lang/String;
    //   569: invokespecial 158	java/io/IOException:<init>	(Ljava/lang/String;)V
    //   572: athrow
    //   573: aload 9
    //   575: invokevirtual 282	java/util/zip/ZipFile:close	()V
    //   578: aload 8
    //   580: areturn
    //   581: astore_0
    //   582: aload 9
    //   584: invokevirtual 282	java/util/zip/ZipFile:close	()V
    //   587: goto +5 -> 592
    //   590: aload_0
    //   591: athrow
    //   592: goto -2 -> 590
    //   595: astore 7
    //   597: goto -358 -> 239
    //   600: astore_0
    //   601: aload 8
    //   603: areturn
    //   604: astore_1
    //   605: goto -18 -> 587
    //   608: ldc_w 284
    //   611: astore 7
    //   613: goto -308 -> 305
    // Local variable table:
    //   start	length	slot	name	signature
    //   0	616	0	paramFile1	File
    //   0	616	1	paramFile2	File
    //   235	224	2	i1	int
    //   60	490	3	i2	int
    //   195	270	4	i3	int
    //   192	265	5	i4	int
    //   212	243	6	i5	int
    //   7	442	7	localObject	Object
    //   595	1	7	localIOException	IOException
    //   611	1	7	str1	String
    //   47	555	8	localArrayList	ArrayList
    //   57	526	9	localZipFile	java.util.zip.ZipFile
    //   32	188	10	str2	String
    //   148	384	11	localA	a
    //   282	92	12	localStringBuilder	StringBuilder
    // Exception table:
    //   from	to	target	type
    //   61	99	581	finally
    //   103	191	581	finally
    //   214	224	581	finally
    //   224	234	581	finally
    //   239	273	581	finally
    //   275	293	581	finally
    //   305	379	581	finally
    //   390	396	581	finally
    //   403	454	581	finally
    //   473	511	581	finally
    //   514	573	581	finally
    //   224	234	595	java/io/IOException
    //   573	578	600	java/io/IOException
    //   582	587	604	java/io/IOException
  }
  
  public static void a(Context paramContext, String paramString, long paramLong1, long paramLong2, List<a> paramList)
  {
    paramContext = a(paramContext).edit();
    Object localObject = new StringBuilder();
    ((StringBuilder)localObject).append(paramString);
    ((StringBuilder)localObject).append("timestamp");
    paramContext.putLong(((StringBuilder)localObject).toString(), paramLong1);
    paramContext.putLong(a.a(new StringBuilder(), paramString, "crc"), paramLong2);
    localObject = new StringBuilder();
    ((StringBuilder)localObject).append(paramString);
    ((StringBuilder)localObject).append("dex.number");
    paramContext.putInt(((StringBuilder)localObject).toString(), paramList.size() + 1);
    paramList = paramList.iterator();
    int i1 = 2;
    while (paramList.hasNext())
    {
      localObject = (a)paramList.next();
      StringBuilder localStringBuilder = new StringBuilder();
      localStringBuilder.append(paramString);
      localStringBuilder.append("dex.crc.");
      localStringBuilder.append(i1);
      paramContext.putLong(localStringBuilder.toString(), a);
      localStringBuilder = new StringBuilder();
      localStringBuilder.append(paramString);
      localStringBuilder.append("dex.time.");
      localStringBuilder.append(i1);
      paramContext.putLong(localStringBuilder.toString(), ((File)localObject).lastModified());
      i1 += 1;
    }
    paramContext.commit();
  }
  
  public static void a(Closeable paramCloseable)
  {
    try
    {
      paramCloseable.close();
      return;
    }
    catch (IOException paramCloseable) {}
  }
  
  public static void a(File paramFile, String paramString)
  {
    paramString = paramFile.listFiles(new c(paramString));
    if (paramString == null)
    {
      paramString = a.b("Failed to list secondary dex dir content (");
      paramString.append(paramFile.getPath());
      paramString.append(").");
      paramString.toString();
      return;
    }
    int i2 = paramString.length;
    int i1 = 0;
    while (i1 < i2)
    {
      paramFile = paramString[i1];
      StringBuilder localStringBuilder = a.b("Trying to delete old file ");
      localStringBuilder.append(paramFile.getPath());
      localStringBuilder.append(" of size ");
      localStringBuilder.append(paramFile.length());
      localStringBuilder.toString();
      if (!paramFile.delete())
      {
        localStringBuilder = a.b("Failed to delete old file ");
        localStringBuilder.append(paramFile.getPath());
        localStringBuilder.toString();
      }
      else
      {
        localStringBuilder = a.b("Deleted old file ");
        localStringBuilder.append(paramFile.getPath());
        localStringBuilder.toString();
      }
      i1 += 1;
    }
  }
  
  /* Error */
  public static void a(java.util.zip.ZipFile paramZipFile, java.util.zip.ZipEntry paramZipEntry, File paramFile, String paramString)
    throws IOException, java.io.FileNotFoundException
  {
    // Byte code:
    //   0: aload_0
    //   1: aload_1
    //   2: invokevirtual 343	java/util/zip/ZipFile:getInputStream	(Ljava/util/zip/ZipEntry;)Ljava/io/InputStream;
    //   5: astore 6
    //   7: ldc_w 345
    //   10: aload_3
    //   11: invokestatic 348	f/a/a/a/a:c	(Ljava/lang/String;Ljava/lang/String;)Ljava/lang/String;
    //   14: ldc 24
    //   16: aload_2
    //   17: invokevirtual 352	java/io/File:getParentFile	()Ljava/io/File;
    //   20: invokestatic 356	java/io/File:createTempFile	(Ljava/lang/String;Ljava/lang/String;Ljava/io/File;)Ljava/io/File;
    //   23: astore_0
    //   24: ldc_w 358
    //   27: invokestatic 162	f/a/a/a/a:b	(Ljava/lang/String;)Ljava/lang/StringBuilder;
    //   30: astore_3
    //   31: aload_3
    //   32: aload_0
    //   33: invokevirtual 165	java/io/File:getPath	()Ljava/lang/String;
    //   36: invokevirtual 92	java/lang/StringBuilder:append	(Ljava/lang/String;)Ljava/lang/StringBuilder;
    //   39: pop
    //   40: aload_3
    //   41: invokevirtual 95	java/lang/StringBuilder:toString	()Ljava/lang/String;
    //   44: pop
    //   45: new 360	java/util/zip/ZipOutputStream
    //   48: dup
    //   49: new 362	java/io/BufferedOutputStream
    //   52: dup
    //   53: new 364	java/io/FileOutputStream
    //   56: dup
    //   57: aload_0
    //   58: invokespecial 365	java/io/FileOutputStream:<init>	(Ljava/io/File;)V
    //   61: invokespecial 368	java/io/BufferedOutputStream:<init>	(Ljava/io/OutputStream;)V
    //   64: invokespecial 369	java/util/zip/ZipOutputStream:<init>	(Ljava/io/OutputStream;)V
    //   67: astore_3
    //   68: new 371	java/util/zip/ZipEntry
    //   71: dup
    //   72: ldc_w 373
    //   75: invokespecial 374	java/util/zip/ZipEntry:<init>	(Ljava/lang/String;)V
    //   78: astore 7
    //   80: aload 7
    //   82: aload_1
    //   83: invokevirtual 377	java/util/zip/ZipEntry:getTime	()J
    //   86: invokevirtual 381	java/util/zip/ZipEntry:setTime	(J)V
    //   89: aload_3
    //   90: aload 7
    //   92: invokevirtual 385	java/util/zip/ZipOutputStream:putNextEntry	(Ljava/util/zip/ZipEntry;)V
    //   95: sipush 16384
    //   98: newarray byte
    //   100: astore_1
    //   101: aload 6
    //   103: aload_1
    //   104: invokevirtual 391	java/io/InputStream:read	([B)I
    //   107: istore 4
    //   109: iload 4
    //   111: iconst_m1
    //   112: if_icmpeq +22 -> 134
    //   115: aload_3
    //   116: aload_1
    //   117: iconst_0
    //   118: iload 4
    //   120: invokevirtual 395	java/util/zip/ZipOutputStream:write	([BII)V
    //   123: aload 6
    //   125: aload_1
    //   126: invokevirtual 391	java/io/InputStream:read	([B)I
    //   129: istore 4
    //   131: goto -22 -> 109
    //   134: aload_3
    //   135: invokevirtual 398	java/util/zip/ZipOutputStream:closeEntry	()V
    //   138: aload_3
    //   139: invokevirtual 399	java/util/zip/ZipOutputStream:close	()V
    //   142: aload_0
    //   143: invokevirtual 402	java/io/File:setReadOnly	()Z
    //   146: ifeq +120 -> 266
    //   149: new 83	java/lang/StringBuilder
    //   152: dup
    //   153: invokespecial 84	java/lang/StringBuilder:<init>	()V
    //   156: astore_1
    //   157: aload_1
    //   158: ldc_w 404
    //   161: invokevirtual 92	java/lang/StringBuilder:append	(Ljava/lang/String;)Ljava/lang/StringBuilder;
    //   164: pop
    //   165: aload_1
    //   166: aload_2
    //   167: invokevirtual 165	java/io/File:getPath	()Ljava/lang/String;
    //   170: invokevirtual 92	java/lang/StringBuilder:append	(Ljava/lang/String;)Ljava/lang/StringBuilder;
    //   173: pop
    //   174: aload_1
    //   175: invokevirtual 95	java/lang/StringBuilder:toString	()Ljava/lang/String;
    //   178: pop
    //   179: aload_0
    //   180: aload_2
    //   181: invokevirtual 408	java/io/File:renameTo	(Ljava/io/File;)Z
    //   184: istore 5
    //   186: iload 5
    //   188: ifeq +16 -> 204
    //   191: aload 6
    //   193: invokeinterface 225 1 0
    //   198: aload_0
    //   199: invokevirtual 272	java/io/File:delete	()Z
    //   202: pop
    //   203: return
    //   204: new 83	java/lang/StringBuilder
    //   207: dup
    //   208: invokespecial 84	java/lang/StringBuilder:<init>	()V
    //   211: astore_1
    //   212: aload_1
    //   213: ldc_w 410
    //   216: invokevirtual 92	java/lang/StringBuilder:append	(Ljava/lang/String;)Ljava/lang/StringBuilder;
    //   219: pop
    //   220: aload_1
    //   221: aload_0
    //   222: invokevirtual 256	java/io/File:getAbsolutePath	()Ljava/lang/String;
    //   225: invokevirtual 92	java/lang/StringBuilder:append	(Ljava/lang/String;)Ljava/lang/StringBuilder;
    //   228: pop
    //   229: aload_1
    //   230: ldc_w 412
    //   233: invokevirtual 92	java/lang/StringBuilder:append	(Ljava/lang/String;)Ljava/lang/StringBuilder;
    //   236: pop
    //   237: aload_1
    //   238: aload_2
    //   239: invokevirtual 256	java/io/File:getAbsolutePath	()Ljava/lang/String;
    //   242: invokevirtual 92	java/lang/StringBuilder:append	(Ljava/lang/String;)Ljava/lang/StringBuilder;
    //   245: pop
    //   246: aload_1
    //   247: ldc_w 414
    //   250: invokevirtual 92	java/lang/StringBuilder:append	(Ljava/lang/String;)Ljava/lang/StringBuilder;
    //   253: pop
    //   254: new 81	java/io/IOException
    //   257: dup
    //   258: aload_1
    //   259: invokevirtual 95	java/lang/StringBuilder:toString	()Ljava/lang/String;
    //   262: invokespecial 158	java/io/IOException:<init>	(Ljava/lang/String;)V
    //   265: athrow
    //   266: new 83	java/lang/StringBuilder
    //   269: dup
    //   270: invokespecial 84	java/lang/StringBuilder:<init>	()V
    //   273: astore_1
    //   274: aload_1
    //   275: ldc_w 416
    //   278: invokevirtual 92	java/lang/StringBuilder:append	(Ljava/lang/String;)Ljava/lang/StringBuilder;
    //   281: pop
    //   282: aload_1
    //   283: aload_0
    //   284: invokevirtual 256	java/io/File:getAbsolutePath	()Ljava/lang/String;
    //   287: invokevirtual 92	java/lang/StringBuilder:append	(Ljava/lang/String;)Ljava/lang/StringBuilder;
    //   290: pop
    //   291: aload_1
    //   292: ldc_w 418
    //   295: invokevirtual 92	java/lang/StringBuilder:append	(Ljava/lang/String;)Ljava/lang/StringBuilder;
    //   298: pop
    //   299: aload_1
    //   300: aload_2
    //   301: invokevirtual 256	java/io/File:getAbsolutePath	()Ljava/lang/String;
    //   304: invokevirtual 92	java/lang/StringBuilder:append	(Ljava/lang/String;)Ljava/lang/StringBuilder;
    //   307: pop
    //   308: aload_1
    //   309: ldc_w 420
    //   312: invokevirtual 92	java/lang/StringBuilder:append	(Ljava/lang/String;)Ljava/lang/StringBuilder;
    //   315: pop
    //   316: new 81	java/io/IOException
    //   319: dup
    //   320: aload_1
    //   321: invokevirtual 95	java/lang/StringBuilder:toString	()Ljava/lang/String;
    //   324: invokespecial 158	java/io/IOException:<init>	(Ljava/lang/String;)V
    //   327: athrow
    //   328: astore_1
    //   329: aload_3
    //   330: invokevirtual 399	java/util/zip/ZipOutputStream:close	()V
    //   333: aload_1
    //   334: athrow
    //   335: astore_1
    //   336: aload 6
    //   338: invokeinterface 225 1 0
    //   343: aload_0
    //   344: invokevirtual 272	java/io/File:delete	()Z
    //   347: pop
    //   348: goto +5 -> 353
    //   351: aload_1
    //   352: athrow
    //   353: goto -2 -> 351
    //   356: astore_1
    //   357: goto -159 -> 198
    //   360: astore_2
    //   361: goto -18 -> 343
    // Local variable table:
    //   start	length	slot	name	signature
    //   0	364	0	paramZipFile	java.util.zip.ZipFile
    //   0	364	1	paramZipEntry	java.util.zip.ZipEntry
    //   0	364	2	paramFile	File
    //   0	364	3	paramString	String
    //   107	23	4	i1	int
    //   184	3	5	bool	boolean
    //   5	332	6	localInputStream	java.io.InputStream
    //   78	13	7	localZipEntry	java.util.zip.ZipEntry
    // Exception table:
    //   from	to	target	type
    //   68	109	328	finally
    //   115	131	328	finally
    //   134	138	328	finally
    //   45	68	335	finally
    //   138	186	335	finally
    //   204	266	335	finally
    //   266	328	335	finally
    //   329	335	335	finally
    //   191	198	356	java/io/IOException
    //   336	343	360	java/io/IOException
  }
  
  public static boolean a(Context paramContext, File paramFile, long paramLong, String paramString)
  {
    paramContext = a(paramContext);
    StringBuilder localStringBuilder = new StringBuilder();
    localStringBuilder.append(paramString);
    localStringBuilder.append("timestamp");
    if (paramContext.getLong(localStringBuilder.toString(), -1L) == a(paramFile))
    {
      paramFile = new StringBuilder();
      paramFile.append(paramString);
      paramFile.append("crc");
      if (paramContext.getLong(paramFile.toString(), -1L) == paramLong) {
        return false;
      }
    }
    return true;
  }
  
  public static long b(File paramFile)
    throws IOException
  {
    long l2 = f.a(paramFile);
    long l1 = l2;
    if (l2 == -1L) {
      l1 = l2 - 1L;
    }
    return l1;
  }
  
  private static class a
    extends File
  {
    public long a = -1L;
    
    public a(File paramFile, String paramString)
    {
      super(paramString);
    }
  }
}
