package b.b.x.b;

import android.content.Context;
import android.database.Cursor;
import android.net.Uri;
import b.b.a.F;
import b.b.a.G;
import b.b.x.j.b;
import java.io.FileDescriptor;
import java.io.PrintWriter;
import java.util.Arrays;

public class d
  extends a<Cursor>
{
  public final f<Cursor>.a a = new f.a(this);
  public Uri b;
  public String[] c;
  public String d;
  public String[] e;
  public String f;
  public Cursor g;
  public b h;
  
  public d(@F Context paramContext)
  {
    super(paramContext);
  }
  
  public d(@F Context paramContext, @F Uri paramUri, @G String[] paramArrayOfString1, @G String paramString1, @G String[] paramArrayOfString2, @G String paramString2)
  {
    super(paramContext);
    b = paramUri;
    c = paramArrayOfString1;
    d = paramString1;
    e = paramArrayOfString2;
    f = paramString2;
  }
  
  public void a(Cursor paramCursor)
  {
    if (isReset())
    {
      if (paramCursor != null) {
        paramCursor.close();
      }
      return;
    }
    Cursor localCursor = g;
    g = paramCursor;
    if (isStarted())
    {
      f.c localC = mListener;
      if (localC != null) {
        localC.onLoadComplete(this, paramCursor);
      }
    }
    if ((localCursor != null) && (localCursor != paramCursor) && (!localCursor.isClosed())) {
      localCursor.close();
    }
  }
  
  public void a(@F Uri paramUri)
  {
    b = paramUri;
  }
  
  public void a(@G String paramString)
  {
    d = paramString;
  }
  
  public void a(@G String[] paramArrayOfString)
  {
    c = paramArrayOfString;
  }
  
  @G
  public String[] a()
  {
    return c;
  }
  
  @G
  public String b()
  {
    return d;
  }
  
  public void b(Cursor paramCursor)
  {
    if ((paramCursor != null) && (!paramCursor.isClosed())) {
      paramCursor.close();
    }
  }
  
  public void b(@G String paramString)
  {
    f = paramString;
  }
  
  public void b(@G String[] paramArrayOfString)
  {
    e = paramArrayOfString;
  }
  
  @G
  public String[] c()
  {
    return e;
  }
  
  public void cancelLoadInBackground()
  {
    try
    {
      if (h != null) {
        h.a();
      }
      return;
    }
    finally {}
  }
  
  @G
  public String d()
  {
    return f;
  }
  
  @Deprecated
  public void dump(String paramString, FileDescriptor paramFileDescriptor, PrintWriter paramPrintWriter, String[] paramArrayOfString)
  {
    super.dump(paramString, paramFileDescriptor, paramPrintWriter, paramArrayOfString);
    paramPrintWriter.print(paramString);
    paramPrintWriter.print("mUri=");
    paramPrintWriter.println(b);
    paramPrintWriter.print(paramString);
    paramPrintWriter.print("mProjection=");
    paramPrintWriter.println(Arrays.toString(c));
    paramPrintWriter.print(paramString);
    paramPrintWriter.print("mSelection=");
    paramPrintWriter.println(d);
    paramPrintWriter.print(paramString);
    paramPrintWriter.print("mSelectionArgs=");
    paramPrintWriter.println(Arrays.toString(e));
    paramPrintWriter.print(paramString);
    paramPrintWriter.print("mSortOrder=");
    paramPrintWriter.println(f);
    paramPrintWriter.print(paramString);
    paramPrintWriter.print("mCursor=");
    paramPrintWriter.println(g);
    paramPrintWriter.print(paramString);
    paramPrintWriter.print("mContentChanged=");
    paramPrintWriter.println(mContentChanged);
  }
  
  @F
  public Uri e()
  {
    return b;
  }
  
  /* Error */
  public Cursor loadInBackground()
  {
    // Byte code:
    //   0: aload_0
    //   1: monitorenter
    //   2: aload_0
    //   3: invokevirtual 145	b/b/x/b/a:isLoadInBackgroundCanceled	()Z
    //   6: ifne +117 -> 123
    //   9: aload_0
    //   10: new 88	b/b/x/j/b
    //   13: dup
    //   14: invokespecial 147	b/b/x/j/b:<init>	()V
    //   17: putfield 86	b/b/x/b/d:h	Lb/b/x/j/b;
    //   20: aload_0
    //   21: monitorexit
    //   22: aload_0
    //   23: invokevirtual 151	b/b/x/b/f:getContext	()Landroid/content/Context;
    //   26: invokevirtual 157	android/content/Context:getContentResolver	()Landroid/content/ContentResolver;
    //   29: aload_0
    //   30: getfield 38	b/b/x/b/d:b	Landroid/net/Uri;
    //   33: aload_0
    //   34: getfield 40	b/b/x/b/d:c	[Ljava/lang/String;
    //   37: aload_0
    //   38: getfield 42	b/b/x/b/d:d	Ljava/lang/String;
    //   41: aload_0
    //   42: getfield 44	b/b/x/b/d:e	[Ljava/lang/String;
    //   45: aload_0
    //   46: getfield 46	b/b/x/b/d:f	Ljava/lang/String;
    //   49: aload_0
    //   50: getfield 86	b/b/x/b/d:h	Lb/b/x/j/b;
    //   53: invokestatic 162	b/b/x/b/b:a	(Landroid/content/ContentResolver;Landroid/net/Uri;[Ljava/lang/String;Ljava/lang/String;[Ljava/lang/String;Ljava/lang/String;Lb/b/x/j/b;)Landroid/database/Cursor;
    //   56: astore_1
    //   57: aload_1
    //   58: ifnull +32 -> 90
    //   61: aload_1
    //   62: invokeinterface 166 1 0
    //   67: pop
    //   68: aload_1
    //   69: aload_0
    //   70: getfield 32	b/b/x/b/d:a	Lb/b/x/b/f$a;
    //   73: invokeinterface 170 2 0
    //   78: goto +12 -> 90
    //   81: astore_2
    //   82: aload_1
    //   83: invokeinterface 59 1 0
    //   88: aload_2
    //   89: athrow
    //   90: aload_0
    //   91: monitorenter
    //   92: aload_0
    //   93: aconst_null
    //   94: putfield 86	b/b/x/b/d:h	Lb/b/x/j/b;
    //   97: aload_0
    //   98: monitorexit
    //   99: aload_1
    //   100: areturn
    //   101: astore_1
    //   102: aload_0
    //   103: monitorexit
    //   104: aload_1
    //   105: athrow
    //   106: astore_1
    //   107: aload_0
    //   108: monitorenter
    //   109: aload_0
    //   110: aconst_null
    //   111: putfield 86	b/b/x/b/d:h	Lb/b/x/j/b;
    //   114: aload_0
    //   115: monitorexit
    //   116: aload_1
    //   117: athrow
    //   118: astore_1
    //   119: aload_0
    //   120: monitorexit
    //   121: aload_1
    //   122: athrow
    //   123: new 172	b/b/x/j/k
    //   126: dup
    //   127: aconst_null
    //   128: invokespecial 174	b/b/x/j/k:<init>	(Ljava/lang/String;)V
    //   131: athrow
    //   132: astore_1
    //   133: aload_0
    //   134: monitorexit
    //   135: aload_1
    //   136: athrow
    // Local variable table:
    //   start	length	slot	name	signature
    //   0	137	0	this	d
    //   56	44	1	localCursor	Cursor
    //   101	4	1	localObject1	Object
    //   106	11	1	localObject2	Object
    //   118	4	1	localObject3	Object
    //   132	4	1	localObject4	Object
    //   81	8	2	localRuntimeException	RuntimeException
    // Exception table:
    //   from	to	target	type
    //   61	78	81	java/lang/RuntimeException
    //   92	99	101	finally
    //   102	104	101	finally
    //   22	57	106	finally
    //   61	78	106	finally
    //   82	90	106	finally
    //   109	116	118	finally
    //   119	121	118	finally
    //   2	22	132	finally
    //   123	132	132	finally
    //   133	135	132	finally
  }
  
  public void onReset()
  {
    onStopLoading();
    Cursor localCursor = g;
    if ((localCursor != null) && (!localCursor.isClosed())) {
      g.close();
    }
    g = null;
  }
  
  public void onStartLoading()
  {
    Cursor localCursor = g;
    if (localCursor != null) {
      a(localCursor);
    }
    if ((takeContentChanged()) || (g == null)) {
      forceLoad();
    }
  }
  
  public void onStopLoading()
  {
    cancelLoad();
  }
}
