package b.b.x.k;

import android.annotation.SuppressLint;
import android.content.Context;
import android.graphics.Bitmap;
import android.graphics.Bitmap.Config;
import android.graphics.BitmapFactory.Options;
import android.graphics.Canvas;
import android.graphics.ColorMatrix;
import android.graphics.ColorMatrixColorFilter;
import android.graphics.Matrix;
import android.graphics.Paint;
import android.graphics.RectF;
import android.net.Uri;
import android.os.AsyncTask;
import android.os.Build.VERSION;
import android.os.Bundle;
import android.os.CancellationSignal;
import android.os.ParcelFileDescriptor;
import android.print.PageRange;
import android.print.PrintAttributes;
import android.print.PrintAttributes.Builder;
import android.print.PrintAttributes.Margins;
import android.print.PrintAttributes.MediaSize;
import android.print.PrintDocumentAdapter;
import android.print.PrintDocumentAdapter.LayoutResultCallback;
import android.print.PrintDocumentAdapter.WriteResultCallback;
import android.print.PrintDocumentInfo.Builder;
import android.print.PrintManager;
import b.b.a.F;
import b.b.a.G;
import b.b.a.K;
import java.io.FileNotFoundException;

public final class b
{
  public static final String a = "PrintHelper";
  public static final int b = 3500;
  public static final boolean c;
  public static final boolean d;
  public static final int e = 1;
  public static final int f = 2;
  @SuppressLint({"InlinedApi"})
  public static final int g = 1;
  @SuppressLint({"InlinedApi"})
  public static final int h = 2;
  public static final int i = 1;
  public static final int j = 2;
  public final Context k;
  public BitmapFactory.Options l = null;
  public final Object m = new Object();
  public int n = 2;
  public int o = 2;
  public int p = 1;
  
  static
  {
    int i1 = Build.VERSION.SDK_INT;
    boolean bool2 = false;
    if ((i1 >= 20) && (i1 <= 23)) {
      bool1 = false;
    } else {
      bool1 = true;
    }
    c = bool1;
    boolean bool1 = bool2;
    if (Build.VERSION.SDK_INT != 23) {
      bool1 = true;
    }
    d = bool1;
  }
  
  public b(@F Context paramContext)
  {
    k = paramContext;
  }
  
  public static Bitmap a(Bitmap paramBitmap, int paramInt)
  {
    if (paramInt != 1) {
      return paramBitmap;
    }
    Bitmap localBitmap = Bitmap.createBitmap(paramBitmap.getWidth(), paramBitmap.getHeight(), Bitmap.Config.ARGB_8888);
    Canvas localCanvas = new Canvas(localBitmap);
    Paint localPaint = new Paint();
    ColorMatrix localColorMatrix = new ColorMatrix();
    localColorMatrix.setSaturation(0.0F);
    localPaint.setColorFilter(new ColorMatrixColorFilter(localColorMatrix));
    localCanvas.drawBitmap(paramBitmap, 0.0F, 0.0F, localPaint);
    localCanvas.setBitmap(null);
    return localBitmap;
  }
  
  /* Error */
  private Bitmap a(Uri paramUri, BitmapFactory.Options paramOptions)
    throws FileNotFoundException
  {
    // Byte code:
    //   0: aload_1
    //   1: ifnull +64 -> 65
    //   4: aload_0
    //   5: getfield 75	b/b/x/k/b:k	Landroid/content/Context;
    //   8: astore 4
    //   10: aload 4
    //   12: ifnull +53 -> 65
    //   15: aconst_null
    //   16: astore_3
    //   17: aload 4
    //   19: invokevirtual 138	android/content/Context:getContentResolver	()Landroid/content/ContentResolver;
    //   22: aload_1
    //   23: invokevirtual 144	android/content/ContentResolver:openInputStream	(Landroid/net/Uri;)Ljava/io/InputStream;
    //   26: astore_1
    //   27: aload_1
    //   28: aconst_null
    //   29: aload_2
    //   30: invokestatic 150	android/graphics/BitmapFactory:decodeStream	(Ljava/io/InputStream;Landroid/graphics/Rect;Landroid/graphics/BitmapFactory$Options;)Landroid/graphics/Bitmap;
    //   33: astore_2
    //   34: aload_1
    //   35: ifnull +7 -> 42
    //   38: aload_1
    //   39: invokevirtual 155	java/io/InputStream:close	()V
    //   42: aload_2
    //   43: areturn
    //   44: astore_3
    //   45: aload_1
    //   46: astore_2
    //   47: aload_3
    //   48: astore_1
    //   49: goto +6 -> 55
    //   52: astore_1
    //   53: aload_3
    //   54: astore_2
    //   55: aload_2
    //   56: ifnull +7 -> 63
    //   59: aload_2
    //   60: invokevirtual 155	java/io/InputStream:close	()V
    //   63: aload_1
    //   64: athrow
    //   65: new 157	java/lang/IllegalArgumentException
    //   68: dup
    //   69: ldc -97
    //   71: invokespecial 162	java/lang/IllegalArgumentException:<init>	(Ljava/lang/String;)V
    //   74: athrow
    //   75: astore_1
    //   76: aload_2
    //   77: areturn
    //   78: astore_2
    //   79: goto -16 -> 63
    // Local variable table:
    //   start	length	slot	name	signature
    //   0	82	0	this	b
    //   0	82	1	paramUri	Uri
    //   0	82	2	paramOptions	BitmapFactory.Options
    //   16	1	3	localObject1	Object
    //   44	10	3	localObject2	Object
    //   8	10	4	localContext	Context
    // Exception table:
    //   from	to	target	type
    //   27	34	44	finally
    //   17	27	52	finally
    //   38	42	75	java/io/IOException
    //   59	63	78	java/io/IOException
  }
  
  public static Matrix a(int paramInt1, int paramInt2, RectF paramRectF, int paramInt3)
  {
    Matrix localMatrix = new Matrix();
    float f1 = paramRectF.width();
    float f2 = paramInt1;
    f1 /= f2;
    if (paramInt3 == 2) {
      f1 = Math.max(f1, paramRectF.height() / paramInt2);
    } else {
      f1 = Math.min(f1, paramRectF.height() / paramInt2);
    }
    localMatrix.postScale(f1, f1);
    localMatrix.postTranslate((paramRectF.width() - f2 * f1) / 2.0F, (paramRectF.height() - paramInt2 * f1) / 2.0F);
    return localMatrix;
  }
  
  @K(19)
  public static PrintAttributes.Builder a(PrintAttributes paramPrintAttributes)
  {
    PrintAttributes.Builder localBuilder = new PrintAttributes.Builder().setMediaSize(paramPrintAttributes.getMediaSize()).setResolution(paramPrintAttributes.getResolution()).setMinMargins(paramPrintAttributes.getMinMargins());
    if (paramPrintAttributes.getColorMode() != 0) {
      localBuilder.setColorMode(paramPrintAttributes.getColorMode());
    }
    if ((Build.VERSION.SDK_INT >= 23) && (paramPrintAttributes.getDuplexMode() != 0)) {
      localBuilder.setDuplexMode(paramPrintAttributes.getDuplexMode());
    }
    return localBuilder;
  }
  
  public static boolean a(Bitmap paramBitmap)
  {
    return paramBitmap.getWidth() <= paramBitmap.getHeight();
  }
  
  public static boolean d()
  {
    int i1 = Build.VERSION.SDK_INT;
    return true;
  }
  
  public int a()
  {
    return o;
  }
  
  /* Error */
  public Bitmap a(Uri arg1)
    throws FileNotFoundException
  {
    // Byte code:
    //   0: aload_1
    //   1: ifnull +217 -> 218
    //   4: aload_0
    //   5: getfield 75	b/b/x/k/b:k	Landroid/content/Context;
    //   8: ifnull +210 -> 218
    //   11: new 243	android/graphics/BitmapFactory$Options
    //   14: dup
    //   15: invokespecial 244	android/graphics/BitmapFactory$Options:<init>	()V
    //   18: astore 6
    //   20: aload 6
    //   22: iconst_1
    //   23: putfield 247	android/graphics/BitmapFactory$Options:inJustDecodeBounds	Z
    //   26: aload_0
    //   27: aload_1
    //   28: aload 6
    //   30: invokespecial 249	b/b/x/k/b:a	(Landroid/net/Uri;Landroid/graphics/BitmapFactory$Options;)Landroid/graphics/Bitmap;
    //   33: pop
    //   34: aload 6
    //   36: getfield 252	android/graphics/BitmapFactory$Options:outWidth	I
    //   39: istore 4
    //   41: aload 6
    //   43: getfield 255	android/graphics/BitmapFactory$Options:outHeight	I
    //   46: istore 5
    //   48: iload 4
    //   50: ifle +166 -> 216
    //   53: iload 5
    //   55: ifgt +5 -> 60
    //   58: aconst_null
    //   59: areturn
    //   60: iload 4
    //   62: iload 5
    //   64: invokestatic 258	java/lang/Math:max	(II)I
    //   67: istore_3
    //   68: iconst_1
    //   69: istore_2
    //   70: iload_3
    //   71: sipush 3500
    //   74: if_icmple +14 -> 88
    //   77: iload_3
    //   78: iconst_1
    //   79: iushr
    //   80: istore_3
    //   81: iload_2
    //   82: iconst_1
    //   83: ishl
    //   84: istore_2
    //   85: goto -15 -> 70
    //   88: iload_2
    //   89: ifle +127 -> 216
    //   92: iload 4
    //   94: iload 5
    //   96: invokestatic 260	java/lang/Math:min	(II)I
    //   99: iload_2
    //   100: idiv
    //   101: ifgt +5 -> 106
    //   104: aconst_null
    //   105: areturn
    //   106: aload_0
    //   107: getfield 67	b/b/x/k/b:m	Ljava/lang/Object;
    //   110: astore 6
    //   112: aload 6
    //   114: monitorenter
    //   115: aload_0
    //   116: new 243	android/graphics/BitmapFactory$Options
    //   119: dup
    //   120: invokespecial 244	android/graphics/BitmapFactory$Options:<init>	()V
    //   123: putfield 65	b/b/x/k/b:l	Landroid/graphics/BitmapFactory$Options;
    //   126: aload_0
    //   127: getfield 65	b/b/x/k/b:l	Landroid/graphics/BitmapFactory$Options;
    //   130: iconst_1
    //   131: putfield 263	android/graphics/BitmapFactory$Options:inMutable	Z
    //   134: aload_0
    //   135: getfield 65	b/b/x/k/b:l	Landroid/graphics/BitmapFactory$Options;
    //   138: iload_2
    //   139: putfield 266	android/graphics/BitmapFactory$Options:inSampleSize	I
    //   142: aload_0
    //   143: getfield 65	b/b/x/k/b:l	Landroid/graphics/BitmapFactory$Options;
    //   146: astore 7
    //   148: aload 6
    //   150: monitorexit
    //   151: aload_0
    //   152: aload_1
    //   153: aload 7
    //   155: invokespecial 249	b/b/x/k/b:a	(Landroid/net/Uri;Landroid/graphics/BitmapFactory$Options;)Landroid/graphics/Bitmap;
    //   158: astore 6
    //   160: aload_0
    //   161: getfield 67	b/b/x/k/b:m	Ljava/lang/Object;
    //   164: astore_1
    //   165: aload_1
    //   166: monitorenter
    //   167: aload_0
    //   168: aconst_null
    //   169: putfield 65	b/b/x/k/b:l	Landroid/graphics/BitmapFactory$Options;
    //   172: aload_1
    //   173: monitorexit
    //   174: aload 6
    //   176: areturn
    //   177: astore 6
    //   179: aload_1
    //   180: monitorexit
    //   181: aload 6
    //   183: athrow
    //   184: astore 6
    //   186: aload_0
    //   187: getfield 67	b/b/x/k/b:m	Ljava/lang/Object;
    //   190: astore_1
    //   191: aload_1
    //   192: monitorenter
    //   193: aload_0
    //   194: aconst_null
    //   195: putfield 65	b/b/x/k/b:l	Landroid/graphics/BitmapFactory$Options;
    //   198: aload_1
    //   199: monitorexit
    //   200: aload 6
    //   202: athrow
    //   203: astore 6
    //   205: aload_1
    //   206: monitorexit
    //   207: aload 6
    //   209: athrow
    //   210: astore_1
    //   211: aload 6
    //   213: monitorexit
    //   214: aload_1
    //   215: athrow
    //   216: aconst_null
    //   217: areturn
    //   218: new 157	java/lang/IllegalArgumentException
    //   221: dup
    //   222: ldc_w 268
    //   225: invokespecial 162	java/lang/IllegalArgumentException:<init>	(Ljava/lang/String;)V
    //   228: astore_1
    //   229: goto +5 -> 234
    //   232: aload_1
    //   233: athrow
    //   234: goto -2 -> 232
    // Local variable table:
    //   start	length	slot	name	signature
    //   0	237	0	this	b
    //   69	70	2	i1	int
    //   67	14	3	i2	int
    //   39	54	4	i3	int
    //   46	49	5	i4	int
    //   18	157	6	localObject1	Object
    //   177	5	6	localObject2	Object
    //   184	17	6	localObject3	Object
    //   203	9	6	localObject4	Object
    //   146	8	7	localOptions	BitmapFactory.Options
    // Exception table:
    //   from	to	target	type
    //   167	174	177	finally
    //   179	181	177	finally
    //   151	160	184	finally
    //   193	200	203	finally
    //   205	207	203	finally
    //   115	151	210	finally
    //   211	214	210	finally
  }
  
  public void a(int paramInt)
  {
    o = paramInt;
  }
  
  @K(19)
  public void a(PrintAttributes paramPrintAttributes, int paramInt, Bitmap paramBitmap, ParcelFileDescriptor paramParcelFileDescriptor, CancellationSignal paramCancellationSignal, PrintDocumentAdapter.WriteResultCallback paramWriteResultCallback)
  {
    PrintAttributes localPrintAttributes;
    if (d) {
      localPrintAttributes = paramPrintAttributes;
    } else {
      localPrintAttributes = a(paramPrintAttributes).setMinMargins(new PrintAttributes.Margins(0, 0, 0, 0)).build();
    }
    new a(this, paramCancellationSignal, localPrintAttributes, paramBitmap, paramPrintAttributes, paramInt, paramParcelFileDescriptor, paramWriteResultCallback).execute(new Void[0]);
  }
  
  public void a(@F String paramString, @F Bitmap paramBitmap)
  {
    a(paramString, paramBitmap, null);
  }
  
  public void a(@F String paramString, @F Bitmap paramBitmap, @G a paramA)
  {
    int i1 = Build.VERSION.SDK_INT;
    if (paramBitmap == null) {
      return;
    }
    PrintManager localPrintManager = (PrintManager)k.getSystemService("print");
    if (a(paramBitmap)) {
      localObject = PrintAttributes.MediaSize.UNKNOWN_PORTRAIT;
    } else {
      localObject = PrintAttributes.MediaSize.UNKNOWN_LANDSCAPE;
    }
    Object localObject = new PrintAttributes.Builder().setMediaSize((PrintAttributes.MediaSize)localObject).setColorMode(o).build();
    localPrintManager.print(paramString, new b(paramString, n, paramBitmap, paramA), (PrintAttributes)localObject);
  }
  
  public void a(@F String paramString, @F Uri paramUri)
    throws FileNotFoundException
  {
    a(paramString, paramUri, null);
  }
  
  public void a(@F String paramString, @F Uri paramUri, @G a paramA)
    throws FileNotFoundException
  {
    int i1 = Build.VERSION.SDK_INT;
    paramUri = new c(paramString, paramUri, paramA, n);
    paramA = (PrintManager)k.getSystemService("print");
    PrintAttributes.Builder localBuilder = new PrintAttributes.Builder();
    localBuilder.setColorMode(o);
    i1 = p;
    if ((i1 != 1) && (i1 != 0))
    {
      if (i1 == 2) {
        localBuilder.setMediaSize(PrintAttributes.MediaSize.UNKNOWN_PORTRAIT);
      }
    }
    else {
      localBuilder.setMediaSize(PrintAttributes.MediaSize.UNKNOWN_LANDSCAPE);
    }
    paramA.print(paramString, paramUri, localBuilder.build());
  }
  
  public int b()
  {
    int i1 = Build.VERSION.SDK_INT;
    int i2 = p;
    i1 = i2;
    if (i2 == 0) {
      i1 = 1;
    }
    return i1;
  }
  
  public void b(int paramInt)
  {
    p = paramInt;
  }
  
  public int c()
  {
    return n;
  }
  
  public void c(int paramInt)
  {
    n = paramInt;
  }
  
  public static abstract interface a
  {
    public abstract void a();
  }
  
  @K(19)
  private class b
    extends PrintDocumentAdapter
  {
    public final String a;
    public final int b;
    public final Bitmap c;
    public final b.a d;
    public PrintAttributes e;
    
    public b(String paramString, int paramInt, Bitmap paramBitmap, b.a paramA)
    {
      a = paramString;
      b = paramInt;
      c = paramBitmap;
      d = paramA;
    }
    
    public void onFinish()
    {
      b.a localA = d;
      if (localA != null) {
        localA.a();
      }
    }
    
    public void onLayout(PrintAttributes paramPrintAttributes1, PrintAttributes paramPrintAttributes2, CancellationSignal paramCancellationSignal, PrintDocumentAdapter.LayoutResultCallback paramLayoutResultCallback, Bundle paramBundle)
    {
      e = paramPrintAttributes2;
      paramLayoutResultCallback.onLayoutFinished(new PrintDocumentInfo.Builder(a).setContentType(1).setPageCount(1).build(), paramPrintAttributes2.equals(paramPrintAttributes1) ^ true);
    }
    
    public void onWrite(PageRange[] paramArrayOfPageRange, ParcelFileDescriptor paramParcelFileDescriptor, CancellationSignal paramCancellationSignal, PrintDocumentAdapter.WriteResultCallback paramWriteResultCallback)
    {
      a(e, b, c, paramParcelFileDescriptor, paramCancellationSignal, paramWriteResultCallback);
    }
  }
  
  @K(19)
  private class c
    extends PrintDocumentAdapter
  {
    public final String a;
    public final Uri b;
    public final b.a c;
    public final int d;
    public PrintAttributes e;
    public AsyncTask<Uri, Boolean, Bitmap> f;
    public Bitmap g;
    
    public c(String paramString, Uri paramUri, b.a paramA, int paramInt)
    {
      a = paramString;
      b = paramUri;
      c = paramA;
      d = paramInt;
      g = null;
    }
    
    public void a()
    {
      synchronized (m)
      {
        if (l != null)
        {
          if (Build.VERSION.SDK_INT < 24) {
            l.requestCancelDecode();
          }
          l = null;
        }
        return;
      }
    }
    
    public void onFinish()
    {
      super.onFinish();
      a();
      Object localObject = f;
      if (localObject != null) {
        ((AsyncTask)localObject).cancel(true);
      }
      localObject = c;
      if (localObject != null) {
        ((b.a)localObject).a();
      }
      localObject = g;
      if (localObject != null)
      {
        ((Bitmap)localObject).recycle();
        g = null;
      }
    }
    
    public void onLayout(PrintAttributes paramPrintAttributes1, PrintAttributes paramPrintAttributes2, CancellationSignal paramCancellationSignal, PrintDocumentAdapter.LayoutResultCallback paramLayoutResultCallback, Bundle paramBundle)
    {
      try
      {
        e = paramPrintAttributes2;
        if (paramCancellationSignal.isCanceled())
        {
          paramLayoutResultCallback.onLayoutCancelled();
          return;
        }
        if (g != null)
        {
          paramLayoutResultCallback.onLayoutFinished(new PrintDocumentInfo.Builder(a).setContentType(1).setPageCount(1).build(), paramPrintAttributes2.equals(paramPrintAttributes1) ^ true);
          return;
        }
        f = new d(this, paramCancellationSignal, paramPrintAttributes2, paramPrintAttributes1, paramLayoutResultCallback).execute(new Uri[0]);
        return;
      }
      finally {}
    }
    
    public void onWrite(PageRange[] paramArrayOfPageRange, ParcelFileDescriptor paramParcelFileDescriptor, CancellationSignal paramCancellationSignal, PrintDocumentAdapter.WriteResultCallback paramWriteResultCallback)
    {
      a(e, d, g, paramParcelFileDescriptor, paramCancellationSignal, paramWriteResultCallback);
    }
  }
}
