package f.c.a.c;

import android.content.Context;
import java.io.ByteArrayOutputStream;
import java.io.File;
import java.io.IOException;
import java.io.InputStream;

public final class Fa
{
  public Fa() {}
  
  public static File a(File paramFile, String paramString)
  {
    paramFile = paramFile.listFiles();
    int j = paramFile.length;
    int i = 0;
    while (i < j)
    {
      File localFile = paramFile[i];
      if (localFile.getName().endsWith(paramString)) {
        return localFile;
      }
      i += 1;
    }
    return null;
  }
  
  public static byte[] a(Context paramContext, String paramString)
    throws IOException
  {
    return new c(paramContext, new Ua()).a(paramString);
  }
  
  public static byte[] a(File paramFile)
  {
    paramFile = a(paramFile, ".device_info");
    if (paramFile == null) {
      return null;
    }
    return d(paramFile);
  }
  
  public static byte[] a(File paramFile, Context paramContext)
    throws IOException
  {
    paramFile = d(paramFile);
    if ((paramFile != null) && (paramFile.length != 0)) {
      return a(paramContext, new String(paramFile));
    }
    return null;
  }
  
  public static byte[] a(InputStream paramInputStream)
    throws IOException
  {
    byte[] arrayOfByte = new byte['?'];
    ByteArrayOutputStream localByteArrayOutputStream = new ByteArrayOutputStream();
    for (;;)
    {
      int i = paramInputStream.read(arrayOfByte);
      if (i == -1) {
        break;
      }
      localByteArrayOutputStream.write(arrayOfByte, 0, i);
    }
    return localByteArrayOutputStream.toByteArray();
  }
  
  public static byte[] b(File paramFile)
  {
    paramFile = a(paramFile, ".dmp");
    if (paramFile == null) {
      return new byte[0];
    }
    return d(paramFile);
  }
  
  public static byte[] b(File paramFile, Context paramContext)
    throws IOException
  {
    File localFile = a(paramFile, ".maps");
    if (localFile != null) {
      return c(localFile, paramContext);
    }
    paramFile = a(paramFile, ".binary_libs");
    if (paramFile != null) {
      return a(paramFile, paramContext);
    }
    return null;
  }
  
  public static byte[] c(File paramFile)
  {
    return d(paramFile);
  }
  
  /* Error */
  public static byte[] c(File paramFile, Context paramContext)
    throws IOException
  {
    // Byte code:
    //   0: aload_0
    //   1: invokevirtual 90	java/io/File:exists	()Z
    //   4: ifne +5 -> 9
    //   7: aconst_null
    //   8: areturn
    //   9: new 92	java/io/BufferedReader
    //   12: dup
    //   13: new 94	java/io/FileReader
    //   16: dup
    //   17: aload_0
    //   18: invokespecial 97	java/io/FileReader:<init>	(Ljava/io/File;)V
    //   21: invokespecial 100	java/io/BufferedReader:<init>	(Ljava/io/Reader;)V
    //   24: astore_0
    //   25: new 32	f/c/a/c/c
    //   28: dup
    //   29: aload_1
    //   30: new 34	f/c/a/c/Ua
    //   33: dup
    //   34: invokespecial 35	f/c/a/c/Ua:<init>	()V
    //   37: invokespecial 38	f/c/a/c/c:<init>	(Landroid/content/Context;Lf/c/a/c/c$a;)V
    //   40: aload_0
    //   41: invokevirtual 103	f/c/a/c/c:a	(Ljava/io/BufferedReader;)[B
    //   44: astore_1
    //   45: aload_0
    //   46: invokestatic 108	l/a/a/a/a/b/l:a	(Ljava/io/Closeable;)V
    //   49: aload_1
    //   50: areturn
    //   51: astore_1
    //   52: goto +6 -> 58
    //   55: astore_1
    //   56: aconst_null
    //   57: astore_0
    //   58: aload_0
    //   59: invokestatic 108	l/a/a/a/a/b/l:a	(Ljava/io/Closeable;)V
    //   62: aload_1
    //   63: athrow
    // Local variable table:
    //   start	length	slot	name	signature
    //   0	64	0	paramFile	File
    //   0	64	1	paramContext	Context
    // Exception table:
    //   from	to	target	type
    //   25	45	51	finally
    //   9	25	55	finally
  }
  
  /* Error */
  public static byte[] d(File paramFile)
  {
    // Byte code:
    //   0: aconst_null
    //   1: astore_2
    //   2: new 112	java/io/FileInputStream
    //   5: dup
    //   6: aload_0
    //   7: invokespecial 113	java/io/FileInputStream:<init>	(Ljava/io/File;)V
    //   10: astore_0
    //   11: aload_0
    //   12: invokestatic 115	f/c/a/c/Fa:a	(Ljava/io/InputStream;)[B
    //   15: astore_1
    //   16: aload_0
    //   17: invokestatic 108	l/a/a/a/a/b/l:a	(Ljava/io/Closeable;)V
    //   20: aload_1
    //   21: areturn
    //   22: astore_1
    //   23: goto +6 -> 29
    //   26: astore_1
    //   27: aload_2
    //   28: astore_0
    //   29: aload_0
    //   30: invokestatic 108	l/a/a/a/a/b/l:a	(Ljava/io/Closeable;)V
    //   33: aload_1
    //   34: athrow
    //   35: aconst_null
    //   36: astore_0
    //   37: aload_0
    //   38: invokestatic 108	l/a/a/a/a/b/l:a	(Ljava/io/Closeable;)V
    //   41: aconst_null
    //   42: areturn
    //   43: aconst_null
    //   44: astore_0
    //   45: aload_0
    //   46: invokestatic 108	l/a/a/a/a/b/l:a	(Ljava/io/Closeable;)V
    //   49: aconst_null
    //   50: areturn
    //   51: astore_0
    //   52: goto -9 -> 43
    //   55: astore_0
    //   56: goto -21 -> 35
    //   59: astore_1
    //   60: goto -15 -> 45
    //   63: astore_1
    //   64: goto -27 -> 37
    // Local variable table:
    //   start	length	slot	name	signature
    //   0	67	0	paramFile	File
    //   15	6	1	arrayOfByte	byte[]
    //   22	1	1	localObject1	Object
    //   26	8	1	localObject2	Object
    //   59	1	1	localFileNotFoundException	java.io.FileNotFoundException
    //   63	1	1	localIOException	IOException
    //   1	27	2	localObject3	Object
    // Exception table:
    //   from	to	target	type
    //   11	16	22	finally
    //   2	11	26	finally
    //   2	11	51	java/io/FileNotFoundException
    //   2	11	55	java/io/IOException
    //   11	16	59	java/io/FileNotFoundException
    //   11	16	63	java/io/IOException
  }
}
