package f.c.a.c;

import java.util.concurrent.atomic.AtomicBoolean;
import l.a.a.a.a.g.v;

public class la
  implements Thread.UncaughtExceptionHandler
{
  public final a a;
  public final b b;
  public final boolean c;
  public final Thread.UncaughtExceptionHandler d;
  public final AtomicBoolean e;
  
  public la(a paramA, b paramB, boolean paramBoolean, Thread.UncaughtExceptionHandler paramUncaughtExceptionHandler)
  {
    a = paramA;
    b = paramB;
    c = paramBoolean;
    d = paramUncaughtExceptionHandler;
    e = new AtomicBoolean(false);
  }
  
  public boolean a()
  {
    return e.get();
  }
  
  /* Error */
  public void uncaughtException(Thread paramThread, Throwable paramThrowable)
  {
    // Byte code:
    //   0: aload_0
    //   1: getfield 40	f/c/a/c/la:e	Ljava/util/concurrent/atomic/AtomicBoolean;
    //   4: iconst_1
    //   5: invokevirtual 52	java/util/concurrent/atomic/AtomicBoolean:set	(Z)V
    //   8: aload_0
    //   9: getfield 27	f/c/a/c/la:a	Lf/c/a/c/la$a;
    //   12: aload_0
    //   13: getfield 29	f/c/a/c/la:b	Lf/c/a/c/la$b;
    //   16: aload_1
    //   17: aload_2
    //   18: aload_0
    //   19: getfield 31	f/c/a/c/la:c	Z
    //   22: invokeinterface 55 5 0
    //   27: invokestatic 61	l/a/a/a/g:h	()Ll/a/a/a/q;
    //   30: ldc 63
    //   32: ldc 65
    //   34: invokeinterface 70 3 0
    //   39: aload_0
    //   40: getfield 33	f/c/a/c/la:d	Ljava/lang/Thread$UncaughtExceptionHandler;
    //   43: aload_1
    //   44: aload_2
    //   45: invokeinterface 72 3 0
    //   50: aload_0
    //   51: getfield 40	f/c/a/c/la:e	Ljava/util/concurrent/atomic/AtomicBoolean;
    //   54: iconst_0
    //   55: invokevirtual 52	java/util/concurrent/atomic/AtomicBoolean:set	(Z)V
    //   58: return
    //   59: astore_3
    //   60: goto +20 -> 80
    //   63: astore_3
    //   64: invokestatic 61	l/a/a/a/g:h	()Ll/a/a/a/q;
    //   67: ldc 63
    //   69: ldc 74
    //   71: aload_3
    //   72: invokeinterface 77 4 0
    //   77: goto -50 -> 27
    //   80: invokestatic 61	l/a/a/a/g:h	()Ll/a/a/a/q;
    //   83: ldc 63
    //   85: ldc 65
    //   87: invokeinterface 70 3 0
    //   92: aload_0
    //   93: getfield 33	f/c/a/c/la:d	Ljava/lang/Thread$UncaughtExceptionHandler;
    //   96: aload_1
    //   97: aload_2
    //   98: invokeinterface 72 3 0
    //   103: aload_0
    //   104: getfield 40	f/c/a/c/la:e	Ljava/util/concurrent/atomic/AtomicBoolean;
    //   107: iconst_0
    //   108: invokevirtual 52	java/util/concurrent/atomic/AtomicBoolean:set	(Z)V
    //   111: goto +5 -> 116
    //   114: aload_3
    //   115: athrow
    //   116: goto -2 -> 114
    // Local variable table:
    //   start	length	slot	name	signature
    //   0	119	0	this	la
    //   0	119	1	paramThread	Thread
    //   0	119	2	paramThrowable	Throwable
    //   59	1	3	localObject	Object
    //   63	52	3	localException	Exception
    // Exception table:
    //   from	to	target	type
    //   8	27	59	finally
    //   64	77	59	finally
    //   8	27	63	java/lang/Exception
  }
  
  public static abstract interface a
  {
    public abstract void a(la.b paramB, Thread paramThread, Throwable paramThrowable, boolean paramBoolean);
  }
  
  public static abstract interface b
  {
    public abstract v a();
  }
}
