package com.google.android.gms.tagmanager;

import android.content.ContentValues;
import android.content.Context;
import android.database.sqlite.SQLiteDatabase;
import android.database.sqlite.SQLiteException;
import android.text.TextUtils;
import com.google.android.gms.common.util.zzd;
import com.google.android.gms.common.util.zzh;
import java.util.Collections;
import java.util.List;

public final class zzec
  implements zzcc
{
  public static final String zzdpj = String.format("CREATE TABLE IF NOT EXISTS %s ( '%s' INTEGER PRIMARY KEY AUTOINCREMENT NOT NULL, '%s' INTEGER NOT NULL, '%s' TEXT NOT NULL,'%s' INTEGER NOT NULL);", new Object[] { "gtm_hits", "hit_id", "hit_time", "hit_url", "hit_first_send_time" });
  public final Context mContext;
  public zzd zzasc;
  public final zzee zzjsx;
  public volatile zzbe zzjsy;
  public final zzcd zzjsz;
  public final String zzjta;
  public long zzjtb;
  public final int zzjtc;
  
  public zzec(zzcd paramZzcd, Context paramContext)
  {
    this(paramZzcd, paramContext, "gtm_urls.db", 2000);
  }
  
  public zzec(zzcd paramZzcd, Context paramContext, String paramString, int paramInt)
  {
    mContext = paramContext.getApplicationContext();
    zzjta = paramString;
    zzjsz = paramZzcd;
    zzasc = zzh.zzfyr;
    zzjsx = new zzee(this, mContext, zzjta);
    zzjsy = new zzfv(mContext, new zzed(this));
    zzjtb = 0L;
    zzjtc = 2000;
  }
  
  /* Error */
  private final int zzbee()
  {
    // Byte code:
    //   0: aload_0
    //   1: ldc 118
    //   3: invokespecial 122	com/google/android/gms/tagmanager/zzec:zzln	(Ljava/lang/String;)Landroid/database/sqlite/SQLiteDatabase;
    //   6: astore 7
    //   8: iconst_0
    //   9: istore_2
    //   10: aload 7
    //   12: ifnonnull +5 -> 17
    //   15: iconst_0
    //   16: ireturn
    //   17: aconst_null
    //   18: astore 5
    //   20: aconst_null
    //   21: astore 6
    //   23: aload 7
    //   25: ldc 124
    //   27: aconst_null
    //   28: invokevirtual 130	android/database/sqlite/SQLiteDatabase:rawQuery	(Ljava/lang/String;[Ljava/lang/String;)Landroid/database/Cursor;
    //   31: astore 7
    //   33: iload_2
    //   34: istore_1
    //   35: aload 7
    //   37: astore 8
    //   39: aload 7
    //   41: astore 6
    //   43: aload 7
    //   45: astore 5
    //   47: aload 7
    //   49: invokeinterface 136 1 0
    //   54: ifeq +27 -> 81
    //   57: aload 7
    //   59: astore 6
    //   61: aload 7
    //   63: astore 5
    //   65: aload 7
    //   67: iconst_0
    //   68: invokeinterface 140 2 0
    //   73: lstore_3
    //   74: lload_3
    //   75: l2i
    //   76: istore_1
    //   77: aload 7
    //   79: astore 8
    //   81: aload 8
    //   83: invokeinterface 143 1 0
    //   88: iload_1
    //   89: ireturn
    //   90: astore 5
    //   92: goto +33 -> 125
    //   95: aload 5
    //   97: astore 6
    //   99: getstatic 149	com/google/android/gms/tagmanager/zzdj:zzjss	Lcom/google/android/gms/tagmanager/zzdk;
    //   102: ldc -105
    //   104: invokeinterface 157 2 0
    //   109: aload 5
    //   111: ifnull +12 -> 123
    //   114: iload_2
    //   115: istore_1
    //   116: aload 5
    //   118: astore 8
    //   120: goto -39 -> 81
    //   123: iconst_0
    //   124: ireturn
    //   125: aload 6
    //   127: ifnull +10 -> 137
    //   130: aload 6
    //   132: invokeinterface 143 1 0
    //   137: goto +6 -> 143
    //   140: aload 5
    //   142: athrow
    //   143: goto -3 -> 140
    //   146: astore 6
    //   148: goto -53 -> 95
    // Local variable table:
    //   start	length	slot	name	signature
    //   0	151	0	this	zzec
    //   34	82	1	i	int
    //   9	106	2	j	int
    //   73	2	3	l	long
    //   18	46	5	localObject1	Object
    //   90	51	5	localObject2	Object
    //   21	110	6	localObject3	Object
    //   146	1	6	localSQLiteException	SQLiteException
    //   6	72	7	localObject4	Object
    //   37	82	8	localObject5	Object
    // Exception table:
    //   from	to	target	type
    //   23	33	90	finally
    //   47	57	90	finally
    //   65	74	90	finally
    //   99	109	90	finally
    //   23	33	146	android/database/sqlite/SQLiteException
    //   47	57	146	android/database/sqlite/SQLiteException
    //   65	74	146	android/database/sqlite/SQLiteException
  }
  
  /* Error */
  private final int zzbef()
  {
    // Byte code:
    //   0: aload_0
    //   1: ldc 118
    //   3: invokespecial 122	com/google/android/gms/tagmanager/zzec:zzln	(Ljava/lang/String;)Landroid/database/sqlite/SQLiteDatabase;
    //   6: astore 5
    //   8: iconst_0
    //   9: istore_1
    //   10: aload 5
    //   12: ifnonnull +5 -> 17
    //   15: iconst_0
    //   16: ireturn
    //   17: aconst_null
    //   18: astore_3
    //   19: aconst_null
    //   20: astore 4
    //   22: aload 5
    //   24: ldc 29
    //   26: iconst_2
    //   27: anewarray 39	java/lang/String
    //   30: dup
    //   31: iconst_0
    //   32: ldc 31
    //   34: aastore
    //   35: dup
    //   36: iconst_1
    //   37: ldc 37
    //   39: aastore
    //   40: ldc -96
    //   42: aconst_null
    //   43: aconst_null
    //   44: aconst_null
    //   45: aconst_null
    //   46: invokevirtual 164	android/database/sqlite/SQLiteDatabase:query	(Ljava/lang/String;[Ljava/lang/String;Ljava/lang/String;[Ljava/lang/String;Ljava/lang/String;Ljava/lang/String;Ljava/lang/String;)Landroid/database/Cursor;
    //   49: astore 5
    //   51: aload 5
    //   53: astore 4
    //   55: aload 5
    //   57: astore_3
    //   58: aload 5
    //   60: invokeinterface 167 1 0
    //   65: istore_2
    //   66: aload 5
    //   68: astore_3
    //   69: iload_2
    //   70: istore_1
    //   71: aload_3
    //   72: invokeinterface 143 1 0
    //   77: iload_1
    //   78: ireturn
    //   79: astore_3
    //   80: goto +25 -> 105
    //   83: aload_3
    //   84: astore 4
    //   86: getstatic 149	com/google/android/gms/tagmanager/zzdj:zzjss	Lcom/google/android/gms/tagmanager/zzdk;
    //   89: ldc -87
    //   91: invokeinterface 157 2 0
    //   96: aload_3
    //   97: ifnull +6 -> 103
    //   100: goto -29 -> 71
    //   103: iconst_0
    //   104: ireturn
    //   105: aload 4
    //   107: ifnull +10 -> 117
    //   110: aload 4
    //   112: invokeinterface 143 1 0
    //   117: goto +5 -> 122
    //   120: aload_3
    //   121: athrow
    //   122: goto -2 -> 120
    //   125: astore 4
    //   127: goto -44 -> 83
    // Local variable table:
    //   start	length	slot	name	signature
    //   0	130	0	this	zzec
    //   9	69	1	i	int
    //   65	5	2	j	int
    //   18	54	3	localObject1	Object
    //   79	42	3	localObject2	Object
    //   20	91	4	localObject3	Object
    //   125	1	4	localSQLiteException	SQLiteException
    //   6	61	5	localObject4	Object
    // Exception table:
    //   from	to	target	type
    //   22	51	79	finally
    //   58	66	79	finally
    //   86	96	79	finally
    //   22	51	125	android/database/sqlite/SQLiteException
    //   58	66	125	android/database/sqlite/SQLiteException
  }
  
  private final void zzd(String[] paramArrayOfString)
  {
    SQLiteDatabase localSQLiteDatabase;
    String str;
    if (paramArrayOfString != null)
    {
      if (paramArrayOfString.length == 0) {
        return;
      }
      localSQLiteDatabase = zzln("Error opening database for deleteHits.");
      if (localSQLiteDatabase == null) {
        return;
      }
      bool = true;
      str = String.format("HIT_ID in (%s)", new Object[] { TextUtils.join(",", Collections.nCopies(paramArrayOfString.length, "?")) });
    }
    try
    {
      localSQLiteDatabase.delete("gtm_hits", str, paramArrayOfString);
      paramArrayOfString = zzjsz;
      if (zzbee() != 0) {
        break label98;
      }
    }
    catch (SQLiteException paramArrayOfString)
    {
      for (;;)
      {
        continue;
        bool = false;
      }
    }
    paramArrayOfString.zzbu(bool);
    return;
    zzdj.zzjss.zzcr("Error deleting hits");
  }
  
  /* Error */
  private final List<String> zzek(int paramInt)
  {
    // Byte code:
    //   0: new 213	java/util/ArrayList
    //   3: dup
    //   4: invokespecial 214	java/util/ArrayList:<init>	()V
    //   7: astore 7
    //   9: iload_1
    //   10: ifgt +16 -> 26
    //   13: getstatic 149	com/google/android/gms/tagmanager/zzdj:zzjss	Lcom/google/android/gms/tagmanager/zzdk;
    //   16: ldc -40
    //   18: invokeinterface 157 2 0
    //   23: aload 7
    //   25: areturn
    //   26: aload_0
    //   27: ldc -38
    //   29: invokespecial 122	com/google/android/gms/tagmanager/zzec:zzln	(Ljava/lang/String;)Landroid/database/sqlite/SQLiteDatabase;
    //   32: astore 8
    //   34: aload 8
    //   36: ifnonnull +6 -> 42
    //   39: aload 7
    //   41: areturn
    //   42: aconst_null
    //   43: astore 6
    //   45: aconst_null
    //   46: astore 5
    //   48: aload 5
    //   50: astore 4
    //   52: aload 6
    //   54: astore_3
    //   55: ldc -36
    //   57: iconst_1
    //   58: anewarray 4	java/lang/Object
    //   61: dup
    //   62: iconst_0
    //   63: ldc 31
    //   65: aastore
    //   66: invokestatic 43	java/lang/String:format	(Ljava/lang/String;[Ljava/lang/Object;)Ljava/lang/String;
    //   69: astore 9
    //   71: aload 5
    //   73: astore 4
    //   75: aload 6
    //   77: astore_3
    //   78: iload_1
    //   79: invokestatic 226	java/lang/Integer:toString	(I)Ljava/lang/String;
    //   82: astore 10
    //   84: aload 5
    //   86: astore 4
    //   88: aload 6
    //   90: astore_3
    //   91: aload 8
    //   93: ldc 29
    //   95: iconst_1
    //   96: anewarray 39	java/lang/String
    //   99: dup
    //   100: iconst_0
    //   101: ldc 31
    //   103: aastore
    //   104: aconst_null
    //   105: aconst_null
    //   106: aconst_null
    //   107: aconst_null
    //   108: aload 9
    //   110: aload 10
    //   112: invokevirtual 229	android/database/sqlite/SQLiteDatabase:query	(Ljava/lang/String;[Ljava/lang/String;Ljava/lang/String;[Ljava/lang/String;Ljava/lang/String;Ljava/lang/String;Ljava/lang/String;Ljava/lang/String;)Landroid/database/Cursor;
    //   115: astore 5
    //   117: aload 5
    //   119: astore 4
    //   121: aload 5
    //   123: astore_3
    //   124: aload 5
    //   126: astore 6
    //   128: aload 5
    //   130: invokeinterface 136 1 0
    //   135: ifeq +134 -> 269
    //   138: aload 5
    //   140: astore 4
    //   142: aload 5
    //   144: astore_3
    //   145: aload 7
    //   147: aload 5
    //   149: iconst_0
    //   150: invokeinterface 140 2 0
    //   155: invokestatic 233	java/lang/String:valueOf	(J)Ljava/lang/String;
    //   158: invokeinterface 239 2 0
    //   163: pop
    //   164: aload 5
    //   166: astore 4
    //   168: aload 5
    //   170: astore_3
    //   171: aload 5
    //   173: invokeinterface 242 1 0
    //   178: istore_2
    //   179: iload_2
    //   180: ifne -42 -> 138
    //   183: aload 5
    //   185: astore 6
    //   187: goto +82 -> 269
    //   190: astore_3
    //   191: goto +88 -> 279
    //   194: astore 5
    //   196: aload_3
    //   197: astore 4
    //   199: aload 5
    //   201: invokevirtual 245	android/database/sqlite/SQLiteException:getMessage	()Ljava/lang/String;
    //   204: invokestatic 248	java/lang/String:valueOf	(Ljava/lang/Object;)Ljava/lang/String;
    //   207: astore 5
    //   209: aload_3
    //   210: astore 4
    //   212: aload 5
    //   214: invokevirtual 251	java/lang/String:length	()I
    //   217: ifeq +18 -> 235
    //   220: aload_3
    //   221: astore 4
    //   223: ldc -3
    //   225: aload 5
    //   227: invokevirtual 257	java/lang/String:concat	(Ljava/lang/String;)Ljava/lang/String;
    //   230: astore 5
    //   232: goto +17 -> 249
    //   235: aload_3
    //   236: astore 4
    //   238: new 39	java/lang/String
    //   241: dup
    //   242: ldc -3
    //   244: invokespecial 259	java/lang/String:<init>	(Ljava/lang/String;)V
    //   247: astore 5
    //   249: aload_3
    //   250: astore 4
    //   252: getstatic 149	com/google/android/gms/tagmanager/zzdj:zzjss	Lcom/google/android/gms/tagmanager/zzdk;
    //   255: aload 5
    //   257: invokeinterface 157 2 0
    //   262: aload_3
    //   263: ifnull +13 -> 276
    //   266: aload_3
    //   267: astore 6
    //   269: aload 6
    //   271: invokeinterface 143 1 0
    //   276: aload 7
    //   278: areturn
    //   279: aload 4
    //   281: ifnull +10 -> 291
    //   284: aload 4
    //   286: invokeinterface 143 1 0
    //   291: goto +5 -> 296
    //   294: aload_3
    //   295: athrow
    //   296: goto -2 -> 294
    // Local variable table:
    //   start	length	slot	name	signature
    //   0	299	0	this	zzec
    //   0	299	1	paramInt	int
    //   178	2	2	bool	boolean
    //   54	117	3	localObject1	Object
    //   190	105	3	localObject2	Object
    //   50	235	4	localObject3	Object
    //   46	138	5	localCursor	android.database.Cursor
    //   194	6	5	localSQLiteException	SQLiteException
    //   207	49	5	str1	String
    //   43	227	6	localObject4	Object
    //   7	270	7	localArrayList	java.util.ArrayList
    //   32	60	8	localSQLiteDatabase	SQLiteDatabase
    //   69	40	9	str2	String
    //   82	29	10	str3	String
    // Exception table:
    //   from	to	target	type
    //   55	71	190	finally
    //   78	84	190	finally
    //   91	117	190	finally
    //   128	138	190	finally
    //   145	164	190	finally
    //   171	179	190	finally
    //   199	209	190	finally
    //   212	220	190	finally
    //   223	232	190	finally
    //   238	249	190	finally
    //   252	262	190	finally
    //   55	71	194	android/database/sqlite/SQLiteException
    //   78	84	194	android/database/sqlite/SQLiteException
    //   91	117	194	android/database/sqlite/SQLiteException
    //   128	138	194	android/database/sqlite/SQLiteException
    //   145	164	194	android/database/sqlite/SQLiteException
    //   171	179	194	android/database/sqlite/SQLiteException
  }
  
  /* Error */
  private final List<zzbx> zzel(int paramInt)
  {
    // Byte code:
    //   0: new 213	java/util/ArrayList
    //   3: dup
    //   4: invokespecial 214	java/util/ArrayList:<init>	()V
    //   7: astore 8
    //   9: aload_0
    //   10: ldc_w 264
    //   13: invokespecial 122	com/google/android/gms/tagmanager/zzec:zzln	(Ljava/lang/String;)Landroid/database/sqlite/SQLiteDatabase;
    //   16: astore 10
    //   18: aload 10
    //   20: ifnonnull +6 -> 26
    //   23: aload 8
    //   25: areturn
    //   26: ldc -36
    //   28: iconst_1
    //   29: anewarray 4	java/lang/Object
    //   32: dup
    //   33: iconst_0
    //   34: ldc 31
    //   36: aastore
    //   37: invokestatic 43	java/lang/String:format	(Ljava/lang/String;[Ljava/lang/Object;)Ljava/lang/String;
    //   40: astore 6
    //   42: bipush 40
    //   44: invokestatic 226	java/lang/Integer:toString	(I)Ljava/lang/String;
    //   47: astore 7
    //   49: iconst_0
    //   50: istore_2
    //   51: aload 10
    //   53: ldc 29
    //   55: iconst_3
    //   56: anewarray 39	java/lang/String
    //   59: dup
    //   60: iconst_0
    //   61: ldc 31
    //   63: aastore
    //   64: dup
    //   65: iconst_1
    //   66: ldc 33
    //   68: aastore
    //   69: dup
    //   70: iconst_2
    //   71: ldc 37
    //   73: aastore
    //   74: aconst_null
    //   75: aconst_null
    //   76: aconst_null
    //   77: aconst_null
    //   78: aload 6
    //   80: aload 7
    //   82: invokevirtual 229	android/database/sqlite/SQLiteDatabase:query	(Ljava/lang/String;[Ljava/lang/String;Ljava/lang/String;[Ljava/lang/String;Ljava/lang/String;Ljava/lang/String;Ljava/lang/String;Ljava/lang/String;)Landroid/database/Cursor;
    //   85: astore 6
    //   87: new 213	java/util/ArrayList
    //   90: dup
    //   91: invokespecial 214	java/util/ArrayList:<init>	()V
    //   94: astore 7
    //   96: aload 6
    //   98: invokeinterface 136 1 0
    //   103: istore 5
    //   105: iload 5
    //   107: ifeq +77 -> 184
    //   110: aload 7
    //   112: new 266	com/google/android/gms/tagmanager/zzbx
    //   115: dup
    //   116: aload 6
    //   118: iconst_0
    //   119: invokeinterface 140 2 0
    //   124: aload 6
    //   126: iconst_1
    //   127: invokeinterface 140 2 0
    //   132: aload 6
    //   134: iconst_2
    //   135: invokeinterface 140 2 0
    //   140: invokespecial 269	com/google/android/gms/tagmanager/zzbx:<init>	(JJJ)V
    //   143: invokeinterface 239 2 0
    //   148: pop
    //   149: aload 6
    //   151: invokeinterface 242 1 0
    //   156: istore 5
    //   158: iload 5
    //   160: ifne -50 -> 110
    //   163: goto +21 -> 184
    //   166: astore 8
    //   168: aload 6
    //   170: astore 7
    //   172: aload 8
    //   174: astore 6
    //   176: goto +588 -> 764
    //   179: astore 8
    //   181: goto +507 -> 688
    //   184: aload 6
    //   186: invokeinterface 143 1 0
    //   191: ldc -36
    //   193: iconst_1
    //   194: anewarray 4	java/lang/Object
    //   197: dup
    //   198: iconst_0
    //   199: ldc 31
    //   201: aastore
    //   202: invokestatic 43	java/lang/String:format	(Ljava/lang/String;[Ljava/lang/Object;)Ljava/lang/String;
    //   205: astore 8
    //   207: bipush 40
    //   209: invokestatic 226	java/lang/Integer:toString	(I)Ljava/lang/String;
    //   212: astore 11
    //   214: aload 7
    //   216: astore 9
    //   218: aload 10
    //   220: ldc 29
    //   222: iconst_2
    //   223: anewarray 39	java/lang/String
    //   226: dup
    //   227: iconst_0
    //   228: ldc 31
    //   230: aastore
    //   231: dup
    //   232: iconst_1
    //   233: ldc 35
    //   235: aastore
    //   236: aconst_null
    //   237: aconst_null
    //   238: aconst_null
    //   239: aconst_null
    //   240: aload 8
    //   242: aload 11
    //   244: invokevirtual 229	android/database/sqlite/SQLiteDatabase:query	(Ljava/lang/String;[Ljava/lang/String;Ljava/lang/String;[Ljava/lang/String;Ljava/lang/String;Ljava/lang/String;Ljava/lang/String;Ljava/lang/String;)Landroid/database/Cursor;
    //   247: astore 10
    //   249: aload 10
    //   251: astore 8
    //   253: aload 10
    //   255: invokeinterface 136 1 0
    //   260: ifeq +124 -> 384
    //   263: iconst_0
    //   264: istore_1
    //   265: aload 10
    //   267: astore 8
    //   269: aload 10
    //   271: checkcast 271	android/database/sqlite/SQLiteCursor
    //   274: invokevirtual 275	android/database/sqlite/SQLiteCursor:getWindow	()Landroid/database/CursorWindow;
    //   277: invokevirtual 280	android/database/CursorWindow:getNumRows	()I
    //   280: ifle +32 -> 312
    //   283: aload 10
    //   285: astore 8
    //   287: aload 9
    //   289: iload_1
    //   290: invokeinterface 284 2 0
    //   295: checkcast 266	com/google/android/gms/tagmanager/zzbx
    //   298: aload 10
    //   300: iconst_1
    //   301: invokeinterface 287 2 0
    //   306: invokevirtual 290	com/google/android/gms/tagmanager/zzbx:zzls	(Ljava/lang/String;)V
    //   309: goto +53 -> 362
    //   312: aload 10
    //   314: astore 8
    //   316: ldc_w 292
    //   319: iconst_1
    //   320: anewarray 4	java/lang/Object
    //   323: dup
    //   324: iconst_0
    //   325: aload 9
    //   327: iload_1
    //   328: invokeinterface 284 2 0
    //   333: checkcast 266	com/google/android/gms/tagmanager/zzbx
    //   336: invokevirtual 296	com/google/android/gms/tagmanager/zzbx:zzbdr	()J
    //   339: invokestatic 301	java/lang/Long:valueOf	(J)Ljava/lang/Long;
    //   342: aastore
    //   343: invokestatic 43	java/lang/String:format	(Ljava/lang/String;[Ljava/lang/Object;)Ljava/lang/String;
    //   346: astore 6
    //   348: aload 10
    //   350: astore 8
    //   352: getstatic 149	com/google/android/gms/tagmanager/zzdj:zzjss	Lcom/google/android/gms/tagmanager/zzdk;
    //   355: aload 6
    //   357: invokeinterface 157 2 0
    //   362: iload_1
    //   363: iconst_1
    //   364: iadd
    //   365: istore_1
    //   366: aload 10
    //   368: astore 8
    //   370: aload 10
    //   372: invokeinterface 242 1 0
    //   377: istore 5
    //   379: iload 5
    //   381: ifne -116 -> 265
    //   384: aload 10
    //   386: invokeinterface 143 1 0
    //   391: aload 9
    //   393: areturn
    //   394: astore 9
    //   396: aload 10
    //   398: astore 6
    //   400: goto +20 -> 420
    //   403: astore 7
    //   405: goto +216 -> 621
    //   408: astore 9
    //   410: goto +10 -> 420
    //   413: astore 7
    //   415: goto +206 -> 621
    //   418: astore 9
    //   420: aload 7
    //   422: astore 10
    //   424: aload 6
    //   426: astore 8
    //   428: aload 9
    //   430: invokevirtual 245	android/database/sqlite/SQLiteException:getMessage	()Ljava/lang/String;
    //   433: invokestatic 248	java/lang/String:valueOf	(Ljava/lang/Object;)Ljava/lang/String;
    //   436: astore 7
    //   438: aload 6
    //   440: astore 8
    //   442: aload 7
    //   444: invokevirtual 251	java/lang/String:length	()I
    //   447: ifeq +20 -> 467
    //   450: aload 6
    //   452: astore 8
    //   454: ldc_w 303
    //   457: aload 7
    //   459: invokevirtual 257	java/lang/String:concat	(Ljava/lang/String;)Ljava/lang/String;
    //   462: astore 7
    //   464: goto +19 -> 483
    //   467: aload 6
    //   469: astore 8
    //   471: new 39	java/lang/String
    //   474: dup
    //   475: ldc_w 303
    //   478: invokespecial 259	java/lang/String:<init>	(Ljava/lang/String;)V
    //   481: astore 7
    //   483: aload 6
    //   485: astore 8
    //   487: getstatic 149	com/google/android/gms/tagmanager/zzdj:zzjss	Lcom/google/android/gms/tagmanager/zzdk;
    //   490: aload 7
    //   492: invokeinterface 157 2 0
    //   497: aload 6
    //   499: astore 8
    //   501: new 213	java/util/ArrayList
    //   504: dup
    //   505: invokespecial 214	java/util/ArrayList:<init>	()V
    //   508: astore 7
    //   510: aload 6
    //   512: astore 8
    //   514: aload 10
    //   516: invokevirtual 306	java/util/ArrayList:size	()I
    //   519: istore 4
    //   521: iconst_0
    //   522: istore_1
    //   523: iload_2
    //   524: iload 4
    //   526: if_icmpge +74 -> 600
    //   529: aload 6
    //   531: astore 8
    //   533: aload 10
    //   535: iload_2
    //   536: invokevirtual 307	java/util/ArrayList:get	(I)Ljava/lang/Object;
    //   539: astore 9
    //   541: iload_2
    //   542: iconst_1
    //   543: iadd
    //   544: istore_3
    //   545: aload 6
    //   547: astore 8
    //   549: aload 9
    //   551: checkcast 266	com/google/android/gms/tagmanager/zzbx
    //   554: astore 9
    //   556: iload_1
    //   557: istore_2
    //   558: aload 6
    //   560: astore 8
    //   562: aload 9
    //   564: invokevirtual 310	com/google/android/gms/tagmanager/zzbx:zzbdt	()Ljava/lang/String;
    //   567: invokestatic 314	android/text/TextUtils:isEmpty	(Ljava/lang/CharSequence;)Z
    //   570: ifeq +9 -> 579
    //   573: iload_1
    //   574: ifne +26 -> 600
    //   577: iconst_1
    //   578: istore_2
    //   579: aload 6
    //   581: astore 8
    //   583: aload 7
    //   585: aload 9
    //   587: invokeinterface 239 2 0
    //   592: pop
    //   593: iload_2
    //   594: istore_1
    //   595: iload_3
    //   596: istore_2
    //   597: goto -74 -> 523
    //   600: aload 6
    //   602: ifnull +10 -> 612
    //   605: aload 6
    //   607: invokeinterface 143 1 0
    //   612: aload 7
    //   614: areturn
    //   615: astore 7
    //   617: aload 8
    //   619: astore 6
    //   621: aload 6
    //   623: ifnull +10 -> 633
    //   626: aload 6
    //   628: invokeinterface 143 1 0
    //   633: aload 7
    //   635: athrow
    //   636: astore 8
    //   638: goto +26 -> 664
    //   641: astore 8
    //   643: aload 6
    //   645: astore 7
    //   647: aload 8
    //   649: astore 6
    //   651: goto +113 -> 764
    //   654: astore 9
    //   656: aload 8
    //   658: astore 7
    //   660: aload 9
    //   662: astore 8
    //   664: goto +24 -> 688
    //   667: astore 6
    //   669: aconst_null
    //   670: astore 7
    //   672: goto +92 -> 764
    //   675: astore 9
    //   677: aconst_null
    //   678: astore 6
    //   680: aload 8
    //   682: astore 7
    //   684: aload 9
    //   686: astore 8
    //   688: aload 8
    //   690: invokevirtual 245	android/database/sqlite/SQLiteException:getMessage	()Ljava/lang/String;
    //   693: invokestatic 248	java/lang/String:valueOf	(Ljava/lang/Object;)Ljava/lang/String;
    //   696: astore 8
    //   698: aload 8
    //   700: invokevirtual 251	java/lang/String:length	()I
    //   703: ifeq +15 -> 718
    //   706: ldc -3
    //   708: aload 8
    //   710: invokevirtual 257	java/lang/String:concat	(Ljava/lang/String;)Ljava/lang/String;
    //   713: astore 8
    //   715: goto +14 -> 729
    //   718: new 39	java/lang/String
    //   721: dup
    //   722: ldc -3
    //   724: invokespecial 259	java/lang/String:<init>	(Ljava/lang/String;)V
    //   727: astore 8
    //   729: getstatic 149	com/google/android/gms/tagmanager/zzdj:zzjss	Lcom/google/android/gms/tagmanager/zzdk;
    //   732: aload 8
    //   734: invokeinterface 157 2 0
    //   739: aload 6
    //   741: ifnull +10 -> 751
    //   744: aload 6
    //   746: invokeinterface 143 1 0
    //   751: aload 7
    //   753: areturn
    //   754: astore 8
    //   756: aload 6
    //   758: astore 7
    //   760: aload 8
    //   762: astore 6
    //   764: aload 7
    //   766: ifnull +10 -> 776
    //   769: aload 7
    //   771: invokeinterface 143 1 0
    //   776: goto +6 -> 782
    //   779: aload 6
    //   781: athrow
    //   782: goto -3 -> 779
    // Local variable table:
    //   start	length	slot	name	signature
    //   0	785	0	this	zzec
    //   0	785	1	paramInt	int
    //   50	547	2	i	int
    //   544	52	3	j	int
    //   519	8	4	k	int
    //   103	277	5	bool	boolean
    //   40	610	6	localObject1	Object
    //   667	1	6	localObject2	Object
    //   678	102	6	localObject3	Object
    //   47	168	7	localObject4	Object
    //   403	1	7	localObject5	Object
    //   413	8	7	localObject6	Object
    //   436	177	7	localObject7	Object
    //   615	19	7	localObject8	Object
    //   645	125	7	localObject9	Object
    //   7	17	8	localArrayList	java.util.ArrayList
    //   166	7	8	localObject10	Object
    //   179	1	8	localSQLiteException1	SQLiteException
    //   205	413	8	localObject11	Object
    //   636	1	8	localSQLiteException2	SQLiteException
    //   641	16	8	localObject12	Object
    //   662	71	8	localObject13	Object
    //   754	7	8	localObject14	Object
    //   216	176	9	localObject15	Object
    //   394	1	9	localSQLiteException3	SQLiteException
    //   408	1	9	localSQLiteException4	SQLiteException
    //   418	11	9	localSQLiteException5	SQLiteException
    //   539	47	9	localObject16	Object
    //   654	7	9	localSQLiteException6	SQLiteException
    //   675	10	9	localSQLiteException7	SQLiteException
    //   16	518	10	localObject17	Object
    //   212	31	11	str	String
    // Exception table:
    //   from	to	target	type
    //   110	158	166	finally
    //   110	158	179	android/database/sqlite/SQLiteException
    //   253	263	394	android/database/sqlite/SQLiteException
    //   269	283	394	android/database/sqlite/SQLiteException
    //   287	309	394	android/database/sqlite/SQLiteException
    //   316	348	394	android/database/sqlite/SQLiteException
    //   352	362	394	android/database/sqlite/SQLiteException
    //   370	379	394	android/database/sqlite/SQLiteException
    //   218	249	403	finally
    //   218	249	408	android/database/sqlite/SQLiteException
    //   191	214	413	finally
    //   191	214	418	android/database/sqlite/SQLiteException
    //   253	263	615	finally
    //   269	283	615	finally
    //   287	309	615	finally
    //   316	348	615	finally
    //   352	362	615	finally
    //   370	379	615	finally
    //   428	438	615	finally
    //   442	450	615	finally
    //   454	464	615	finally
    //   471	483	615	finally
    //   487	497	615	finally
    //   501	510	615	finally
    //   514	521	615	finally
    //   533	541	615	finally
    //   549	556	615	finally
    //   562	573	615	finally
    //   583	593	615	finally
    //   96	105	636	android/database/sqlite/SQLiteException
    //   87	96	641	finally
    //   96	105	641	finally
    //   87	96	654	android/database/sqlite/SQLiteException
    //   26	49	667	finally
    //   51	87	667	finally
    //   26	49	675	android/database/sqlite/SQLiteException
    //   51	87	675	android/database/sqlite/SQLiteException
    //   688	715	754	finally
    //   718	729	754	finally
    //   729	739	754	finally
  }
  
  private final void zzh(long paramLong1, long paramLong2)
  {
    Object localObject = zzln("Error opening database for getNumStoredHits.");
    if (localObject == null) {
      return;
    }
    ContentValues localContentValues = new ContentValues();
    localContentValues.put("hit_first_send_time", Long.valueOf(paramLong2));
    try
    {
      ((SQLiteDatabase)localObject).update("gtm_hits", localContentValues, "hit_id=?", new String[] { String.valueOf(paramLong1) });
      return;
    }
    catch (SQLiteException localSQLiteException)
    {
      for (;;) {}
    }
    localObject = new StringBuilder(69);
    ((StringBuilder)localObject).append("Error setting HIT_FIRST_DISPATCH_TIME for hitId: ");
    ((StringBuilder)localObject).append(paramLong1);
    localObject = ((StringBuilder)localObject).toString();
    zzdj.zzjss.zzcr((String)localObject);
    zzp(paramLong1);
  }
  
  private final SQLiteDatabase zzln(String paramString)
  {
    try
    {
      SQLiteDatabase localSQLiteDatabase = zzjsx.getWritableDatabase();
      return localSQLiteDatabase;
    }
    catch (SQLiteException localSQLiteException)
    {
      for (;;) {}
    }
    zzdj.zzjss.zzcr(paramString);
    return null;
  }
  
  private final void zzp(long paramLong)
  {
    zzd(new String[] { String.valueOf(paramLong) });
  }
  
  public final void dispatch()
  {
    zzdj.zzjss.v("GTM Dispatch running...");
    if (!zzjsy.zzbdk()) {
      return;
    }
    List localList = zzel(40);
    if (localList.isEmpty())
    {
      zzdj.zzjss.v("...nothing to dispatch");
      zzjsz.zzbu(true);
      return;
    }
    zzjsy.zzai(localList);
    if (zzbef() > 0) {
      zzfo.zzbez().dispatch();
    }
  }
  
  public final void zzb(long paramLong, String paramString)
  {
    long l = zzasc.currentTimeMillis();
    if (l > zzjtb + 86400000L)
    {
      zzjtb = l;
      localObject1 = zzln("Error opening database for deleteStaleHits.");
      if (localObject1 != null)
      {
        ((SQLiteDatabase)localObject1).delete("gtm_hits", "HIT_TIME < ?", new String[] { Long.toString(zzasc.currentTimeMillis() - 2592000000L) });
        localObject1 = zzjsz;
        boolean bool;
        if (zzbee() == 0) {
          bool = true;
        } else {
          bool = false;
        }
        ((zzcd)localObject1).zzbu(bool);
      }
    }
    int i = zzbee() - zzjtc + 1;
    Object localObject2;
    if (i > 0)
    {
      localObject1 = zzek(i);
      i = ((List)localObject1).size();
      localObject2 = new StringBuilder(51);
      ((StringBuilder)localObject2).append("Store full, deleting ");
      ((StringBuilder)localObject2).append(i);
      ((StringBuilder)localObject2).append(" hits to make room.");
      localObject2 = ((StringBuilder)localObject2).toString();
      zzdj.zzjss.v((String)localObject2);
      zzd((String[])((List)localObject1).toArray(new String[0]));
    }
    Object localObject1 = zzln("Error opening database for putHit");
    if (localObject1 != null)
    {
      localObject2 = new ContentValues();
      ((ContentValues)localObject2).put("hit_time", Long.valueOf(paramLong));
      ((ContentValues)localObject2).put("hit_url", paramString);
      ((ContentValues)localObject2).put("hit_first_send_time", Integer.valueOf(0));
    }
    try
    {
      ((SQLiteDatabase)localObject1).insert("gtm_hits", null, (ContentValues)localObject2);
      zzjsz.zzbu(false);
      return;
    }
    catch (SQLiteException paramString)
    {
      for (;;) {}
    }
    zzdj.zzjss.zzcr("Error storing hit");
  }
}
