package com.google.android.gms.tagmanager;

import android.content.Context;
import android.database.Cursor;
import android.database.sqlite.SQLiteDatabase;
import android.database.sqlite.SQLiteException;
import android.database.sqlite.SQLiteOpenHelper;
import android.os.Build.VERSION;
import com.google.android.gms.common.util.zzd;
import java.io.File;
import java.util.HashSet;
import java.util.Set;

public final class zzee
  extends SQLiteOpenHelper
{
  public boolean zzjte;
  public long zzjtf = 0L;
  
  public zzee(zzec paramZzec, Context paramContext, String paramString)
  {
    super(paramContext, paramString, null, 1);
  }
  
  /* Error */
  public static boolean zza(String paramString, SQLiteDatabase paramSQLiteDatabase)
  {
    // Byte code:
    //   0: aconst_null
    //   1: astore 4
    //   3: aconst_null
    //   4: astore_3
    //   5: aload_1
    //   6: ldc 26
    //   8: iconst_1
    //   9: anewarray 28	java/lang/String
    //   12: dup
    //   13: iconst_0
    //   14: ldc 30
    //   16: aastore
    //   17: ldc 32
    //   19: iconst_1
    //   20: anewarray 28	java/lang/String
    //   23: dup
    //   24: iconst_0
    //   25: aload_0
    //   26: aastore
    //   27: aconst_null
    //   28: aconst_null
    //   29: aconst_null
    //   30: invokevirtual 38	android/database/sqlite/SQLiteDatabase:query	(Ljava/lang/String;[Ljava/lang/String;Ljava/lang/String;[Ljava/lang/String;Ljava/lang/String;Ljava/lang/String;Ljava/lang/String;)Landroid/database/Cursor;
    //   33: astore_1
    //   34: aload_1
    //   35: astore_3
    //   36: aload_1
    //   37: astore 4
    //   39: aload_1
    //   40: invokeinterface 44 1 0
    //   45: istore_2
    //   46: aload_1
    //   47: invokeinterface 48 1 0
    //   52: iload_2
    //   53: ireturn
    //   54: astore_0
    //   55: goto +73 -> 128
    //   58: aload 4
    //   60: astore_3
    //   61: aload_0
    //   62: invokestatic 52	java/lang/String:valueOf	(Ljava/lang/Object;)Ljava/lang/String;
    //   65: astore_0
    //   66: aload 4
    //   68: astore_3
    //   69: aload_0
    //   70: invokevirtual 56	java/lang/String:length	()I
    //   73: ifeq +16 -> 89
    //   76: aload 4
    //   78: astore_3
    //   79: ldc 58
    //   81: aload_0
    //   82: invokevirtual 62	java/lang/String:concat	(Ljava/lang/String;)Ljava/lang/String;
    //   85: astore_0
    //   86: goto +16 -> 102
    //   89: aload 4
    //   91: astore_3
    //   92: new 28	java/lang/String
    //   95: dup
    //   96: ldc 58
    //   98: invokespecial 65	java/lang/String:<init>	(Ljava/lang/String;)V
    //   101: astore_0
    //   102: aload 4
    //   104: astore_3
    //   105: getstatic 71	com/google/android/gms/tagmanager/zzdj:zzjss	Lcom/google/android/gms/tagmanager/zzdk;
    //   108: aload_0
    //   109: invokeinterface 76 2 0
    //   114: aload 4
    //   116: ifnull +10 -> 126
    //   119: aload 4
    //   121: invokeinterface 48 1 0
    //   126: iconst_0
    //   127: ireturn
    //   128: aload_3
    //   129: ifnull +9 -> 138
    //   132: aload_3
    //   133: invokeinterface 48 1 0
    //   138: aload_0
    //   139: athrow
    //   140: astore_1
    //   141: goto -83 -> 58
    // Local variable table:
    //   start	length	slot	name	signature
    //   0	144	0	paramString	String
    //   0	144	1	paramSQLiteDatabase	SQLiteDatabase
    //   45	8	2	bool	boolean
    //   4	129	3	localSQLiteDatabase1	SQLiteDatabase
    //   1	119	4	localSQLiteDatabase2	SQLiteDatabase
    // Exception table:
    //   from	to	target	type
    //   5	34	54	finally
    //   39	46	54	finally
    //   61	66	54	finally
    //   69	76	54	finally
    //   79	86	54	finally
    //   92	102	54	finally
    //   105	114	54	finally
    //   5	34	140	android/database/sqlite/SQLiteException
    //   39	46	140	android/database/sqlite/SQLiteException
  }
  
  public final SQLiteDatabase getWritableDatabase()
  {
    if ((zzjte) && (zzjtf + 3600000L > zzec.zza(zzjtd).currentTimeMillis())) {
      throw new SQLiteException("Database creation failed");
    }
    Object localObject1 = null;
    zzjte = true;
    zzjtf = zzec.zza(zzjtd).currentTimeMillis();
    try
    {
      localObject2 = super.getWritableDatabase();
      localObject1 = localObject2;
    }
    catch (SQLiteException localSQLiteException)
    {
      Object localObject2;
      for (;;) {}
    }
    zzec.zzc(zzjtd).getDatabasePath(zzec.zzb(zzjtd)).delete();
    localObject2 = localObject1;
    if (localObject1 == null) {
      localObject2 = super.getWritableDatabase();
    }
    zzjte = false;
    return localObject2;
  }
  
  public final void onCreate(SQLiteDatabase paramSQLiteDatabase)
  {
    zzbs.zzlr(paramSQLiteDatabase.getPath());
  }
  
  public final void onDowngrade(SQLiteDatabase paramSQLiteDatabase, int paramInt1, int paramInt2) {}
  
  public final void onOpen(SQLiteDatabase paramSQLiteDatabase)
  {
    int i = Build.VERSION.SDK_INT;
    if (!zza("gtm_hits", paramSQLiteDatabase))
    {
      paramSQLiteDatabase.execSQL(zzec.zzdpj);
      return;
    }
    paramSQLiteDatabase = paramSQLiteDatabase.rawQuery("SELECT * FROM gtm_hits WHERE 0", null);
    HashSet localHashSet = new HashSet();
    try
    {
      String[] arrayOfString = paramSQLiteDatabase.getColumnNames();
      i = 0;
      while (i < arrayOfString.length)
      {
        localHashSet.add(arrayOfString[i]);
        i += 1;
      }
      paramSQLiteDatabase.close();
      if ((localHashSet.remove("hit_id")) && (localHashSet.remove("hit_url")) && (localHashSet.remove("hit_time")) && (localHashSet.remove("hit_first_send_time")))
      {
        if (localHashSet.isEmpty()) {
          return;
        }
        throw new SQLiteException("Database has extra columns");
      }
      throw new SQLiteException("Database column missing");
    }
    finally
    {
      paramSQLiteDatabase.close();
    }
    for (;;)
    {
      throw localObject;
    }
  }
  
  public final void onUpgrade(SQLiteDatabase paramSQLiteDatabase, int paramInt1, int paramInt2) {}
}
