package com.google.android.gms.tagmanager;

public class zzei
{
  public static zzei zzjti;
  public volatile String zzjoz = null;
  public volatile zza zzjtj = zza.zzjtm;
  public volatile String zzjtk = null;
  public volatile String zzjtl = null;
  
  public zzei() {}
  
  public static zzei zzbeh()
  {
    try
    {
      if (zzjti == null) {
        zzjti = new zzei();
      }
      zzei localZzei = zzjti;
      return localZzei;
    }
    finally {}
  }
  
  public static String zzlx(String paramString)
  {
    return paramString.split("&")[0].split("=")[1];
  }
  
  public final String getContainerId()
  {
    return zzjoz;
  }
  
  public final zza zzbei()
  {
    return zzjtj;
  }
  
  public final String zzbej()
  {
    return zzjtk;
  }
  
  /* Error */
  public final boolean zzq(android.net.Uri paramUri)
  {
    // Byte code:
    //   0: aload_0
    //   1: monitorenter
    //   2: aload_1
    //   3: invokevirtual 62	android/net/Uri:toString	()Ljava/lang/String;
    //   6: ldc 64
    //   8: invokestatic 70	java/net/URLDecoder:decode	(Ljava/lang/String;Ljava/lang/String;)Ljava/lang/String;
    //   11: astore_3
    //   12: aload_3
    //   13: ldc 72
    //   15: invokevirtual 76	java/lang/String:matches	(Ljava/lang/String;)Z
    //   18: ifeq +157 -> 175
    //   21: aload_3
    //   22: invokevirtual 80	java/lang/String:length	()I
    //   25: ifeq +13 -> 38
    //   28: ldc 82
    //   30: aload_3
    //   31: invokevirtual 85	java/lang/String:concat	(Ljava/lang/String;)Ljava/lang/String;
    //   34: astore_2
    //   35: goto +13 -> 48
    //   38: new 42	java/lang/String
    //   41: dup
    //   42: ldc 82
    //   44: invokespecial 88	java/lang/String:<init>	(Ljava/lang/String;)V
    //   47: astore_2
    //   48: getstatic 94	com/google/android/gms/tagmanager/zzdj:zzjss	Lcom/google/android/gms/tagmanager/zzdk;
    //   51: aload_2
    //   52: invokeinterface 99 2 0
    //   57: aload_3
    //   58: ldc 101
    //   60: invokevirtual 76	java/lang/String:matches	(Ljava/lang/String;)Z
    //   63: ifeq +15 -> 78
    //   66: getstatic 104	com/google/android/gms/tagmanager/zzei$zza:zzjto	Lcom/google/android/gms/tagmanager/zzei$zza;
    //   69: astore_2
    //   70: aload_0
    //   71: aload_2
    //   72: putfield 24	com/google/android/gms/tagmanager/zzei:zzjtj	Lcom/google/android/gms/tagmanager/zzei$zza;
    //   75: goto +10 -> 85
    //   78: getstatic 107	com/google/android/gms/tagmanager/zzei$zza:zzjtn	Lcom/google/android/gms/tagmanager/zzei$zza;
    //   81: astore_2
    //   82: goto -12 -> 70
    //   85: aload_0
    //   86: aload_1
    //   87: invokevirtual 110	android/net/Uri:getQuery	()Ljava/lang/String;
    //   90: ldc 112
    //   92: ldc 114
    //   94: invokevirtual 118	java/lang/String:replace	(Ljava/lang/CharSequence;Ljava/lang/CharSequence;)Ljava/lang/String;
    //   97: putfield 30	com/google/android/gms/tagmanager/zzei:zzjtl	Ljava/lang/String;
    //   100: aload_0
    //   101: getfield 24	com/google/android/gms/tagmanager/zzei:zzjtj	Lcom/google/android/gms/tagmanager/zzei$zza;
    //   104: getstatic 107	com/google/android/gms/tagmanager/zzei$zza:zzjtn	Lcom/google/android/gms/tagmanager/zzei$zza;
    //   107: if_acmpeq +13 -> 120
    //   110: aload_0
    //   111: getfield 24	com/google/android/gms/tagmanager/zzei:zzjtj	Lcom/google/android/gms/tagmanager/zzei$zza;
    //   114: getstatic 104	com/google/android/gms/tagmanager/zzei$zza:zzjto	Lcom/google/android/gms/tagmanager/zzei$zza;
    //   117: if_acmpne +43 -> 160
    //   120: aload_0
    //   121: getfield 30	com/google/android/gms/tagmanager/zzei:zzjtl	Ljava/lang/String;
    //   124: invokestatic 122	java/lang/String:valueOf	(Ljava/lang/Object;)Ljava/lang/String;
    //   127: astore_1
    //   128: aload_1
    //   129: invokevirtual 80	java/lang/String:length	()I
    //   132: ifeq +13 -> 145
    //   135: ldc 124
    //   137: aload_1
    //   138: invokevirtual 85	java/lang/String:concat	(Ljava/lang/String;)Ljava/lang/String;
    //   141: astore_1
    //   142: goto +13 -> 155
    //   145: new 42	java/lang/String
    //   148: dup
    //   149: ldc 124
    //   151: invokespecial 88	java/lang/String:<init>	(Ljava/lang/String;)V
    //   154: astore_1
    //   155: aload_0
    //   156: aload_1
    //   157: putfield 26	com/google/android/gms/tagmanager/zzei:zzjtk	Ljava/lang/String;
    //   160: aload_0
    //   161: aload_0
    //   162: getfield 30	com/google/android/gms/tagmanager/zzei:zzjtl	Ljava/lang/String;
    //   165: invokestatic 126	com/google/android/gms/tagmanager/zzei:zzlx	(Ljava/lang/String;)Ljava/lang/String;
    //   168: putfield 28	com/google/android/gms/tagmanager/zzei:zzjoz	Ljava/lang/String;
    //   171: aload_0
    //   172: monitorexit
    //   173: iconst_1
    //   174: ireturn
    //   175: aload_3
    //   176: ldc -128
    //   178: invokevirtual 76	java/lang/String:matches	(Ljava/lang/String;)Z
    //   181: ifeq +84 -> 265
    //   184: aload_1
    //   185: invokevirtual 110	android/net/Uri:getQuery	()Ljava/lang/String;
    //   188: invokestatic 126	com/google/android/gms/tagmanager/zzei:zzlx	(Ljava/lang/String;)Ljava/lang/String;
    //   191: aload_0
    //   192: getfield 28	com/google/android/gms/tagmanager/zzei:zzjoz	Ljava/lang/String;
    //   195: invokevirtual 132	java/lang/String:equals	(Ljava/lang/Object;)Z
    //   198: ifeq +63 -> 261
    //   201: aload_0
    //   202: getfield 28	com/google/android/gms/tagmanager/zzei:zzjoz	Ljava/lang/String;
    //   205: invokestatic 122	java/lang/String:valueOf	(Ljava/lang/Object;)Ljava/lang/String;
    //   208: astore_1
    //   209: aload_1
    //   210: invokevirtual 80	java/lang/String:length	()I
    //   213: ifeq +13 -> 226
    //   216: ldc -122
    //   218: aload_1
    //   219: invokevirtual 85	java/lang/String:concat	(Ljava/lang/String;)Ljava/lang/String;
    //   222: astore_1
    //   223: goto +13 -> 236
    //   226: new 42	java/lang/String
    //   229: dup
    //   230: ldc -122
    //   232: invokespecial 88	java/lang/String:<init>	(Ljava/lang/String;)V
    //   235: astore_1
    //   236: getstatic 94	com/google/android/gms/tagmanager/zzdj:zzjss	Lcom/google/android/gms/tagmanager/zzdk;
    //   239: aload_1
    //   240: invokeinterface 99 2 0
    //   245: aload_0
    //   246: getstatic 22	com/google/android/gms/tagmanager/zzei$zza:zzjtm	Lcom/google/android/gms/tagmanager/zzei$zza;
    //   249: putfield 24	com/google/android/gms/tagmanager/zzei:zzjtj	Lcom/google/android/gms/tagmanager/zzei$zza;
    //   252: aload_0
    //   253: aconst_null
    //   254: putfield 26	com/google/android/gms/tagmanager/zzei:zzjtk	Ljava/lang/String;
    //   257: aload_0
    //   258: monitorexit
    //   259: iconst_1
    //   260: ireturn
    //   261: aload_0
    //   262: monitorexit
    //   263: iconst_0
    //   264: ireturn
    //   265: aload_3
    //   266: invokevirtual 80	java/lang/String:length	()I
    //   269: ifeq +13 -> 282
    //   272: ldc -120
    //   274: aload_3
    //   275: invokevirtual 85	java/lang/String:concat	(Ljava/lang/String;)Ljava/lang/String;
    //   278: astore_1
    //   279: goto +13 -> 292
    //   282: new 42	java/lang/String
    //   285: dup
    //   286: ldc -120
    //   288: invokespecial 88	java/lang/String:<init>	(Ljava/lang/String;)V
    //   291: astore_1
    //   292: getstatic 94	com/google/android/gms/tagmanager/zzdj:zzjss	Lcom/google/android/gms/tagmanager/zzdk;
    //   295: aload_1
    //   296: invokeinterface 139 2 0
    //   301: aload_0
    //   302: monitorexit
    //   303: iconst_0
    //   304: ireturn
    //   305: astore_1
    //   306: aload_0
    //   307: monitorexit
    //   308: aload_1
    //   309: athrow
    //   310: aload_0
    //   311: monitorexit
    //   312: iconst_0
    //   313: ireturn
    //   314: astore_1
    //   315: goto -5 -> 310
    // Local variable table:
    //   start	length	slot	name	signature
    //   0	318	0	this	zzei
    //   0	318	1	paramUri	android.net.Uri
    //   34	48	2	localObject	Object
    //   11	264	3	str	String
    // Exception table:
    //   from	to	target	type
    //   2	12	305	finally
    //   12	35	305	finally
    //   38	48	305	finally
    //   48	70	305	finally
    //   70	75	305	finally
    //   78	82	305	finally
    //   85	120	305	finally
    //   120	142	305	finally
    //   145	155	305	finally
    //   155	160	305	finally
    //   160	171	305	finally
    //   175	223	305	finally
    //   226	236	305	finally
    //   236	257	305	finally
    //   265	279	305	finally
    //   282	292	305	finally
    //   292	301	305	finally
    //   2	12	314	java/io/UnsupportedEncodingException
  }
  
  public static enum zza
  {
    public zza() {}
  }
}
