package k.a.a.m;

import android.content.Context;
import android.util.Log;
import java.security.Key;
import javax.crypto.Cipher;
import javax.crypto.spec.SecretKeySpec;

public final class C
{
  public String a = null;
  public String b = null;
  public String c = null;
  public byte[] d = null;
  public byte[] e = null;
  public byte[] f = null;
  public String g = null;
  public Key h = null;
  public Cipher i = null;
  public Context j;
  public V k;
  
  public C(Context paramContext)
  {
    j = paramContext;
    k = new V(paramContext);
  }
  
  private Key a(String paramString)
    throws Exception
  {
    paramString = paramString.substring(0, 16);
    try
    {
      h = new SecretKeySpec(paramString.getBytes(), "AES");
    }
    catch (Exception paramString)
    {
      b.a(paramString);
      try
      {
        Ea.m(j, Log.getStackTraceString(paramString));
      }
      catch (Exception localException)
      {
        b.a(localException);
      }
      try
      {
        f.c.a.b.a(paramString);
      }
      catch (Exception paramString)
      {
        b.a(paramString);
      }
    }
    return h;
  }
  
  /* Error */
  public String a(String paramString1, String paramString2)
    throws Exception
  {
    // Byte code:
    //   0: aload_0
    //   1: aload_1
    //   2: putfield 40	k/a/a/m/C:g	Ljava/lang/String;
    //   5: aload_0
    //   6: aload_0
    //   7: aload_2
    //   8: invokespecial 99	k/a/a/m/C:a	(Ljava/lang/String;)Ljava/security/Key;
    //   11: putfield 42	k/a/a/m/C:h	Ljava/security/Key;
    //   14: aload_0
    //   15: ldc 70
    //   17: invokestatic 105	javax/crypto/Cipher:getInstance	(Ljava/lang/String;)Ljavax/crypto/Cipher;
    //   20: putfield 44	k/a/a/m/C:i	Ljavax/crypto/Cipher;
    //   23: aload_0
    //   24: getfield 44	k/a/a/m/C:i	Ljavax/crypto/Cipher;
    //   27: iconst_2
    //   28: aload_0
    //   29: getfield 42	k/a/a/m/C:h	Ljava/security/Key;
    //   32: invokevirtual 109	javax/crypto/Cipher:init	(ILjava/security/Key;)V
    //   35: iconst_0
    //   36: istore_3
    //   37: iload_3
    //   38: iconst_2
    //   39: if_icmpge +115 -> 154
    //   42: aload_0
    //   43: aload_0
    //   44: getfield 40	k/a/a/m/C:g	Ljava/lang/String;
    //   47: iconst_2
    //   48: invokestatic 115	android/util/Base64:decode	(Ljava/lang/String;I)[B
    //   51: putfield 36	k/a/a/m/C:e	[B
    //   54: aload_0
    //   55: aload_0
    //   56: getfield 44	k/a/a/m/C:i	Ljavax/crypto/Cipher;
    //   59: aload_0
    //   60: getfield 36	k/a/a/m/C:e	[B
    //   63: invokevirtual 119	javax/crypto/Cipher:doFinal	([B)[B
    //   66: putfield 38	k/a/a/m/C:f	[B
    //   69: aload_0
    //   70: new 58	java/lang/String
    //   73: dup
    //   74: aload_0
    //   75: getfield 38	k/a/a/m/C:f	[B
    //   78: invokespecial 122	java/lang/String:<init>	([B)V
    //   81: getstatic 127	in/spicedigital/umang/application/MyApplication:o	Ljava/lang/String;
    //   84: invokevirtual 131	java/lang/String:length	()I
    //   87: invokevirtual 134	java/lang/String:substring	(I)Ljava/lang/String;
    //   90: putfield 30	k/a/a/m/C:b	Ljava/lang/String;
    //   93: aload_0
    //   94: aload_0
    //   95: getfield 30	k/a/a/m/C:b	Ljava/lang/String;
    //   98: putfield 40	k/a/a/m/C:g	Ljava/lang/String;
    //   101: iload_3
    //   102: iconst_1
    //   103: iadd
    //   104: istore_3
    //   105: goto -68 -> 37
    //   108: astore_1
    //   109: goto +75 -> 184
    //   112: astore_1
    //   113: aload_0
    //   114: ldc -120
    //   116: putfield 30	k/a/a/m/C:b	Ljava/lang/String;
    //   119: aload_1
    //   120: invokestatic 78	k/a/a/m/b:a	(Ljava/lang/Exception;)V
    //   123: aload_0
    //   124: getfield 46	k/a/a/m/C:j	Landroid/content/Context;
    //   127: aload_1
    //   128: invokestatic 84	android/util/Log:getStackTraceString	(Ljava/lang/Throwable;)Ljava/lang/String;
    //   131: invokestatic 90	k/a/a/m/Ea:m	(Landroid/content/Context;Ljava/lang/String;)V
    //   134: goto +8 -> 142
    //   137: astore_2
    //   138: aload_2
    //   139: invokestatic 78	k/a/a/m/b:a	(Ljava/lang/Exception;)V
    //   142: aload_1
    //   143: invokestatic 95	f/c/a/b:a	(Ljava/lang/Throwable;)V
    //   146: goto +8 -> 154
    //   149: astore_1
    //   150: aload_1
    //   151: invokestatic 78	k/a/a/m/b:a	(Ljava/lang/Exception;)V
    //   154: aload_0
    //   155: aconst_null
    //   156: putfield 44	k/a/a/m/C:i	Ljavax/crypto/Cipher;
    //   159: aload_0
    //   160: aconst_null
    //   161: putfield 36	k/a/a/m/C:e	[B
    //   164: aload_0
    //   165: aconst_null
    //   166: putfield 38	k/a/a/m/C:f	[B
    //   169: aload_0
    //   170: aconst_null
    //   171: putfield 40	k/a/a/m/C:g	Ljava/lang/String;
    //   174: aload_0
    //   175: aconst_null
    //   176: putfield 42	k/a/a/m/C:h	Ljava/security/Key;
    //   179: aload_0
    //   180: getfield 30	k/a/a/m/C:b	Ljava/lang/String;
    //   183: areturn
    //   184: aload_0
    //   185: aconst_null
    //   186: putfield 44	k/a/a/m/C:i	Ljavax/crypto/Cipher;
    //   189: aload_0
    //   190: aconst_null
    //   191: putfield 36	k/a/a/m/C:e	[B
    //   194: aload_0
    //   195: aconst_null
    //   196: putfield 38	k/a/a/m/C:f	[B
    //   199: aload_0
    //   200: aconst_null
    //   201: putfield 40	k/a/a/m/C:g	Ljava/lang/String;
    //   204: aload_0
    //   205: aconst_null
    //   206: putfield 42	k/a/a/m/C:h	Ljava/security/Key;
    //   209: goto +5 -> 214
    //   212: aload_1
    //   213: athrow
    //   214: goto -2 -> 212
    // Local variable table:
    //   start	length	slot	name	signature
    //   0	217	0	this	C
    //   0	217	1	paramString1	String
    //   0	217	2	paramString2	String
    //   36	69	3	m	int
    // Exception table:
    //   from	to	target	type
    //   5	35	108	finally
    //   42	101	108	finally
    //   113	123	108	finally
    //   123	134	108	finally
    //   138	142	108	finally
    //   142	146	108	finally
    //   150	154	108	finally
    //   5	35	112	java/lang/Exception
    //   42	101	112	java/lang/Exception
    //   123	134	137	java/lang/Exception
    //   142	146	149	java/lang/Exception
  }
  
  /* Error */
  public String b(String paramString1, String paramString2)
    throws Exception
  {
    // Byte code:
    //   0: aload_0
    //   1: aload_1
    //   2: putfield 32	k/a/a/m/C:c	Ljava/lang/String;
    //   5: aload_0
    //   6: aload_0
    //   7: aload_2
    //   8: invokespecial 99	k/a/a/m/C:a	(Ljava/lang/String;)Ljava/security/Key;
    //   11: putfield 42	k/a/a/m/C:h	Ljava/security/Key;
    //   14: aload_0
    //   15: ldc 70
    //   17: invokestatic 105	javax/crypto/Cipher:getInstance	(Ljava/lang/String;)Ljavax/crypto/Cipher;
    //   20: putfield 44	k/a/a/m/C:i	Ljavax/crypto/Cipher;
    //   23: aload_0
    //   24: getfield 44	k/a/a/m/C:i	Ljavax/crypto/Cipher;
    //   27: iconst_1
    //   28: aload_0
    //   29: getfield 42	k/a/a/m/C:h	Ljava/security/Key;
    //   32: invokevirtual 109	javax/crypto/Cipher:init	(ILjava/security/Key;)V
    //   35: iconst_0
    //   36: istore_3
    //   37: iload_3
    //   38: iconst_2
    //   39: if_icmpge +119 -> 158
    //   42: new 138	java/lang/StringBuilder
    //   45: dup
    //   46: invokespecial 139	java/lang/StringBuilder:<init>	()V
    //   49: astore_1
    //   50: aload_1
    //   51: getstatic 127	in/spicedigital/umang/application/MyApplication:o	Ljava/lang/String;
    //   54: invokevirtual 143	java/lang/StringBuilder:append	(Ljava/lang/String;)Ljava/lang/StringBuilder;
    //   57: pop
    //   58: aload_1
    //   59: aload_0
    //   60: getfield 32	k/a/a/m/C:c	Ljava/lang/String;
    //   63: invokevirtual 143	java/lang/StringBuilder:append	(Ljava/lang/String;)Ljava/lang/StringBuilder;
    //   66: pop
    //   67: aload_0
    //   68: aload_1
    //   69: invokevirtual 147	java/lang/StringBuilder:toString	()Ljava/lang/String;
    //   72: putfield 28	k/a/a/m/C:a	Ljava/lang/String;
    //   75: aload_0
    //   76: aload_0
    //   77: getfield 44	k/a/a/m/C:i	Ljavax/crypto/Cipher;
    //   80: aload_0
    //   81: getfield 28	k/a/a/m/C:a	Ljava/lang/String;
    //   84: invokevirtual 68	java/lang/String:getBytes	()[B
    //   87: invokevirtual 119	javax/crypto/Cipher:doFinal	([B)[B
    //   90: putfield 34	k/a/a/m/C:d	[B
    //   93: aload_0
    //   94: aload_0
    //   95: getfield 34	k/a/a/m/C:d	[B
    //   98: iconst_2
    //   99: invokestatic 151	android/util/Base64:encodeToString	([BI)Ljava/lang/String;
    //   102: putfield 32	k/a/a/m/C:c	Ljava/lang/String;
    //   105: iload_3
    //   106: iconst_1
    //   107: iadd
    //   108: istore_3
    //   109: goto -72 -> 37
    //   112: astore_1
    //   113: goto +70 -> 183
    //   116: astore_1
    //   117: aload_0
    //   118: ldc -120
    //   120: putfield 32	k/a/a/m/C:c	Ljava/lang/String;
    //   123: aload_1
    //   124: invokestatic 78	k/a/a/m/b:a	(Ljava/lang/Exception;)V
    //   127: aload_0
    //   128: getfield 46	k/a/a/m/C:j	Landroid/content/Context;
    //   131: aload_1
    //   132: invokestatic 84	android/util/Log:getStackTraceString	(Ljava/lang/Throwable;)Ljava/lang/String;
    //   135: invokestatic 90	k/a/a/m/Ea:m	(Landroid/content/Context;Ljava/lang/String;)V
    //   138: goto +8 -> 146
    //   141: astore_2
    //   142: aload_2
    //   143: invokestatic 78	k/a/a/m/b:a	(Ljava/lang/Exception;)V
    //   146: aload_1
    //   147: invokestatic 95	f/c/a/b:a	(Ljava/lang/Throwable;)V
    //   150: goto +8 -> 158
    //   153: astore_1
    //   154: aload_1
    //   155: invokestatic 78	k/a/a/m/b:a	(Ljava/lang/Exception;)V
    //   158: aload_0
    //   159: aconst_null
    //   160: putfield 44	k/a/a/m/C:i	Ljavax/crypto/Cipher;
    //   163: aload_0
    //   164: aconst_null
    //   165: putfield 28	k/a/a/m/C:a	Ljava/lang/String;
    //   168: aload_0
    //   169: aconst_null
    //   170: putfield 34	k/a/a/m/C:d	[B
    //   173: aload_0
    //   174: aconst_null
    //   175: putfield 42	k/a/a/m/C:h	Ljava/security/Key;
    //   178: aload_0
    //   179: getfield 32	k/a/a/m/C:c	Ljava/lang/String;
    //   182: areturn
    //   183: aload_0
    //   184: aconst_null
    //   185: putfield 44	k/a/a/m/C:i	Ljavax/crypto/Cipher;
    //   188: aload_0
    //   189: aconst_null
    //   190: putfield 28	k/a/a/m/C:a	Ljava/lang/String;
    //   193: aload_0
    //   194: aconst_null
    //   195: putfield 34	k/a/a/m/C:d	[B
    //   198: aload_0
    //   199: aconst_null
    //   200: putfield 42	k/a/a/m/C:h	Ljava/security/Key;
    //   203: goto +5 -> 208
    //   206: aload_1
    //   207: athrow
    //   208: goto -2 -> 206
    // Local variable table:
    //   start	length	slot	name	signature
    //   0	211	0	this	C
    //   0	211	1	paramString1	String
    //   0	211	2	paramString2	String
    //   36	73	3	m	int
    // Exception table:
    //   from	to	target	type
    //   5	35	112	finally
    //   42	105	112	finally
    //   117	127	112	finally
    //   127	138	112	finally
    //   142	146	112	finally
    //   146	150	112	finally
    //   154	158	112	finally
    //   5	35	116	java/lang/Exception
    //   42	105	116	java/lang/Exception
    //   127	138	141	java/lang/Exception
    //   146	150	153	java/lang/Exception
  }
}
