package k.a.a.m;

import android.content.Context;
import android.util.Log;
import in.spicedigital.umang.application.MyApplication;
import java.security.Key;
import javax.crypto.Cipher;
import javax.crypto.spec.SecretKeySpec;

public final class y
{
  public String a = null;
  public String b = null;
  public String c = null;
  public byte[] d = null;
  public byte[] e = null;
  public byte[] f = null;
  public String g = null;
  public Key h = null;
  public Cipher i = null;
  public Context j;
  public V k;
  
  public y(Context paramContext)
  {
    j = paramContext;
    k = new V(paramContext);
  }
  
  private Key a()
    throws Exception
  {
    try
    {
      h = new SecretKeySpec(MyApplication.w.getBytes(), "AES");
    }
    catch (Exception localException1)
    {
      b.a(localException1);
      try
      {
        Ea.m(j, Log.getStackTraceString(localException1));
      }
      catch (Exception localException3)
      {
        b.a(localException3);
      }
      try
      {
        f.c.a.b.a(localException1);
        StringBuilder localStringBuilder = new StringBuilder();
        localStringBuilder.append("generateKey u_k : ");
        localStringBuilder.append(MyApplication.w);
        f.c.a.b.a(localStringBuilder.toString());
      }
      catch (Exception localException2)
      {
        b.a(localException2);
      }
    }
    return h;
  }
  
  /* Error */
  public String a(String paramString)
    throws Exception
  {
    // Byte code:
    //   0: aload_0
    //   1: aload_1
    //   2: putfield 40	k/a/a/m/y:g	Ljava/lang/String;
    //   5: aload_0
    //   6: aload_0
    //   7: invokespecial 116	k/a/a/m/y:a	()Ljava/security/Key;
    //   10: putfield 42	k/a/a/m/y:h	Ljava/security/Key;
    //   13: aload_0
    //   14: ldc 71
    //   16: invokestatic 122	javax/crypto/Cipher:getInstance	(Ljava/lang/String;)Ljavax/crypto/Cipher;
    //   19: putfield 44	k/a/a/m/y:i	Ljavax/crypto/Cipher;
    //   22: aload_0
    //   23: getfield 44	k/a/a/m/y:i	Ljavax/crypto/Cipher;
    //   26: iconst_2
    //   27: aload_0
    //   28: getfield 42	k/a/a/m/y:h	Ljava/security/Key;
    //   31: invokevirtual 126	javax/crypto/Cipher:init	(ILjava/security/Key;)V
    //   34: iconst_0
    //   35: istore_2
    //   36: iload_2
    //   37: iconst_2
    //   38: if_icmpge +65 -> 103
    //   41: aload_0
    //   42: aload_0
    //   43: getfield 40	k/a/a/m/y:g	Ljava/lang/String;
    //   46: iconst_2
    //   47: invokestatic 132	android/util/Base64:decode	(Ljava/lang/String;I)[B
    //   50: putfield 36	k/a/a/m/y:e	[B
    //   53: aload_0
    //   54: aload_0
    //   55: getfield 44	k/a/a/m/y:i	Ljavax/crypto/Cipher;
    //   58: aload_0
    //   59: getfield 36	k/a/a/m/y:e	[B
    //   62: invokevirtual 136	javax/crypto/Cipher:doFinal	([B)[B
    //   65: putfield 38	k/a/a/m/y:f	[B
    //   68: aload_0
    //   69: new 65	java/lang/String
    //   72: dup
    //   73: aload_0
    //   74: getfield 38	k/a/a/m/y:f	[B
    //   77: invokespecial 139	java/lang/String:<init>	([B)V
    //   80: bipush 16
    //   82: invokevirtual 143	java/lang/String:substring	(I)Ljava/lang/String;
    //   85: putfield 30	k/a/a/m/y:b	Ljava/lang/String;
    //   88: aload_0
    //   89: aload_0
    //   90: getfield 30	k/a/a/m/y:b	Ljava/lang/String;
    //   93: putfield 40	k/a/a/m/y:g	Ljava/lang/String;
    //   96: iload_2
    //   97: iconst_1
    //   98: iadd
    //   99: istore_2
    //   100: goto -64 -> 36
    //   103: aload_0
    //   104: aconst_null
    //   105: putfield 44	k/a/a/m/y:i	Ljavax/crypto/Cipher;
    //   108: aload_0
    //   109: aconst_null
    //   110: putfield 36	k/a/a/m/y:e	[B
    //   113: aload_0
    //   114: aconst_null
    //   115: putfield 38	k/a/a/m/y:f	[B
    //   118: aload_0
    //   119: aconst_null
    //   120: putfield 40	k/a/a/m/y:g	Ljava/lang/String;
    //   123: aload_0
    //   124: aconst_null
    //   125: putfield 42	k/a/a/m/y:h	Ljava/security/Key;
    //   128: goto +82 -> 210
    //   131: astore_1
    //   132: goto +83 -> 215
    //   135: astore_3
    //   136: aload_0
    //   137: ldc -111
    //   139: putfield 30	k/a/a/m/y:b	Ljava/lang/String;
    //   142: aload_3
    //   143: invokestatic 79	k/a/a/m/b:a	(Ljava/lang/Exception;)V
    //   146: aload_0
    //   147: getfield 46	k/a/a/m/y:j	Landroid/content/Context;
    //   150: aload_3
    //   151: invokestatic 85	android/util/Log:getStackTraceString	(Ljava/lang/Throwable;)Ljava/lang/String;
    //   154: invokestatic 91	k/a/a/m/Ea:m	(Landroid/content/Context;Ljava/lang/String;)V
    //   157: goto +10 -> 167
    //   160: astore 4
    //   162: aload 4
    //   164: invokestatic 79	k/a/a/m/b:a	(Ljava/lang/Exception;)V
    //   167: aload_3
    //   168: invokestatic 96	f/c/a/b:a	(Ljava/lang/Throwable;)V
    //   171: new 98	java/lang/StringBuilder
    //   174: dup
    //   175: invokespecial 99	java/lang/StringBuilder:<init>	()V
    //   178: astore_3
    //   179: aload_3
    //   180: ldc -109
    //   182: invokevirtual 105	java/lang/StringBuilder:append	(Ljava/lang/String;)Ljava/lang/StringBuilder;
    //   185: pop
    //   186: aload_3
    //   187: aload_1
    //   188: invokevirtual 105	java/lang/StringBuilder:append	(Ljava/lang/String;)Ljava/lang/StringBuilder;
    //   191: pop
    //   192: aload_3
    //   193: invokevirtual 109	java/lang/StringBuilder:toString	()Ljava/lang/String;
    //   196: invokestatic 112	f/c/a/b:a	(Ljava/lang/String;)V
    //   199: goto -96 -> 103
    //   202: astore_1
    //   203: aload_1
    //   204: invokestatic 79	k/a/a/m/b:a	(Ljava/lang/Exception;)V
    //   207: goto -104 -> 103
    //   210: aload_0
    //   211: getfield 30	k/a/a/m/y:b	Ljava/lang/String;
    //   214: areturn
    //   215: aload_0
    //   216: aconst_null
    //   217: putfield 44	k/a/a/m/y:i	Ljavax/crypto/Cipher;
    //   220: aload_0
    //   221: aconst_null
    //   222: putfield 36	k/a/a/m/y:e	[B
    //   225: aload_0
    //   226: aconst_null
    //   227: putfield 38	k/a/a/m/y:f	[B
    //   230: aload_0
    //   231: aconst_null
    //   232: putfield 40	k/a/a/m/y:g	Ljava/lang/String;
    //   235: aload_0
    //   236: aconst_null
    //   237: putfield 42	k/a/a/m/y:h	Ljava/security/Key;
    //   240: goto +5 -> 245
    //   243: aload_1
    //   244: athrow
    //   245: goto -2 -> 243
    // Local variable table:
    //   start	length	slot	name	signature
    //   0	248	0	this	y
    //   0	248	1	paramString	String
    //   35	65	2	m	int
    //   135	33	3	localException1	Exception
    //   178	15	3	localStringBuilder	StringBuilder
    //   160	3	4	localException2	Exception
    // Exception table:
    //   from	to	target	type
    //   5	34	131	finally
    //   41	96	131	finally
    //   136	146	131	finally
    //   146	157	131	finally
    //   162	167	131	finally
    //   167	199	131	finally
    //   203	207	131	finally
    //   5	34	135	java/lang/Exception
    //   41	96	135	java/lang/Exception
    //   146	157	160	java/lang/Exception
    //   167	199	202	java/lang/Exception
  }
  
  /* Error */
  public String b(String paramString)
    throws Exception
  {
    // Byte code:
    //   0: aload_0
    //   1: aload_1
    //   2: putfield 32	k/a/a/m/y:c	Ljava/lang/String;
    //   5: aload_0
    //   6: aload_0
    //   7: invokespecial 116	k/a/a/m/y:a	()Ljava/security/Key;
    //   10: putfield 42	k/a/a/m/y:h	Ljava/security/Key;
    //   13: aload_0
    //   14: ldc 71
    //   16: invokestatic 122	javax/crypto/Cipher:getInstance	(Ljava/lang/String;)Ljavax/crypto/Cipher;
    //   19: putfield 44	k/a/a/m/y:i	Ljavax/crypto/Cipher;
    //   22: aload_0
    //   23: getfield 44	k/a/a/m/y:i	Ljavax/crypto/Cipher;
    //   26: iconst_1
    //   27: aload_0
    //   28: getfield 42	k/a/a/m/y:h	Ljava/security/Key;
    //   31: invokevirtual 126	javax/crypto/Cipher:init	(ILjava/security/Key;)V
    //   34: iconst_0
    //   35: istore_2
    //   36: iload_2
    //   37: iconst_2
    //   38: if_icmpge +73 -> 111
    //   41: new 98	java/lang/StringBuilder
    //   44: dup
    //   45: invokespecial 99	java/lang/StringBuilder:<init>	()V
    //   48: astore_3
    //   49: aload_3
    //   50: getstatic 150	in/spicedigital/umang/application/MyApplication:o	Ljava/lang/String;
    //   53: invokevirtual 105	java/lang/StringBuilder:append	(Ljava/lang/String;)Ljava/lang/StringBuilder;
    //   56: pop
    //   57: aload_3
    //   58: aload_0
    //   59: getfield 32	k/a/a/m/y:c	Ljava/lang/String;
    //   62: invokevirtual 105	java/lang/StringBuilder:append	(Ljava/lang/String;)Ljava/lang/StringBuilder;
    //   65: pop
    //   66: aload_0
    //   67: aload_3
    //   68: invokevirtual 109	java/lang/StringBuilder:toString	()Ljava/lang/String;
    //   71: putfield 28	k/a/a/m/y:a	Ljava/lang/String;
    //   74: aload_0
    //   75: aload_0
    //   76: getfield 44	k/a/a/m/y:i	Ljavax/crypto/Cipher;
    //   79: aload_0
    //   80: getfield 28	k/a/a/m/y:a	Ljava/lang/String;
    //   83: invokevirtual 69	java/lang/String:getBytes	()[B
    //   86: invokevirtual 136	javax/crypto/Cipher:doFinal	([B)[B
    //   89: putfield 34	k/a/a/m/y:d	[B
    //   92: aload_0
    //   93: aload_0
    //   94: getfield 34	k/a/a/m/y:d	[B
    //   97: iconst_2
    //   98: invokestatic 154	android/util/Base64:encodeToString	([BI)Ljava/lang/String;
    //   101: putfield 32	k/a/a/m/y:c	Ljava/lang/String;
    //   104: iload_2
    //   105: iconst_1
    //   106: iadd
    //   107: istore_2
    //   108: goto -72 -> 36
    //   111: aload_0
    //   112: aconst_null
    //   113: putfield 44	k/a/a/m/y:i	Ljavax/crypto/Cipher;
    //   116: aload_0
    //   117: aconst_null
    //   118: putfield 28	k/a/a/m/y:a	Ljava/lang/String;
    //   121: aload_0
    //   122: aconst_null
    //   123: putfield 34	k/a/a/m/y:d	[B
    //   126: aload_0
    //   127: aconst_null
    //   128: putfield 42	k/a/a/m/y:h	Ljava/security/Key;
    //   131: goto +97 -> 228
    //   134: astore_1
    //   135: goto +98 -> 233
    //   138: astore_3
    //   139: aload_0
    //   140: ldc -111
    //   142: putfield 32	k/a/a/m/y:c	Ljava/lang/String;
    //   145: aload_3
    //   146: invokestatic 79	k/a/a/m/b:a	(Ljava/lang/Exception;)V
    //   149: aload_0
    //   150: getfield 46	k/a/a/m/y:j	Landroid/content/Context;
    //   153: aload_3
    //   154: invokestatic 85	android/util/Log:getStackTraceString	(Ljava/lang/Throwable;)Ljava/lang/String;
    //   157: invokestatic 91	k/a/a/m/Ea:m	(Landroid/content/Context;Ljava/lang/String;)V
    //   160: goto +10 -> 170
    //   163: astore 4
    //   165: aload 4
    //   167: invokestatic 79	k/a/a/m/b:a	(Ljava/lang/Exception;)V
    //   170: aload_3
    //   171: invokestatic 96	f/c/a/b:a	(Ljava/lang/Throwable;)V
    //   174: new 98	java/lang/StringBuilder
    //   177: dup
    //   178: invokespecial 99	java/lang/StringBuilder:<init>	()V
    //   181: astore_3
    //   182: aload_3
    //   183: ldc -100
    //   185: invokevirtual 105	java/lang/StringBuilder:append	(Ljava/lang/String;)Ljava/lang/StringBuilder;
    //   188: pop
    //   189: aload_3
    //   190: getstatic 150	in/spicedigital/umang/application/MyApplication:o	Ljava/lang/String;
    //   193: invokevirtual 105	java/lang/StringBuilder:append	(Ljava/lang/String;)Ljava/lang/StringBuilder;
    //   196: pop
    //   197: aload_3
    //   198: ldc -98
    //   200: invokevirtual 105	java/lang/StringBuilder:append	(Ljava/lang/String;)Ljava/lang/StringBuilder;
    //   203: pop
    //   204: aload_3
    //   205: aload_1
    //   206: invokevirtual 105	java/lang/StringBuilder:append	(Ljava/lang/String;)Ljava/lang/StringBuilder;
    //   209: pop
    //   210: aload_3
    //   211: invokevirtual 109	java/lang/StringBuilder:toString	()Ljava/lang/String;
    //   214: invokestatic 112	f/c/a/b:a	(Ljava/lang/String;)V
    //   217: goto -106 -> 111
    //   220: astore_1
    //   221: aload_1
    //   222: invokestatic 79	k/a/a/m/b:a	(Ljava/lang/Exception;)V
    //   225: goto -114 -> 111
    //   228: aload_0
    //   229: getfield 32	k/a/a/m/y:c	Ljava/lang/String;
    //   232: areturn
    //   233: aload_0
    //   234: aconst_null
    //   235: putfield 44	k/a/a/m/y:i	Ljavax/crypto/Cipher;
    //   238: aload_0
    //   239: aconst_null
    //   240: putfield 28	k/a/a/m/y:a	Ljava/lang/String;
    //   243: aload_0
    //   244: aconst_null
    //   245: putfield 34	k/a/a/m/y:d	[B
    //   248: aload_0
    //   249: aconst_null
    //   250: putfield 42	k/a/a/m/y:h	Ljava/security/Key;
    //   253: goto +5 -> 258
    //   256: aload_1
    //   257: athrow
    //   258: goto -2 -> 256
    // Local variable table:
    //   start	length	slot	name	signature
    //   0	261	0	this	y
    //   0	261	1	paramString	String
    //   35	73	2	m	int
    //   48	20	3	localStringBuilder1	StringBuilder
    //   138	33	3	localException1	Exception
    //   181	30	3	localStringBuilder2	StringBuilder
    //   163	3	4	localException2	Exception
    // Exception table:
    //   from	to	target	type
    //   5	34	134	finally
    //   41	104	134	finally
    //   139	149	134	finally
    //   149	160	134	finally
    //   165	170	134	finally
    //   170	217	134	finally
    //   221	225	134	finally
    //   5	34	138	java/lang/Exception
    //   41	104	138	java/lang/Exception
    //   149	160	163	java/lang/Exception
    //   170	217	220	java/lang/Exception
  }
}
